Workbook

Sheet EMENDAS_CODIFICACAO
A1: id_emenda | B1: ano | C1: linha_origem | D1: arquivo_origem | E1: id_vereador_ano | F1: numero_emenda | G1: status_original | H1: parlamentar_original | I1: partido_base | J1: objeto_emenda | K1: dotacao_original | L1: uo_dec | M1: nome_uo | N1: func_dec | O1: nome_funcao | P1: sub_dec | Q1: nome_subfuncao | R1: prog_dec | S1: nome_programa | T1: acao_dec | U1: nome_acao | V1: nat_dec | W1: categoria_economica | X1: grupo_despesa | Y1: fonte_dec | Z1: orgao_executor | AA1: valor_emenda | AB1: valor_empenhado | AC1: valor_liquidado | AD1: valor_pago | AE1: credor_original | AF1: cnpj_credor_original | AG1: tipo_beneficiario_original | AH1: beneficiario_final_original | AI1: cnpj_beneficiario_final_original | AJ1: saude_orcamentaria | AK1: saude_tematica | AL1: subcodigo_cap_final | AM1: subcodigo_cap | AN1: subcodigo_cap_descricao | AO1: localidade_final | AP1: localidade_resumo | AQ1: N_localidades | AR1: georreferenciavel | AS1: georreferenciacao | AT1: publico_alvo_final | AU1: publico_alvo_resumo | AV1: credor_disponivel_final | AW1: credor_padronizado | AX1: status_codificacao | AY1: confianca | AZ1: data_codificacao | BA1: regra_decisao_id | BB1: cultura_ou_esporte
A2: 2022_ALVARO_DAMIAO_290_01 | B2: 2022 | C2: 4274 | D2: emendas_conslidadas(1).xlsx | E2: 2022_ALVARO_DAMIAO | F2: 290 | G2: Concluída | H2: Álvaro Damião | I2: DEM | J2: Ao reforço à dotação orçamentária para reforma e manutenção do Centro de Saúde Alcides Lins, localizado na rua Panema n. 275, bairro Concórdia; | K2: 2302.0400.10.122.117.1.216.449051 | L2: 2302 | M2: FUNDO MUNICIPAL DE SAÚDE | N2: 10 | O2: Saúde | P2: 122 | Q2: Administração Geral | R2: 0117 | S2: Gestão do SUS | T2: 1216 | U2: Construção, Ampliação e Reforma de Unidades de Saúde | V2: 449051 | W2: Despesa de capital | X2: Investimentos | Z2: SMSA | AA2: 400000 | AB2: 400000 | AC2: 240595 | AD2: 240595 | AE2: CONSTRUTORA CAMPOS E FILHOS LTDA | AF2: 15862332000152 | AG2: PBH | AH2: Município de Belo Horizonte | AI2: 18715383000140 | AJ2: 1 | AK2: 1 | AL2: 0322 | AM2: =IF(AL2="","",AL2&" - "&IFERROR(VLOOKUP(AL2,CODEBOOK_CAP!$C$2:$D$212,2,FALSE),"")) -> 0322 - ESTRUTURAS, HOSPITAIS, CLÍNICAS | AN2: =IF(AL2="","",IFERROR(VLOOKUP(AL2,CODEBOOK_CAP!$C$2:$E$212,3,FALSE),"")) -> Observações relacionadas as estruturas do sistema de saúde, como a construção de hospitais, postos de saúde, construção de maternidades, laboratórios, centros de saúde avançado, SAMU, Ambulâncias, UTI Móveis, leitos, compra de equipamentos médicos, Raio X, Ultrasom, equipamentos de diálise, capacidade de atendimento, estrutura e funcionamento de equipamentos públicos de saúde. | AO2: 1 | AP2: rua Panema n. 275, bairro Concórdia | AQ2: 1 | AR2: 1 | AS2: Centro de Saúde Alcides Lins, localizado na rua Panema n. 275, bairro Concórdia; | AT2: 0 | AV2: 1 | AW2: CONSTRUTORA CAMPOS E FILHOS LTDA | AX2: Pendente
A3: 2022_ALVARO_DAMIAO_291_01 | B3: 2022 | C3: 4275 | D3: emendas_conslidadas(1).xlsx | E3: 2022_ALVARO_DAMIAO | F3: 291 | G3: Concluída | H3: Álvaro Damião | I3: DEM | J3: Ao reforço à dotação orçamentária para reforma e manutenção do Centro de Saúde Cachoeirinha, estabelecido na rua Borborema n. 1325, bairro Cachoeirinha; | K3: 2302.0400.10.122.117.1.216.449051 | L3: 2302 | M3: FUNDO MUNICIPAL DE SAÚDE | N3: 10 | O3: Saúde | P3: 122 | Q3: Administração Geral | R3: 0117 | S3: Gestão do SUS | T3: 1216 | U3: Construção, Ampliação e Reforma de Unidades de Saúde | V3: 449051 | W3: Despesa de capital | X3: Investimentos | Z3: SMSA | AA3: 65000 | AB3: 59878 | AD3: 41513.2 | AE3: CONSTRUTORA CAMPOS E FILHOS LTDA | AF3: 15862332000152 | AG3: PBH | AH3: Município de Belo Horizonte | AI3: 18715383000140 | AJ3: 1 | AK3: 1 | AL3: 0322 | AM3: =IF(AL3="","",AL3&" - "&IFERROR(VLOOKUP(AL3,CODEBOOK_CAP!$C$2:$D$212,2,FALSE),"")) -> 0322 - ESTRUTURAS, HOSPITAIS, CLÍNICAS | AN3: =IF(AL3="","",IFERROR(VLOOKUP(AL3,CODEBOOK_CAP!$C$2:$E$212,3,FALSE),"")) -> Observações relacionadas as estruturas do sistema de saúde, como a construção de hospitais, postos de saúde, construção de maternidades, laboratórios, centros de saúde avançado, SAMU, Ambulâncias, UTI Móveis, leitos, compra de equipamentos médicos, Raio X, Ultrasom, equipamentos de diálise, capacidade de atendimento, estrutura e funcionamento de equipamentos públicos de saúde. | AO3: 1 | AP3: rua Borborema n. 1325, bairro Cachoeirinha | AQ3: 1 | AR3: 1 | AS3: Centro de Saúde Cachoeirinha, estabelecido na rua Borborema n. 1325, bairro Cachoeirinha; | AT3: 0 | AV3: 1 | AW3: CONSTRUTORA CAMPOS E FILHOS LTDA | AX3: Pendente
A4: 2022_ALVARO_DAMIAO_292_01 | B4: 2022 | C4: 4276 | D4: emendas_conslidadas(1).xlsx | E4: 2022_ALVARO_DAMIAO | F4: 292 | G4: Concluída | H4: Álvaro Damião | I4: DEM | J4: Destinação de recursos para o Instituto Cultural, Esportivo e Social Bacana Demais - ICESBADE, CNPJ: 20.997.880/0001-20, para a execução de atividades socioassistenciais, de acordo com o disposto na Lei Federal nº 8.742/93, em consonância com a referida inscrição no Conselho Municipal de Assistência Social de Belo Horizonte – CMAS-BH; | K4: 1011.1100.08.244.113.2.804.339039 | L4: 1011 | M4: FUNDO MUNICIPAL DE ASSISTÊNCIA SOCIAL | N4: 08 | O4: Assistência Social | P4: 244 | Q4: Assistência Comunitária | R4: 0113 | S4: Aprimoramento da Gestão do SUAS | T4: 2804 | U4: Gestão dos Equipamentos e Promoção Social | V4: 339039 | W4: Despesa corrente | X4: Outras despesas correntes | Z4: SMASDH | AA4: 640000 | AB4: 640000 | AC4: 640000 | AD4: 640000 | AE4: INSTITUTO CULTURAL ESPORTIVO E SOCIAL BACANA DEMAIS ICESBADE | AF4: 20997880000120 | AG4: Associações Diversas | AH4: Associações Diversas | AJ4: 0 | AK4: 0 | AL4: 1300 | AM4: =IF(AL4="","",AL4&" - "&IFERROR(VLOOKUP(AL4,CODEBOOK_CAP!$C$2:$D$212,2,FALSE),"")) -> 1300 - GERAL | AN4: =IF(AL4="","",IFERROR(VLOOKUP(AL4,CODEBOOK_CAP!$C$2:$E$212,3,FALSE),"")) -> Observações gerais sobre políticas sociais que envolvam mais de um casos dos subtópicos, políticas gerais de assistência social, welfare state, bem estar social, Ministérios e orcamentos como do Desenvolvimento social e combate e fome, desenvolvimento social, sistemas de gestão de políticas de assistencia, CAD UNICO, cadastros, sistemas computacionais para desenvolvimento de ações e políticas sociais, BPC - Benefício de Prestação Continuada geral para idosos e deficientes. NÃO CONFUNDIR POLÍTICAS SOCIAIS COM POLÍTICA DE EMPREGO E RENDA. Todas as questões, direitos, políticas que se relacionem com o TRABALHO como contrapartida, estão no código 5. Maternidade, Paternidade aposentadoria por tempo de serviço, INSS. | AO4: 0 | AQ4: 0 | AR4: 0 | AT4: 0 | AV4: 1 | AW4: INSTITUTO CULTURAL ESPORTIVO E SOCIAL BACANA DEMAIS ICESBADE | AX4: Pendente
A5: 2022_ALVARO_DAMIAO_293_01 | B5: 2022 | C5: 4277 | D5: emendas_conslidadas(1).xlsx | E5: 2022_ALVARO_DAMIAO | F5: 293 | G5: Concluída | H5: Álvaro Damião | I5: DEM | J5: Ao reforço à dotação orçamentária para reforma e manutenção do Centro de Saúde Efigênia Murta Figueiredo, localizado na Rua Serra do Cipó, 170, bairro Conjunto Ribeiro de Abreu; | K5: 2302.0400.10.122.117.1.216.449051 | L5: 2302 | M5: FUNDO MUNICIPAL DE SAÚDE | N5: 10 | O5: Saúde | P5: 122 | Q5: Administração Geral | R5: 0117 | S5: Gestão do SUS | T5: 1216 | U5: Construção, Ampliação e Reforma de Unidades de Saúde | V5: 449051 | W5: Despesa de capital | X5: Investimentos | Z5: SMSA | AA5: 250000 | AB5: 250000 | AC5: 151265.75 | AD5: 151265.75 | AE5: CONSTRUTORA CAMPOS E FILHOS LTDA | AF5: 15862332000152 | AG5: - | AH5: - | AI5: - | AJ5: 1 | AK5: 1 | AL5: 0322 | AM5: =IF(AL5="","",AL5&" - "&IFERROR(VLOOKUP(AL5,CODEBOOK_CAP!$C$2:$D$212,2,FALSE),"")) -> 0322 - ESTRUTURAS, HOSPITAIS, CLÍNICAS | AN5: =IF(AL5="","",IFERROR(VLOOKUP(AL5,CODEBOOK_CAP!$C$2:$E$212,3,FALSE),"")) -> Observações relacionadas as estruturas do sistema de saúde, como a construção de hospitais, postos de saúde, construção de maternidades, laboratórios, centros de saúde avançado, SAMU, Ambulâncias, UTI Móveis, leitos, compra de equipamentos médicos, Raio X, Ultrasom, equipamentos de diálise, capacidade de atendimento, estrutura e funcionamento de equipamentos públicos de saúde. | AO5: 1 | AP5: Rua Serra do Cipó, 170, bairro Conjunto Ribeiro de Abreu | AQ5: 1 | AR5: 1 | AS5: Centro de Saúde Efigênia Murta Figueiredo, localizado na Rua Serra do Cipó, 170, bairro Conjunto Ribeiro de Abreu; | AT5: 0 | AV5: 1 | AW5: CONSTRUTORA CAMPOS E FILHOS LTDA | AX5: Pendente
A6: 2022_ALVARO_DAMIAO_294_01 | B6: 2022 | C6: 4278 | D6: emendas_conslidadas(1).xlsx | E6: 2022_ALVARO_DAMIAO | F6: 294 | G6: Concluída | H6: Álvaro Damião | I6: DEM | J6: Ao recapeamento asfáltico no bairro Concórdia; | K6: 2700.1100.15.451.062.1.230.449051 | L6: 2700 | M6: SECRETARIA MUNICIPAL DE OBRAS E INFRAESTRUTURA | N6: 15 | O6: Urbanismo | P6: 451 | Q6: Infra-Estrutura Urbana | R6: 0062 | S6: Gestão do Sistema Viário Municipal | T6: 1230 | U6: Implantação e Reconstrução de Vias Públicas | V6: 449051 | W6: Despesa de capital | X6: Investimentos | Z6: SMOBI | AA6: 515000 | AB6: 515000 | AC6: 0 | AD6: 0 | AE6: LM CONSTRUCOES E PAVIMENTACOES LTDA | AF6: 1631484000130 | AG6: - | AH6: - | AI6: - | AJ6: 0 | AK6: 0 | AL6: 1002 | AM6: =IF(AL6="","",AL6&" - "&IFERROR(VLOOKUP(AL6,CODEBOOK_CAP!$C$2:$D$212,2,FALSE),"")) -> 1002 - CARROS, TRÂNSITO, CONSTRUÇÃO E MANUTENÇÃO DE RUAS E ESTRADAS | AN6: =IF(AL6="","",IFERROR(VLOOKUP(AL6,CODEBOOK_CAP!$C$2:$E$212,3,FALSE),"")) -> Construção, manutenção de ruas, avenidas, estradas. BRs, pedágios, privatizações, concessinárias, segurança nas estradas, leis de trânsito relacionadas a via, limite de velocidade, sinalização, recapeamento de ruas, pavimentação estradas de terra, não pavimentadas, acidentes e camapanhas de prevencao contra acidentes de transito. Observações sobre regulação de transportes não públicos de carros, veículos de passeio, uber, taxi, transporte de cargas terrestre, frete, trânsito em vias públicas, regulamentação de tipos de carteira de motorista, especificações para caminhoneiros, testes e exames de habilitação, exigências de carteira de habilitação, obrigatoriedade de itens em veículos (extintor, kit primeiros socorros, airbag, freios abs) Quando tratar de grandes obras de construções de rodovias, olhar codigo 1010 para ver qual se encaixa melhor. | AO6: 1 | AP6: bairro Concórdia | AQ6: 0 | AR6: 0 | AT6: 0 | AV6: 1 | AW6: LM CONSTRUCOES E PAVIMENTACOES LTDA | AX6: Pendente
A7: 2022_ALVARO_DAMIAO_295_01 | B7: 2022 | C7: 4279 | D7: emendas_conslidadas(1).xlsx | E7: 2022_ALVARO_DAMIAO | F7: 295 | G7: Cancelada | H7: Álvaro Damião | I7: DEM | J7: - | K7: - | Z7: Cancelada | AA7: 85000 | AE7: - | AF7: - | AG7: - | AH7: - | AI7: - | AM7: =IF(AL7="","",AL7&" - "&IFERROR(VLOOKUP(AL7,CODEBOOK_CAP!$C$2:$D$212,2,FALSE),"")) | AN7: =IF(AL7="","",IFERROR(VLOOKUP(AL7,CODEBOOK_CAP!$C$2:$E$212,3,FALSE),"")) | AX7: Pendente
A8: 2022_ALVARO_DAMIAO_296_01 | B8: 2022 | C8: 4280 | D8: emendas_conslidadas(1).xlsx | E8: 2022_ALVARO_DAMIAO | F8: 296 | G8: Cancelada | H8: Álvaro Damião | I8: DEM | J8: - | K8: - | Z8: Cancelada | AA8: 175000 | AE8: - | AF8: - | AG8: - | AH8: - | AI8: - | AM8: =IF(AL8="","",AL8&" - "&IFERROR(VLOOKUP(AL8,CODEBOOK_CAP!$C$2:$D$212,2,FALSE),"")) | AN8: =IF(AL8="","",IFERROR(VLOOKUP(AL8,CODEBOOK_CAP!$C$2:$E$212,3,FALSE),"")) | AX8: Pendente
A9: 2022_ALVARO_DAMIAO_297_01 | B9: 2022 | C9: 4281 | D9: emendas_conslidadas(1).xlsx | E9: 2022_ALVARO_DAMIAO | F9: 297 | G9: Cancelada | H9: Álvaro Damião | I9: DEM | J9: Ao recapeamento asfáltico da Rua Saquarema, no trecho situado entre as ruas Jequiriçá e Juparanã, com extensão aproximada de 100 m (cem metros) com 5 cm (cinco centímetros) de espessura, no Bairro Concórdia; | K9: - | Z9: Cancelada | AA9: 85000 | AE9: - | AF9: - | AG9: - | AH9: - | AI9: - | AK9: 0 | AL9: 1002 | AM9: =IF(AL9="","",AL9&" - "&IFERROR(VLOOKUP(AL9,CODEBOOK_CAP!$C$2:$D$212,2,FALSE),"")) -> 1002 - CARROS, TRÂNSITO, CONSTRUÇÃO E MANUTENÇÃO DE RUAS E ESTRADAS | AN9: =IF(AL9="","",IFERROR(VLOOKUP(AL9,CODEBOOK_CAP!$C$2:$E$212,3,FALSE),"")) -> Construção, manutenção de ruas, avenidas, estradas. BRs, pedágios, privatizações, concessinárias, segurança nas estradas, leis de trânsito relacionadas a via, limite de velocidade, sinalização, recapeamento de ruas, pavimentação estradas de terra, não pavimentadas, acidentes e camapanhas de prevencao contra acidentes de transito. Observações sobre regulação de transportes não públicos de carros, veículos de passeio, uber, taxi, transporte de cargas terrestre, frete, trânsito em vias públicas, regulamentação de tipos de carteira de motorista, especificações para caminhoneiros, testes e exames de habilitação, exigências de carteira de habilitação, obrigatoriedade de itens em veículos (extintor, kit primeiros socorros, airbag, freios abs) Quando tratar de grandes obras de construções de rodovias, olhar codigo 1010 para ver qual se encaixa melhor. | AO9: 1 | AP9: Rua Saquarema, no trecho situado entre as ruas Jequiriçá e Juparanã, com extensão aproximada de 100 m (cem metros) com 5 cm (cinco centímetros) de espessura, no Bairro Concórdia; | AQ9: 1 | AR9: 1 | AS9: Rua Saquarema, no trecho situado entre as ruas Jequiriçá e Juparanã, com extensão aproximada de 100 m (cem metros) com 5 cm (cinco centímetros) de espessura, no Bairro Concórdia; | AT9: 0 | AX9: Pendente
A10: 2022_ALVARO_DAMIAO_298_01 | B10: 2022 | C10: 4282 | D10: emendas_conslidadas(1).xlsx | E10: 2022_ALVARO_DAMIAO | F10: 298 | G10: Cancelada | H10: Álvaro Damião | I10: DEM | J10: Ao recapeamento asfáltico da Rua Jacuípe, no trecho situado entre as ruas Itaquera e Itapeva, com extensão aproximada de 100 m (cem metros) e 5 cm (cinco centímetros) de espessura, no Bairro Concórdia; | K10: - | Z10: Cancelada | AA10: 85000 | AE10: - | AF10: - | AG10: - | AH10: - | AI10: - | AK10: 0 | AL10: 1002 | AM10: =IF(AL10="","",AL10&" - "&IFERROR(VLOOKUP(AL10,CODEBOOK_CAP!$C$2:$D$212,2,FALSE),"")) -> 1002 - CARROS, TRÂNSITO, CONSTRUÇÃO E MANUTENÇÃO DE RUAS E ESTRADAS | AN10: =IF(AL10="","",IFERROR(VLOOKUP(AL10,CODEBOOK_CAP!$C$2:$E$212,3,FALSE),"")) -> Construção, manutenção de ruas, avenidas, estradas. BRs, pedágios, privatizações, concessinárias, segurança nas estradas, leis de trânsito relacionadas a via, limite de velocidade, sinalização, recapeamento de ruas, pavimentação estradas de terra, não pavimentadas, acidentes e camapanhas de prevencao contra acidentes de transito. Observações sobre regulação de transportes não públicos de carros, veículos de passeio, uber, taxi, transporte de cargas terrestre, frete, trânsito em vias públicas, regulamentação de tipos de carteira de motorista, especificações para caminhoneiros, testes e exames de habilitação, exigências de carteira de habilitação, obrigatoriedade de itens em veículos (extintor, kit primeiros socorros, airbag, freios abs) Quando tratar de grandes obras de construções de rodovias, olhar codigo 1010 para ver qual se encaixa melhor. | AO10: 1 | AP10: Rua Jacuípe, no trecho situado entre as ruas Itaquera e Itapeva, com extensão aproximada de 100 m (cem metros) e 5 cm (cinco centímetros) de espessura, no Bairro Concórdia; | AQ10: 1 | AR10: 1 | AS10: Rua Jacuípe, no trecho situado entre as ruas Itaquera e Itapeva, com extensão aproximada de 100 m (cem metros) e 5 cm (cinco centímetros) de espessura, no Bairro Concórdia; | AT10: 0 | AX10: Pendente
A11: 2022_ALVARO_DAMIAO_299_01 | B11: 2022 | C11: 4283 | D11: emendas_conslidadas(1).xlsx | E11: 2022_ALVARO_DAMIAO | F11: 299 | G11: Concluída | H11: Álvaro Damião | I11: DEM | J11: Ao reforço de dotação orçamentária da Empresa Municipal de Turismo de Belo Horizonte S/A visando o desenvolvimento econômico do turismo e o fomento do carnaval em Belo Horizonte; | K11: 2805.1100.23.695.086.2.629.339039 | L11: 2805 | M11: EMPRESA MUNICIPAL DE TURISMO DE BELO HORIZONTE S/A | N11: 23 | O11: Comércio e Serviços | P11: 695 | Q11: Turismo | R11: 0086 | S11: Fomento ao Turismo de Lazer, Eventos e Negócios | T11: 2629 | U11: Desenvolvimento e Promoção do Turismo | V11: 339039 | W11: Despesa corrente | X11: Outras despesas correntes | Z11: BELOTUR | AA11: 129000 | AB11: 129000 | AC11: 129000 | AD11: 129000 | AE11: LOCABET MAQUINAS E EQUIPAMENTOS LTDA | AF11: 3778642000104 | AG11: PBH | AH11: Município de Belo Horizonte | AI11: 18715383000140 | AJ11: 0 | AK11: 0 | AL11: 1524 | AM11: =IF(AL11="","",AL11&" - "&IFERROR(VLOOKUP(AL11,CODEBOOK_CAP!$C$2:$D$212,2,FALSE),"")) -> 1524 - TURISMO | AN11: =IF(AL11="","",IFERROR(VLOOKUP(AL11,CODEBOOK_CAP!$C$2:$E$212,3,FALSE),"")) -> Assuntos que se relacionam com a política de desenvolvimento de turismo, cidades turisticas, obras turisticas, assuntos relacioandos a incentismo aos turismo, apoios setoriais para promocao de turismo, visto de turismo, promoção do turismo brasileiro. | AO11: 0 | AQ11: 0 | AR11: 0 | AT11: 0 | AX11: Pendente
A12: 2022_BELLA_GONCALVES_607_01 | B12: 2022 | C12: 4548 | D12: emendas_conslidadas(1).xlsx | E12: 2022_BELLA_GONCALVES | F12: 607 | G12: Concluída | H12: Bella Gonçalves | I12: PSOL | J12: Ao reforço da subação 0001 - Política Municipal Cultura Viva, inserida na ação 2930 - Promoção e democratização do acesso à cultura e no programa 0154 - Promoção e Acesso às Artes e à Cultura; | K12: 3100.13.392.154.2930.339039 | L12: 3100 | M12: SECRETARIA MUNICIPAL DE CULTURA | N12: 13 | O12: Cultura | P12: 392 | Q12: Difusão Cultural | R12: 0154 | S12: Promoção e Acesso às Artes e à Cultura | T12: 2930 | U12: PROMOÇÃO E DEMOCRATIZAÇÃO DO ACESSO À CULTURA | V12: 339039 | W12: Despesa corrente | X12: Outras despesas correntes | Z12: SMC | AA12: 300000 | AB12: 300000 | AC12: 300000 | AD12: 300000 | AE12: ASSOCIACAO MOVIMENTO DE TEATRO DE GRUPO DE MINAS GERAIS ASSOCIACAO DE RESISTENCIA CULTURAL DA COMUNIDADE QUILOMBOLA MANZO NGUNZO KAIANGO ASSOCIACAO DE RESISTENCIA CULTURAL DA COMUNIDADE QUILOMBOLA MANZO NGUNZO KAIANGO | AF12: 00784491000109 07981042000108 07981042000108 | AG12: PBH | AH12: Município de Belo Horizonte | AI12: 18715383000140 | AJ12: 0 | AK12: 0 | AL12: 2300 | AM12: =IF(AL12="","",AL12&" - "&IFERROR(VLOOKUP(AL12,CODEBOOK_CAP!$C$2:$D$212,2,FALSE),"")) -> 2300 - GERAL | AN12: =IF(AL12="","",IFERROR(VLOOKUP(AL12,CODEBOOK_CAP!$C$2:$E$212,3,FALSE),"")) -> Observações relativas as políticas de cultura, Lei rouanet, patrimônio cultural, imaterial, políticas de artes, incentivos fiscais para artes, promoção de eventos culturais, amostras, teatro, dança, artes plásticas, artes visuais, museus, galerias públicas, idioma, lingua portuguesa. Grandes eventos esportivos, Copa do Mundo, Olimpiadas, Esporte e Lazer. | AO12: 0 | AQ12: 0 | AR12: 0 | AT12: 0 | AX12: Pendente | BB12: cultura
A13: 2022_BELLA_GONCALVES_634_01 | B13: 2022 | C13: 4573 | D13: emendas_conslidadas(1).xlsx | E13: 2022_BELLA_GONCALVES | F13: 634 | G13: Concluída | H13: Bella Gonçalves | I13: PSOL | J13: Ao reforço da subação 0006 atendimento da população na rede de saúde mental; ação 2891 rede especializada; programa 0114 Atenção secundária e terciária à saúde; | K13: 2302.10.302.114.2891.339039 | L13: 2302 | M13: FUNDO MUNICIPAL DE SAÚDE | N13: 10 | O13: Saúde | P13: 302 | Q13: Assistência Hospitalar e Ambulatorial | R13: 0114 | S13: Atenção Secundária e Terciária à Saúde | T13: 2891 | U13: Rede Especializada | V13: 339039 | W13: Despesa corrente | X13: Outras despesas correntes | Z13: SMSA | AA13: 1064319 | AB13: 1064319 | AC13: 1064319 | AD13: 1064319 | AE13: NUTRIVIP ALIMENTACAO LTDA. ORGANIZACOES PAULA E CASTRO LTDA ASSOCIACAO DE TRABALHO E PRODUCAO SOLIDARIA - SURICATO MOVIMENTO DE PROMOCAO E ASSISTENCIA SOCIAL SOPAO MINEIRO CARITAS BRASILEIRA CARITAS BRASILEIRA CONSORCIO OPERACIONAL DO TRANSPORTE COLETIVO DE PASSAGEIROS POR ONIBUS DO MUNICIPIO DE BELO HORIZONTE CONSORCIO OPERACIONAL DO TRANSPORTE COLETIVO DE PASSAGEIROS POR ONIBUS DO MUNICIPIO DE BELO HORIZONTE | AF13: 09487591000571 01940433000270 08808991000145 38731899000195 33654419000892 33654419000892 04398505000107 04398505000107 | AG13: PBH | AH13: Município de Belo Horizonte | AI13: 18715383000140 | AJ13: 1 | AK13: 1 | AL13: 0333 | AM13: =IF(AL13="","",AL13&" - "&IFERROR(VLOOKUP(AL13,CODEBOOK_CAP!$C$2:$D$212,2,FALSE),"")) -> 0333 - SAÚDE MENTAL | AN13: =IF(AL13="","",IFERROR(VLOOKUP(AL13,CODEBOOK_CAP!$C$2:$E$212,3,FALSE),"")) -> Serviços de atendimento a saúde mental e psico-social. CAPS, Controle de qualidade mental, esquizofrenia, bipolaridade, transtornos mentais, ansiedade, alucinançao, depressão, suicídio, CVV, atendimento psicológico e psiquiátrico, sanatório, manicomio. Não confundir com dependências de alcool (342) e drogas (343) | AO13: 0 | AQ13: 0 | AR13: 0 | AT13: 0 | AX13: Pendente
A14: 2022_BELLA_GONCALVES_674_01 | B14: 2022 | C14: 4612 | D14: emendas_conslidadas(1).xlsx | E14: 2022_BELLA_GONCALVES | F14: 674 | G14: Concluída | H14: Bella Gonçalves | I14: PSOL | J14: Ao reforço de dotação orçamentária na subação 004 (Implantação e agricultura em Unidades Produtivas Coletivas/Comunitárias), ação 2121 (Fortalecimento da Produção da Agricultura Urbana Agroecológica), 308 (BH Cidade Sustentável: Mobilizar, Educar e Cultivar Alimentação Saudável) para implantação e manutenção de Sistemas de produção agroecológicos nos 5 Territórios Quilombolas de Belo Horizonte: Quilombo Mangueiras, Quilombo Luízes, Quilombo Manzo Ngunzo Kaiango e Quilombo Souza e Quilombo Matia; | K14: 1010.20.608.308.2121.339039 | L14: 1010 | M14: FUNDO MUNICIPAL DE SEGURANÇA ALIMENTAR E NUTRICIONAL | N14: 20 | O14: Agricultura | P14: 608 | Q14: Promoção da Produção Agropecuária | R14: 0308 | S14: BH Cidade Sustentável: Mobilizar, Educar e Cultivar Alimentação Saudável | T14: 2121 | U14: Fortalecimento da Produção da Agricultura Urbana Agroecológica | V14: 339039 | W14: Despesa corrente | X14: Outras despesas correntes | Z14: SMASDH | AA14: 200000 | AB14: 200000 | AC14: 200000 | AD14: 200000 | AE14: BAMBUZERIA CRUZEIRO DO SUL BAMBUZERIA CRUZEIRO DO SUL | AF14: 03211130000161 03211130000161 | AG14: PBH | AH14: Município de Belo Horizonte | AI14: 18715383000140 | AJ14: 0 | AK14: 0 | AL14: 2102 | AM14: =IF(AL14="","",AL14&" - "&IFERROR(VLOOKUP(AL14,CODEBOOK_CAP!$C$2:$D$212,2,FALSE),"")) -> 2102 - POPULAÇÕES TRADICIONAIS BRASILEIRAS - INDÍGENAS, QUILOMBOLAS, RIBEIRINHOS, SERINGUEIROS, CAIÇARAS | AN14: =IF(AL14="","",IFERROR(VLOOKUP(AL14,CODEBOOK_CAP!$C$2:$E$212,3,FALSE),"")) -> Todos os temas, de todas as políticas setoriais que envolvam populações tradicionais nativas brasileiras. Temas relacionados ao uso da terra por populações nativas como uso de terra por indígenas e reservas indígenas, quilombolas e populações ribeirinhas. Saude, educacao, assistencia, terras. Populações Nativas não se codifica em política setoria, mas sim aqui! | AO14: 1 | AP14: 5 Territórios Quilombolas de Belo Horizonte: Quilombo Mangueiras, Quilombo Luízes, Quilombo Manzo Ngunzo Kaiango e Quilombo Souza e Quilombo Matia | AQ14: 5 | AR14: 1 | AS14: 5 Territórios Quilombolas de Belo Horizonte: Quilombo Mangueiras, Quilombo Luízes, Quilombo Manzo Ngunzo Kaiango e Quilombo Souza e Quilombo Matia | AT14: 1 | AU14: quilombolas | AX14: Pendente
A15: 2022_BELLA_GONCALVES_684_01 | B15: 2022 | C15: 4617 | D15: emendas_conslidadas(1).xlsx | E15: 2022_BELLA_GONCALVES | F15: 684 | G15: Concluída | H15: Bella Gonçalves | I15: PSOL | J15: Ao reforço de dotação orçamentária para a subação 0004 - CENTRO DE EDUCAÇÃO AMBIENTAL DE INCLUSÃO PRODUTIVA VOLTADA PARA EMPREGOS VERDES; ação: 2913 - Capacitação e Conscientização Ambiental. promoção de sustentabilidade, educação ambiental; Programa 0307 - SUSTENTABILIDADE, EDUCAÇÃO AMBIENTAL E MODERNIZAÇÃO DA GESTÃO AMBIENTAL visando a gestão ambiental nos quilombos urbanos de Belo Horizonte; | K15: 2500.18.541.307.2913.339039 | L15: 2500 | M15: SECRETARIA MUNICIPAL DE MEIO AMBIENTE | N15: 18 | O15: Gestão Ambiental | P15: 541 | Q15: Preservação e Conservação Ambiental | R15: 0307 | S15: Sustentabilidade, Educação Ambiental e Modernização da Gestão Ambiental | T15: 2913 | U15: Capacitação e Conscientização Ambiental | V15: 339039 | W15: Despesa corrente | X15: Outras despesas correntes | Z15: SMMA | AA15: 500000 | AB15: 0 | AC15: 0 | AD15: 0 | AG15: PBH | AH15: Município de Belo Horizonte | AI15: 18715383000140 | AJ15: 0 | AK15: 0 | AL15: 2102 | AM15: =IF(AL15="","",AL15&" - "&IFERROR(VLOOKUP(AL15,CODEBOOK_CAP!$C$2:$D$212,2,FALSE),"")) -> 2102 - POPULAÇÕES TRADICIONAIS BRASILEIRAS - INDÍGENAS, QUILOMBOLAS, RIBEIRINHOS, SERINGUEIROS, CAIÇARAS | AN15: =IF(AL15="","",IFERROR(VLOOKUP(AL15,CODEBOOK_CAP!$C$2:$E$212,3,FALSE),"")) -> Todos os temas, de todas as políticas setoriais que envolvam populações tradicionais nativas brasileiras. Temas relacionados ao uso da terra por populações nativas como uso de terra por indígenas e reservas indígenas, quilombolas e populações ribeirinhas. Saude, educacao, assistencia, terras. Populações Nativas não se codifica em política setoria, mas sim aqui! | AO15: 0 | AQ15: 0 | AR15: 0 | AT15: 1 | AU15: quilombolas | AX15: Pendente
A16: 2022_BELLA_GONCALVES_730_01 | B16: 2022 | C16: 4663 | D16: emendas_conslidadas(1).xlsx | E16: 2022_BELLA_GONCALVES | F16: 730 | G16: Concluída | H16: Bella Gonçalves | I16: PSOL | J16: Ao reforço de dotação orçamentária para garantia do acesso ao direito de retificação do social para pessoas travestis e/ou transexuais; | K16: 1000.14.422.127.2928.339039 | L16: 1000 | M16: SECRETARIA MUNICIPAL DE ASSISTÊNCIA SOCIAL, SEGURANÇA ALIMENTAR E CIDADANIA | N16: 14 | O16: Direitos da Cidadania | P16: 422 | Q16: Direitos Individuais, Coletivos e Difusos | R16: 0127 | S16: Promoção e Defesa de Direitos Humanos e Cidadania | T16: 2928 | U16: Promoção, Proteção e Defesa das pessoas LGBT | V16: 339039 | W16: Despesa corrente | X16: Outras despesas correntes | Z16: SMASDH | AA16: 100000 | AB16: 40000 | AC16: 40000 | AD16: 40000 | AE16: INSTITUTO DE PROMOCAO SOCIAL E HUMANA DARCY RIBEIRO | AF16: 00794227000156 | AG16: PBH | AH16: Município de Belo Horizonte | AI16: 18715383000140 | AJ16: 0 | AK16: 0 | AL16: 0202 | AM16: =IF(AL16="","",AL16&" - "&IFERROR(VLOOKUP(AL16,CODEBOOK_CAP!$C$2:$D$212,2,FALSE),"")) -> 0202 - DISCRIMINAÇÃO POR GÊNERO OU ORIENTAÇÃO SEXUAL (MISOGINIA E HOMOFOBIA) | AN16: =IF(AL16="","",IFERROR(VLOOKUP(AL16,CODEBOOK_CAP!$C$2:$E$212,3,FALSE),"")) -> Políticas de promoção de igualdade de gênero e de igualdade de relações sociais relacionadas a gênero e orientação sexual. Misoginia, Homofobia, ataques homofóbicos, casamento homoafetivo, igualdade salarial para mulheres, igualdade de trabalho para mulheres, feminismo, Parada LGBT, LGBTQI, transexuais, homossexuais, bissexuais, travestis, relações de gênero com emprego ( tipos de posições, renda, promoção , salário) . VIOLÊNCIA DOMESTICA contra mulheres deve ser codificado em 1208 | AO16: 0 | AQ16: 0 | AR16: 0 | AT16: 1 | AU16: trans/travestis | AX16: Pendente
A17: 2022_BELLA_GONCALVES_746_01 | B17: 2022 | C17: 4676 | D17: emendas_conslidadas(1).xlsx | E17: 2022_BELLA_GONCALVES | F17: 746 | G17: Concluída | H17: Bella Gonçalves | I17: PSOL | J17: Ao reforço de dotação orçamentária para a Subação 0005 - PROMOÇÃO, PROTEÇÃO E DEFESA DE DIREITOS HUMANOS E CIDADANIA com foco em ações de formação, capacitação, serviços, cursos, programas, projetos e benefícios mitigadores de vulnerabilidade social para a população LGBTQl; | K17: 1019.14.422.127.2335.339036 | L17: 1019 | M17: FUNDO MUNICIPAL DE PROTEÇÃO E DEFESA DAS MINORIAS | N17: 14 | O17: Direitos da Cidadania | P17: 422 | Q17: Direitos Individuais, Coletivos e Difusos | R17: 0127 | S17: Promoção e Defesa de Direitos Humanos e Cidadania | T17: 2335 | U17: Gestão da Política de Direitos Humanos e de Cidadania | V17: 339036 | W17: Despesa corrente | X17: Outras despesas correntes | Z17: SMASDH | AA17: 100000 | AB17: 99400 | AC17: 99400 | AD17: 99400 | AE17: F ALVES DE QUEIROZ LTDA | AF17: 17599187000194 | AG17: PBH | AH17: Município de Belo Horizonte | AI17: 18715383000140 | AJ17: 0 | AK17: 0 | AL17: 0202 | AM17: =IF(AL17="","",AL17&" - "&IFERROR(VLOOKUP(AL17,CODEBOOK_CAP!$C$2:$D$212,2,FALSE),"")) -> 0202 - DISCRIMINAÇÃO POR GÊNERO OU ORIENTAÇÃO SEXUAL (MISOGINIA E HOMOFOBIA) | AN17: =IF(AL17="","",IFERROR(VLOOKUP(AL17,CODEBOOK_CAP!$C$2:$E$212,3,FALSE),"")) -> Políticas de promoção de igualdade de gênero e de igualdade de relações sociais relacionadas a gênero e orientação sexual. Misoginia, Homofobia, ataques homofóbicos, casamento homoafetivo, igualdade salarial para mulheres, igualdade de trabalho para mulheres, feminismo, Parada LGBT, LGBTQI, transexuais, homossexuais, bissexuais, travestis, relações de gênero com emprego ( tipos de posições, renda, promoção , salário) . VIOLÊNCIA DOMESTICA contra mulheres deve ser codificado em 1208 | AO17: 0 | AQ17: 0 | AR17: 0 | AT17: 1 | AU17: LGBT | AX17: Pendente
A18: 2022_BELLA_GONCALVES_747_01 | B18: 2022 | C18: 4677 | D18: emendas_conslidadas(1).xlsx | E18: 2022_BELLA_GONCALVES | F18: 747 | G18: Concluída | H18: Bella Gonçalves | I18: PSOL | J18: Ao reforço de dotação orçamentária da Subação 0005 - PROMOÇÃO, PROTEÇÃO E DEFESA DE DIREITOS HUMANOS E CIDADANIA com foco em ações de formação, capacitação, serviços, cursos, oficinas e projetos, a partir referências de notório saber popular, voltadas às minorias; | K18: 1019.14.422.127.2335.339036 | L18: 1019 | M18: FUNDO MUNICIPAL DE PROTEÇÃO E DEFESA DAS MINORIAS | N18: 14 | O18: Direitos da Cidadania | P18: 422 | Q18: Direitos Individuais, Coletivos e Difusos | R18: 0127 | S18: Promoção e Defesa de Direitos Humanos e Cidadania | T18: 2335 | U18: Gestão da Política de Direitos Humanos e de Cidadania | V18: 339036 | W18: Despesa corrente | X18: Outras despesas correntes | Z18: SMASDH | AA18: 89220 | AB18: 78900 | AC18: 77940 | AD18: 77940 | AE18: F ALVES DE QUEIROZ LTDA | AF18: 17599187000194 | AG18: PBH | AH18: Município de Belo Horizonte | AI18: 18715383000140 | AJ18: 0 | AK18: 0 | AL18: 0200 | AM18: =IF(AL18="","",AL18&" - "&IFERROR(VLOOKUP(AL18,CODEBOOK_CAP!$C$2:$D$212,2,FALSE),"")) -> 0200 - GERAL | AN18: =IF(AL18="","",IFERROR(VLOOKUP(AL18,CODEBOOK_CAP!$C$2:$E$212,3,FALSE),"")) -> Quando há combinação de diversos assuntos relacionado aos direitos civis, liberdade e atores indetificados como minorias. Questões gerais e amplas tais como Comissões, violações de direitos sem especificação, criação ou modificação ou atuação de Ministérios, departamentos ou instituições gerais, direito a propriedade privada, violação e atentados contra direitos civis em geral, cotas gerais (quando existem várias linhas, nao apenas racial), coberturas jornalisticas, estatisticas sobre minorias e sobre direitos básicos, discriminações e preconceito gerais sobre múltiplos aspectos. Quando o tema abordado for sobre uma única parte (sexo ou raça ou idade ou deficiência, codificar nos subcódigos específicos. Geral somente quando há combinação de fatores. Quando aparecer DIREITOS HUMANOS e assuntos de direito civil internacional, codificar em 1925. | AO18: 0 | AQ18: 0 | AR18: 0 | AT18: 0 | AX18: Pendente
A19: 2022_BELLA_GONCALVES_860_01 | B19: 2022 | C19: 4781 | D19: emendas_conslidadas(1).xlsx | E19: 2022_BELLA_GONCALVES | F19: 860 | G19: Concluída | H19: Bella Gonçalves | I19: PSOL | J19: Ao reforço de dotação do projeto Arte de Saúde da Rede de Saúde Mental; | K19: 2302.10.302.114.2891.335043 | L19: 2302 | M19: FUNDO MUNICIPAL DE SAÚDE | N19: 10 | O19: Saúde | P19: 302 | Q19: Assistência Hospitalar e Ambulatorial | R19: 0114 | S19: Atenção Secundária e Terciária à Saúde | T19: 2891 | U19: Rede Especializada | V19: 335043 | W19: Despesa corrente | X19: Outras despesas correntes | Z19: SMSA | AA19: 224901 | AB19: 224901 | AC19: 224901 | AD19: 224901 | AE19: CARITAS BRASILEIRA | AF19: 33654419000892 | AG19: PBH | AH19: Município de Belo Horizonte | AI19: 18715383000140 | AJ19: 1 | AK19: 1 | AL19: 0333 | AM19: =IF(AL19="","",AL19&" - "&IFERROR(VLOOKUP(AL19,CODEBOOK_CAP!$C$2:$D$212,2,FALSE),"")) -> 0333 - SAÚDE MENTAL | AN19: =IF(AL19="","",IFERROR(VLOOKUP(AL19,CODEBOOK_CAP!$C$2:$E$212,3,FALSE),"")) -> Serviços de atendimento a saúde mental e psico-social. CAPS, Controle de qualidade mental, esquizofrenia, bipolaridade, transtornos mentais, ansiedade, alucinançao, depressão, suicídio, CVV, atendimento psicológico e psiquiátrico, sanatório, manicomio. Não confundir com dependências de alcool (342) e drogas (343) | AO19: 0 | AQ19: 0 | AR19: 0 | AT19: 0 | AX19: Pendente
A20: 2022_BIM_DA_AMBULANCIA_780_01 | B20: 2022 | C20: 4708 | D20: emendas_conslidadas(1).xlsx | E20: 2022_BIM_DA_AMBULANCIA | F20: 780 | G20: Concluída | H20: Bim da Ambulância | I20: PSD | J20: Destinação de recursos para a Associação Mineira de Educação Continuada - ASMEC, CNPJ: 05.263.848/0001-27, para a execução de atividades socioassistenciais, de acordo com o disposto na Lei Federal nº 8.742/93, em consonância com a referida inscrição no Conselho Municipal de Assistência Social de Belo Horizonte – CMAS-BH; | K20: 1011.08.244.113.2804.339039 | L20: 1011 | M20: FUNDO MUNICIPAL DE ASSISTÊNCIA SOCIAL | N20: 08 | O20: Assistência Social | P20: 244 | Q20: Assistência Comunitária | R20: 0113 | S20: Aprimoramento da Gestão do SUAS | T20: 2804 | U20: Gestão dos Equipamentos e Promoção Social | V20: 339039 | W20: Despesa corrente | X20: Outras despesas correntes | Z20: SMASDH | AA20: 644610 | AB20: 644610 | AC20: 644610 | AD20: 644610 | AE20: ASSOCIACAO MINEIRA DE EDUCACAO CONTINUADA ASMEC ASSOCIACAO MINEIRA DE EDUCACAO CONTINUADA ASMEC | AF20: 05263848000127 05263848000127 | AG20: Associações Diversas | AH20: Associações Diversas | AJ20: 0 | AK20: 0 | AL20: 1300 | AM20: =IF(AL20="","",AL20&" - "&IFERROR(VLOOKUP(AL20,CODEBOOK_CAP!$C$2:$D$212,2,FALSE),"")) -> 1300 - GERAL | AN20: =IF(AL20="","",IFERROR(VLOOKUP(AL20,CODEBOOK_CAP!$C$2:$E$212,3,FALSE),"")) -> Observações gerais sobre políticas sociais que envolvam mais de um casos dos subtópicos, políticas gerais de assistência social, welfare state, bem estar social, Ministérios e orcamentos como do Desenvolvimento social e combate e fome, desenvolvimento social, sistemas de gestão de políticas de assistencia, CAD UNICO, cadastros, sistemas computacionais para desenvolvimento de ações e políticas sociais, BPC - Benefício de Prestação Continuada geral para idosos e deficientes. NÃO CONFUNDIR POLÍTICAS SOCIAIS COM POLÍTICA DE EMPREGO E RENDA. Todas as questões, direitos, políticas que se relacionem com o TRABALHO como contrapartida, estão no código 5. Maternidade, Paternidade aposentadoria por tempo de serviço, INSS. | AO20: 0 | AQ20: 0 | AR20: 0 | AT20: 1 | AU20: criancas e adolescentes | AX20: Pendente
A21: 2022_BIM_DA_AMBULANCIA_788_01 | B21: 2022 | C21: 4716 | D21: emendas_conslidadas(1).xlsx | E21: 2022_BIM_DA_AMBULANCIA | F21: 788 | G21: Impedimento Técnico | H21: Bim da Ambulância | I21: PSD | J21: Reforço à dotação para reforma do Campo de Futebol Milan, localizado na Rua Flávio Sampaio, 408, no bairro Serra Verde; | K21: - | Z21: Impedimento Técnico | AA21: 217000 | AE21: - | AG21: PBH | AH21: Município de Belo Horizonte | AI21: 18715383000140 | AJ21: 0 | AK21: 0 | AL21: 2300 | AM21: =IF(AL21="","",AL21&" - "&IFERROR(VLOOKUP(AL21,CODEBOOK_CAP!$C$2:$D$212,2,FALSE),"")) -> 2300 - GERAL | AN21: =IF(AL21="","",IFERROR(VLOOKUP(AL21,CODEBOOK_CAP!$C$2:$E$212,3,FALSE),"")) -> Observações relativas as políticas de cultura, Lei rouanet, patrimônio cultural, imaterial, políticas de artes, incentivos fiscais para artes, promoção de eventos culturais, amostras, teatro, dança, artes plásticas, artes visuais, museus, galerias públicas, idioma, lingua portuguesa. Grandes eventos esportivos, Copa do Mundo, Olimpiadas, Esporte e Lazer. | AO21: 1 | AP21: Rua Flávio Sampaio, 408, no bairro Serra Verde | AQ21: 1 | AR21: 1 | AS21: Campo de Futebol Milan, localizado na Rua Flávio Sampaio, 408, no bairro Serra Verde | AT21: 0 | AX21: Pendente | BB21: esporte e lazer
A22: 2022_BIM_DA_AMBULANCIA_789_01 | B22: 2022 | C22: 4717 | D22: emendas_conslidadas(1).xlsx | E22: 2022_BIM_DA_AMBULANCIA | F22: 789 | G22: Cancelada | H22: Bim da Ambulância | I22: PSD | J22: Reforço à dotação para reforma do Campo no bairro Serra Verde, localizado na Rua Guido Leão, 501 no bairro Serra Verde; | K22: - | Z22: Cancelada | AA22: 217000 | AE22: - | AF22: - | AG22: PBH | AH22: Município de Belo Horizonte | AI22: 18715383000140 | AJ22: 0 | AK22: 0 | AL22: 2300 | AM22: =IF(AL22="","",AL22&" - "&IFERROR(VLOOKUP(AL22,CODEBOOK_CAP!$C$2:$D$212,2,FALSE),"")) -> 2300 - GERAL | AN22: =IF(AL22="","",IFERROR(VLOOKUP(AL22,CODEBOOK_CAP!$C$2:$E$212,3,FALSE),"")) -> Observações relativas as políticas de cultura, Lei rouanet, patrimônio cultural, imaterial, políticas de artes, incentivos fiscais para artes, promoção de eventos culturais, amostras, teatro, dança, artes plásticas, artes visuais, museus, galerias públicas, idioma, lingua portuguesa. Grandes eventos esportivos, Copa do Mundo, Olimpiadas, Esporte e Lazer. | AO22: 1 | AP22: Rua Guido Leão, 501 no bairro Serra Verde; | AQ22: 1 | AR22: 1 | AS22: Campo no bairro Serra Verde, localizado na Rua Guido Leão, 501 no bairro Serra Verde; | AT22: 0 | AX22: Pendente | BB22: esporte e lazer
A23: 2022_BIM_DA_AMBULANCIA_853_01 | B23: 2022 | C23: 4775 | D23: emendas_conslidadas(1).xlsx | E23: 2022_BIM_DA_AMBULANCIA | F23: 853 | G23: Concluída | H23: Bim da Ambulância | I23: PSD | J23: Aquisição de kit EPI para a guarda municipal com destinação de R$66.000 segundo subação 0001 da ação 2802; | K23: 2100.06.122.109.2802.449052 | L23: 2100 | M23: SECRETARIA MUNICIPAL DE SEGURANÇA E PREVENÇÃO | N23: 06 | O23: Segurança Pública | P23: 122 | Q23: Administração Geral | R23: 0109 | S23: Operacionalização dos serviços de segurança | T23: 2802 | U23: Gestão da Política de Segurança e Prevenção | V23: 449052 | W23: Despesa de capital | X23: Investimentos | Z23: SMSP | AA23: 66000 | AB23: 65039 | AC23: 0 | AD23: 65039 | AE23: O. FILIZZOLA CIA. LTDA. EPP | AF23: 61182424000109 | AG23: - | AH23: - | AI23: - | AJ23: 0 | AK23: 0 | AL23: 1201 | AM23: =IF(AL23="","",AL23&" - "&IFERROR(VLOOKUP(AL23,CODEBOOK_CAP!$C$2:$D$212,2,FALSE),"")) -> 1201 - POLÍCIA, AGENCIAS E INSTITUIÇÕES - LEI E CRIMES | AN23: =IF(AL23="","",IFERROR(VLOOKUP(AL23,CODEBOOK_CAP!$C$2:$E$212,3,FALSE),"")) -> Questões relacionadas aos atores, intituições, agencias e agentes que atuam em questões relacionadas a justiça, lei, crime e violência. Servicos e instituições de apoio civil. Assuntos relacionados a atuação de Bombeiros, socorristas, guarda floresta, guarda costeira e proteção civil. Ministério Público, Ministério da Justiça, Polícia Federal, Tribunal de Contas, inteligência, proteção a vítimas, delação premiada, sistemas e banco de dados de justiça, computação vinculada a sistemas de combate a crimes e fraudes. Aqui a observação é sobre as INSTITUIÇÕES EM SI, e não sobre o assunto do qual ela trata, Os assuntos estão nos próximos sub-códigos | AO23: 0 | AQ23: 0 | AR23: 0 | AT23: 0 | AX23: Pendente
A24: 2022_BRAULIO_LARA_741_01 | B24: 2022 | C24: 4671 | D24: emendas_conslidadas(1).xlsx | E24: 2022_BRAULIO_LARA | F24: 741 | G24: Concluída | H24: Braulio Lara | I24: NOVO | J24: Ao reforço de dotação orçamentária para estudos, projetos e implantação de acessos e/ou outras benfeitorias no bairro Buritis, em especial, na Rua Elza Beatriz de Araújo, que interliga à Rua Tereza Mota Valadares com a Rua Maria Heilbuth Surette; Rua Márcio Maia Ferreira, que interliga à Av. Professor Mário Werneck com a Rua Eli Seabra Filho; e Rua VDP3981, que interliga a Rua Deputado Sebastião Nascimento com a Rua Deputado Fábio Vasconcelos; e estudos, projetos e implantação de pista de Skate na Praça Moisés Kalil, dentre outros; | K24: -2700.15.451.233.1208.449051 | L24: 2700 | M24: SECRETARIA MUNICIPAL DE OBRAS E INFRAESTRUTURA | N24: 15 | O24: Urbanismo | P24: 451 | Q24: Infra-Estrutura Urbana | R24: 0233 | S24: Manutenção da Cidade | T24: 1208 | U24: Conservação de Vias Urbanas | V24: 449051 | W24: Despesa de capital | X24: Investimentos | Z24: SMOBI | AA24: 1000000 | AB24: 584328.08 | AC24: 0 | AD24: 584328.08 | AE24: ESTRUTURA ENGENHARIA E CONSTRUCAO LTDA. ESTRUTURA ENGENHARIA E CONSTRUCAO LTDA. TECHVIAS ENGENHARIA LTDA | AF24: 19590967000107 19590967000107 11871903000164 | AG24: - | AH24: - | AI24: - | AJ24: 0 | AK24: 0 | AL24: 1403 | AM24: =IF(AL24="","",AL24&" - "&IFERROR(VLOOKUP(AL24,CODEBOOK_CAP!$C$2:$D$212,2,FALSE),"")) -> 1403 - REABILITAÇÃO URBANA, ECONOMIA URBANA | AN24: =IF(AL24="","",IFERROR(VLOOKUP(AL24,CODEBOOK_CAP!$C$2:$E$212,3,FALSE),"")) -> Reabilitação de áreas urbanas, revitalização urbana, modernização de áreas, mercados públicos, revitalização de praças, política urbana nacional, desenvolvimento urbano , desenvolvimento econômico de estados e cidades, modernização de espaços urbanos | AO24: 1 | AP24: Rua Elza Beatriz de Araújo, que interliga à Rua Tereza Mota Valadares com a Rua Maria Heilbuth Surette; Rua Márcio Maia Ferreira, que interliga à Av. Professor Mário Werneck com a Rua Eli Seabra Filho; e Rua VDP3981, que interliga a Rua Deputado Sebastião Nascimento com a Rua Deputado Fábio Vasconcelos; e estudos, projetos e implantação de pista de Skate na Praça Moisés Kalil, dentre outros; | AQ24: 4 | AR24: 1 | AS24: Rua Elza Beatriz de Araújo, que interliga à Rua Tereza Mota Valadares com a Rua Maria Heilbuth Surette; Rua Márcio Maia Ferreira, que interliga à Av. Professor Mário Werneck com a Rua Eli Seabra Filho; e Rua VDP3981, que interliga a Rua Deputado Sebastião Nascimento com a Rua Deputado Fábio Vasconcelos; e estudos, projetos e implantação de pista de Skate na Praça Moisés Kalil, dentre outros; | AT24: 0 | AX24: Pendente
A25: 2022_BRAULIO_LARA_742_01 | B25: 2022 | C25: 4672 | D25: emendas_conslidadas(1).xlsx | E25: 2022_BRAULIO_LARA | F25: 742 | G25: Concluída | H25: Braulio Lara | I25: NOVO | J25: Destinação de recursos para a Instituto Pedra Viva, CNPJ: 08.878.503/0001-76, para a execução de atividades socioassistenciais, de acordo com o disposto na Lei Federal nº 8.742/93, em consonância com a referida inscrição no Conselho Municipal de Assistência Social de Belo Horizonte – CMAS-BH; | K25: 1011.08.244.113.2804.339039 | L25: 1011 | M25: FUNDO MUNICIPAL DE ASSISTÊNCIA SOCIAL | N25: 08 | O25: Assistência Social | P25: 244 | Q25: Assistência Comunitária | R25: 0113 | S25: Aprimoramento da Gestão do SUAS | T25: 2804 | U25: Gestão dos Equipamentos e Promoção Social | V25: 339039 | W25: Despesa corrente | X25: Outras despesas correntes | Z25: SMASDH | AA25: 50000 | AB25: 50000 | AC25: 50000 | AD25: 50000 | AE25: INSTITUTO PEDRA VIVA | AF25: 08878503000176 | AG25: Associações Diversas | AH25: Associações Diversas | AJ25: 0 | AK25: 0 | AL25: 1300 | AM25: =IF(AL25="","",AL25&" - "&IFERROR(VLOOKUP(AL25,CODEBOOK_CAP!$C$2:$D$212,2,FALSE),"")) -> 1300 - GERAL | AN25: =IF(AL25="","",IFERROR(VLOOKUP(AL25,CODEBOOK_CAP!$C$2:$E$212,3,FALSE),"")) -> Observações gerais sobre políticas sociais que envolvam mais de um casos dos subtópicos, políticas gerais de assistência social, welfare state, bem estar social, Ministérios e orcamentos como do Desenvolvimento social e combate e fome, desenvolvimento social, sistemas de gestão de políticas de assistencia, CAD UNICO, cadastros, sistemas computacionais para desenvolvimento de ações e políticas sociais, BPC - Benefício de Prestação Continuada geral para idosos e deficientes. NÃO CONFUNDIR POLÍTICAS SOCIAIS COM POLÍTICA DE EMPREGO E RENDA. Todas as questões, direitos, políticas que se relacionem com o TRABALHO como contrapartida, estão no código 5. Maternidade, Paternidade aposentadoria por tempo de serviço, INSS. | AO25: 0 | AQ25: 0 | AR25: 0 | AT25: 0 | AX25: Pendente
A26: 2022_BRAULIO_LARA_743_01 | B26: 2022 | C26: 4673 | D26: emendas_conslidadas(1).xlsx | E26: 2022_BRAULIO_LARA | F26: 743 | G26: Cancelada | H26: Braulio Lara | I26: Novo | J26: Ao reforço de dotação orçamentária para complemento de obras da Rua VDP3981, conforme CP273009M, que interliga a Rua Deputado Sebastião Nascimento com a Rua Deputado Fábio Vasconcelos Plano de Obras 0505: L4-U- URB-11: Taquaril 1a Etapa; | K26: - | Z26: Cancelada | AA26: 300000 | AE26: - | AF26: - | AG26: - | AH26: - | AI26: - | AJ26: 0 | AK26: 0 | AL26: 1002 | AM26: =IF(AL26="","",AL26&" - "&IFERROR(VLOOKUP(AL26,CODEBOOK_CAP!$C$2:$D$212,2,FALSE),"")) -> 1002 - CARROS, TRÂNSITO, CONSTRUÇÃO E MANUTENÇÃO DE RUAS E ESTRADAS | AN26: =IF(AL26="","",IFERROR(VLOOKUP(AL26,CODEBOOK_CAP!$C$2:$E$212,3,FALSE),"")) -> Construção, manutenção de ruas, avenidas, estradas. BRs, pedágios, privatizações, concessinárias, segurança nas estradas, leis de trânsito relacionadas a via, limite de velocidade, sinalização, recapeamento de ruas, pavimentação estradas de terra, não pavimentadas, acidentes e camapanhas de prevencao contra acidentes de transito. Observações sobre regulação de transportes não públicos de carros, veículos de passeio, uber, taxi, transporte de cargas terrestre, frete, trânsito em vias públicas, regulamentação de tipos de carteira de motorista, especificações para caminhoneiros, testes e exames de habilitação, exigências de carteira de habilitação, obrigatoriedade de itens em veículos (extintor, kit primeiros socorros, airbag, freios abs) Quando tratar de grandes obras de construções de rodovias, olhar codigo 1010 para ver qual se encaixa melhor. | AO26: 1 | AP26: Rua VDP3981, conforme CP273009M, que interliga a Rua Deputado Sebastião Nascimento com a Rua Deputado Fábio Vasconcelos Plano de Obras 0505: L4-U- URB-11: Taquaril 1a Etapa; | AQ26: 1 | AR26: 1 | AS26: Rua VDP3981, conforme CP273009M, que interliga a Rua Deputado Sebastião Nascimento com a Rua Deputado Fábio Vasconcelos Plano de Obras 0505: L4-U- URB-11: Taquaril 1a Etapa; | AT26: 0 | AX26: Pendente
A27: 2022_BRAULIO_LARA_800_01 | B27: 2022 | C27: 4726 | D27: emendas_conslidadas(1).xlsx | E27: 2022_BRAULIO_LARA | F27: 800 | G27: Concluída | H27: Braulio Lara | I27: NOVO | J27: Ao reforço de dotação orçamentária destinada ao Centro de Saúde Havaí (R. Manila, 432 - Estrela Dalva, Belo Horizonte - MG, 30570-360), para contratação de serviços ligados a manutenções, melhorias e revitalização de instalações; | K27: 2302.10.301.157.2902.336783 | L27: 2302 | M27: FUNDO MUNICIPAL DE SAÚDE | N27: 10 | O27: Saúde | P27: 301 | Q27: Atenção Básica | R27: 0157 | S27: Atenção Primária à Saúde | T27: 2902 | U27: Gestão das Parcerias Público-Privadas | V27: 336783 | W27: Despesa corrente | X27: Outras despesas correntes | Z27: SMSA | AA27: 50000 | AB27: 50000 | AC27: 50000 | AD27: 50000 | AE27: SPE SAUDE PRIMARIA BH S/A | AF27: 23921007000141 | AG27: PBH | AH27: Município de Belo Horizonte | AI27: 18715383000140 | AJ27: 1 | AK27: 1 | AL27: 0322 | AM27: =IF(AL27="","",AL27&" - "&IFERROR(VLOOKUP(AL27,CODEBOOK_CAP!$C$2:$D$212,2,FALSE),"")) -> 0322 - ESTRUTURAS, HOSPITAIS, CLÍNICAS | AN27: =IF(AL27="","",IFERROR(VLOOKUP(AL27,CODEBOOK_CAP!$C$2:$E$212,3,FALSE),"")) -> Observações relacionadas as estruturas do sistema de saúde, como a construção de hospitais, postos de saúde, construção de maternidades, laboratórios, centros de saúde avançado, SAMU, Ambulâncias, UTI Móveis, leitos, compra de equipamentos médicos, Raio X, Ultrasom, equipamentos de diálise, capacidade de atendimento, estrutura e funcionamento de equipamentos públicos de saúde. | AO27: 1 | AP27: Centro de Saúde Havaí (R. Manila, 432 - Estrela Dalva, Belo Horizonte - MG, 30570-360) | AQ27: 1 | AR27: 1 | AS27: Centro de Saúde Havaí (R. Manila, 432 - Estrela Dalva, Belo Horizonte - MG, 30570-360) | AT27: 0 | AX27: Pendente
A28: 2022_BRAULIO_LARA_801_01 | B28: 2022 | C28: 4727 | D28: emendas_conslidadas(1).xlsx | E28: 2022_BRAULIO_LARA | F28: 801 | G28: Concluída | H28: Braulio Lara | I28: NOVO | J28: Ao reforço de dotação orçamentária destinada ao Centro de Saúde Palmeiras (Av. Dom João VI, 1821 - Palmeiras, Belo Horizonte - MG, 30575-460), para contratação de serviços ligados a manutenções, melhorias e revitalização de instalações; | K28: 2302.10.122.117.1216.449051 | L28: 2302 | M28: FUNDO MUNICIPAL DE SAÚDE | N28: 10 | O28: Saúde | P28: 122 | Q28: Administração Geral | R28: 0117 | S28: Gestão do SUS | T28: 1216 | U28: Construção, Ampliação e Reforma de Unidades de Saúde | V28: 449051 | W28: Despesa de capital | X28: Investimentos | Z28: SMSA | AA28: 50000 | AB28: 47505 | AC28: 47505 | AD28: 47505 | AE28: CONSTRUTORA CAMPOS E FILHOS LTDA. | AF28: 15862332000152 | AG28: PBH | AH28: Município de Belo Horizonte | AI28: 18715383000140 | AJ28: 1 | AK28: 1 | AL28: 0322 | AM28: =IF(AL28="","",AL28&" - "&IFERROR(VLOOKUP(AL28,CODEBOOK_CAP!$C$2:$D$212,2,FALSE),"")) -> 0322 - ESTRUTURAS, HOSPITAIS, CLÍNICAS | AN28: =IF(AL28="","",IFERROR(VLOOKUP(AL28,CODEBOOK_CAP!$C$2:$E$212,3,FALSE),"")) -> Observações relacionadas as estruturas do sistema de saúde, como a construção de hospitais, postos de saúde, construção de maternidades, laboratórios, centros de saúde avançado, SAMU, Ambulâncias, UTI Móveis, leitos, compra de equipamentos médicos, Raio X, Ultrasom, equipamentos de diálise, capacidade de atendimento, estrutura e funcionamento de equipamentos públicos de saúde. | AO28: 1 | AP28: Centro de Saúde Palmeiras (Av. Dom João VI, 1821 - Palmeiras, Belo Horizonte - MG, 30575-460) | AQ28: 1 | AR28: 1 | AS28: Centro de Saúde Palmeiras (Av. Dom João VI, 1821 - Palmeiras, Belo Horizonte - MG, 30575-460) | AT28: 0 | AX28: Pendente
A29: 2022_BRAULIO_LARA_802_01 | B29: 2022 | C29: 4728 | D29: emendas_conslidadas(1).xlsx | E29: 2022_BRAULIO_LARA | F29: 802 | G29: Concluída | H29: Braulio Lara | I29: NOVO | J29: Ao reforço de dotação orçamentária destinada ao Centro de Saúde Vila Leonina (Praça do Ensino, 240 - Alpes, Belo Horizonte - MG, 30421-484), para contratação de serviços ligados a manutenções, melhorias e revitalização de instalações; | K29: 2302.10.122.117.1216.449051 | L29: 2302 | M29: FUNDO MUNICIPAL DE SAÚDE | N29: 10 | O29: Saúde | P29: 122 | Q29: Administração Geral | R29: 0117 | S29: Gestão do SUS | T29: 1216 | U29: Construção, Ampliação e Reforma de Unidades de Saúde | V29: 449051 | W29: Despesa de capital | X29: Investimentos | Z29: SMSA | AA29: 50000 | AB29: 47499 | AC29: 47499 | AD29: 47499 | AE29: MAUMA ENGENHARIA E SERVICOS LTDA. | AF29: 02496187000191 | AG29: PBH | AH29: Município de Belo Horizonte | AI29: 18715383000140 | AJ29: 1 | AK29: 1 | AL29: 0322 | AM29: =IF(AL29="","",AL29&" - "&IFERROR(VLOOKUP(AL29,CODEBOOK_CAP!$C$2:$D$212,2,FALSE),"")) -> 0322 - ESTRUTURAS, HOSPITAIS, CLÍNICAS | AN29: =IF(AL29="","",IFERROR(VLOOKUP(AL29,CODEBOOK_CAP!$C$2:$E$212,3,FALSE),"")) -> Observações relacionadas as estruturas do sistema de saúde, como a construção de hospitais, postos de saúde, construção de maternidades, laboratórios, centros de saúde avançado, SAMU, Ambulâncias, UTI Móveis, leitos, compra de equipamentos médicos, Raio X, Ultrasom, equipamentos de diálise, capacidade de atendimento, estrutura e funcionamento de equipamentos públicos de saúde. | AO29: 1 | AP29: Centro de Saúde Vila Leonina (Praça do Ensino, 240 - Alpes, Belo Horizonte - MG, 30421-484) | AQ29: 1 | AR29: 1 | AS29: Centro de Saúde Vila Leonina (Praça do Ensino, 240 - Alpes, Belo Horizonte - MG, 30421-484) | AT29: 0 | AX29: Pendente
A30: 2022_BRAULIO_LARA_803_01 | B30: 2022 | C30: 4729 | D30: emendas_conslidadas(1).xlsx | E30: 2022_BRAULIO_LARA | F30: 803 | G30: Concluída | H30: Braulio Lara | I30: NOVO | J30: Ao reforço de dotação orçamentária destinada ao Centro de Saúde Salgado Filho (R. Campína Verde, 375 - Salgado Filho, Belo Horizonte - MG, 30550-340), para contratação de serviços ligados a manutenções, melhorias e revitalização de instalações; | K30: 2302.10.122.117.1216.449051 | L30: 2302 | M30: FUNDO MUNICIPAL DE SAÚDE | N30: 10 | O30: Saúde | P30: 122 | Q30: Administração Geral | R30: 0117 | S30: Gestão do SUS | T30: 1216 | U30: Construção, Ampliação e Reforma de Unidades de Saúde | V30: 449051 | W30: Despesa de capital | X30: Investimentos | Z30: SMSA | AA30: 50000 | AB30: 43924 | AC30: 43924 | AD30: 43924 | AE30: CONSTRUTORA CAMPOS E FILHOS LTDA. | AF30: 15862332000152 | AG30: PBH | AH30: Município de Belo Horizonte | AI30: 18715383000140 | AJ30: 1 | AK30: 1 | AL30: 0322 | AM30: =IF(AL30="","",AL30&" - "&IFERROR(VLOOKUP(AL30,CODEBOOK_CAP!$C$2:$D$212,2,FALSE),"")) -> 0322 - ESTRUTURAS, HOSPITAIS, CLÍNICAS | AN30: =IF(AL30="","",IFERROR(VLOOKUP(AL30,CODEBOOK_CAP!$C$2:$E$212,3,FALSE),"")) -> Observações relacionadas as estruturas do sistema de saúde, como a construção de hospitais, postos de saúde, construção de maternidades, laboratórios, centros de saúde avançado, SAMU, Ambulâncias, UTI Móveis, leitos, compra de equipamentos médicos, Raio X, Ultrasom, equipamentos de diálise, capacidade de atendimento, estrutura e funcionamento de equipamentos públicos de saúde. | AO30: 1 | AP30: Centro de Saúde Salgado Filho (R. Campína Verde, 375 - Salgado Filho, Belo Horizonte - MG, 30550-340) | AQ30: 1 | AR30: 1 | AS30: Centro de Saúde Salgado Filho (R. Campína Verde, 375 - Salgado Filho, Belo Horizonte - MG, 30550-340) | AT30: 0 | AX30: Pendente
A31: 2022_BRAULIO_LARA_804_01 | B31: 2022 | C31: 4730 | D31: emendas_conslidadas(1).xlsx | E31: 2022_BRAULIO_LARA | F31: 804 | G31: Concluída | H31: Braulio Lara | I31: NOVO | J31: Ao reforço de dotação orçamentária destinada ao Centro de Saúde Betânia, para realização de manutenções, melhorias e revitalização de instalações; | K31: 2302.10.122.117.1216.449051 | L31: 2302 | M31: FUNDO MUNICIPAL DE SAÚDE | N31: 10 | O31: Saúde | P31: 122 | Q31: Administração Geral | R31: 0117 | S31: Gestão do SUS | T31: 1216 | U31: Construção, Ampliação e Reforma de Unidades de Saúde | V31: 449051 | W31: Despesa de capital | X31: Investimentos | Z31: SMSA | AA31: 50000 | AB31: 33672 | AC31: 33672 | AD31: 33672 | AE31: MAUMA ENGENHARIA E SERVICOS LTDA. | AF31: 02496187000191 | AG31: PBH | AH31: Município de Belo Horizonte | AI31: 18715383000140 | AJ31: 1 | AK31: 1 | AL31: 0322 | AM31: =IF(AL31="","",AL31&" - "&IFERROR(VLOOKUP(AL31,CODEBOOK_CAP!$C$2:$D$212,2,FALSE),"")) -> 0322 - ESTRUTURAS, HOSPITAIS, CLÍNICAS | AN31: =IF(AL31="","",IFERROR(VLOOKUP(AL31,CODEBOOK_CAP!$C$2:$E$212,3,FALSE),"")) -> Observações relacionadas as estruturas do sistema de saúde, como a construção de hospitais, postos de saúde, construção de maternidades, laboratórios, centros de saúde avançado, SAMU, Ambulâncias, UTI Móveis, leitos, compra de equipamentos médicos, Raio X, Ultrasom, equipamentos de diálise, capacidade de atendimento, estrutura e funcionamento de equipamentos públicos de saúde. | AO31: 1 | AP31: Centro de Saúde Betânia | AQ31: 1 | AR31: 1 | AS31: Centro de Saúde Betânia | AT31: 0 | AX31: Pendente
A32: 2022_BRAULIO_LARA_805_01 | B32: 2022 | C32: 4731 | D32: emendas_conslidadas(1).xlsx | E32: 2022_BRAULIO_LARA | F32: 805 | G32: Concluída | H32: Braulio Lara | I32: NOVO | J32: Ao reforço de dotação orçamentária destinada ao Centro de Saúde de Amilcar Vianna Martins (R. Nelson de Senna, 90 - Cinquentenário, Belo Horizonte - MG, 30570-060), para contratação de serviços ligados a manutenções, melhorias e revitalização de instalações; | K32: 2302.10.122.117.1216.449051 | L32: 2302 | M32: FUNDO MUNICIPAL DE SAÚDE | N32: 10 | O32: Saúde | P32: 122 | Q32: Administração Geral | R32: 0117 | S32: Gestão do SUS | T32: 1216 | U32: Construção, Ampliação e Reforma de Unidades de Saúde | V32: 449051 | W32: Despesa de capital | X32: Investimentos | Z32: SMSA | AA32: 50000 | AB32: 49814 | AC32: 49814 | AD32: 49814 | AE32: MAUMA ENGENHARIA E SERVICOS LTDA. MAUMA ENGENHARIA E SERVICOS LTDA. | AF32: 02496187000191 02496187000191 | AG32: PBH | AH32: Município de Belo Horizonte | AI32: 18715383000140 | AJ32: 1 | AK32: 1 | AL32: 0322 | AM32: =IF(AL32="","",AL32&" - "&IFERROR(VLOOKUP(AL32,CODEBOOK_CAP!$C$2:$D$212,2,FALSE),"")) -> 0322 - ESTRUTURAS, HOSPITAIS, CLÍNICAS | AN32: =IF(AL32="","",IFERROR(VLOOKUP(AL32,CODEBOOK_CAP!$C$2:$E$212,3,FALSE),"")) -> Observações relacionadas as estruturas do sistema de saúde, como a construção de hospitais, postos de saúde, construção de maternidades, laboratórios, centros de saúde avançado, SAMU, Ambulâncias, UTI Móveis, leitos, compra de equipamentos médicos, Raio X, Ultrasom, equipamentos de diálise, capacidade de atendimento, estrutura e funcionamento de equipamentos públicos de saúde. | AO32: 1 | AP32: Centro de Saúde de Amilcar Vianna Martins (R. Nelson de Senna, 90 - Cinquentenário, Belo Horizonte - MG, 30570-060) | AQ32: 1 | AR32: 1 | AS32: Centro de Saúde de Amilcar Vianna Martins (R. Nelson de Senna, 90 - Cinquentenário, Belo Horizonte - MG, 30570-060) | AT32: 0 | AX32: Pendente
A33: 2022_BRAULIO_LARA_806_01 | B33: 2022 | C33: 4732 | D33: emendas_conslidadas(1).xlsx | E33: 2022_BRAULIO_LARA | F33: 806 | G33: Concluída | H33: Braulio Lara | I33: NOVO | J33: Ao reforço de dotação orçamentária destinada ao Centro de Saúde Vila Imperial (Rua Guilherme Pinto da Fonseca, 350 - Me. Gertrudes, Belo Horizonte - MG, 30518-240), para contratação de serviços ligados a manutenções, melhorias e revitalização de instalações; | K33: 2302.10.122.117.1216.449051 | L33: 2302 | M33: FUNDO MUNICIPAL DE SAÚDE | N33: 10 | O33: Saúde | P33: 122 | Q33: Administração Geral | R33: 0117 | S33: Gestão do SUS | T33: 1216 | U33: Construção, Ampliação e Reforma de Unidades de Saúde | V33: 449051 | W33: Despesa de capital | X33: Investimentos | Z33: SMSA | AA33: 50000 | AB33: 50000 | AC33: 50000 | AD33: 50000 | AE33: MAUMA ENGENHARIA E SERVICOS LTDA. | AF33: 02496187000191 | AG33: PBH | AH33: Município de Belo Horizonte | AI33: 18715383000140 | AJ33: 1 | AK33: 1 | AL33: 0322 | AM33: =IF(AL33="","",AL33&" - "&IFERROR(VLOOKUP(AL33,CODEBOOK_CAP!$C$2:$D$212,2,FALSE),"")) -> 0322 - ESTRUTURAS, HOSPITAIS, CLÍNICAS | AN33: =IF(AL33="","",IFERROR(VLOOKUP(AL33,CODEBOOK_CAP!$C$2:$E$212,3,FALSE),"")) -> Observações relacionadas as estruturas do sistema de saúde, como a construção de hospitais, postos de saúde, construção de maternidades, laboratórios, centros de saúde avançado, SAMU, Ambulâncias, UTI Móveis, leitos, compra de equipamentos médicos, Raio X, Ultrasom, equipamentos de diálise, capacidade de atendimento, estrutura e funcionamento de equipamentos públicos de saúde. | AO33: 1 | AP33: Centro de Saúde Vila Imperial (Rua Guilherme Pinto da Fonseca, 350 - Me. Gertrudes, Belo Horizonte - MG, 30518-240) | AQ33: 1 | AR33: 1 | AS33: Centro de Saúde Vila Imperial (Rua Guilherme Pinto da Fonseca, 350 - Me. Gertrudes, Belo Horizonte - MG, 30518-240) | AT33: 0 | AX33: Pendente
A34: 2022_BRAULIO_LARA_807_01 | B34: 2022 | C34: 4733 | D34: emendas_conslidadas(1).xlsx | E34: 2022_BRAULIO_LARA | F34: 807 | G34: Concluída | H34: Braulio Lara | I34: NOVO | J34: Ao reforço de dotação orçamentária destinada ao Centro de Saúde de Cabana (R. Centro Social, 536 - Cabana, Belo Horizonte - MG, 30510-670) e ao Centro de Saúde Cícero Ildefonso (R. Caviana, 77, Jardinópolis, Belo Horizonte - MG, 30510-510), para contratação de serviços ligados a manutenções, melhorias e revitalização de instalações; | K34: 2302.10.301.157.2902.336783 | L34: 2302 | M34: FUNDO MUNICIPAL DE SAÚDE | N34: 10 | O34: Saúde | P34: 301 | Q34: Atenção Básica | R34: 0157 | S34: Atenção Primária à Saúde | T34: 2902 | U34: Gestão das Parcerias Público-Privadas | V34: 336783 | W34: Despesa corrente | X34: Outras despesas correntes | Z34: SMSA | AA34: 50000 | AB34: 50000 | AC34: 50000 | AD34: 50000 | AE34: SPE SAUDE PRIMARIA BH S/A | AF34: 23921007000141 | AG34: PBH | AH34: Município de Belo Horizonte | AI34: 18715383000140 | AJ34: 1 | AK34: 1 | AL34: 0322 | AM34: =IF(AL34="","",AL34&" - "&IFERROR(VLOOKUP(AL34,CODEBOOK_CAP!$C$2:$D$212,2,FALSE),"")) -> 0322 - ESTRUTURAS, HOSPITAIS, CLÍNICAS | AN34: =IF(AL34="","",IFERROR(VLOOKUP(AL34,CODEBOOK_CAP!$C$2:$E$212,3,FALSE),"")) -> Observações relacionadas as estruturas do sistema de saúde, como a construção de hospitais, postos de saúde, construção de maternidades, laboratórios, centros de saúde avançado, SAMU, Ambulâncias, UTI Móveis, leitos, compra de equipamentos médicos, Raio X, Ultrasom, equipamentos de diálise, capacidade de atendimento, estrutura e funcionamento de equipamentos públicos de saúde. | AO34: 1 | AP34: Centro de Saúde de Cabana (R. Centro Social, 536 - Cabana, Belo Horizonte - MG, 30510-670) e ao Centro de Saúde Cícero Ildefonso (R. Caviana, 77, Jardinópolis, Belo Horizonte - MG, 30510-510) | AQ34: 2 | AR34: 1 | AS34: Centro de Saúde de Cabana (R. Centro Social, 536 - Cabana, Belo Horizonte - MG, 30510-670) e ao Centro de Saúde Cícero Ildefonso (R. Caviana, 77, Jardinópolis, Belo Horizonte - MG, 30510-510) | AT34: 0 | AX34: Pendente
A35: 2022_BRAULIO_LARA_808_01 | B35: 2022 | C35: 4734 | D35: emendas_conslidadas(1).xlsx | E35: 2022_BRAULIO_LARA | F35: 808 | G35: Concluída | H35: Braulio Lara | I35: NOVO | J35: Ao reforço de dotação orçamentária destinada ao Centro de Saúde Ventosa, para contraprestação de serviços ligados a manutenção, melhorias e adequações de instalações; | K35: 2302.10.301.157.2902.336783 | L35: 2302 | M35: FUNDO MUNICIPAL DE SAÚDE | N35: 10 | O35: Saúde | P35: 301 | Q35: Atenção Básica | R35: 0157 | S35: Atenção Primária à Saúde | T35: 2902 | U35: Gestão das Parcerias Público-Privadas | V35: 336783 | W35: Despesa corrente | X35: Outras despesas correntes | Z35: SMSA | AA35: 50000 | AB35: 50000 | AC35: 50000 | AD35: 50000 | AE35: SPE SAUDE PRIMARIA BH S/A | AF35: 23921007000141 | AG35: PBH | AH35: Município de Belo Horizonte | AI35: 18715383000140 | AJ35: 1 | AK35: 1 | AL35: 0322 | AM35: =IF(AL35="","",AL35&" - "&IFERROR(VLOOKUP(AL35,CODEBOOK_CAP!$C$2:$D$212,2,FALSE),"")) -> 0322 - ESTRUTURAS, HOSPITAIS, CLÍNICAS | AN35: =IF(AL35="","",IFERROR(VLOOKUP(AL35,CODEBOOK_CAP!$C$2:$E$212,3,FALSE),"")) -> Observações relacionadas as estruturas do sistema de saúde, como a construção de hospitais, postos de saúde, construção de maternidades, laboratórios, centros de saúde avançado, SAMU, Ambulâncias, UTI Móveis, leitos, compra de equipamentos médicos, Raio X, Ultrasom, equipamentos de diálise, capacidade de atendimento, estrutura e funcionamento de equipamentos públicos de saúde. | AO35: 1 | AP35: Centro de Saúde Ventosa | AQ35: 1 | AR35: 1 | AS35: Centro de Saúde Ventosa | AT35: 0 | AX35: Pendente
A36: 2022_BRAULIO_LARA_809_01 | B36: 2022 | C36: 4735 | D36: emendas_conslidadas(1).xlsx | E36: 2022_BRAULIO_LARA | F36: 809 | G36: Concluída | H36: Braulio Lara | I36: NOVO | J36: Ao reforço de dotação orçamentária destinada ao Centro de Saúde Pilar Olhos D’água (R. São Pedro da Aldeia, 55 - Pilar, Belo Horizonte - MG, 30390-000), para contratação de serviços ligados a manutenções, melhorias e revitalização de instalações; | K36: 2302.10.122.117.1216.449051 | L36: 2302 | M36: FUNDO MUNICIPAL DE SAÚDE | N36: 10 | O36: Saúde | P36: 122 | Q36: Administração Geral | R36: 0117 | S36: Gestão do SUS | T36: 1216 | U36: Construção, Ampliação e Reforma de Unidades de Saúde | V36: 449051 | W36: Despesa de capital | X36: Investimentos | Z36: SMSA | AA36: 50000 | AB36: 0 | AC36: 0 | AD36: 0 | AE36: MCM EMPREENDIMENTOS EIRELI EPP | AF36: 15211038000180 | AG36: - | AH36: - | AI36: - | AJ36: 1 | AK36: 1 | AL36: 0322 | AM36: =IF(AL36="","",AL36&" - "&IFERROR(VLOOKUP(AL36,CODEBOOK_CAP!$C$2:$D$212,2,FALSE),"")) -> 0322 - ESTRUTURAS, HOSPITAIS, CLÍNICAS | AN36: =IF(AL36="","",IFERROR(VLOOKUP(AL36,CODEBOOK_CAP!$C$2:$E$212,3,FALSE),"")) -> Observações relacionadas as estruturas do sistema de saúde, como a construção de hospitais, postos de saúde, construção de maternidades, laboratórios, centros de saúde avançado, SAMU, Ambulâncias, UTI Móveis, leitos, compra de equipamentos médicos, Raio X, Ultrasom, equipamentos de diálise, capacidade de atendimento, estrutura e funcionamento de equipamentos públicos de saúde. | AO36: 1 | AP36: Centro de Saúde Pilar Olhos D’água (R. São Pedro da Aldeia, 55 - Pilar, Belo Horizonte - MG, 30390-000) | AQ36: 1 | AR36: 1 | AS36: Centro de Saúde Pilar Olhos D’água (R. São Pedro da Aldeia, 55 - Pilar, Belo Horizonte - MG, 30390-000) | AT36: 0 | AX36: Pendente
A37: 2022_BRAULIO_LARA_810_01 | B37: 2022 | C37: 4736 | D37: emendas_conslidadas(1).xlsx | E37: 2022_BRAULIO_LARA | F37: 810 | G37: Concluída | H37: Braulio Lara | I37: NOVO | J37: Ao reforço de dotação orçamentária destinada ao Centro de Saúde Serrano, para contraprestação de serviços ligados a manutenção, melhorias e adequações de instalações; | K37: 2302.10.301.157.2902.336783 | L37: 2302 | M37: FUNDO MUNICIPAL DE SAÚDE | N37: 10 | O37: Saúde | P37: 301 | Q37: Atenção Básica | R37: 0157 | S37: Atenção Primária à Saúde | T37: 2902 | U37: Gestão das Parcerias Público-Privadas | V37: 336783 | W37: Despesa corrente | X37: Outras despesas correntes | Z37: SMSA | AA37: 44610 | AB37: 44610 | AC37: 44610 | AD37: 44610 | AE37: SPE SAUDE PRIMARIA BH S/A | AF37: 23921007000141 | AG37: PBH | AH37: Município de Belo Horizonte | AI37: 18715383000140 | AJ37: 1 | AK37: 1 | AL37: 0322 | AM37: =IF(AL37="","",AL37&" - "&IFERROR(VLOOKUP(AL37,CODEBOOK_CAP!$C$2:$D$212,2,FALSE),"")) -> 0322 - ESTRUTURAS, HOSPITAIS, CLÍNICAS | AN37: =IF(AL37="","",IFERROR(VLOOKUP(AL37,CODEBOOK_CAP!$C$2:$E$212,3,FALSE),"")) -> Observações relacionadas as estruturas do sistema de saúde, como a construção de hospitais, postos de saúde, construção de maternidades, laboratórios, centros de saúde avançado, SAMU, Ambulâncias, UTI Móveis, leitos, compra de equipamentos médicos, Raio X, Ultrasom, equipamentos de diálise, capacidade de atendimento, estrutura e funcionamento de equipamentos públicos de saúde. | AO37: 1 | AP37: Centro de Saúde Serrano | AQ37: 1 | AR37: 1 | AS37: Centro de Saúde Serrano | AT37: 0 | AX37: Pendente
A38: 2022_BRAULIO_LARA_811_01 | B38: 2022 | C38: 4737 | D38: emendas_conslidadas(1).xlsx | E38: 2022_BRAULIO_LARA | F38: 811 | G38: Impedimento Técnico | H38: Braulio Lara | I38: NOVO | J38: Ao reforço de dotação orçamentária destinada a UPA Oeste (Av. Barão Homem de Melo, 1710 - Jardim América, Belo Horizonte - MG, 30160-090), para contratação de serviços ligados a manutenções, melhorias e revitalização de instalações; | K38: - | Z38: Impedimento Técnico | AA38: 100000 | AE38: - | AF38: - | AG38: - | AH38: - | AI38: - | AJ38: 1 | AK38: 1 | AL38: 0322 | AM38: =IF(AL38="","",AL38&" - "&IFERROR(VLOOKUP(AL38,CODEBOOK_CAP!$C$2:$D$212,2,FALSE),"")) -> 0322 - ESTRUTURAS, HOSPITAIS, CLÍNICAS | AN38: =IF(AL38="","",IFERROR(VLOOKUP(AL38,CODEBOOK_CAP!$C$2:$E$212,3,FALSE),"")) -> Observações relacionadas as estruturas do sistema de saúde, como a construção de hospitais, postos de saúde, construção de maternidades, laboratórios, centros de saúde avançado, SAMU, Ambulâncias, UTI Móveis, leitos, compra de equipamentos médicos, Raio X, Ultrasom, equipamentos de diálise, capacidade de atendimento, estrutura e funcionamento de equipamentos públicos de saúde. | AO38: 1 | AP38: UPA Oeste (Av. Barão Homem de Melo, 1710 - Jardim América, Belo Horizonte - MG, 30160-090) | AQ38: 1 | AR38: 1 | AS38: UPA Oeste (Av. Barão Homem de Melo, 1710 - Jardim América, Belo Horizonte - MG, 30160-090) | AT38: 0 | AX38: Pendente
A39: 2022_BRAULIO_LARA_829_01 | B39: 2022 | C39: 4753 | D39: emendas_conslidadas(1).xlsx | E39: 2022_BRAULIO_LARA | F39: 829 | G39: Concluída | H39: Braulio Lara | I39: NOVO | J39: Ao reforço de dotação orçamentária destinada ao Centro de Saúde Santa Terezinha, localizado na Rua Senador Virgílio Távora, n. 157, bairro Santa Terezinha, Belo Horizonte/MG, CEP 31.620-210, para contratação de serviços ligados a manutenções, melhorias e revitalização de instalações; | K39: 2302.10.122.117.1216.449051 | L39: 2302 | M39: FUNDO MUNICIPAL DE SAÚDE | N39: 10 | O39: Saúde | P39: 122 | Q39: Administração Geral | R39: 0117 | S39: Gestão do SUS | T39: 1216 | U39: Construção, Ampliação e Reforma de Unidades de Saúde | V39: 449051 | W39: Despesa de capital | X39: Investimentos | Z39: SMSA | AA39: 44610 | AB39: 44610 | AC39: 44610 | AD39: 44610 | AE39: CONSTRUTORA TORQUETE GONCALVES LTDA | AF39: 71354922000145 | AG39: PBH | AH39: Município de Belo Horizonte | AI39: 18715383000140 | AJ39: 1 | AK39: 1 | AL39: 0322 | AM39: =IF(AL39="","",AL39&" - "&IFERROR(VLOOKUP(AL39,CODEBOOK_CAP!$C$2:$D$212,2,FALSE),"")) -> 0322 - ESTRUTURAS, HOSPITAIS, CLÍNICAS | AN39: =IF(AL39="","",IFERROR(VLOOKUP(AL39,CODEBOOK_CAP!$C$2:$E$212,3,FALSE),"")) -> Observações relacionadas as estruturas do sistema de saúde, como a construção de hospitais, postos de saúde, construção de maternidades, laboratórios, centros de saúde avançado, SAMU, Ambulâncias, UTI Móveis, leitos, compra de equipamentos médicos, Raio X, Ultrasom, equipamentos de diálise, capacidade de atendimento, estrutura e funcionamento de equipamentos públicos de saúde. | AO39: 1 | AP39: Centro de Saúde Santa Terezinha, localizado na Rua Senador Virgílio Távora, n. 157, bairro Santa Terezinha, Belo Horizonte/MG, CEP 31.620-210 | AQ39: 1 | AR39: 1 | AS39: Centro de Saúde Santa Terezinha, localizado na Rua Senador Virgílio Távora, n. 157, bairro Santa Terezinha, Belo Horizonte/MG, CEP 31.620-210 | AT39: 0 | AX39: Pendente
A40: 2022_BRAULIO_LARA_830_01 | B40: 2022 | C40: 4754 | D40: emendas_conslidadas(1).xlsx | E40: 2022_BRAULIO_LARA | F40: 830 | G40: Concluída | H40: Braulio Lara | I40: NOVO | J40: Ao reforço de dotação orçamentária para revitalização de espaço e construção de espaço para desenvolvimento de atividades físicas, na interseção da Rua Estrada do Cercadinho e da Rua Olenka Dias Bicalho, no bairro Vila Ventosa; | K40: 2700.18.541.233.2811.449051 | L40: 2700 | M40: SECRETARIA MUNICIPAL DE OBRAS E INFRAESTRUTURA | N40: 18 | O40: Gestão Ambiental | P40: 541 | Q40: Preservação e Conservação Ambiental | R40: 0233 | S40: Manutenção da Cidade | T40: 2811 | U40: Serviços de Manutenção de Praças, Jardins e Arborização da Cidade | V40: 449051 | W40: Despesa de capital | X40: Investimentos | Z40: SMOBI | AA40: 20220 | AB40: 6466 | AC40: 6466 | AD40: 6466 | AE40: JTT LOCACOES E SERVICOS LTDA. | AF40: 07823480000130 | AG40: PBH | AH40: Município de Belo Horizonte | AI40: 18715383000140 | AJ40: 0 | AK40: 0 | AL40: 1403 | AM40: =IF(AL40="","",AL40&" - "&IFERROR(VLOOKUP(AL40,CODEBOOK_CAP!$C$2:$D$212,2,FALSE),"")) -> 1403 - REABILITAÇÃO URBANA, ECONOMIA URBANA | AN40: =IF(AL40="","",IFERROR(VLOOKUP(AL40,CODEBOOK_CAP!$C$2:$E$212,3,FALSE),"")) -> Reabilitação de áreas urbanas, revitalização urbana, modernização de áreas, mercados públicos, revitalização de praças, política urbana nacional, desenvolvimento urbano , desenvolvimento econômico de estados e cidades, modernização de espaços urbanos | AO40: 1 | AP40: Rua Estrada do Cercadinho e da Rua Olenka Dias Bicalho, no bairro Vila Ventosa | AQ40: 1 | AR40: 1 | AS40: Rua Estrada do Cercadinho e da Rua Olenka Dias Bicalho, no bairro Vila Ventosa | AT40: 0 | AX40: Pendente
A41: 2022_BRAULIO_LARA_831_01 | B41: 2022 | C41: 4755 | D41: emendas_conslidadas(1).xlsx | E41: 2022_BRAULIO_LARA | F41: 831 | G41: Concluída | H41: Braulio Lara | I41: NOVO | J41: Ao reforço de dotação orçamentária destinada ao Centro de Saúde Noraldino de Lima, localizado na Av. Amazonas, n. 4373, bairro Nova Suíça, Belo Horizonte/MG, CEP 30.421-169, para contratação de serviços ligados a manutenções, melhorias e revitalização de instalações; | K41: 2302.10.122.117.1216.449051 | L41: 2302 | M41: FUNDO MUNICIPAL DE SAÚDE | N41: 10 | O41: Saúde | P41: 122 | Q41: Administração Geral | R41: 0117 | S41: Gestão do SUS | T41: 1216 | U41: Construção, Ampliação e Reforma de Unidades de Saúde | V41: 449051 | W41: Despesa de capital | X41: Investimentos | Z41: SMSA | AA41: 80000 | AB41: 71844 | AC41: 71844 | AD41: 71844 | AE41: MAUMA ENGENHARIA E SERVICOS LTDA. | AF41: 02496187000191 | AG41: PBH | AH41: Município de Belo Horizonte | AI41: 18715383000140 | AJ41: 1 | AK41: 1 | AL41: 0322 | AM41: =IF(AL41="","",AL41&" - "&IFERROR(VLOOKUP(AL41,CODEBOOK_CAP!$C$2:$D$212,2,FALSE),"")) -> 0322 - ESTRUTURAS, HOSPITAIS, CLÍNICAS | AN41: =IF(AL41="","",IFERROR(VLOOKUP(AL41,CODEBOOK_CAP!$C$2:$E$212,3,FALSE),"")) -> Observações relacionadas as estruturas do sistema de saúde, como a construção de hospitais, postos de saúde, construção de maternidades, laboratórios, centros de saúde avançado, SAMU, Ambulâncias, UTI Móveis, leitos, compra de equipamentos médicos, Raio X, Ultrasom, equipamentos de diálise, capacidade de atendimento, estrutura e funcionamento de equipamentos públicos de saúde. | AO41: 1 | AP41: Centro de Saúde Noraldino de Lima, localizado na Av. Amazonas, n. 4373, bairro Nova Suíça, Belo Horizonte/MG, CEP 30.421-169 | AQ41: 1 | AR41: 1 | AS41: Centro de Saúde Noraldino de Lima, localizado na Av. Amazonas, n. 4373, bairro Nova Suíça, Belo Horizonte/MG, CEP 30.421-169 | AT41: 0 | AX41: Pendente
A42: 2022_BRAULIO_LARA_832_01 | B42: 2022 | C42: 4756 | D42: emendas_conslidadas(1).xlsx | E42: 2022_BRAULIO_LARA | F42: 832 | G42: Concluída | H42: Braulio Lara | I42: NOVO | J42: Ao reforço de dotação orçamentária destinada ao repasse para a Associação Mario Penna; | K42: 2302.10.302.114.2894.339039 | L42: 2302 | M42: FUNDO MUNICIPAL DE SAÚDE | N42: 10 | O42: Saúde | P42: 302 | Q42: Assistência Hospitalar e Ambulatorial | R42: 0114 | S42: Atenção Secundária e Terciária à Saúde | T42: 2894 | U42: Rede Hospitalar | V42: 339039 | W42: Despesa corrente | X42: Outras despesas correntes | Z42: SMSA | AA42: 80000 | AB42: 80000 | AC42: 80000 | AD42: 80000 | AE42: ASSOCIACAO MARIO PENNA | AF42: 17513235000180 | AG42: Hospitais | AH42: Hospitais | AJ42: 1 | AK42: 1 | AL42: 0322 | AM42: =IF(AL42="","",AL42&" - "&IFERROR(VLOOKUP(AL42,CODEBOOK_CAP!$C$2:$D$212,2,FALSE),"")) -> 0322 - ESTRUTURAS, HOSPITAIS, CLÍNICAS | AN42: =IF(AL42="","",IFERROR(VLOOKUP(AL42,CODEBOOK_CAP!$C$2:$E$212,3,FALSE),"")) -> Observações relacionadas as estruturas do sistema de saúde, como a construção de hospitais, postos de saúde, construção de maternidades, laboratórios, centros de saúde avançado, SAMU, Ambulâncias, UTI Móveis, leitos, compra de equipamentos médicos, Raio X, Ultrasom, equipamentos de diálise, capacidade de atendimento, estrutura e funcionamento de equipamentos públicos de saúde. | AO42: 0 | AQ42: 1 | AR42: 1 | AS42: Associação Mario Penna | AT42: 0 | AX42: Pendente
A43: 2022_BRAULIO_LARA_833_01 | B43: 2022 | C43: 4757 | D43: emendas_conslidadas(1).xlsx | E43: 2022_BRAULIO_LARA | F43: 833 | G43: Concluída | H43: Braulio Lara | I43: NOVO | J43: Ao reforço de dotação orçamentária destinada ao repasse para a Fundação Benjamin Guimarães (Hospital da Baleia); | K43: 2302.10.302.114.2894.339039 | L43: 2302 | M43: FUNDO MUNICIPAL DE SAÚDE | N43: 10 | O43: Saúde | P43: 302 | Q43: Assistência Hospitalar e Ambulatorial | R43: 0114 | S43: Atenção Secundária e Terciária à Saúde | T43: 2894 | U43: Rede Hospitalar | V43: 339039 | W43: Despesa corrente | X43: Outras despesas correntes | Z43: SMSA | AA43: 80000 | AB43: 80000 | AC43: 80000 | AD43: 80000 | AE43: FUNDACAO BENJAMIN GUIMARAES | AF43: 17200429000125 | AG43: Hospitais | AH43: Hospitais | AJ43: 1 | AK43: 1 | AL43: 0322 | AM43: =IF(AL43="","",AL43&" - "&IFERROR(VLOOKUP(AL43,CODEBOOK_CAP!$C$2:$D$212,2,FALSE),"")) -> 0322 - ESTRUTURAS, HOSPITAIS, CLÍNICAS | AN43: =IF(AL43="","",IFERROR(VLOOKUP(AL43,CODEBOOK_CAP!$C$2:$E$212,3,FALSE),"")) -> Observações relacionadas as estruturas do sistema de saúde, como a construção de hospitais, postos de saúde, construção de maternidades, laboratórios, centros de saúde avançado, SAMU, Ambulâncias, UTI Móveis, leitos, compra de equipamentos médicos, Raio X, Ultrasom, equipamentos de diálise, capacidade de atendimento, estrutura e funcionamento de equipamentos públicos de saúde. | AO43: 0 | AQ43: 1 | AR43: 1 | AS43: Fundação Benjamin Guimarães (Hospital da Baleia) | AT43: 0 | AX43: Pendente
A44: 2022_BRAULIO_LARA_834_01 | B44: 2022 | C44: 4758 | D44: emendas_conslidadas(1).xlsx | E44: 2022_BRAULIO_LARA | F44: 834 | G44: Concluída | H44: Braulio Lara | I44: NOVO | J44: Ao reforço de dotação orçamentária destinada ao repasse para o Hospital Metropolitano Dr. Célio de Castro; | K44: 2302.10.302.114.2894.339039 | L44: 2302 | M44: FUNDO MUNICIPAL DE SAÚDE | N44: 10 | O44: Saúde | P44: 302 | Q44: Assistência Hospitalar e Ambulatorial | R44: 0114 | S44: Atenção Secundária e Terciária à Saúde | T44: 2894 | U44: Rede Hospitalar | V44: 339039 | W44: Despesa corrente | X44: Outras despesas correntes | Z44: SMSA | AA44: 80000 | AB44: 80000 | AC44: 80000 | AD44: 80000 | AE44: SERVICO SOCIAL AUTONOMO HOSPITAL METROPOLITANO DOUTOR CELIO DE CASTRO | AF44: 22012907000103 | AG44: Hospitais | AH44: Hospitais | AJ44: 1 | AK44: 1 | AL44: 0322 | AM44: =IF(AL44="","",AL44&" - "&IFERROR(VLOOKUP(AL44,CODEBOOK_CAP!$C$2:$D$212,2,FALSE),"")) -> 0322 - ESTRUTURAS, HOSPITAIS, CLÍNICAS | AN44: =IF(AL44="","",IFERROR(VLOOKUP(AL44,CODEBOOK_CAP!$C$2:$E$212,3,FALSE),"")) -> Observações relacionadas as estruturas do sistema de saúde, como a construção de hospitais, postos de saúde, construção de maternidades, laboratórios, centros de saúde avançado, SAMU, Ambulâncias, UTI Móveis, leitos, compra de equipamentos médicos, Raio X, Ultrasom, equipamentos de diálise, capacidade de atendimento, estrutura e funcionamento de equipamentos públicos de saúde. | AO44: 0 | AQ44: 1 | AR44: 1 | AS44: Hospital Metropolitano Dr. Célio de Castro | AT44: 0 | AX44: Pendente
A45: 2022_BRAULIO_LARA_835_01 | B45: 2022 | C45: 4759 | D45: emendas_conslidadas(1).xlsx | E45: 2022_BRAULIO_LARA | F45: 835 | G45: Concluída | H45: Braulio Lara | I45: NOVO | J45: Ao reforço de dotação orçamentária destinada ao repasse para a Fundação de Assistência Integral a Saúde - Hospital Sofia Feldman; | K45: 2302.10.302.114.2894.339039 | L45: 2302 | M45: FUNDO MUNICIPAL DE SAÚDE | N45: 10 | O45: Saúde | P45: 302 | Q45: Assistência Hospitalar e Ambulatorial | R45: 0114 | S45: Atenção Secundária e Terciária à Saúde | T45: 2894 | U45: Rede Hospitalar | V45: 339039 | W45: Despesa corrente | X45: Outras despesas correntes | Z45: SMSA | AA45: 80000 | AB45: 80000 | AC45: 80000 | AD45: 80000 | AE45: FUNDACAO DE ASSISTENCIA INTEGRAL A SAUDE FAIS | AF45: 25459256000192 | AG45: Hospitais | AH45: Hospitais | AJ45: 1 | AK45: 1 | AL45: 0332 | AM45: =IF(AL45="","",AL45&" - "&IFERROR(VLOOKUP(AL45,CODEBOOK_CAP!$C$2:$D$212,2,FALSE),"")) -> 0332 - SAÚDE INFANTIL, GRAVIDEZ E PRÉ-NATAL | AN45: =IF(AL45="","",IFERROR(VLOOKUP(AL45,CODEBOOK_CAP!$C$2:$E$212,3,FALSE),"")) -> Questões relacionadas a saúde da mãe, bebê e criança desde a gravidez. Campanhas de prevenção de gravidez indesejada, gravidez na adolescencia, Vacinação infantil ou vacina para doenças já existentes, atendimento pediátrico, atendimento obstétrico, parto, parto normal, cesariana, parto natural, pré-natal, consultas e exames pré-natal, atividades relacionadas a gravidez, saúde da mãe e do bebê, cuidados dentários infantís. Quando a política de prevenção for sobre crianças ou gravidez, codificar aqui 332. | AO45: 0 | AQ45: 1 | AR45: 1 | AS45: Hospital Sofia Feldman | AT45: 1 | AU45: gestantes;parturientes;puérperas;recém-nascidos | AX45: Pendente
A46: 2022_BRAULIO_LARA_836_01 | B46: 2022 | C46: 4760 | D46: emendas_conslidadas(1).xlsx | E46: 2022_BRAULIO_LARA | F46: 836 | G46: Concluída | H46: Braulio Lara | I46: NOVO | J46: Ao reforço de dotação orçamentária destinada ao repasse para a Santa Casa de Misericórdia de Belo Horizonte; | K46: 2302.10.302.114.2894.339039 | L46: 2302 | M46: FUNDO MUNICIPAL DE SAÚDE | N46: 10 | O46: Saúde | P46: 302 | Q46: Assistência Hospitalar e Ambulatorial | R46: 0114 | S46: Atenção Secundária e Terciária à Saúde | T46: 2894 | U46: Rede Hospitalar | V46: 339039 | W46: Despesa corrente | X46: Outras despesas correntes | Z46: SMSA | AA46: 80000 | AB46: 80000 | AC46: 80000 | AD46: 80000 | AE46: SANTA CASA DE MISERICORDIA DE BELO HORIZONTE | AF46: 17209891000193 | AG46: Hospitais | AH46: Hospitais | AJ46: 1 | AK46: 1 | AL46: 0322 | AM46: =IF(AL46="","",AL46&" - "&IFERROR(VLOOKUP(AL46,CODEBOOK_CAP!$C$2:$D$212,2,FALSE),"")) -> 0322 - ESTRUTURAS, HOSPITAIS, CLÍNICAS | AN46: =IF(AL46="","",IFERROR(VLOOKUP(AL46,CODEBOOK_CAP!$C$2:$E$212,3,FALSE),"")) -> Observações relacionadas as estruturas do sistema de saúde, como a construção de hospitais, postos de saúde, construção de maternidades, laboratórios, centros de saúde avançado, SAMU, Ambulâncias, UTI Móveis, leitos, compra de equipamentos médicos, Raio X, Ultrasom, equipamentos de diálise, capacidade de atendimento, estrutura e funcionamento de equipamentos públicos de saúde. | AO46: 0 | AQ46: 1 | AR46: 1 | AS46: Santa Casa de Misericórdia de Belo Horizonte | AT46: 0 | AX46: Pendente
A47: 2022_BRAULIO_LARA_837_01 | B47: 2022 | C47: 4761 | D47: emendas_conslidadas(1).xlsx | E47: 2022_BRAULIO_LARA | F47: 837 | G47: Concluída | H47: Braulio Lara | I47: NOVO | J47: Ao reforço de dotação orçamentária destinada ao repasse para a Associação Evangélica Beneficente de Minas Gerais - AEBMG; | K47: 2302.10.302.114.2894.339039 | L47: 2302 | M47: FUNDO MUNICIPAL DE SAÚDE | N47: 10 | O47: Saúde | P47: 302 | Q47: Assistência Hospitalar e Ambulatorial | R47: 0114 | S47: Atenção Secundária e Terciária à Saúde | T47: 2894 | U47: Rede Hospitalar | V47: 339039 | W47: Despesa corrente | X47: Outras despesas correntes | Z47: SMSA | AA47: 80000 | AB47: 0 | AC47: 0 | AD47: 0 | AE47: ASSOCIACAO EVANGELICA BENEFICENTE DE MINAS GERAIS | AF47: 17214743000167 | AG47: - | AH47: - | AI47: - | AJ47: 1 | AK47: 1 | AL47: 0322 | AM47: =IF(AL47="","",AL47&" - "&IFERROR(VLOOKUP(AL47,CODEBOOK_CAP!$C$2:$D$212,2,FALSE),"")) -> 0322 - ESTRUTURAS, HOSPITAIS, CLÍNICAS | AN47: =IF(AL47="","",IFERROR(VLOOKUP(AL47,CODEBOOK_CAP!$C$2:$E$212,3,FALSE),"")) -> Observações relacionadas as estruturas do sistema de saúde, como a construção de hospitais, postos de saúde, construção de maternidades, laboratórios, centros de saúde avançado, SAMU, Ambulâncias, UTI Móveis, leitos, compra de equipamentos médicos, Raio X, Ultrasom, equipamentos de diálise, capacidade de atendimento, estrutura e funcionamento de equipamentos públicos de saúde. | AO47: 0 | AQ47: 1 | AR47: 1 | AS47: Associação Evangélica Beneficente de Minas Gerais - AEBMG; | AT47: 0 | AX47: Pendente
A48: 2022_BRAULIO_LARA_838_01 | B48: 2022 | C48: 4762 | D48: emendas_conslidadas(1).xlsx | E48: 2022_BRAULIO_LARA | F48: 838 | G48: Concluída | H48: Braulio Lara | I48: NOVO | J48: Ao reforço de dotação orçamentária destinada ao Centro de Saúde Ouro Preto, localizado na Rua Jonas Jean, n. 77, bairro Ouro Preto, Belo Horizonte/MG, CEP 31.320-335, para contratação de serviços ligados a manutenções, melhorias e revitalização de instalações; | K48: 2302.10.122.117.1216.449051 | L48: 2302 | M48: FUNDO MUNICIPAL DE SAÚDE | N48: 10 | O48: Saúde | P48: 122 | Q48: Administração Geral | R48: 0117 | S48: Gestão do SUS | T48: 1216 | U48: Construção, Ampliação e Reforma de Unidades de Saúde | V48: 449051 | W48: Despesa de capital | X48: Investimentos | Z48: SMSA | AA48: 40000 | AB48: 40000 | AC48: 40000 | AD48: 40000 | AE48: CONSTRUTORA TORQUETE GONCALVES LTDA | AF48: 71354922000145 | AG48: PBH | AH48: Município de Belo Horizonte | AI48: 18715383000140 | AJ48: 1 | AK48: 1 | AL48: 0322 | AM48: =IF(AL48="","",AL48&" - "&IFERROR(VLOOKUP(AL48,CODEBOOK_CAP!$C$2:$D$212,2,FALSE),"")) -> 0322 - ESTRUTURAS, HOSPITAIS, CLÍNICAS | AN48: =IF(AL48="","",IFERROR(VLOOKUP(AL48,CODEBOOK_CAP!$C$2:$E$212,3,FALSE),"")) -> Observações relacionadas as estruturas do sistema de saúde, como a construção de hospitais, postos de saúde, construção de maternidades, laboratórios, centros de saúde avançado, SAMU, Ambulâncias, UTI Móveis, leitos, compra de equipamentos médicos, Raio X, Ultrasom, equipamentos de diálise, capacidade de atendimento, estrutura e funcionamento de equipamentos públicos de saúde. | AO48: 1 | AP48: Centro de Saúde Ouro Preto, localizado na Rua Jonas Jean, n. 77, bairro Ouro Preto, Belo Horizonte/MG, CEP 31.320-335 | AQ48: 1 | AR48: 1 | AS48: Centro de Saúde Ouro Preto, localizado na Rua Jonas Jean, n. 77, bairro Ouro Preto, Belo Horizonte/MG, CEP 31.320-335 | AT48: 0 | AX48: Pendente
A49: 2022_BRAULIO_LARA_854_01 | B49: 2022 | C49: 4776 | D49: emendas_conslidadas(1).xlsx | E49: 2022_BRAULIO_LARA | F49: 854 | G49: Concluída | H49: Braulio Lara | I49: NOVO | J49: Ao reforço de dotação orçamentária para pintura e revitalização da quadra poliesportiva no Parque Ageo Pio Sobrinho, situado na Av. Professor Mário Werneck, 2691 - Buritis; | K49: 2700.18.541.233.2811.449051 | L49: 2700 | M49: SECRETARIA MUNICIPAL DE OBRAS E INFRAESTRUTURA | N49: 18 | O49: Gestão Ambiental | P49: 541 | Q49: Preservação e Conservação Ambiental | R49: 0233 | S49: Manutenção da Cidade | T49: 2811 | U49: Serviços de Manutenção de Praças, Jardins e Arborização da Cidade | V49: 449051 | W49: Despesa de capital | X49: Investimentos | Z49: SMOBI | AA49: 59000 | AB49: 59000 | AC49: 59000 | AD49: 59000 | AE49: MAUMA ENGENHARIA E SERVICOS LTDA. | AF49: 02496187000191 | AG49: PBH | AH49: Município de Belo Horizonte | AI49: 18715383000140 | AJ49: 0 | AK49: 0 | AL49: 2300 | AM49: =IF(AL49="","",AL49&" - "&IFERROR(VLOOKUP(AL49,CODEBOOK_CAP!$C$2:$D$212,2,FALSE),"")) -> 2300 - GERAL | AN49: =IF(AL49="","",IFERROR(VLOOKUP(AL49,CODEBOOK_CAP!$C$2:$E$212,3,FALSE),"")) -> Observações relativas as políticas de cultura, Lei rouanet, patrimônio cultural, imaterial, políticas de artes, incentivos fiscais para artes, promoção de eventos culturais, amostras, teatro, dança, artes plásticas, artes visuais, museus, galerias públicas, idioma, lingua portuguesa. Grandes eventos esportivos, Copa do Mundo, Olimpiadas, Esporte e Lazer. | AO49: 1 | AP49: quadra poliesportiva no Parque Ageo Pio Sobrinho, situado na Av. Professor Mário Werneck, 2691 - Buritis | AQ49: 1 | AR49: 1 | AS49: quadra poliesportiva no Parque Ageo Pio Sobrinho, situado na Av. Professor Mário Werneck, 2691 - Buritis | AT49: 0 | AX49: Pendente | BB49: esporte e lazer
A50: 2022_BRAULIO_LARA_859_01 | B50: 2022 | C50: 4780 | D50: emendas_conslidadas(1).xlsx | E50: 2022_BRAULIO_LARA | F50: 859 | G50: Concluída | H50: Braulio Lara | I50: NOVO | J50: Ao reforço de dotação orçamentária para pintura, iluminação e reparos no vestiário e alambrado do Campo da ventosa, situado na Rua João Paulo II, 189 - Ventosa; | K50: 2700.04.122.233.1219.449051 | L50: 2700 | M50: SECRETARIA MUNICIPAL DE OBRAS E INFRAESTRUTURA | N50: 04 | O50: Administração | P50: 122 | Q50: Administração Geral | R50: 0233 | S50: Manutenção da Cidade | T50: 1219 | U50: Aquisição, Construção, Reforma e Readaptação de Imóveis | V50: 449051 | W50: Despesa de capital | X50: Investimentos | Z50: SMOBI | AA50: 40000 | AB50: 40000 | AC50: 40000 | AD50: 40000 | AE50: MAUMA ENGENHARIA E SERVICOS LTDA. | AF50: 02496187000191 | AG50: PBH | AH50: Município de Belo Horizonte | AI50: 18715383000140 | AJ50: 0 | AK50: 0 | AL50: 2300 | AM50: =IF(AL50="","",AL50&" - "&IFERROR(VLOOKUP(AL50,CODEBOOK_CAP!$C$2:$D$212,2,FALSE),"")) -> 2300 - GERAL | AN50: =IF(AL50="","",IFERROR(VLOOKUP(AL50,CODEBOOK_CAP!$C$2:$E$212,3,FALSE),"")) -> Observações relativas as políticas de cultura, Lei rouanet, patrimônio cultural, imaterial, políticas de artes, incentivos fiscais para artes, promoção de eventos culturais, amostras, teatro, dança, artes plásticas, artes visuais, museus, galerias públicas, idioma, lingua portuguesa. Grandes eventos esportivos, Copa do Mundo, Olimpiadas, Esporte e Lazer. | AO50: 1 | AP50: Campo da ventosa, situado na Rua João Paulo II, 189 - Ventosa | AQ50: 1 | AR50: 1 | AS50: Campo da ventosa, situado na Rua João Paulo II, 189 - Ventosa | AT50: 0 | AX50: Pendente | BB50: esporte e lazer
A51: 2022_BRAULIO_LARA_861_01 | B51: 2022 | C51: 4782 | D51: emendas_conslidadas(1).xlsx | E51: 2022_BRAULIO_LARA | F51: 861 | G51: Concluída | H51: Braulio Lara | I51: NOVO | J51: Ao reforço de dotação orçamentária para pintura de muros, bancos, piso e iluminação da quadra esportiva da Praça Osvaldo Zucheratte, situado na Avenida Teresa Cristina, 4.517-4.565 (antigos 245-247); | K51: 2700.18.541.233.2811.449051 | L51: 2700 | M51: SECRETARIA MUNICIPAL DE OBRAS E INFRAESTRUTURA | N51: 18 | O51: Gestão Ambiental | P51: 541 | Q51: Preservação e Conservação Ambiental | R51: 0233 | S51: Manutenção da Cidade | T51: 2811 | U51: Serviços de Manutenção de Praças, Jardins e Arborização da Cidade | V51: 449051 | W51: Despesa de capital | X51: Investimentos | Z51: SMOBI | AA51: 40000 | AB51: 0 | AC51: 0 | AD51: 0 | AE51: JTT LOCACOES E SERVICOS LTDA. | AF51: 07823480000130 | AG51: PBH | AH51: Município de Belo Horizonte | AI51: 18715383000140 | AJ51: 0 | AK51: 0 | AL51: 2300 | AM51: =IF(AL51="","",AL51&" - "&IFERROR(VLOOKUP(AL51,CODEBOOK_CAP!$C$2:$D$212,2,FALSE),"")) -> 2300 - GERAL | AN51: =IF(AL51="","",IFERROR(VLOOKUP(AL51,CODEBOOK_CAP!$C$2:$E$212,3,FALSE),"")) -> Observações relativas as políticas de cultura, Lei rouanet, patrimônio cultural, imaterial, políticas de artes, incentivos fiscais para artes, promoção de eventos culturais, amostras, teatro, dança, artes plásticas, artes visuais, museus, galerias públicas, idioma, lingua portuguesa. Grandes eventos esportivos, Copa do Mundo, Olimpiadas, Esporte e Lazer. | AO51: 1 | AP51: Quadra da praça Osvaldo Zucheratte, situado na Avenida Teresa Cristina, 4.517-4.565 (antigos 245-247); | AQ51: 1 | AR51: 1 | AS51: Quadra da praça Osvaldo Zucheratte, situado na Avenida Teresa Cristina, 4.517-4.565 (antigos 245-247); | AT51: 0 | AX51: Pendente | BB51: esporte e lazer
A52: 2022_BRAULIO_LARA_862_01 | B52: 2022 | C52: 4783 | D52: emendas_conslidadas(1).xlsx | E52: 2022_BRAULIO_LARA | F52: 862 | G52: Concluída | H52: Braulio Lara | I52: NOVO | J52: Ao reforço de dotação orçamentária para pintura e revitalização da quadra poliesportiva do Conjunto Betânia, localizada em local denominado Campo do Havaí, na Av. Teresa Cristina, 7883 - Betânia; | K52: 2700.18.541.233.2811.449051 | L52: 2700 | M52: SECRETARIA MUNICIPAL DE OBRAS E INFRAESTRUTURA | N52: 18 | O52: Gestão Ambiental | P52: 541 | Q52: Preservação e Conservação Ambiental | R52: 0233 | S52: Manutenção da Cidade | T52: 2811 | U52: Serviços de Manutenção de Praças, Jardins e Arborização da Cidade | V52: 449051 | W52: Despesa de capital | X52: Investimentos | Z52: SMOBI | AA52: 40000 | AB52: 0 | AC52: 0 | AD52: 0 | AE52: CONSTRUTORA CAMPOS E FILHOS LTDA. | AF52: 15862332000152 | AG52: - | AH52: - | AI52: - | AJ52: 0 | AK52: 0 | AL52: 2300 | AM52: =IF(AL52="","",AL52&" - "&IFERROR(VLOOKUP(AL52,CODEBOOK_CAP!$C$2:$D$212,2,FALSE),"")) -> 2300 - GERAL | AN52: =IF(AL52="","",IFERROR(VLOOKUP(AL52,CODEBOOK_CAP!$C$2:$E$212,3,FALSE),"")) -> Observações relativas as políticas de cultura, Lei rouanet, patrimônio cultural, imaterial, políticas de artes, incentivos fiscais para artes, promoção de eventos culturais, amostras, teatro, dança, artes plásticas, artes visuais, museus, galerias públicas, idioma, lingua portuguesa. Grandes eventos esportivos, Copa do Mundo, Olimpiadas, Esporte e Lazer. | AO52: 1 | AP52: quadra poliesportiva do Conjunto Betânia, localizada em local denominado Campo do Havaí, na Av. Teresa Cristina, 7883 - Betânia | AQ52: 1 | AR52: 1 | AS52: quadra poliesportiva do Conjunto Betânia, localizada em local denominado Campo do Havaí, na Av. Teresa Cristina, 7883 - Betânia | AT52: 0 | AX52: Pendente | BB52: esporte e lazer
A53: 2022_BRAULIO_LARA_863_01 | B53: 2022 | C53: 4784 | D53: emendas_conslidadas(1).xlsx | E53: 2022_BRAULIO_LARA | F53: 863 | G53: Concluída | H53: Braulio Lara | I53: NOVO | J53: Ao reforço de dotação orçamentária para pintura e revitalização da quadra poliesportiva do Complexo Esportivo Salgado Filho, situado na Avenida Teresa Cristina, 6849 Entre Ruas Carmelita Prates da Silva e Carlos Quadros - Salgado Filho; | K53: 2700.18.541.233.2811.449051 | L53: 2700 | M53: SECRETARIA MUNICIPAL DE OBRAS E INFRAESTRUTURA | N53: 18 | O53: Gestão Ambiental | P53: 541 | Q53: Preservação e Conservação Ambiental | R53: 0233 | S53: Manutenção da Cidade | T53: 2811 | U53: Serviços de Manutenção de Praças, Jardins e Arborização da Cidade | V53: 449051 | W53: Despesa de capital | X53: Investimentos | Z53: SMOBI | AA53: 40000 | AB53: 36053 | AC53: 36053 | AD53: 36053 | AE53: MAUMA ENGENHARIA E SERVICOS LTDA. | AF53: 02496187000191 | AG53: PBH | AH53: Município de Belo Horizonte | AI53: 18715383000140 | AJ53: 0 | AK53: 0 | AL53: 2300 | AM53: =IF(AL53="","",AL53&" - "&IFERROR(VLOOKUP(AL53,CODEBOOK_CAP!$C$2:$D$212,2,FALSE),"")) -> 2300 - GERAL | AN53: =IF(AL53="","",IFERROR(VLOOKUP(AL53,CODEBOOK_CAP!$C$2:$E$212,3,FALSE),"")) -> Observações relativas as políticas de cultura, Lei rouanet, patrimônio cultural, imaterial, políticas de artes, incentivos fiscais para artes, promoção de eventos culturais, amostras, teatro, dança, artes plásticas, artes visuais, museus, galerias públicas, idioma, lingua portuguesa. Grandes eventos esportivos, Copa do Mundo, Olimpiadas, Esporte e Lazer. | AO53: 1 | AP53: quadra poliesportiva do Complexo Esportivo Salgado Filho, situado na Avenida Teresa Cristina, 6849 Entre Ruas Carmelita Prates da Silva e Carlos Quadros - Salgado Filho | AQ53: 1 | AR53: 1 | AS53: quadra poliesportiva do Complexo Esportivo Salgado Filho, situado na Avenida Teresa Cristina, 6849 Entre Ruas Carmelita Prates da Silva e Carlos Quadros - Salgado Filho | AT53: 0 | AX53: Pendente | BB53: esporte e lazer
A54: 2022_BRUNO_MIRANDA_495_01 | B54: 2022 | C54: 4443 | D54: emendas_conslidadas(1).xlsx | E54: 2022_BRUNO_MIRANDA | F54: 495 | G54: Concluída | H54: Bruno Miranda | I54: PDT | J54: Ao reforço de dotação orçamentária para aquisição de playground para a Secretaria Municipal de Esporte e Lazer. A destinação se justifica uma vez que contribuirá para o desenvolvimento e formação integral das crianças através da brincadeira, estimulando também o convívio social; | K54: 2700.18.541.233.2811.449051 | L54: 2700 | M54: SECRETARIA MUNICIPAL DE OBRAS E INFRAESTRUTURA | N54: 18 | O54: Gestão Ambiental | P54: 541 | Q54: Preservação e Conservação Ambiental | R54: 0233 | S54: Manutenção da Cidade | T54: 2811 | U54: Serviços de Manutenção de Praças, Jardins e Arborização da Cidade | V54: 449051 | W54: Despesa de capital | X54: Investimentos | Z54: SMOBI | AA54: 384000 | AB54: 316726 | AC54: 316726 | AD54: 316726 | AE54: CONSTRUTORA SERVCOPA LTDA D.L.A ENGENHARIA LTDA GENESIS INDUSTRIA E COMERCIO DE ARTIGOS ESPORTIVOS LTDA CONSTRUTORA SERVCOPA LTDA GPO MERCANTIL E ENGENHARIA LTDA FLAT ENGENHARIA E CONSTRUCOES LTDA CONSTRUTORA TORQUETE GONCALVES LTDA CONSTRUTORA ITAMARACA LTDA | AG54: PBH | AH54: Município de Belo Horizonte | AI54: 18715383000140 | AJ54: 0 | AK54: 0 | AL54: 2300 | AM54: =IF(AL54="","",AL54&" - "&IFERROR(VLOOKUP(AL54,CODEBOOK_CAP!$C$2:$D$212,2,FALSE),"")) -> 2300 - GERAL | AN54: =IF(AL54="","",IFERROR(VLOOKUP(AL54,CODEBOOK_CAP!$C$2:$E$212,3,FALSE),"")) -> Observações relativas as políticas de cultura, Lei rouanet, patrimônio cultural, imaterial, políticas de artes, incentivos fiscais para artes, promoção de eventos culturais, amostras, teatro, dança, artes plásticas, artes visuais, museus, galerias públicas, idioma, lingua portuguesa. Grandes eventos esportivos, Copa do Mundo, Olimpiadas, Esporte e Lazer. | AO54: 0 | AQ54: 0 | AR54: 0 | AT54: 1 | AU54: criancas | AX54: Pendente | BB54: esporte e lazer
A55: 2022_BRUNO_MIRANDA_504_01 | B55: 2022 | C55: 4451 | D55: emendas_conslidadas(1).xlsx | E55: 2022_BRUNO_MIRANDA | F55: 504 | G55: Concluída | H55: Bruno Miranda | I55: PDT | J55: Ao reforço de dotação orçamentária para ampliação do atendimento de 800 pessoas que realizarão curso de qualificação para o trabalho na área de inclusão digital, com destinação de recursos no valor de 300.000,00 (trezentos mil reais) para realização da subação 0001 da ação 2404. A destinação de recursos se justifica uma vez que o conhecimento na área da inclusão digital incidi positivamente na empregabilidade e renda, gera maiores oportunidades, ampliando o leque de vagas de trabalho; | K55: 2800.11.334.237.2404.339039 | L55: 2800 | M55: SECRETARIA MUNICIPAL DE DESENVOLVIMENTO ECONÔMICO | N55: 11 | O55: Trabalho | P55: 334 | Q55: Fomento ao Trabalho | R55: 0237 | S55: Qualificação, Profissionalização e Emprego | T55: 2404 | U55: Ações de Qualificação, Profissionalização e Emprego | V55: 339039 | W55: Despesa corrente | X55: Outras despesas correntes | Z55: SMDE | AA55: 300000 | AB55: 0 | AC55: 0 | AD55: 0 | AE55: -FUNDO DE ACELERACAO PARA O DESENVOLVIMENTO VELA (FA.VELA) | AF55: - | AG55: - | AH55: - | AI55: - | AJ55: 0 | AK55: 0 | AL55: 0502 | AM55: =IF(AL55="","",AL55&" - "&IFERROR(VLOOKUP(AL55,CODEBOOK_CAP!$C$2:$D$212,2,FALSE),"")) -> 0502 - FORMAÇÃO E DESENVOLVIMENTO PROFISSIONAL | AN55: =IF(AL55="","",IFERROR(VLOOKUP(AL55,CODEBOOK_CAP!$C$2:$E$212,3,FALSE),"")) -> Programas de capacitação profissional, programas de incentivo ao emprego geral, reciclagem, realocação profissional em outra área, acordos e parcerias do estado com empresas privadas na capacitação, formação e treinamento profissional. | AO55: 0 | AQ55: 0 | AR55: 0 | AT55: 0 | AX55: Pendente
A56: 2022_BRUNO_MIRANDA_529_01 | B56: 2022 | C56: 4476 | D56: emendas_conslidadas(1).xlsx | E56: 2022_BRUNO_MIRANDA | F56: 529 | G56: Concluída | H56: Bruno Miranda | I56: PDT | J56: Destinação de recursos para a Associação Mineira de Educação Continuada - ASMEC, CNPJ: 05.263.848/0001-27, para a execução de atividades socioassistenciais, de acordo com o disposto na Lei Federal nº 8.742/93, em consonância com a referida inscrição no Conselho Municipal de Assistência Social de Belo Horizonte – CMAS-BH; | K56: 1011.08.244.113.2804.339039 | L56: 1011 | M56: FUNDO MUNICIPAL DE ASSISTÊNCIA SOCIAL | N56: 08 | O56: Assistência Social | P56: 244 | Q56: Assistência Comunitária | R56: 0113 | S56: Aprimoramento da Gestão do SUAS | T56: 2804 | U56: Gestão dos Equipamentos e Promoção Social | V56: 339039 | W56: Despesa corrente | X56: Outras despesas correntes | Z56: SMASDH | AA56: 644000 | AB56: 644000 | AC56: 644000 | AD56: 644000 | AE56: ASSOCIACAO MINEIRA DE EDUCACAO CONTINUADA ASMEC ASSOCIACAO MINEIRA DE EDUCACAO CONTINUADA ASMEC | AF56: 05263848000127 05263848000127 | AG56: Associações Diversas | AH56: Associações Diversas | AJ56: 0 | AK56: 0 | AL56: 1300 | AM56: =IF(AL56="","",AL56&" - "&IFERROR(VLOOKUP(AL56,CODEBOOK_CAP!$C$2:$D$212,2,FALSE),"")) -> 1300 - GERAL | AN56: =IF(AL56="","",IFERROR(VLOOKUP(AL56,CODEBOOK_CAP!$C$2:$E$212,3,FALSE),"")) -> Observações gerais sobre políticas sociais que envolvam mais de um casos dos subtópicos, políticas gerais de assistência social, welfare state, bem estar social, Ministérios e orcamentos como do Desenvolvimento social e combate e fome, desenvolvimento social, sistemas de gestão de políticas de assistencia, CAD UNICO, cadastros, sistemas computacionais para desenvolvimento de ações e políticas sociais, BPC - Benefício de Prestação Continuada geral para idosos e deficientes. NÃO CONFUNDIR POLÍTICAS SOCIAIS COM POLÍTICA DE EMPREGO E RENDA. Todas as questões, direitos, políticas que se relacionem com o TRABALHO como contrapartida, estão no código 5. Maternidade, Paternidade aposentadoria por tempo de serviço, INSS. | AO56: 0 | AQ56: 0 | AR56: 0 | AT56: 1 | AU56: criancas e adolescentes | AX56: Pendente
A57: 2022_BRUNO_MIRANDA_567_01 | B57: 2022 | C57: 4510 | D57: emendas_conslidadas(1).xlsx | E57: 2022_BRUNO_MIRANDA | F57: 567 | G57: Concluída | H57: Bruno Miranda | I57: PDT | J57: Ao reforço de dotação orçamentária para ampliação do atendimento para 23.000 pessoas da Faculdade de Odontologia da Universidade Federal de Minas Gerias, entidade pública que contratualiza com o Município de Belo Horizonte e presta serviço odontológico para a população, com destinação de recursos no valor de 1.000.000,00 para execução da subação 0001 da ação 2891; | K57: 2302.10.302.114.2891.339039 | L57: 2302 | M57: FUNDO MUNICIPAL DE SAÚDE | N57: 10 | O57: Saúde | P57: 302 | Q57: Assistência Hospitalar e Ambulatorial | R57: 0114 | S57: Atenção Secundária e Terciária à Saúde | T57: 2891 | U57: Rede Especializada | V57: 339039 | W57: Despesa corrente | X57: Outras despesas correntes | Z57: SMSA | AA57: 1000000 | AB57: 1000000 | AC57: 1000000 | AD57: 1000000 | AE57: FUNDACAO DE DESENVOLVIMENTO DA PESQUISA | AF57: 18720938000141 | AG57: Hospital público | AH57: UFMG | AI57: 17217985002743 | AJ57: 1 | AK57: 1 | AL57: 0399 | AM57: =IF(AL57="","",AL57&" - "&IFERROR(VLOOKUP(AL57,CODEBOOK_CAP!$C$2:$D$212,2,FALSE),"")) -> 0399 - OUTROS | AN57: =IF(AL57="","",IFERROR(VLOOKUP(AL57,CODEBOOK_CAP!$C$2:$E$212,3,FALSE),"")) -> Observações que versam sobre SAÚDE, mas que não se enquadram em nenhum dos itens acima. | AO57: 0 | AQ57: 0 | AR57: 0 | AT57: 0 | AX57: Pendente
A58: 2022_BRUNO_MIRANDA_574_01 | B58: 2022 | C58: 4517 | D58: emendas_conslidadas(1).xlsx | E58: 2022_BRUNO_MIRANDA | F58: 574 | G58: Concluída | H58: Bruno Miranda | I58: PDT | J58: Realização de projeto para construção de pista de skate no Centro de Vivência Agroecológica - CEVAE Coqueiros, localizado na Rua Eneida, 1589-1521, no bairro Coqueiros; | K58: 2700.18.541.233.2811.449051 | L58: 2700 | M58: SECRETARIA MUNICIPAL DE OBRAS E INFRAESTRUTURA | N58: 18 | O58: Gestão Ambiental | P58: 541 | Q58: Preservação e Conservação Ambiental | R58: 0233 | S58: Manutenção da Cidade | T58: 2811 | U58: Serviços de Manutenção de Praças, Jardins e Arborização da Cidade | V58: 449051 | W58: Despesa de capital | X58: Investimentos | Z58: SMOBI | AA58: 250000 | AB58: 250000 | AC58: 250000 | AD58: 250000 | AE58: ANIBAL BRAVIM DE MEIRA | AF58: 15026991000159 | AG58: PBH | AH58: Município de Belo Horizonte | AI58: 18715383000140 | AJ58: 0 | AK58: 0 | AL58: 2300 | AM58: =IF(AL58="","",AL58&" - "&IFERROR(VLOOKUP(AL58,CODEBOOK_CAP!$C$2:$D$212,2,FALSE),"")) -> 2300 - GERAL | AN58: =IF(AL58="","",IFERROR(VLOOKUP(AL58,CODEBOOK_CAP!$C$2:$E$212,3,FALSE),"")) -> Observações relativas as políticas de cultura, Lei rouanet, patrimônio cultural, imaterial, políticas de artes, incentivos fiscais para artes, promoção de eventos culturais, amostras, teatro, dança, artes plásticas, artes visuais, museus, galerias públicas, idioma, lingua portuguesa. Grandes eventos esportivos, Copa do Mundo, Olimpiadas, Esporte e Lazer. | AO58: 1 | AP58: pista de skate no Centro de Vivência Agroecológica - CEVAE Coqueiros, localizado na Rua Eneida, 1589-1521, no bairro Coqueiros | AQ58: 1 | AR58: 1 | AS58: pista de skate no Centro de Vivência Agroecológica - CEVAE Coqueiros, localizado na Rua Eneida, 1589-1521, no bairro Coqueiros | AT58: 0 | AX58: Pendente | BB58: esporte e lazer
A59: 2022_CIRO_PEREIRA_280_01 | B59: 2022 | C59: 4266 | D59: emendas_conslidadas(1).xlsx | E59: 2022_CIRO_PEREIRA | F59: 280 | G59: Concluída | H59: Ciro Pereira | I59: PTB | J59: Destinação de recursos para o Instituto Herdar, CNPJ: 09.047.452/0001-01, para a execução de atividades socioassistenciais, de acordo com o disposto na Lei Federal nº 8.742/93, em consonância com a referida inscrição no Conselho Municipal de Assistência Social de Belo Horizonte – CMAS-BH; | K59: 1011.1100.08.244.113.2.804.339039 | L59: 1011 | M59: FUNDO MUNICIPAL DE ASSISTÊNCIA SOCIAL | N59: 08 | O59: Assistência Social | P59: 244 | Q59: Assistência Comunitária | R59: 0113 | S59: Aprimoramento da Gestão do SUAS | T59: 2804 | U59: Gestão dos Equipamentos e Promoção Social | V59: 339039 | W59: Despesa corrente | X59: Outras despesas correntes | Z59: SMASDH | AA59: 60000 | AB59: 60000 | AC59: 60000 | AD59: 60000 | AE59: INSTITUTO HERDAR | AF59: 9047452000101 | AG59: Associações Diversas | AH59: Associações Diversas | AJ59: 0 | AK59: 0 | AL59: 1300 | AM59: =IF(AL59="","",AL59&" - "&IFERROR(VLOOKUP(AL59,CODEBOOK_CAP!$C$2:$D$212,2,FALSE),"")) -> 1300 - GERAL | AN59: =IF(AL59="","",IFERROR(VLOOKUP(AL59,CODEBOOK_CAP!$C$2:$E$212,3,FALSE),"")) -> Observações gerais sobre políticas sociais que envolvam mais de um casos dos subtópicos, políticas gerais de assistência social, welfare state, bem estar social, Ministérios e orcamentos como do Desenvolvimento social e combate e fome, desenvolvimento social, sistemas de gestão de políticas de assistencia, CAD UNICO, cadastros, sistemas computacionais para desenvolvimento de ações e políticas sociais, BPC - Benefício de Prestação Continuada geral para idosos e deficientes. NÃO CONFUNDIR POLÍTICAS SOCIAIS COM POLÍTICA DE EMPREGO E RENDA. Todas as questões, direitos, políticas que se relacionem com o TRABALHO como contrapartida, estão no código 5. Maternidade, Paternidade aposentadoria por tempo de serviço, INSS. | AO59: 0 | AQ59: 0 | AR59: 0 | AT59: 0 | AX59: Pendente
A60: 2022_CIRO_PEREIRA_282_01 | B60: 2022 | C60: 4267 | D60: emendas_conslidadas(1).xlsx | E60: 2022_CIRO_PEREIRA | F60: 282 | G60: Concluída | H60: Ciro Pereira | I60: PTB | J60: Emenda destinada ao Hospital Mario Penna, Associação Mario Penna, CNPJ 17.513.235/0001-80 CNES 2200457, com a finalidade de custeio para as atividades ambulatoriais e hospitalares, podendo a verba ser direcionada para a aquisição de medicamentos e insumos; | K60: 2302.3401.10.302.114.2.894.339039 | L60: 2302 | M60: FUNDO MUNICIPAL DE SAÚDE | N60: 10 | O60: Saúde | P60: 302 | Q60: Assistência Hospitalar e Ambulatorial | R60: 0114 | S60: Atenção Secundária e Terciária à Saúde | T60: 2894 | U60: Rede Hospitalar | V60: 339039 | W60: Despesa corrente | X60: Outras despesas correntes | Z60: SMSA | AA60: 540000 | AB60: 540000 | AC60: 540000 | AD60: 540000 | AE60: ASSOCIACAO MARIO PENNA | AF60: 17513235000180 | AG60: PBH | AH60: Município de Belo Horizonte | AI60: 18715383000140 | AJ60: 1 | AK60: 1 | AL60: 0322 | AM60: =IF(AL60="","",AL60&" - "&IFERROR(VLOOKUP(AL60,CODEBOOK_CAP!$C$2:$D$212,2,FALSE),"")) -> 0322 - ESTRUTURAS, HOSPITAIS, CLÍNICAS | AN60: =IF(AL60="","",IFERROR(VLOOKUP(AL60,CODEBOOK_CAP!$C$2:$E$212,3,FALSE),"")) -> Observações relacionadas as estruturas do sistema de saúde, como a construção de hospitais, postos de saúde, construção de maternidades, laboratórios, centros de saúde avançado, SAMU, Ambulâncias, UTI Móveis, leitos, compra de equipamentos médicos, Raio X, Ultrasom, equipamentos de diálise, capacidade de atendimento, estrutura e funcionamento de equipamentos públicos de saúde. | AO60: 0 | AQ60: 1 | AR60: 1 | AS60: Hospital Mario Penna | AT60: 0 | AX60: Pendente
A61: 2022_CIRO_PEREIRA_283_01 | B61: 2022 | C61: 4268 | D61: emendas_conslidadas(1).xlsx | E61: 2022_CIRO_PEREIRA | F61: 283 | G61: Concluída | H61: Ciro Pereira | I61: PTB | J61: Ao reforço de dotação orçamentária para a REDE PRÓPRIA DO SUS BH: NORDESTE. aquisição de material e equipamento permanente; | K61: 2302.10.301.157.2690.449052 | L61: 2302 | M61: FUNDO MUNICIPAL DE SAÚDE | N61: 10 | O61: Saúde | P61: 301 | Q61: Atenção Básica | R61: 0157 | S61: Atenção Primária à Saúde | T61: 2690 | U61: Atenção Primária à Saúde | V61: 449052 | W61: Despesa de capital | X61: Investimentos | Z61: SMSA | AA61: 100000 | AB61: 99987 | AC61: 99987 | AD61: 99987 | AG61: PBH | AH61: Município de Belo Horizonte | AI61: 18715383000140 | AJ61: 1 | AK61: 1 | AL61: 0304 | AM61: =IF(AL61="","",AL61&" - "&IFERROR(VLOOKUP(AL61,CODEBOOK_CAP!$C$2:$D$212,2,FALSE),"")) -> 0304 - CUIDADOS PRIMARIOS E ATENÇÃO BÁSICA | AN61: =IF(AL61="","",IFERROR(VLOOKUP(AL61,CODEBOOK_CAP!$C$2:$E$212,3,FALSE),"")) -> Medicina da familia, cuidados básicos e informativos de saude, higiene pessoal e higiene alimentar. Normalmente vinculada a comunidades carentes e de exercício de práticas gerenciais e sanitárias democráticas, atuacao de trabalho em equipe, dirigidas a populações de territórios bem delimitados, pelas quais assume a responsabilidade sanitária, considerando a dinamicidade existente no território em que vivem essas populações. Programa saúde da família, Política Nacional de atenção básica, Equipes de Saúde da Família, Agentes comunitários de saúde. Mias médicos quando se tratar de inclusão regional, interiorização do atendimento. Quando tratar apenas de prevenção e promoção a saude, como campanhas específicas contra dengue, DSTs, codificar em (331) | AO61: 1 | AP61: nordeste | AQ61: 0 | AR61: 0 | AT61: 0 | AX61: Pendente
A62: 2022_CIRO_PEREIRA_284_01 | B62: 2022 | C62: 4269 | D62: emendas_conslidadas(1).xlsx | E62: 2022_CIRO_PEREIRA | F62: 284 | G62: Concluída | H62: Ciro Pereira | I62: PTB | J62: Ao reforço de dotação orçamentária para a REDE PRÓPRIA DO SUS BH: NOROESTE. aquisição de material e equipamento permanente; | K62: 2302.10.301.157.2690.449052 | L62: 2302 | M62: FUNDO MUNICIPAL DE SAÚDE | N62: 10 | O62: Saúde | P62: 301 | Q62: Atenção Básica | R62: 0157 | S62: Atenção Primária à Saúde | T62: 2690 | U62: Atenção Primária à Saúde | V62: 449052 | W62: Despesa de capital | X62: Investimentos | Z62: SMSA | AA62: 100000 | AB62: 99882 | AC62: 99882 | AD62: 99882 | AE62: Nome Credor REPREMIG REPRESENTACAO E COMERCIO DE MINAS GERAIS LTDA COMERCIAL SILVESTRE LTDA COMERCIAL SILVESTRE LTDA ALFA MED SISTEMAS MEDICOS LTDA DRIVE A INFORMATICA LTDA | AF62: 65149197000251 41823463000130 41823463000130 11405384000149 00677870000108 | AG62: PBH | AH62: Município de Belo Horizonte | AI62: 18715383000140 | AJ62: 1 | AK62: 1 | AL62: 0304 | AM62: =IF(AL62="","",AL62&" - "&IFERROR(VLOOKUP(AL62,CODEBOOK_CAP!$C$2:$D$212,2,FALSE),"")) -> 0304 - CUIDADOS PRIMARIOS E ATENÇÃO BÁSICA | AN62: =IF(AL62="","",IFERROR(VLOOKUP(AL62,CODEBOOK_CAP!$C$2:$E$212,3,FALSE),"")) -> Medicina da familia, cuidados básicos e informativos de saude, higiene pessoal e higiene alimentar. Normalmente vinculada a comunidades carentes e de exercício de práticas gerenciais e sanitárias democráticas, atuacao de trabalho em equipe, dirigidas a populações de territórios bem delimitados, pelas quais assume a responsabilidade sanitária, considerando a dinamicidade existente no território em que vivem essas populações. Programa saúde da família, Política Nacional de atenção básica, Equipes de Saúde da Família, Agentes comunitários de saúde. Mias médicos quando se tratar de inclusão regional, interiorização do atendimento. Quando tratar apenas de prevenção e promoção a saude, como campanhas específicas contra dengue, DSTs, codificar em (331) | AO62: 1 | AP62: noroeste | AQ62: 0 | AR62: 0 | AT62: 0 | AX62: Pendente
A63: 2022_CIRO_PEREIRA_285_01 | B63: 2022 | C63: 4270 | D63: emendas_conslidadas(1).xlsx | E63: 2022_CIRO_PEREIRA | F63: 285 | G63: Concluída | H63: Ciro Pereira | I63: PTB | J63: Ao reforço de dotação orçamentária atenção primária a saúde: OESTE. aquisição de material e equipamento permanente; | K63: 2302.10.301.157.2690.449052 | L63: 2302 | M63: FUNDO MUNICIPAL DE SAÚDE | N63: 10 | O63: Saúde | P63: 301 | Q63: Atenção Básica | R63: 0157 | S63: Atenção Primária à Saúde | T63: 2690 | U63: Atenção Primária à Saúde | V63: 449052 | W63: Despesa de capital | X63: Investimentos | Z63: SMSA | AA63: 100000 | AB63: 99917 | AC63: 99917 | AD63: 99917 | AE63: REPREMIG REPRESENTACAO E COMERCIO DE MINAS GERAIS LTDA COMERCIAL SILVESTRE LTDA COMERCIAL SILVESTRE LTDA DRIVE A INFORMATICA LTDA ALFA MED SISTEMAS MEDICOS LTDA DRIVE A INFORMATICA LTDA | AF63: 65149197000251 41823463000130 41823463000130 00677870000108 11405384000149 00677870000108 | AG63: PBH | AH63: Município de Belo Horizonte | AI63: 18715383000140 | AJ63: 1 | AK63: 1 | AL63: 0304 | AM63: =IF(AL63="","",AL63&" - "&IFERROR(VLOOKUP(AL63,CODEBOOK_CAP!$C$2:$D$212,2,FALSE),"")) -> 0304 - CUIDADOS PRIMARIOS E ATENÇÃO BÁSICA | AN63: =IF(AL63="","",IFERROR(VLOOKUP(AL63,CODEBOOK_CAP!$C$2:$E$212,3,FALSE),"")) -> Medicina da familia, cuidados básicos e informativos de saude, higiene pessoal e higiene alimentar. Normalmente vinculada a comunidades carentes e de exercício de práticas gerenciais e sanitárias democráticas, atuacao de trabalho em equipe, dirigidas a populações de territórios bem delimitados, pelas quais assume a responsabilidade sanitária, considerando a dinamicidade existente no território em que vivem essas populações. Programa saúde da família, Política Nacional de atenção básica, Equipes de Saúde da Família, Agentes comunitários de saúde. Mias médicos quando se tratar de inclusão regional, interiorização do atendimento. Quando tratar apenas de prevenção e promoção a saude, como campanhas específicas contra dengue, DSTs, codificar em (331) | AO63: 0 | AQ63: 0 | AR63: 0 | AT63: 0 | AX63: Pendente
A64: 2022_CIRO_PEREIRA_286_01 | B64: 2022 | C64: 4271 | D64: emendas_conslidadas(1).xlsx | E64: 2022_CIRO_PEREIRA | F64: 286 | G64: Concluída | H64: Ciro Pereira | I64: PTB | J64: Ao reforço de dotação orçamentária UPA (PALMARES) para aquisição de material e equipamento permanente; | K64: 2302.10.302.114.2893.449052 | L64: 2302 | M64: FUNDO MUNICIPAL DE SAÚDE | N64: 10 | O64: Saúde | P64: 302 | Q64: Assistência Hospitalar e Ambulatorial | R64: 0114 | S64: Atenção Secundária e Terciária à Saúde | T64: 2893 | U64: Rede de Urgência e Emergência | V64: 449052 | W64: Despesa de capital | X64: Investimentos | Z64: SMSA | AA64: 50000 | AB64: 34320 | AC64: 34320 | AD64: 34320 | AE64: INSTRAMED INDUSTRIA MEDICO HOSPITALAR LTDA DRIVE A INFORMATICA LTDA IGM COMERCIO VAREJISTA DE PECAS E ACESSORIOS PARA VEICULOS LTDA | AF64: 90909631000110 00677870000108 23140085000109 | AG64: PBH | AH64: Município de Belo Horizonte | AI64: 18715383000140 | AJ64: 1 | AK64: 1 | AL64: 0322 | AM64: =IF(AL64="","",AL64&" - "&IFERROR(VLOOKUP(AL64,CODEBOOK_CAP!$C$2:$D$212,2,FALSE),"")) -> 0322 - ESTRUTURAS, HOSPITAIS, CLÍNICAS | AN64: =IF(AL64="","",IFERROR(VLOOKUP(AL64,CODEBOOK_CAP!$C$2:$E$212,3,FALSE),"")) -> Observações relacionadas as estruturas do sistema de saúde, como a construção de hospitais, postos de saúde, construção de maternidades, laboratórios, centros de saúde avançado, SAMU, Ambulâncias, UTI Móveis, leitos, compra de equipamentos médicos, Raio X, Ultrasom, equipamentos de diálise, capacidade de atendimento, estrutura e funcionamento de equipamentos públicos de saúde. | AO64: 0 | AQ64: 0 | AR64: 0 | AT64: 0 | AX64: Pendente
A65: 2022_CIRO_PEREIRA_287_01 | B65: 2022 | C65: 4272 | D65: emendas_conslidadas(1).xlsx | E65: 2022_CIRO_PEREIRA | F65: 287 | G65: Concluída | H65: Ciro Pereira | I65: PTB | J65: Reforço a dotação orçamentária para as despesas de equipamento e material permanente, UPA, Fernão Dias; | K65: 2302.10.302.114.2893.449052 | L65: 2302 | M65: FUNDO MUNICIPAL DE SAÚDE | N65: 10 | O65: Saúde | P65: 302 | Q65: Assistência Hospitalar e Ambulatorial | R65: 0114 | S65: Atenção Secundária e Terciária à Saúde | T65: 2893 | U65: Rede de Urgência e Emergência | V65: 449052 | W65: Despesa de capital | X65: Investimentos | Z65: SMSA | AA65: 50000 | AB65: 32568 | AC65: 32568 | AD65: 32568 | AE65: ESFERA MASTER COMERCIAL LTDA REPREMIG REPRESENTACAO E COMERCIO DE MINAS GERAIS LTDA GERBRA COMERCIO LTDA DRIVE A INFORMATICA LTDA | AF65: 26527362000129 65149197000251 21559804000103 00677870000108 | AG65: PBH | AH65: Município de Belo Horizonte | AI65: 18715383000140 | AJ65: 1 | AK65: 1 | AL65: 0322 | AM65: =IF(AL65="","",AL65&" - "&IFERROR(VLOOKUP(AL65,CODEBOOK_CAP!$C$2:$D$212,2,FALSE),"")) -> 0322 - ESTRUTURAS, HOSPITAIS, CLÍNICAS | AN65: =IF(AL65="","",IFERROR(VLOOKUP(AL65,CODEBOOK_CAP!$C$2:$E$212,3,FALSE),"")) -> Observações relacionadas as estruturas do sistema de saúde, como a construção de hospitais, postos de saúde, construção de maternidades, laboratórios, centros de saúde avançado, SAMU, Ambulâncias, UTI Móveis, leitos, compra de equipamentos médicos, Raio X, Ultrasom, equipamentos de diálise, capacidade de atendimento, estrutura e funcionamento de equipamentos públicos de saúde. | AO65: 0 | AQ65: 0 | AR65: 0 | AT65: 0 | AX65: Pendente
A66: 2022_CIRO_PEREIRA_288_01 | B66: 2022 | C66: 4273 | D66: emendas_conslidadas(1).xlsx | E66: 2022_CIRO_PEREIRA | F66: 288 | G66: Concluída | H66: Ciro Pereira | I66: PTB | J66: Ao reforço de dotação orçamentária atenção primária a saúde - REDE SUS BH - PAMPULHA. aquisição de material e equipamento permanente; | K66: 2302.3401.10.301.157.2.690.449052 | L66: 2302 | M66: FUNDO MUNICIPAL DE SAÚDE | N66: 10 | O66: Saúde | P66: 301 | Q66: Atenção Básica | R66: 0157 | S66: Atenção Primária à Saúde | T66: 2690 | U66: Atenção Primária à Saúde | V66: 449052 | W66: Despesa de capital | X66: Investimentos | Z66: SMSA | AA66: 100000 | AB66: 12600 | AC66: 12600 | AD66: 12600 | AE66: REPREMIG REPRESENTACAO E COMERCIO DE MINAS GERAIS LTDA COMERCIAL SILVESTRE LTDA ALFA MED SISTEMAS MEDICOS LTDA DRIVE A INFORMATICA LTDA | AF66: 65149197000251 41823463000130 11405384000149 00677870000108 | AG66: PBH | AH66: Município de Belo Horizonte | AI66: 18715383000140 | AJ66: 1 | AK66: 1 | AL66: 0304 | AM66: =IF(AL66="","",AL66&" - "&IFERROR(VLOOKUP(AL66,CODEBOOK_CAP!$C$2:$D$212,2,FALSE),"")) -> 0304 - CUIDADOS PRIMARIOS E ATENÇÃO BÁSICA | AN66: =IF(AL66="","",IFERROR(VLOOKUP(AL66,CODEBOOK_CAP!$C$2:$E$212,3,FALSE),"")) -> Medicina da familia, cuidados básicos e informativos de saude, higiene pessoal e higiene alimentar. Normalmente vinculada a comunidades carentes e de exercício de práticas gerenciais e sanitárias democráticas, atuacao de trabalho em equipe, dirigidas a populações de territórios bem delimitados, pelas quais assume a responsabilidade sanitária, considerando a dinamicidade existente no território em que vivem essas populações. Programa saúde da família, Política Nacional de atenção básica, Equipes de Saúde da Família, Agentes comunitários de saúde. Mias médicos quando se tratar de inclusão regional, interiorização do atendimento. Quando tratar apenas de prevenção e promoção a saude, como campanhas específicas contra dengue, DSTs, codificar em (331) | AO66: 1 | AP66: pampulha | AQ66: 0 | AR66: 0 | AT66: 0 | AX66: Pendente
A67: 2022_CLAUDIO_DO_MUNDO_NOVO_109_01 | B67: 2022 | C67: 4189 | D67: emendas_conslidadas(1).xlsx | E67: 2022_CLAUDIO_DO_MUNDO_NOVO | F67: 109 | G67: Concluída | H67: Cláudio do Mundo Novo | I67: PSD | J67: À reforma, adequação e revisão do telhado da Escola Municipal DORA TOMICH LAENDER, com sede na R. Julita Nunes Lima, nº 53, Bairro: Minas Caixa; | K67: 2200.0900.12.361.168.2.046.445042 | L67: 2200 | M67: SECRETARIA MUNICIPAL DE EDUCAÇÃO | N67: 12 | O67: Educação | P67: 361 | Q67: Ensino Fundamental | R67: 0168 | S67: Gestão da Política do Ensino Fundamental | T67: 2046 | U67: Gestão Descentralizada da Educação | V67: 445042 | W67: Despesa de capital | X67: Investimentos | Z67: SMED | AA67: 80000 | AB67: 80000 | AC67: 80000 | AD67: 80000 | AE67: CAIXA ESCOLAR ESCOLA MUNICIPAL DORA TOMICH LAENDER | AF67: 668417000127 | AG67: PBH | AH67: Município de Belo Horizonte | AI67: 18715383000140 | AJ67: 0 | AK67: 0 | AL67: 0607 | AM67: =IF(AL67="","",AL67&" - "&IFERROR(VLOOKUP(AL67,CODEBOOK_CAP!$C$2:$D$212,2,FALSE),"")) -> 0607 - PROMOCAO DA QUALIDADE, ESTRUTURA E AÇÕES | AN67: =IF(AL67="","",IFERROR(VLOOKUP(AL67,CODEBOOK_CAP!$C$2:$E$212,3,FALSE),"")) -> Atividades extra-curriculares de promoção da educação, ações em disciplinas específicos, como reforço em matemática, visitas escolares, renovação de edifícios, construção de bibliotecas, bibliotecas públicas e populares, campanhas de doação de livros, campanha de leitura, aquisição de livros e material pedagógico, ensino de informática extra curricular, idiomas, Ingles sem fronteiras. Construcao e reforma em escolas, creches. | AO67: 1 | AP67: R. Julita Nunes Lima, nº 53, Bairro: Minas Caixa | AQ67: 1 | AR67: 1 | AS67: Escola Municipal DORA TOMICH LAENDER, com sede na R. Julita Nunes Lima, nº 53, Bairro: Minas Caixa; | AT67: 1 | AU67: criancas e adolescentes | AX67: Pendente
A68: 2022_CLAUDIO_DO_MUNDO_NOVO_121_01 | B68: 2022 | C68: 4197 | D68: emendas_conslidadas(1).xlsx | E68: 2022_CLAUDIO_DO_MUNDO_NOVO | F68: 121 | G68: Concluída | H68: Cláudio do Mundo Novo | I68: PSD | J68: Pintura em geral da Escola Municipal Aurélio Pires, localizada na Rua Barrinha, 171, bairro Liberdade; | K68: 2200.0800.12.361.168.2.046.445042 | L68: 2200 | M68: SECRETARIA MUNICIPAL DE EDUCAÇÃO | N68: 12 | O68: Educação | P68: 361 | Q68: Ensino Fundamental | R68: 0168 | S68: Gestão da Política do Ensino Fundamental | T68: 2046 | U68: Gestão Descentralizada da Educação | V68: 445042 | W68: Despesa de capital | X68: Investimentos | Z68: SMED | AA68: 80000 | AB68: 80000 | AC68: 80000 | AD68: 80000 | AE68: CAIXA ESCOLAR DA ESCOLA MUNICIPAL AURELIO PIRES | AF68: 669024000138 | AG68: PBH | AH68: Município de Belo Horizonte | AI68: 18715383000140 | AJ68: 0 | AK68: 0 | AL68: 0607 | AM68: =IF(AL68="","",AL68&" - "&IFERROR(VLOOKUP(AL68,CODEBOOK_CAP!$C$2:$D$212,2,FALSE),"")) -> 0607 - PROMOCAO DA QUALIDADE, ESTRUTURA E AÇÕES | AN68: =IF(AL68="","",IFERROR(VLOOKUP(AL68,CODEBOOK_CAP!$C$2:$E$212,3,FALSE),"")) -> Atividades extra-curriculares de promoção da educação, ações em disciplinas específicos, como reforço em matemática, visitas escolares, renovação de edifícios, construção de bibliotecas, bibliotecas públicas e populares, campanhas de doação de livros, campanha de leitura, aquisição de livros e material pedagógico, ensino de informática extra curricular, idiomas, Ingles sem fronteiras. Construcao e reforma em escolas, creches. | AO68: 1 | AP68: Rua Barrinha, 171, bairro Liberdade | AQ68: 1 | AR68: 1 | AS68: Escola Municipal Aurélio Pires, localizada na Rua Barrinha, 171, bairro Liberdade | AT68: 1 | AU68: criancas e adolescentes | AX68: Pendente
A69: 2022_CLAUDIO_DO_MUNDO_NOVO_122_01 | B69: 2022 | C69: 4198 | D69: emendas_conslidadas(1).xlsx | E69: 2022_CLAUDIO_DO_MUNDO_NOVO | F69: 122 | G69: Concluída | H69: Cláudio do Mundo Novo | I69: PSD | J69: Reforma na Escola Municipal Padre Marzano Matias, localizada na Rua Érico Veríssimo, 1280, bairro Rio Branco; | K69: 2200.12.361.168.2046.445042 | L69: 2200 | M69: SECRETARIA MUNICIPAL DE EDUCAÇÃO | N69: 12 | O69: Educação | P69: 361 | Q69: Ensino Fundamental | R69: 0168 | S69: Gestão da Política do Ensino Fundamental | T69: 2046 | U69: Gestão Descentralizada da Educação | V69: 445042 | W69: Despesa de capital | X69: Investimentos | Z69: SMED | AA69: 80000 | AB69: 80000 | AC69: 80000 | AD69: 80000 | AE69: CAIXA ESCOLAR DA ESCOLA MUNICIPAL PADRE MARZANO MATIAS | AF69: 3711456000158 | AG69: PBH | AH69: Município de Belo Horizonte | AI69: 18715383000140 | AJ69: 0 | AK69: 0 | AL69: 0607 | AM69: =IF(AL69="","",AL69&" - "&IFERROR(VLOOKUP(AL69,CODEBOOK_CAP!$C$2:$D$212,2,FALSE),"")) -> 0607 - PROMOCAO DA QUALIDADE, ESTRUTURA E AÇÕES | AN69: =IF(AL69="","",IFERROR(VLOOKUP(AL69,CODEBOOK_CAP!$C$2:$E$212,3,FALSE),"")) -> Atividades extra-curriculares de promoção da educação, ações em disciplinas específicos, como reforço em matemática, visitas escolares, renovação de edifícios, construção de bibliotecas, bibliotecas públicas e populares, campanhas de doação de livros, campanha de leitura, aquisição de livros e material pedagógico, ensino de informática extra curricular, idiomas, Ingles sem fronteiras. Construcao e reforma em escolas, creches. | AO69: 1 | AP69: Rua Érico Veríssimo, 1280, bairro Rio Branco | AQ69: 1 | AR69: 1 | AS69: Escola Municipal Padre Marzano Matias, localizada na Rua Érico Veríssimo, 1280, bairro Rio Branco | AT69: 1 | AU69: criancas e adolescentes | AX69: Pendente
A70: 2022_CLAUDIO_DO_MUNDO_NOVO_123_01 | B70: 2022 | C70: 4199 | D70: emendas_conslidadas(1).xlsx | E70: 2022_CLAUDIO_DO_MUNDO_NOVO | F70: 123 | G70: Concluída | H70: Cláudio do Mundo Novo | I70: PSD | J70: Reforma na Escola Municipal Antônio Gomes Horta, localizada na Rua Antônio José de Oliveira, 161, bairro Parque São Pedro; | K70: 2200.0900.12.361.168.2.046.445042 | L70: 2200 | M70: SECRETARIA MUNICIPAL DE EDUCAÇÃO | N70: 12 | O70: Educação | P70: 361 | Q70: Ensino Fundamental | R70: 0168 | S70: Gestão da Política do Ensino Fundamental | T70: 2046 | U70: Gestão Descentralizada da Educação | V70: 445042 | W70: Despesa de capital | X70: Investimentos | Z70: SMED | AA70: 80000 | AB70: 80000 | AC70: 80000 | AD70: 80000 | AE70: CAIXA ESCOLAR DA ESCOLA MUNICIPAL ANTONIO GOMES HORTA | AF70: 20996229000135 | AG70: PBH | AH70: Município de Belo Horizonte | AI70: 18715383000140 | AJ70: 0 | AK70: 0 | AL70: 0607 | AM70: =IF(AL70="","",AL70&" - "&IFERROR(VLOOKUP(AL70,CODEBOOK_CAP!$C$2:$D$212,2,FALSE),"")) -> 0607 - PROMOCAO DA QUALIDADE, ESTRUTURA E AÇÕES | AN70: =IF(AL70="","",IFERROR(VLOOKUP(AL70,CODEBOOK_CAP!$C$2:$E$212,3,FALSE),"")) -> Atividades extra-curriculares de promoção da educação, ações em disciplinas específicos, como reforço em matemática, visitas escolares, renovação de edifícios, construção de bibliotecas, bibliotecas públicas e populares, campanhas de doação de livros, campanha de leitura, aquisição de livros e material pedagógico, ensino de informática extra curricular, idiomas, Ingles sem fronteiras. Construcao e reforma em escolas, creches. | AO70: 1 | AP70: Rua Antônio José de Oliveira, 161, bairro Parque São Pedro | AQ70: 1 | AR70: 1 | AS70: Escola Municipal Antônio Gomes Horta, localizada na Rua Antônio José de Oliveira, 161, bairro Parque São Pedro | AT70: 1 | AU70: criancas e adolescentes | AX70: Pendente
A71: 2022_CLAUDIO_DO_MUNDO_NOVO_150_01 | B71: 2022 | C71: 4201 | D71: emendas_conslidadas(1).xlsx | E71: 2022_CLAUDIO_DO_MUNDO_NOVO | F71: 150 | G71: Cancelada | H71: Cláudio do Mundo Novo | I71: PSD | J71: À Associação Fazenda Renascer, CNPJ: 17.515.115/0001-00, para obtenção de material de consumo alimentar; | K71: - | Z71: Cancelada | AA71: 30000 | AE71: - | AF71: - | AG71: - | AH71: - | AI71: - | AJ71: 0 | AK71: 0 | AL71: 1301 | AM71: =IF(AL71="","",AL71&" - "&IFERROR(VLOOKUP(AL71,CODEBOOK_CAP!$C$2:$D$212,2,FALSE),"")) -> 1301 - ASSISTÊNCIA ALIMENTAR | AN71: =IF(AL71="","",IFERROR(VLOOKUP(AL71,CODEBOOK_CAP!$C$2:$E$212,3,FALSE),"")) -> Políticas de combate a fome, políticas de educação alimentar, políticas de alimentos, incentivos a alimentos não industrializados, apoios a necessidades de alimentação, subnutrição, fome, desnutrição, somente políticas cujo foco principal seja a questão alimentar e o combate a fome. Fome Zero, Leve Leite, políticas de merenda escolar, alimentação nas escolas, creches. | AO71: 0 | AQ71: 0 | AR71: 0 | AT71: 0 | AX71: Pendente
A72: 2022_CLAUDIO_DO_MUNDO_NOVO_154_01 | B72: 2022 | C72: 4202 | D72: emendas_conslidadas(1).xlsx | E72: 2022_CLAUDIO_DO_MUNDO_NOVO | F72: 154 | G72: Concluída | H72: Cláudio do Mundo Novo | I72: PSD | J72: Associação Beneficente Paulo de Tarso/ Hospital Paulo de Tarso, CNPJ: 18.715.383.0001-40, destinados às obras e implantações de uma clínica especializada na realização de atendimento aos pacientes após a alta hospitalar; | K72: 2302.3401.10.302.114.2.894.339039 | L72: 2302 | M72: FUNDO MUNICIPAL DE SAÚDE | N72: 10 | O72: Saúde | P72: 302 | Q72: Assistência Hospitalar e Ambulatorial | R72: 0114 | S72: Atenção Secundária e Terciária à Saúde | T72: 2894 | U72: Rede Hospitalar | V72: 339039 | W72: Despesa corrente | X72: Outras despesas correntes | Z72: SMSA | AA72: 40000 | AB72: 40000 | AC72: 40000 | AD72: 40000 | AE72: REDE PAULO DE TARSO | AF72: 17226044000137 | AG72: - | AH72: - | AI72: - | AJ72: 1 | AK72: 1 | AL72: 0322 | AM72: =IF(AL72="","",AL72&" - "&IFERROR(VLOOKUP(AL72,CODEBOOK_CAP!$C$2:$D$212,2,FALSE),"")) -> 0322 - ESTRUTURAS, HOSPITAIS, CLÍNICAS | AN72: =IF(AL72="","",IFERROR(VLOOKUP(AL72,CODEBOOK_CAP!$C$2:$E$212,3,FALSE),"")) -> Observações relacionadas as estruturas do sistema de saúde, como a construção de hospitais, postos de saúde, construção de maternidades, laboratórios, centros de saúde avançado, SAMU, Ambulâncias, UTI Móveis, leitos, compra de equipamentos médicos, Raio X, Ultrasom, equipamentos de diálise, capacidade de atendimento, estrutura e funcionamento de equipamentos públicos de saúde. | AO72: 0 | AQ72: 0 | AR72: 0 | AT72: 0 | AX72: Pendente
A73: 2022_CLAUDIO_DO_MUNDO_NOVO_155_01 | B73: 2022 | C73: 4203 | D73: emendas_conslidadas(1).xlsx | E73: 2022_CLAUDIO_DO_MUNDO_NOVO | F73: 155 | G73: Concluída | H73: Cláudio do Mundo Novo | I73: PSD | J73: À compra de 34 computadores destinados para a Escola Municipal Tabajara Pedroso, localizada na rua Geraldo Assunção, nº:45, bairro: Candelária; | K73: 2200.12.122.140.2926.449052 | L73: 2200 | M73: SECRETARIA MUNICIPAL DE EDUCAÇÃO | N73: 12 | O73: Educação | P73: 122 | Q73: Administração Geral | R73: 0140 | S73: Gestão e Operacionalização da Política Educacional | T73: 2926 | U73: Tecnologia aplicada à Educação | V73: 449052 | W73: Despesa de capital | X73: Investimentos | Z73: SMED | AA73: 80000 | AB73: 0 | AC73: 0 | AD73: 0 | AG73: PBH | AH73: Município de Belo Horizonte | AI73: 18715383000140 | AJ73: 0 | AK73: 0 | AL73: 0607 | AM73: =IF(AL73="","",AL73&" - "&IFERROR(VLOOKUP(AL73,CODEBOOK_CAP!$C$2:$D$212,2,FALSE),"")) -> 0607 - PROMOCAO DA QUALIDADE, ESTRUTURA E AÇÕES | AN73: =IF(AL73="","",IFERROR(VLOOKUP(AL73,CODEBOOK_CAP!$C$2:$E$212,3,FALSE),"")) -> Atividades extra-curriculares de promoção da educação, ações em disciplinas específicos, como reforço em matemática, visitas escolares, renovação de edifícios, construção de bibliotecas, bibliotecas públicas e populares, campanhas de doação de livros, campanha de leitura, aquisição de livros e material pedagógico, ensino de informática extra curricular, idiomas, Ingles sem fronteiras. Construcao e reforma em escolas, creches. | AO73: 1 | AP73: rua Geraldo Assunção, nº:45, bairro: Candelária | AQ73: 1 | AR73: 1 | AS73: Escola Municipal Tabajara Pedroso, localizada na rua Geraldo Assunção, nº:45, bairro: Candelária | AT73: 1 | AU73: criancas e adolescentes | AX73: Pendente
A74: 2022_CLAUDIO_DO_MUNDO_NOVO_157_01 | B74: 2022 | C74: 4204 | D74: emendas_conslidadas(1).xlsx | E74: 2022_CLAUDIO_DO_MUNDO_NOVO | F74: 157 | G74: Cancelada | H74: Cláudio do Mundo Novo | I74: PSD | J74: À compra de materiais permanentes, tais como: 02 (duas) Geladeiras, 02 (dois) freezers, 02 (dois) fogões industriais, 02 (dois) fornos elétricos, 02 (dois) espremedores de frutas industrial, 02 (duas) batedeiras, ventiladores, 02 (dois) Liquidificadores resistentes e utensílios que guarnecem a cozinha, destinados a Casa Azul Acolhimento Só Por Hoje; | K74: - | Z74: Cancelada | AA74: 30000 | AE74: - | AF74: - | AG74: - | AH74: - | AI74: - | AJ74: 0 | AK74: 0 | AL74: 1300 | AM74: =IF(AL74="","",AL74&" - "&IFERROR(VLOOKUP(AL74,CODEBOOK_CAP!$C$2:$D$212,2,FALSE),"")) -> 1300 - GERAL | AN74: =IF(AL74="","",IFERROR(VLOOKUP(AL74,CODEBOOK_CAP!$C$2:$E$212,3,FALSE),"")) -> Observações gerais sobre políticas sociais que envolvam mais de um casos dos subtópicos, políticas gerais de assistência social, welfare state, bem estar social, Ministérios e orcamentos como do Desenvolvimento social e combate e fome, desenvolvimento social, sistemas de gestão de políticas de assistencia, CAD UNICO, cadastros, sistemas computacionais para desenvolvimento de ações e políticas sociais, BPC - Benefício de Prestação Continuada geral para idosos e deficientes. NÃO CONFUNDIR POLÍTICAS SOCIAIS COM POLÍTICA DE EMPREGO E RENDA. Todas as questões, direitos, políticas que se relacionem com o TRABALHO como contrapartida, estão no código 5. Maternidade, Paternidade aposentadoria por tempo de serviço, INSS. | AO74: 0 | AQ74: 1 | AR74: 1 | AS74: Casa Azul Acolhimento Só Por Hoje | AT74: 0 | AX74: Pendente
A75: 2022_CLAUDIO_DO_MUNDO_NOVO_158_01 | B75: 2022 | C75: 4205 | D75: emendas_conslidadas(1).xlsx | E75: 2022_CLAUDIO_DO_MUNDO_NOVO | F75: 158 | G75: Concluída | H75: Cláudio do Mundo Novo | I75: PSD | J75: À compra de medicamentos destinados à Fundação Benjamim Guimarães/Hospital da Baleia, CNPJ: 17.200.429/0001-25; | K75: 2302.3401.10.302.114.2.894.339039 | L75: 2302 | M75: FUNDO MUNICIPAL DE SAÚDE | N75: 10 | O75: Saúde | P75: 302 | Q75: Assistência Hospitalar e Ambulatorial | R75: 0114 | S75: Atenção Secundária e Terciária à Saúde | T75: 2894 | U75: Rede Hospitalar | V75: 339039 | W75: Despesa corrente | X75: Outras despesas correntes | Z75: SMSA | AA75: 40000 | AB75: 40000 | AC75: 40000 | AD75: 40000 | AE75: FUNDACAO BENJAMIN GUIMARAES | AF75: 17200429000125 | AG75: Hospitais | AH75: Hospitais | AJ75: 1 | AK75: 1 | AL75: 0322 | AM75: =IF(AL75="","",AL75&" - "&IFERROR(VLOOKUP(AL75,CODEBOOK_CAP!$C$2:$D$212,2,FALSE),"")) -> 0322 - ESTRUTURAS, HOSPITAIS, CLÍNICAS | AN75: =IF(AL75="","",IFERROR(VLOOKUP(AL75,CODEBOOK_CAP!$C$2:$E$212,3,FALSE),"")) -> Observações relacionadas as estruturas do sistema de saúde, como a construção de hospitais, postos de saúde, construção de maternidades, laboratórios, centros de saúde avançado, SAMU, Ambulâncias, UTI Móveis, leitos, compra de equipamentos médicos, Raio X, Ultrasom, equipamentos de diálise, capacidade de atendimento, estrutura e funcionamento de equipamentos públicos de saúde. | AO75: 0 | AQ75: 1 | AR75: 1 | AS75: Fundação Benjamim Guimarães/Hospital da Baleia | AT75: 0 | AX75: Pendente
A76: 2022_CLAUDIO_DO_MUNDO_NOVO_159_01 | B76: 2022 | C76: 4206 | D76: emendas_conslidadas(1).xlsx | E76: 2022_CLAUDIO_DO_MUNDO_NOVO | F76: 159 | G76: Concluída | H76: Cláudio do Mundo Novo | I76: PSD | J76: À compra de medicamentos e material de consumo para o Hospital Risoleta Tolentino Neves; | K76: 2302.3401.10.302.114.2.894.339039 | L76: 2302 | M76: FUNDO MUNICIPAL DE SAÚDE | N76: 10 | O76: Saúde | P76: 302 | Q76: Assistência Hospitalar e Ambulatorial | R76: 0114 | S76: Atenção Secundária e Terciária à Saúde | T76: 2894 | U76: Rede Hospitalar | V76: 339039 | W76: Despesa corrente | X76: Outras despesas correntes | Z76: SMSA | AA76: 150000 | AB76: 150000 | AC76: 150000 | AD76: 150000 | AE76: FUNDACAO DE DESENVOLVIMENTO DA PESQUISA | AF76: 18720938000141 | AG76: Hospitais | AH76: Hospitais | AJ76: 1 | AK76: 1 | AL76: 0322 | AM76: =IF(AL76="","",AL76&" - "&IFERROR(VLOOKUP(AL76,CODEBOOK_CAP!$C$2:$D$212,2,FALSE),"")) -> 0322 - ESTRUTURAS, HOSPITAIS, CLÍNICAS | AN76: =IF(AL76="","",IFERROR(VLOOKUP(AL76,CODEBOOK_CAP!$C$2:$E$212,3,FALSE),"")) -> Observações relacionadas as estruturas do sistema de saúde, como a construção de hospitais, postos de saúde, construção de maternidades, laboratórios, centros de saúde avançado, SAMU, Ambulâncias, UTI Móveis, leitos, compra de equipamentos médicos, Raio X, Ultrasom, equipamentos de diálise, capacidade de atendimento, estrutura e funcionamento de equipamentos públicos de saúde. | AO76: 0 | AQ76: 1 | AR76: 1 | AS76: Hospital Risoleta Tolentino Neves | AT76: 0 | AX76: Pendente
A77: 2022_CLAUDIO_DO_MUNDO_NOVO_161_01 | B77: 2022 | C77: 4207 | D77: emendas_conslidadas(1).xlsx | E77: 2022_CLAUDIO_DO_MUNDO_NOVO | F77: 161 | G77: Concluída | H77: Cláudio do Mundo Novo | I77: PSD | J77: Reforma na Escola EMEI Céu Azul na Rua São João Batista do Glória, 530, bairro Piratininga; | K77: 2200.0900.12.365.169.2.046.445042 | L77: 2200 | M77: SECRETARIA MUNICIPAL DE EDUCAÇÃO | N77: 12 | O77: Educação | P77: 365 | Q77: Educação Infantil | R77: 0169 | S77: Gestão da Política de Educação Infantil | T77: 2046 | U77: Gestão Descentralizada da Educação | V77: 445042 | W77: Despesa de capital | X77: Investimentos | Z77: SMED | AA77: 80000 | AB77: 80000 | AC77: 80000 | AD77: 80000 | AE77: CAIXA ESCOLAR DA ESCOLA MUNICIPAL DE EDUCACAO INFANTIL CEU AZUL | AF77: 32608510000132 | AG77: PBH | AH77: Município de Belo Horizonte | AI77: 18715383000140 | AJ77: 0 | AK77: 0 | AL77: 0607 | AM77: =IF(AL77="","",AL77&" - "&IFERROR(VLOOKUP(AL77,CODEBOOK_CAP!$C$2:$D$212,2,FALSE),"")) -> 0607 - PROMOCAO DA QUALIDADE, ESTRUTURA E AÇÕES | AN77: =IF(AL77="","",IFERROR(VLOOKUP(AL77,CODEBOOK_CAP!$C$2:$E$212,3,FALSE),"")) -> Atividades extra-curriculares de promoção da educação, ações em disciplinas específicos, como reforço em matemática, visitas escolares, renovação de edifícios, construção de bibliotecas, bibliotecas públicas e populares, campanhas de doação de livros, campanha de leitura, aquisição de livros e material pedagógico, ensino de informática extra curricular, idiomas, Ingles sem fronteiras. Construcao e reforma em escolas, creches. | AO77: 1 | AP77: Rua São João Batista do Glória, 530, bairro Piratininga | AQ77: 1 | AR77: 1 | AS77: Escola EMEI Céu Azul na Rua São João Batista do Glória, 530, bairro Piratininga | AT77: 1 | AU77: criancas | AX77: Pendente
A78: 2022_CLAUDIO_DO_MUNDO_NOVO_162_01 | B78: 2022 | C78: 4208 | D78: emendas_conslidadas(1).xlsx | E78: 2022_CLAUDIO_DO_MUNDO_NOVO | F78: 162 | G78: Impedimento Técnico | H78: Cláudio do Mundo Novo | I78: PSD | J78: À compra de medicamentos, destinados ao Hospital Metropolitano Dr. Célio de Castro/HMDCC; | K78: 2302.3401.10.302.114.2.894.339039 | L78: 2302 | M78: FUNDO MUNICIPAL DE SAÚDE | N78: 10 | O78: Saúde | P78: 302 | Q78: Assistência Hospitalar e Ambulatorial | R78: 0114 | S78: Atenção Secundária e Terciária à Saúde | T78: 2894 | U78: Rede Hospitalar | V78: 339039 | W78: Despesa corrente | X78: Outras despesas correntes | Z78: SMSA | AA78: 200000 | AB78: 200000 | AC78: 200000 | AD78: 200000 | AE78: SERVICO SOCIAL AUTONOMO HOSPITAL METROPOLITANO DOUTOR CELIO DE CASTRO | AF78: 22012907000103 | AG78: PBH | AH78: Município de Belo Horizonte | AI78: 18715383000140 | AJ78: 1 | AK78: 1 | AL78: 0322 | AM78: =IF(AL78="","",AL78&" - "&IFERROR(VLOOKUP(AL78,CODEBOOK_CAP!$C$2:$D$212,2,FALSE),"")) -> 0322 - ESTRUTURAS, HOSPITAIS, CLÍNICAS | AN78: =IF(AL78="","",IFERROR(VLOOKUP(AL78,CODEBOOK_CAP!$C$2:$E$212,3,FALSE),"")) -> Observações relacionadas as estruturas do sistema de saúde, como a construção de hospitais, postos de saúde, construção de maternidades, laboratórios, centros de saúde avançado, SAMU, Ambulâncias, UTI Móveis, leitos, compra de equipamentos médicos, Raio X, Ultrasom, equipamentos de diálise, capacidade de atendimento, estrutura e funcionamento de equipamentos públicos de saúde. | AO78: 0 | AQ78: 1 | AR78: 1 | AS78: Hospital Metropolitano Dr. Célio de Castro/HMDCC | AT78: 0 | AX78: Pendente
A79: 2022_CLAUDIO_DO_MUNDO_NOVO_163_01 | B79: 2022 | C79: 4209 | D79: emendas_conslidadas(1).xlsx | E79: 2022_CLAUDIO_DO_MUNDO_NOVO | F79: 163 | G79: Concluída | H79: Cláudio do Mundo Novo | I79: PSD | J79: À compra de medicamentos para a instituição Santa Casa de Misericórdia de Belo Horizonte; | K79: 2302.3401.10.302.114.2.894.339039 | L79: 2302 | M79: FUNDO MUNICIPAL DE SAÚDE | N79: 10 | O79: Saúde | P79: 302 | Q79: Assistência Hospitalar e Ambulatorial | R79: 0114 | S79: Atenção Secundária e Terciária à Saúde | T79: 2894 | U79: Rede Hospitalar | V79: 339039 | W79: Despesa corrente | X79: Outras despesas correntes | Z79: SMSA | AA79: 40000 | AB79: 40000 | AC79: 40000 | AD79: 40000 | AE79: SANTA CASA DE MISERICORDIA DE BELO HORIZONTE | AF79: 17209891000193 | AG79: PBH | AH79: Município de Belo Horizonte | AI79: 18715383000140 | AJ79: 1 | AK79: 1 | AL79: 0322 | AM79: =IF(AL79="","",AL79&" - "&IFERROR(VLOOKUP(AL79,CODEBOOK_CAP!$C$2:$D$212,2,FALSE),"")) -> 0322 - ESTRUTURAS, HOSPITAIS, CLÍNICAS | AN79: =IF(AL79="","",IFERROR(VLOOKUP(AL79,CODEBOOK_CAP!$C$2:$E$212,3,FALSE),"")) -> Observações relacionadas as estruturas do sistema de saúde, como a construção de hospitais, postos de saúde, construção de maternidades, laboratórios, centros de saúde avançado, SAMU, Ambulâncias, UTI Móveis, leitos, compra de equipamentos médicos, Raio X, Ultrasom, equipamentos de diálise, capacidade de atendimento, estrutura e funcionamento de equipamentos públicos de saúde. | AO79: 0 | AQ79: 1 | AR79: 1 | AS79: Santa Casa de Misericórdia de Belo Horizonte | AT79: 0 | AX79: Pendente
A80: 2022_CLAUDIO_DO_MUNDO_NOVO_164_01 | B80: 2022 | C80: 4210 | D80: emendas_conslidadas(1).xlsx | E80: 2022_CLAUDIO_DO_MUNDO_NOVO | F80: 164 | G80: Concluída | H80: Cláudio do Mundo Novo | I80: PSD | J80: Destinação de recursos para a Comunidade Católica Reviver, CNPJ 26.232.447/0001-00, para a execução de atividades socioassistenciais, de acordo com o disposto na Lei Federal nº 8.742/93, em consonância com a referida inscrição no Conselho Municipal de Assistência Social de Belo Horizonte – CMAS-BH; | K80: 1011.08.244.113.2804.339039 | L80: 1011 | M80: FUNDO MUNICIPAL DE ASSISTÊNCIA SOCIAL | N80: 08 | O80: Assistência Social | P80: 244 | Q80: Assistência Comunitária | R80: 0113 | S80: Aprimoramento da Gestão do SUAS | T80: 2804 | U80: Gestão dos Equipamentos e Promoção Social | V80: 339039 | W80: Despesa corrente | X80: Outras despesas correntes | Z80: SMASDH | AA80: 30000 | AB80: 0 | AC80: 0 | AD80: 0 | AG80: Associações Diversas | AH80: Associações Diversas | AJ80: 0 | AK80: 0 | AL80: 1300 | AM80: =IF(AL80="","",AL80&" - "&IFERROR(VLOOKUP(AL80,CODEBOOK_CAP!$C$2:$D$212,2,FALSE),"")) -> 1300 - GERAL | AN80: =IF(AL80="","",IFERROR(VLOOKUP(AL80,CODEBOOK_CAP!$C$2:$E$212,3,FALSE),"")) -> Observações gerais sobre políticas sociais que envolvam mais de um casos dos subtópicos, políticas gerais de assistência social, welfare state, bem estar social, Ministérios e orcamentos como do Desenvolvimento social e combate e fome, desenvolvimento social, sistemas de gestão de políticas de assistencia, CAD UNICO, cadastros, sistemas computacionais para desenvolvimento de ações e políticas sociais, BPC - Benefício de Prestação Continuada geral para idosos e deficientes. NÃO CONFUNDIR POLÍTICAS SOCIAIS COM POLÍTICA DE EMPREGO E RENDA. Todas as questões, direitos, políticas que se relacionem com o TRABALHO como contrapartida, estão no código 5. Maternidade, Paternidade aposentadoria por tempo de serviço, INSS. | AO80: 0 | AQ80: 0 | AR80: 0 | AT80: 0 | AX80: Pendente
A81: 2022_CLAUDIO_DO_MUNDO_NOVO_204_01 | B81: 2022 | C81: 4241 | D81: emendas_conslidadas(1).xlsx | E81: 2022_CLAUDIO_DO_MUNDO_NOVO | F81: 204 | G81: Concluída | H81: Cláudio do Mundo Novo | I81: PSD | J81: À compra de Monitores Mindray Umec 10 destinados ao Hospital Sofia Feldman; | K81: 2302.3401.10.302.114.2.894.339039 | L81: 2302 | M81: FUNDO MUNICIPAL DE SAÚDE | N81: 10 | O81: Saúde | P81: 302 | Q81: Assistência Hospitalar e Ambulatorial | R81: 0114 | S81: Atenção Secundária e Terciária à Saúde | T81: 2894 | U81: Rede Hospitalar | V81: 339039 | W81: Despesa corrente | X81: Outras despesas correntes | Z81: SMSA | AA81: 24000 | AB81: 24000 | AC81: 24000 | AD81: 24000 | AE81: FUNDACAO DE ASSISTENCIA INTEGRAL A SAUDE FAIS | AF81: 25459256000192 | AG81: PBH | AH81: Município de Belo Horizonte | AI81: 18715383000140 | AJ81: 1 | AK81: 1 | AL81: 0332 | AM81: =IF(AL81="","",AL81&" - "&IFERROR(VLOOKUP(AL81,CODEBOOK_CAP!$C$2:$D$212,2,FALSE),"")) -> 0332 - SAÚDE INFANTIL, GRAVIDEZ E PRÉ-NATAL | AN81: =IF(AL81="","",IFERROR(VLOOKUP(AL81,CODEBOOK_CAP!$C$2:$E$212,3,FALSE),"")) -> Questões relacionadas a saúde da mãe, bebê e criança desde a gravidez. Campanhas de prevenção de gravidez indesejada, gravidez na adolescencia, Vacinação infantil ou vacina para doenças já existentes, atendimento pediátrico, atendimento obstétrico, parto, parto normal, cesariana, parto natural, pré-natal, consultas e exames pré-natal, atividades relacionadas a gravidez, saúde da mãe e do bebê, cuidados dentários infantís. Quando a política de prevenção for sobre crianças ou gravidez, codificar aqui 332. | AO81: 0 | AQ81: 1 | AR81: 1 | AS81: Hospital Sofia Feldman | AT81: 1 | AU81: gestantes;parturientes;puérperas;recém-nascidos | AX81: Pendente
A82: 2022_CLAUDIO_DO_MUNDO_NOVO_205_01 | B82: 2022 | C82: 4242 | D82: emendas_conslidadas(1).xlsx | E82: 2022_CLAUDIO_DO_MUNDO_NOVO | F82: 205 | G82: Concluída | H82: Cláudio do Mundo Novo | I82: PSD | J82: À Escola Municipal Professor Moacyr Andrade, localizada na Rua dos Caçadores, nº 93, Lagoa, para a reforma dos pisos das salas de aula e do piso da entrada lateral da escola; | K82: 2200.0900.12.361.168.2.046.445042 | L82: 2200 | M82: SECRETARIA MUNICIPAL DE EDUCAÇÃO | N82: 12 | O82: Educação | P82: 361 | Q82: Ensino Fundamental | R82: 0168 | S82: Gestão da Política do Ensino Fundamental | T82: 2046 | U82: Gestão Descentralizada da Educação | V82: 445042 | W82: Despesa de capital | X82: Investimentos | Z82: SMED | AA82: 80000 | AB82: 80000 | AC82: 80000 | AD82: 80000 | AE82: CAIXA ESCOLAR ESCOLA MUNICIPAL PROFESSOR MOACYR ANDRADE | AF82: 702446000168 | AG82: PBH | AH82: Município de Belo Horizonte | AI82: 18715383000140 | AJ82: 0 | AK82: 0 | AL82: 0607 | AM82: =IF(AL82="","",AL82&" - "&IFERROR(VLOOKUP(AL82,CODEBOOK_CAP!$C$2:$D$212,2,FALSE),"")) -> 0607 - PROMOCAO DA QUALIDADE, ESTRUTURA E AÇÕES | AN82: =IF(AL82="","",IFERROR(VLOOKUP(AL82,CODEBOOK_CAP!$C$2:$E$212,3,FALSE),"")) -> Atividades extra-curriculares de promoção da educação, ações em disciplinas específicos, como reforço em matemática, visitas escolares, renovação de edifícios, construção de bibliotecas, bibliotecas públicas e populares, campanhas de doação de livros, campanha de leitura, aquisição de livros e material pedagógico, ensino de informática extra curricular, idiomas, Ingles sem fronteiras. Construcao e reforma em escolas, creches. | AO82: 1 | AP82: Rua dos Caçadores, nº 93, Lagoa | AQ82: 1 | AR82: 1 | AS82: Escola Municipal Professor Moacyr Andrade, localizada na Rua dos Caçadores, nº 93, Lagoa | AT82: 1 | AU82: criancas e adolescentes | AX82: Pendente
A83: 2022_CLAUDIO_DO_MUNDO_NOVO_206_01 | B83: 2022 | C83: 4243 | D83: emendas_conslidadas(1).xlsx | E83: 2022_CLAUDIO_DO_MUNDO_NOVO | F83: 206 | G83: Concluída | H83: Cláudio do Mundo Novo | I83: PSD | J83: À compra de equipamentos de proteção e segurança destinados a Guarda Municipal; | K83: 2100.1100.06.181.109.2.803.339030 | L83: 2100 | M83: SECRETARIA MUNICIPAL DE SEGURANÇA E PREVENÇÃO | N83: 06 | O83: Segurança Pública | P83: 181 | Q83: Policiamento | R83: 0109 | S83: Operacionalização dos serviços de segurança | T83: 2803 | U83: Operacionalização da Guarda Municipal de Belo Horizonte | V83: 339030 | W83: Despesa corrente | X83: Outras despesas correntes | Z83: SMSP | AA83: 100000 | AB83: 96763.75 | AC83: 0 | AD83: 0 | AE83: MAQNETE COMERCIO E SERVICOS EIRELI EPP | AF83: 18152404000166 | AG83: PBH | AH83: Município de Belo Horizonte | AI83: 18715383000140 | AJ83: 0 | AK83: 0 | AL83: 1201 | AM83: =IF(AL83="","",AL83&" - "&IFERROR(VLOOKUP(AL83,CODEBOOK_CAP!$C$2:$D$212,2,FALSE),"")) -> 1201 - POLÍCIA, AGENCIAS E INSTITUIÇÕES - LEI E CRIMES | AN83: =IF(AL83="","",IFERROR(VLOOKUP(AL83,CODEBOOK_CAP!$C$2:$E$212,3,FALSE),"")) -> Questões relacionadas aos atores, intituições, agencias e agentes que atuam em questões relacionadas a justiça, lei, crime e violência. Servicos e instituições de apoio civil. Assuntos relacionados a atuação de Bombeiros, socorristas, guarda floresta, guarda costeira e proteção civil. Ministério Público, Ministério da Justiça, Polícia Federal, Tribunal de Contas, inteligência, proteção a vítimas, delação premiada, sistemas e banco de dados de justiça, computação vinculada a sistemas de combate a crimes e fraudes. Aqui a observação é sobre as INSTITUIÇÕES EM SI, e não sobre o assunto do qual ela trata, Os assuntos estão nos próximos sub-códigos | AO83: 0 | AQ83: 0 | AR83: 0 | AT83: 0 | AX83: Pendente
A84: 2022_CLAUDIO_DO_MUNDO_NOVO_207_01 | B84: 2022 | C84: 4244 | D84: emendas_conslidadas(1).xlsx | E84: 2022_CLAUDIO_DO_MUNDO_NOVO | F84: 207 | G84: Impedimento Técnico | H84: Cláudio do Mundo Novo | I84: PSD | J84: Destinação de recursos para a Creche São João Paulo II, CNPJ: 00.056.897/0001-75, para a execução de atividades socioassistenciais, de acordo com o disposto na Lei Federal nº 8.742/93, em consonância com a referida inscrição no Conselho Municipal de Assistência Social de Belo Horizonte – CMAS-BH; | K84: 1011.08.244.113.2804.339039 | L84: 1011 | M84: FUNDO MUNICIPAL DE ASSISTÊNCIA SOCIAL | N84: 08 | O84: Assistência Social | P84: 244 | Q84: Assistência Comunitária | R84: 0113 | S84: Aprimoramento da Gestão do SUAS | T84: 2804 | U84: Gestão dos Equipamentos e Promoção Social | V84: 339039 | W84: Despesa corrente | X84: Outras despesas correntes | Z84: SMASDH | AA84: 30000 | AB84: 0 | AC84: 0 | AD84: 0 | AG84: Associações Diversas | AH84: Associações Diversas | AJ84: 0 | AK84: 0 | AL84: 1308 | AM84: =IF(AL84="","",AL84&" - "&IFERROR(VLOOKUP(AL84,CODEBOOK_CAP!$C$2:$D$212,2,FALSE),"")) -> 1308 - POLÍTICAS SOCIAIS PARA FAMÍLIAS E INFÂNCIA | AN84: =IF(AL84="","",IFERROR(VLOOKUP(AL84,CODEBOOK_CAP!$C$2:$E$212,3,FALSE),"")) -> Assuntos relacionados a guarda de crianças em casos de separação, assuntos relacionados a adoção de crianças, políticas para manutenção de crianças em lares, orfanatos, políticas voltadas para facilitar a adoção tardia. Licença maternidade, paternidade e auxilios que sejam derivados do trabalho formal, usar 503. | AO84: 0 | AQ84: 1 | AR84: 1 | AS84: Creche São João Paulo II | AT84: 1 | AU84: criancas | AX84: Pendente
A85: 2022_CLAUDIO_DO_MUNDO_NOVO_208_01 | B85: 2022 | C85: 4245 | D85: emendas_conslidadas(1).xlsx | E85: 2022_CLAUDIO_DO_MUNDO_NOVO | F85: 208 | G85: Concluída | H85: Cláudio do Mundo Novo | I85: PSD | J85: Destinação de recursos para a Associação de Resgate da Dignidade Humana Providência Divina, CNPJ 22.643.399/0001-61, para a execução de atividades socioassistenciais, de acordo com o disposto na Lei Federal nº 8.742/93, em consonância com a referida inscrição no Conselho Municipal de Assistência Social de Belo Horizonte – CMAS-BH; | K85: 1011.1100.08.244.113.2.804.339039 | L85: 1011 | M85: FUNDO MUNICIPAL DE ASSISTÊNCIA SOCIAL | N85: 08 | O85: Assistência Social | P85: 244 | Q85: Assistência Comunitária | R85: 0113 | S85: Aprimoramento da Gestão do SUAS | T85: 2804 | U85: Gestão dos Equipamentos e Promoção Social | V85: 339039 | W85: Despesa corrente | X85: Outras despesas correntes | Z85: SMASDH | AA85: 30000 | AB85: 30000 | AC85: 30000 | AD85: 30000 | AE85: ASSOCIACAO DE RESGATE DA DIGNIDADE HUMANA PROVIDENCIA DIVINA | AF85: 22643399000161 | AG85: Associações Diversas | AH85: Associações Diversas | AJ85: 0 | AK85: 0 | AL85: 1300 | AM85: =IF(AL85="","",AL85&" - "&IFERROR(VLOOKUP(AL85,CODEBOOK_CAP!$C$2:$D$212,2,FALSE),"")) -> 1300 - GERAL | AN85: =IF(AL85="","",IFERROR(VLOOKUP(AL85,CODEBOOK_CAP!$C$2:$E$212,3,FALSE),"")) -> Observações gerais sobre políticas sociais que envolvam mais de um casos dos subtópicos, políticas gerais de assistência social, welfare state, bem estar social, Ministérios e orcamentos como do Desenvolvimento social e combate e fome, desenvolvimento social, sistemas de gestão de políticas de assistencia, CAD UNICO, cadastros, sistemas computacionais para desenvolvimento de ações e políticas sociais, BPC - Benefício de Prestação Continuada geral para idosos e deficientes. NÃO CONFUNDIR POLÍTICAS SOCIAIS COM POLÍTICA DE EMPREGO E RENDA. Todas as questões, direitos, políticas que se relacionem com o TRABALHO como contrapartida, estão no código 5. Maternidade, Paternidade aposentadoria por tempo de serviço, INSS. | AO85: 0 | AQ85: 0 | AR85: 0 | AT85: 0 | AX85: Pendente
A86: 2022_CLAUDIO_DO_MUNDO_NOVO_209_01 | B86: 2022 | C86: 4246 | D86: emendas_conslidadas(1).xlsx | E86: 2022_CLAUDIO_DO_MUNDO_NOVO | F86: 209 | G86: Concluída | H86: Cláudio do Mundo Novo | I86: PSD | J86: Destinação de recursos para o Lar dos Meninos Dom Orione, CNPJ 17.313.388/0001-83, para a execução de atividades socioassistenciais, de acordo com o disposto na Lei Federal nº 8.742/93, em consonância com a referida inscrição no Conselho Municipal de Assistência Social de Belo Horizonte – CMAS-BH; | K86: 1011.1100.08.244.113.2.804.339039 | L86: 1011 | M86: FUNDO MUNICIPAL DE ASSISTÊNCIA SOCIAL | N86: 08 | O86: Assistência Social | P86: 244 | Q86: Assistência Comunitária | R86: 0113 | S86: Aprimoramento da Gestão do SUAS | T86: 2804 | U86: Gestão dos Equipamentos e Promoção Social | V86: 339039 | W86: Despesa corrente | X86: Outras despesas correntes | Z86: SMASDH | AA86: 30000 | AB86: 30000 | AC86: 30000 | AD86: 30000 | AE86: LAR DOS MENINOS DOM ORIONE | AF86: 17313388000183 | AG86: Associações Diversas | AH86: Associações Diversas | AJ86: 0 | AK86: 0 | AL86: 1308 | AM86: =IF(AL86="","",AL86&" - "&IFERROR(VLOOKUP(AL86,CODEBOOK_CAP!$C$2:$D$212,2,FALSE),"")) -> 1308 - POLÍTICAS SOCIAIS PARA FAMÍLIAS E INFÂNCIA | AN86: =IF(AL86="","",IFERROR(VLOOKUP(AL86,CODEBOOK_CAP!$C$2:$E$212,3,FALSE),"")) -> Assuntos relacionados a guarda de crianças em casos de separação, assuntos relacionados a adoção de crianças, políticas para manutenção de crianças em lares, orfanatos, políticas voltadas para facilitar a adoção tardia. Licença maternidade, paternidade e auxilios que sejam derivados do trabalho formal, usar 503. | AO86: 0 | AQ86: 1 | AR86: 1 | AS86: Lar dos Meninos Dom Orione | AT86: 1 | AU86: criancas e adolescentes | AX86: Pendente
A87: 2022_CLAUDIO_DO_MUNDO_NOVO_211_01 | B87: 2022 | C87: 4247 | D87: emendas_conslidadas(1).xlsx | E87: 2022_CLAUDIO_DO_MUNDO_NOVO | F87: 211 | G87: Concluída | H87: Cláudio do Mundo Novo | I87: PSD | J87: Destinação de recursos para o Instituto de Acolhimento Casa do Caminho, CNPJ 29.937.767/0001-23, para a execução de atividades socioassistenciais, de acordo com o disposto na Lei Federal nº 8.742/93, em consonância com a referida inscrição no Conselho Municipal de Assistência Social de Belo Horizonte – CMAS-BH; | K87: 1011.08.244.113.2804.339039 | L87: 1011 | M87: FUNDO MUNICIPAL DE ASSISTÊNCIA SOCIAL | N87: 08 | O87: Assistência Social | P87: 244 | Q87: Assistência Comunitária | R87: 0113 | S87: Aprimoramento da Gestão do SUAS | T87: 2804 | U87: Gestão dos Equipamentos e Promoção Social | V87: 339039 | W87: Despesa corrente | X87: Outras despesas correntes | Z87: SMASDH | AA87: 30000 | AB87: 30000 | AC87: 30000 | AD87: 30000 | AE87: INSTITUTO DE ACOLHIMENTO CASA DO CAMINHO | AF87: 29937767000123 | AG87: Associações Diversas | AH87: Associações Diversas | AJ87: 0 | AK87: 0 | AL87: 1300 | AM87: =IF(AL87="","",AL87&" - "&IFERROR(VLOOKUP(AL87,CODEBOOK_CAP!$C$2:$D$212,2,FALSE),"")) -> 1300 - GERAL | AN87: =IF(AL87="","",IFERROR(VLOOKUP(AL87,CODEBOOK_CAP!$C$2:$E$212,3,FALSE),"")) -> Observações gerais sobre políticas sociais que envolvam mais de um casos dos subtópicos, políticas gerais de assistência social, welfare state, bem estar social, Ministérios e orcamentos como do Desenvolvimento social e combate e fome, desenvolvimento social, sistemas de gestão de políticas de assistencia, CAD UNICO, cadastros, sistemas computacionais para desenvolvimento de ações e políticas sociais, BPC - Benefício de Prestação Continuada geral para idosos e deficientes. NÃO CONFUNDIR POLÍTICAS SOCIAIS COM POLÍTICA DE EMPREGO E RENDA. Todas as questões, direitos, políticas que se relacionem com o TRABALHO como contrapartida, estão no código 5. Maternidade, Paternidade aposentadoria por tempo de serviço, INSS. | AO87: 0 | AQ87: 0 | AR87: 0 | AT87: 0 | AX87: Pendente
A88: 2022_CLAUDIO_DO_MUNDO_NOVO_212_01 | B88: 2022 | C88: 4248 | D88: emendas_conslidadas(1).xlsx | E88: 2022_CLAUDIO_DO_MUNDO_NOVO | F88: 212 | G88: Concluída | H88: Cláudio do Mundo Novo | I88: PSD | J88: Destinação de recursos para Associação Gospa Mira, CNPJ 07.153.969/0001-41, para a execução de atividades socioassistenciais, de acordo com o disposto na Lei Federal nº 8.742/93, em consonância com a referida inscrição no Conselho Municipal de Assistência Social de Belo Horizonte – CMAS-BH; | K88: 1011.1100.08.244.113.2.804.339039 | L88: 1011 | M88: FUNDO MUNICIPAL DE ASSISTÊNCIA SOCIAL | N88: 08 | O88: Assistência Social | P88: 244 | Q88: Assistência Comunitária | R88: 0113 | S88: Aprimoramento da Gestão do SUAS | T88: 2804 | U88: Gestão dos Equipamentos e Promoção Social | V88: 339039 | W88: Despesa corrente | X88: Outras despesas correntes | Z88: SMASDH | AA88: 30000 | AB88: 30000 | AC88: 30000 | AD88: 30000 | AE88: ASSOCIACAO GOSPA MIRA | AF88: 7153969000141 | AG88: Associações Diversas | AH88: Associações Diversas | AJ88: 0 | AK88: 0 | AL88: 1300 | AM88: =IF(AL88="","",AL88&" - "&IFERROR(VLOOKUP(AL88,CODEBOOK_CAP!$C$2:$D$212,2,FALSE),"")) -> 1300 - GERAL | AN88: =IF(AL88="","",IFERROR(VLOOKUP(AL88,CODEBOOK_CAP!$C$2:$E$212,3,FALSE),"")) -> Observações gerais sobre políticas sociais que envolvam mais de um casos dos subtópicos, políticas gerais de assistência social, welfare state, bem estar social, Ministérios e orcamentos como do Desenvolvimento social e combate e fome, desenvolvimento social, sistemas de gestão de políticas de assistencia, CAD UNICO, cadastros, sistemas computacionais para desenvolvimento de ações e políticas sociais, BPC - Benefício de Prestação Continuada geral para idosos e deficientes. NÃO CONFUNDIR POLÍTICAS SOCIAIS COM POLÍTICA DE EMPREGO E RENDA. Todas as questões, direitos, políticas que se relacionem com o TRABALHO como contrapartida, estão no código 5. Maternidade, Paternidade aposentadoria por tempo de serviço, INSS. | AO88: 0 | AQ88: 0 | AR88: 0 | AT88: 0 | AX88: Pendente
A89: 2022_CLAUDIO_DO_MUNDO_NOVO_213_01 | B89: 2022 | C89: 4249 | D89: emendas_conslidadas(1).xlsx | E89: 2022_CLAUDIO_DO_MUNDO_NOVO | F89: 213 | G89: Concluída | H89: Cláudio do Mundo Novo | I89: PSD | J89: Destinação de recursos para Associação Ponto Cultural, CNPJ 05.768.787/0001-50, para a execução de atividades socioassistenciais, de acordo com o disposto na Lei Federal nº 8.742/93, em consonância com a referida inscrição no Conselho Municipal de Assistência Social de Belo Horizonte – CMAS-BH; | K89: 1011.1100.08.244.113.2.804.339039 | L89: 1011 | M89: FUNDO MUNICIPAL DE ASSISTÊNCIA SOCIAL | N89: 08 | O89: Assistência Social | P89: 244 | Q89: Assistência Comunitária | R89: 0113 | S89: Aprimoramento da Gestão do SUAS | T89: 2804 | U89: Gestão dos Equipamentos e Promoção Social | V89: 339039 | W89: Despesa corrente | X89: Outras despesas correntes | Z89: SMASDH | AA89: 30000 | AB89: 30000 | AC89: 30000 | AD89: 30000 | AE89: ASSOCIACAO PONTO CULTURAL | AF89: 5768787000150 | AG89: Associações Diversas | AH89: Associações Diversas | AJ89: 0 | AK89: 0 | AL89: 1300 | AM89: =IF(AL89="","",AL89&" - "&IFERROR(VLOOKUP(AL89,CODEBOOK_CAP!$C$2:$D$212,2,FALSE),"")) -> 1300 - GERAL | AN89: =IF(AL89="","",IFERROR(VLOOKUP(AL89,CODEBOOK_CAP!$C$2:$E$212,3,FALSE),"")) -> Observações gerais sobre políticas sociais que envolvam mais de um casos dos subtópicos, políticas gerais de assistência social, welfare state, bem estar social, Ministérios e orcamentos como do Desenvolvimento social e combate e fome, desenvolvimento social, sistemas de gestão de políticas de assistencia, CAD UNICO, cadastros, sistemas computacionais para desenvolvimento de ações e políticas sociais, BPC - Benefício de Prestação Continuada geral para idosos e deficientes. NÃO CONFUNDIR POLÍTICAS SOCIAIS COM POLÍTICA DE EMPREGO E RENDA. Todas as questões, direitos, políticas que se relacionem com o TRABALHO como contrapartida, estão no código 5. Maternidade, Paternidade aposentadoria por tempo de serviço, INSS. | AO89: 0 | AQ89: 0 | AR89: 0 | AT89: 0 | AX89: Pendente
A90: 2022_CLAUDIO_DO_MUNDO_NOVO_214_01 | B90: 2022 | C90: 4250 | D90: emendas_conslidadas(1).xlsx | E90: 2022_CLAUDIO_DO_MUNDO_NOVO | F90: 214 | G90: Concluída | H90: Cláudio do Mundo Novo | I90: PSD | J90: À compra de materiais permanentes destinados ao Hospital Júlia Kubitschek, localizado na Rua Doutor Cristiano Resende, 2745, bairro Milionários; | K90: 2302.3401.10.302.114.2.894.339039 | L90: 2302 | M90: FUNDO MUNICIPAL DE SAÚDE | N90: 10 | O90: Saúde | P90: 302 | Q90: Assistência Hospitalar e Ambulatorial | R90: 0114 | S90: Atenção Secundária e Terciária à Saúde | T90: 2894 | U90: Rede Hospitalar | V90: 339039 | W90: Despesa corrente | X90: Outras despesas correntes | Z90: SMSA | AA90: 100000 | AB90: 100000 | AC90: 100000 | AD90: 100000 | AE90: FUNDACAO HOSPITALAR DO ESTADO DE MINAS GERAIS | AF90: 19843929002820 | AG90: Hospitais | AH90: Hospitais | AJ90: 1 | AK90: 1 | AL90: 0322 | AM90: =IF(AL90="","",AL90&" - "&IFERROR(VLOOKUP(AL90,CODEBOOK_CAP!$C$2:$D$212,2,FALSE),"")) -> 0322 - ESTRUTURAS, HOSPITAIS, CLÍNICAS | AN90: =IF(AL90="","",IFERROR(VLOOKUP(AL90,CODEBOOK_CAP!$C$2:$E$212,3,FALSE),"")) -> Observações relacionadas as estruturas do sistema de saúde, como a construção de hospitais, postos de saúde, construção de maternidades, laboratórios, centros de saúde avançado, SAMU, Ambulâncias, UTI Móveis, leitos, compra de equipamentos médicos, Raio X, Ultrasom, equipamentos de diálise, capacidade de atendimento, estrutura e funcionamento de equipamentos públicos de saúde. | AO90: 1 | AP90: Rua Doutor Cristiano Resende, 2745, bairro Milionários; | AQ90: 1 | AR90: 1 | AS90: Hospital Júlia Kubitschek, localizado na Rua Doutor Cristiano Resende, 2745, bairro Milionários; | AT90: 0 | AX90: Pendente
A91: 2022_CLAUDIO_DO_MUNDO_NOVO_215_01 | B91: 2022 | C91: 4251 | D91: emendas_conslidadas(1).xlsx | E91: 2022_CLAUDIO_DO_MUNDO_NOVO | F91: 215 | G91: Concluída | H91: Cláudio do Mundo Novo | I91: PSD | J91: À compra de STENT FARMACOLÓGICO, destinado ao Hospital Madre Teresa/Instituto das Pequenas Missionárias de Maria Imaculada; | K91: 2302.10.302.114.2894.339039 | L91: 2302 | M91: FUNDO MUNICIPAL DE SAÚDE | N91: 10 | O91: Saúde | P91: 302 | Q91: Assistência Hospitalar e Ambulatorial | R91: 0114 | S91: Atenção Secundária e Terciária à Saúde | T91: 2894 | U91: Rede Hospitalar | V91: 339039 | W91: Despesa corrente | X91: Outras despesas correntes | Z91: SMSA | AA91: 40000 | AB91: 40000 | AC91: 40000 | AD91: 40000 | AE91: INSTITUTO DAS PEQUENAS MISSIONARIAS DE MARIA IMACULADA | AF91: 60194990000844 | AG91: - | AH91: - | AI91: - | AJ91: 1 | AK91: 1 | AL91: 0322 | AM91: =IF(AL91="","",AL91&" - "&IFERROR(VLOOKUP(AL91,CODEBOOK_CAP!$C$2:$D$212,2,FALSE),"")) -> 0322 - ESTRUTURAS, HOSPITAIS, CLÍNICAS | AN91: =IF(AL91="","",IFERROR(VLOOKUP(AL91,CODEBOOK_CAP!$C$2:$E$212,3,FALSE),"")) -> Observações relacionadas as estruturas do sistema de saúde, como a construção de hospitais, postos de saúde, construção de maternidades, laboratórios, centros de saúde avançado, SAMU, Ambulâncias, UTI Móveis, leitos, compra de equipamentos médicos, Raio X, Ultrasom, equipamentos de diálise, capacidade de atendimento, estrutura e funcionamento de equipamentos públicos de saúde. | AO91: 0 | AQ91: 1 | AR91: 1 | AS91: Hospital Madre Teresa/Instituto das Pequenas Missionárias de Maria Imaculada | AT91: 0 | AX91: Pendente
A92: 2022_CLAUDIO_DO_MUNDO_NOVO_216_01 | B92: 2022 | C92: 4252 | D92: emendas_conslidadas(1).xlsx | E92: 2022_CLAUDIO_DO_MUNDO_NOVO | F92: 216 | G92: Concluída | H92: Cláudio do Mundo Novo | I92: PSD | J92: À compra de material de consumos destinado ao Hospital Metropolitano Odilon Behrens; | K92: 2302.3401.10.302.114.2.894.339139 | L92: 2302 | M92: FUNDO MUNICIPAL DE SAÚDE | N92: 10 | O92: Saúde | P92: 302 | Q92: Assistência Hospitalar e Ambulatorial | R92: 0114 | S92: Atenção Secundária e Terciária à Saúde | T92: 2894 | U92: Rede Hospitalar | V92: 339139 | W92: Despesa corrente | X92: Outras despesas correntes | Z92: SMSA | AA92: 100000 | AB92: 100000 | AC92: 100000 | AD92: 100000 | AE92: HOSPITAL METROPOLITANO ODILON BEHRENS HOB | AF92: 16692121000181 | AG92: PBH | AH92: Município de Belo Horizonte | AI92: 18715383000140 | AJ92: 1 | AK92: 1 | AL92: 0322 | AM92: =IF(AL92="","",AL92&" - "&IFERROR(VLOOKUP(AL92,CODEBOOK_CAP!$C$2:$D$212,2,FALSE),"")) -> 0322 - ESTRUTURAS, HOSPITAIS, CLÍNICAS | AN92: =IF(AL92="","",IFERROR(VLOOKUP(AL92,CODEBOOK_CAP!$C$2:$E$212,3,FALSE),"")) -> Observações relacionadas as estruturas do sistema de saúde, como a construção de hospitais, postos de saúde, construção de maternidades, laboratórios, centros de saúde avançado, SAMU, Ambulâncias, UTI Móveis, leitos, compra de equipamentos médicos, Raio X, Ultrasom, equipamentos de diálise, capacidade de atendimento, estrutura e funcionamento de equipamentos públicos de saúde. | AO92: 0 | AQ92: 1 | AR92: 1 | AS92: Hospital Metropolitano Odilon Behrens | AT92: 0 | AX92: Pendente
A93: 2022_CLAUDIO_DO_MUNDO_NOVO_264_01 | B93: 2022 | C93: 4260 | D93: emendas_conslidadas(1).xlsx | E93: 2022_CLAUDIO_DO_MUNDO_NOVO | F93: 264 | G93: Concluída | H93: Cláudio do Mundo Novo | I93: PSD | J93: Destinação de recursos para Associação Cruz de Malta, CNPJ 00.436.790/0003-14, para a execução de atividades socioassistenciais, de acordo com o disposto na Lei Federal nº 8.742/93, em consonância com a referida inscrição no Conselho Municipal de Assistência Social de Belo Horizonte – CMAS-BH; | K93: 1011.1100.08.244.113.2.804.339039 | L93: 1011 | M93: FUNDO MUNICIPAL DE ASSISTÊNCIA SOCIAL | N93: 08 | O93: Assistência Social | P93: 244 | Q93: Assistência Comunitária | R93: 0113 | S93: Aprimoramento da Gestão do SUAS | T93: 2804 | U93: Gestão dos Equipamentos e Promoção Social | V93: 339039 | W93: Despesa corrente | X93: Outras despesas correntes | Z93: SMASDH | AA93: 30000 | AB93: 30000 | AC93: 30000 | AD93: 30000 | AE93: ASSOCIACAO CRUZ DE MALTA | AF93: 436790000314 | AG93: Associações Diversas | AH93: Associações Diversas | AJ93: 0 | AK93: 0 | AL93: 1300 | AM93: =IF(AL93="","",AL93&" - "&IFERROR(VLOOKUP(AL93,CODEBOOK_CAP!$C$2:$D$212,2,FALSE),"")) -> 1300 - GERAL | AN93: =IF(AL93="","",IFERROR(VLOOKUP(AL93,CODEBOOK_CAP!$C$2:$E$212,3,FALSE),"")) -> Observações gerais sobre políticas sociais que envolvam mais de um casos dos subtópicos, políticas gerais de assistência social, welfare state, bem estar social, Ministérios e orcamentos como do Desenvolvimento social e combate e fome, desenvolvimento social, sistemas de gestão de políticas de assistencia, CAD UNICO, cadastros, sistemas computacionais para desenvolvimento de ações e políticas sociais, BPC - Benefício de Prestação Continuada geral para idosos e deficientes. NÃO CONFUNDIR POLÍTICAS SOCIAIS COM POLÍTICA DE EMPREGO E RENDA. Todas as questões, direitos, políticas que se relacionem com o TRABALHO como contrapartida, estão no código 5. Maternidade, Paternidade aposentadoria por tempo de serviço, INSS. | AO93: 0 | AQ93: 0 | AR93: 0 | AT93: 0 | AX93: Pendente
A94: 2022_CLAUDIO_DO_MUNDO_NOVO_265_01 | B94: 2022 | C94: 4261 | D94: emendas_conslidadas(1).xlsx | E94: 2022_CLAUDIO_DO_MUNDO_NOVO | F94: 265 | G94: Concluída | H94: Cláudio do Mundo Novo | I94: PSD | J94: À compra de materiais de consumo, bem como: medicamentos, gases, entre outros para o Instituto Mário Penna; | K94: 2302.3401.10.302.114.2.894.339039 | L94: 2302 | M94: FUNDO MUNICIPAL DE SAÚDE | N94: 10 | O94: Saúde | P94: 302 | Q94: Assistência Hospitalar e Ambulatorial | R94: 0114 | S94: Atenção Secundária e Terciária à Saúde | T94: 2894 | U94: Rede Hospitalar | V94: 339039 | W94: Despesa corrente | X94: Outras despesas correntes | Z94: SMSA | AA94: 40000 | AB94: 40000 | AC94: 40000 | AD94: 40000 | AE94: ASSOCIACAO MARIO PENNA | AF94: 17513235000180 | AG94: PBH | AH94: Município de Belo Horizonte | AI94: 18715383000140 | AJ94: 1 | AK94: 1 | AL94: 0322 | AM94: =IF(AL94="","",AL94&" - "&IFERROR(VLOOKUP(AL94,CODEBOOK_CAP!$C$2:$D$212,2,FALSE),"")) -> 0322 - ESTRUTURAS, HOSPITAIS, CLÍNICAS | AN94: =IF(AL94="","",IFERROR(VLOOKUP(AL94,CODEBOOK_CAP!$C$2:$E$212,3,FALSE),"")) -> Observações relacionadas as estruturas do sistema de saúde, como a construção de hospitais, postos de saúde, construção de maternidades, laboratórios, centros de saúde avançado, SAMU, Ambulâncias, UTI Móveis, leitos, compra de equipamentos médicos, Raio X, Ultrasom, equipamentos de diálise, capacidade de atendimento, estrutura e funcionamento de equipamentos públicos de saúde. | AO94: 0 | AQ94: 1 | AR94: 1 | AS94: Instituto Mário Penna; | AT94: 0 | AX94: Pendente
A95: 2022_CLAUDIO_DO_MUNDO_NOVO_268_01 | B95: 2022 | C95: 4262 | D95: emendas_conslidadas(1).xlsx | E95: 2022_CLAUDIO_DO_MUNDO_NOVO | F95: 268 | G95: Concluída | H95: Cláudio do Mundo Novo | I95: PSD | J95: Valor destinado a obras no canteiro central da Avenida Sebastião de Brito, bairro: Dona Clara; | K95: 2700.1100.15.451.233.1.396.449051 | L95: 2700 | M95: SECRETARIA MUNICIPAL DE OBRAS E INFRAESTRUTURA | N95: 15 | O95: Urbanismo | P95: 451 | Q95: Infra-Estrutura Urbana | R95: 0233 | S95: Manutenção da Cidade | T95: 1396 | U95: Infraestrutura Urbana | V95: 449051 | W95: Despesa de capital | X95: Investimentos | Z95: SMOBI | AA95: 90610 | AB95: 77779 | AC95: 77779 | AD95: 77779 | AE95: CONSTRUTORA CAMPOS E FILHOS LTDA | AF95: 15862332000152 | AG95: PBH | AH95: Município de Belo Horizonte | AI95: 18715383000140 | AJ95: 0 | AK95: 0 | AL95: 1002 | AM95: =IF(AL95="","",AL95&" - "&IFERROR(VLOOKUP(AL95,CODEBOOK_CAP!$C$2:$D$212,2,FALSE),"")) -> 1002 - CARROS, TRÂNSITO, CONSTRUÇÃO E MANUTENÇÃO DE RUAS E ESTRADAS | AN95: =IF(AL95="","",IFERROR(VLOOKUP(AL95,CODEBOOK_CAP!$C$2:$E$212,3,FALSE),"")) -> Construção, manutenção de ruas, avenidas, estradas. BRs, pedágios, privatizações, concessinárias, segurança nas estradas, leis de trânsito relacionadas a via, limite de velocidade, sinalização, recapeamento de ruas, pavimentação estradas de terra, não pavimentadas, acidentes e camapanhas de prevencao contra acidentes de transito. Observações sobre regulação de transportes não públicos de carros, veículos de passeio, uber, taxi, transporte de cargas terrestre, frete, trânsito em vias públicas, regulamentação de tipos de carteira de motorista, especificações para caminhoneiros, testes e exames de habilitação, exigências de carteira de habilitação, obrigatoriedade de itens em veículos (extintor, kit primeiros socorros, airbag, freios abs) Quando tratar de grandes obras de construções de rodovias, olhar codigo 1010 para ver qual se encaixa melhor. | AO95: 1 | AP95: Avenida Sebastião de Brito, bairro: Dona Clara; | AQ95: 1 | AR95: 1 | AS95: Avenida Sebastião de Brito, bairro: Dona Clara; | AT95: 0 | AX95: Pendente
A96: 2022_CLAUDIO_DO_MUNDO_NOVO_276_01 | B96: 2022 | C96: 4263 | D96: emendas_conslidadas(1).xlsx | E96: 2022_CLAUDIO_DO_MUNDO_NOVO | F96: 276 | G96: Concluída | H96: Cláudio do Mundo Novo | I96: PSD | J96: Destinação de recursos para Fundação Sara, CNPJ 02.663.494/0002-09, para a execução de atividades socioassistenciais, de acordo com o disposto na Lei Federal nº 8.742/93, em consonância com a referida inscrição no Conselho Municipal de Assistência Social de Belo Horizonte – CMAS-BH; | K96: 1011.1100.08.244.113.2.804.339039 | L96: 1011 | M96: FUNDO MUNICIPAL DE ASSISTÊNCIA SOCIAL | N96: 08 | O96: Assistência Social | P96: 244 | Q96: Assistência Comunitária | R96: 0113 | S96: Aprimoramento da Gestão do SUAS | T96: 2804 | U96: Gestão dos Equipamentos e Promoção Social | V96: 339039 | W96: Despesa corrente | X96: Outras despesas correntes | Z96: SMASDH | AA96: 30000 | AB96: 30000 | AC96: 30000 | AD96: 30000 | AE96: FUNDACAO SARA ALBUQUERQUE COSTA | AF96: 2663494000209 | AG96: Associações Diversas | AH96: Associações Diversas | AJ96: 0 | AK96: 0 | AL96: 1300 | AM96: =IF(AL96="","",AL96&" - "&IFERROR(VLOOKUP(AL96,CODEBOOK_CAP!$C$2:$D$212,2,FALSE),"")) -> 1300 - GERAL | AN96: =IF(AL96="","",IFERROR(VLOOKUP(AL96,CODEBOOK_CAP!$C$2:$E$212,3,FALSE),"")) -> Observações gerais sobre políticas sociais que envolvam mais de um casos dos subtópicos, políticas gerais de assistência social, welfare state, bem estar social, Ministérios e orcamentos como do Desenvolvimento social e combate e fome, desenvolvimento social, sistemas de gestão de políticas de assistencia, CAD UNICO, cadastros, sistemas computacionais para desenvolvimento de ações e políticas sociais, BPC - Benefício de Prestação Continuada geral para idosos e deficientes. NÃO CONFUNDIR POLÍTICAS SOCIAIS COM POLÍTICA DE EMPREGO E RENDA. Todas as questões, direitos, políticas que se relacionem com o TRABALHO como contrapartida, estão no código 5. Maternidade, Paternidade aposentadoria por tempo de serviço, INSS. | AO96: 0 | AQ96: 0 | AR96: 0 | AT96: 0 | AX96: Pendente
A97: 2022_CLAUDIO_DO_MUNDO_NOVO_344_01 | B97: 2022 | C97: 4321 | D97: emendas_conslidadas(1).xlsx | E97: 2022_CLAUDIO_DO_MUNDO_NOVO | F97: 344 | G97: Concluída | H97: Cláudio do Mundo Novo | I97: PSD | J97: Destinado a compra de materiais de consumo permanente para o Centro de Saúde Alameda dos Ipês, localizado na Rua Ministro Oliveira Salazar, 1.186 - Santa Mônica; | K97: 2302.0900.10.301.157.2.690.449052 | L97: 2302 | M97: FUNDO MUNICIPAL DE SAÚDE | N97: 10 | O97: Saúde | P97: 301 | Q97: Atenção Básica | R97: 0157 | S97: Atenção Primária à Saúde | T97: 2690 | U97: Atenção Primária à Saúde | V97: 449052 | W97: Despesa de capital | X97: Investimentos | Z97: SMSA | AA97: 50000 | AB97: 30117 | AC97: 30117 | AD97: 30117 | AE97: DRIVE A INFORMATICA LTDA MICROFORT INFORMATICA LTDA. COMERCIAL SILVESTRE LTDA DRIVE A INFORMATICA LTDA ALFA MED SISTEMAS MEDICOS LTDA | AF97: 00677870000108 24675507000103 41823463000130 00677870000108 11405384000149 | AG97: PBH | AH97: Município de Belo Horizonte | AI97: 18715383000140 | AJ97: 1 | AK97: 1 | AL97: 0322 | AM97: =IF(AL97="","",AL97&" - "&IFERROR(VLOOKUP(AL97,CODEBOOK_CAP!$C$2:$D$212,2,FALSE),"")) -> 0322 - ESTRUTURAS, HOSPITAIS, CLÍNICAS | AN97: =IF(AL97="","",IFERROR(VLOOKUP(AL97,CODEBOOK_CAP!$C$2:$E$212,3,FALSE),"")) -> Observações relacionadas as estruturas do sistema de saúde, como a construção de hospitais, postos de saúde, construção de maternidades, laboratórios, centros de saúde avançado, SAMU, Ambulâncias, UTI Móveis, leitos, compra de equipamentos médicos, Raio X, Ultrasom, equipamentos de diálise, capacidade de atendimento, estrutura e funcionamento de equipamentos públicos de saúde. | AO97: 1 | AP97: Rua Ministro Oliveira Salazar, 1.186 - Santa Mônica | AQ97: 1 | AR97: 1 | AS97: Centro de Saúde Alameda dos Ipês, localizado na Rua Ministro Oliveira Salazar, 1.186 - Santa Mônica | AT97: 0 | AX97: Pendente
A98: 2022_CLAUDIO_DO_MUNDO_NOVO_345_01 | B98: 2022 | C98: 4322 | D98: emendas_conslidadas(1).xlsx | E98: 2022_CLAUDIO_DO_MUNDO_NOVO | F98: 345 | G98: Concluída | H98: Cláudio do Mundo Novo | I98: PSD | J98: para compra de materiais de consumo permanentes destinados ao Centro de Saúde Céu Azul, localizado na Rua Alice Marques, 187 - Céu Azul; | K98: 2302.10.301.157.2690.449052 | L98: 2302 | M98: FUNDO MUNICIPAL DE SAÚDE | N98: 10 | O98: Saúde | P98: 301 | Q98: Atenção Básica | R98: 0157 | S98: Atenção Primária à Saúde | T98: 2690 | U98: Atenção Primária à Saúde | V98: 449052 | W98: Despesa de capital | X98: Investimentos | Z98: SMSA | AA98: 50000 | AB98: 25549 | AC98: 25549 | AD98: 25549 | AE98: DRIVE A INFORMATICA LTDA DRIVE A INFORMATICA LTDA IGM COMERCIO VAREJISTA DE PECAS E ACESSORIOS PARA VEICULOS LTDA REPREMIG REPRESENTACAO E COMERCIO DE MINAS GERAIS LTDA COMERCIAL SILVESTRE LTDA IGM COMERCIO VAREJISTA DE PECAS E ACESSORIOS PARA VEICULOS LTDA | AF98: 00677870000108 00677870000108 23140085000109 65149197000251 41823463000130 23140085000109 | AG98: PBH | AH98: Município de Belo Horizonte | AI98: 18715383000140 | AJ98: 1 | AK98: 1 | AL98: 0322 | AM98: =IF(AL98="","",AL98&" - "&IFERROR(VLOOKUP(AL98,CODEBOOK_CAP!$C$2:$D$212,2,FALSE),"")) -> 0322 - ESTRUTURAS, HOSPITAIS, CLÍNICAS | AN98: =IF(AL98="","",IFERROR(VLOOKUP(AL98,CODEBOOK_CAP!$C$2:$E$212,3,FALSE),"")) -> Observações relacionadas as estruturas do sistema de saúde, como a construção de hospitais, postos de saúde, construção de maternidades, laboratórios, centros de saúde avançado, SAMU, Ambulâncias, UTI Móveis, leitos, compra de equipamentos médicos, Raio X, Ultrasom, equipamentos de diálise, capacidade de atendimento, estrutura e funcionamento de equipamentos públicos de saúde. | AO98: 1 | AP98: Rua Alice Marques, 187 - Céu Azul | AQ98: 1 | AR98: 1 | AS98: Centro de Saúde Céu Azul, localizado na Rua Alice Marques, 187 - Céu Azul | AT98: 0 | AX98: Pendente
A99: 2022_CLAUDIO_DO_MUNDO_NOVO_346_01 | B99: 2022 | C99: 4323 | D99: emendas_conslidadas(1).xlsx | E99: 2022_CLAUDIO_DO_MUNDO_NOVO | F99: 346 | G99: Concluída | H99: Cláudio do Mundo Novo | I99: PSD | J99: À compra de materiais de consumo permanente destinado ao Centro de Saúde Padre Joaquim Maia, localizado na Rua Boaventura, 1.900 - Liberdade; | K99: 2302.10.301.157.2690.449052 | L99: 2302 | M99: FUNDO MUNICIPAL DE SAÚDE | N99: 10 | O99: Saúde | P99: 301 | Q99: Atenção Básica | R99: 0157 | S99: Atenção Primária à Saúde | T99: 2690 | U99: Atenção Primária à Saúde | V99: 449052 | W99: Despesa de capital | X99: Investimentos | Z99: SMSA | AA99: 50000 | AB99: 31496 | AC99: 31496 | AD99: 31496 | AE99: COMERCIAL SILVESTRE LTDA ALFA MED SISTEMAS MEDICOS LTDA REPREMIG REPRESENTACAO E COMERCIO DE MINAS GERAIS LTDA DRIVE A INFORMATICA LTDA IGM COMERCIO VAREJISTA DE PECAS E ACESSORIOS PARA VEICULOS LTDA | AF99: 41823463000130 11405384000149 65149197000251 00677870000108 23140085000109 | AG99: PBH | AH99: Município de Belo Horizonte | AI99: 18715383000140 | AJ99: 1 | AK99: 1 | AL99: 0322 | AM99: =IF(AL99="","",AL99&" - "&IFERROR(VLOOKUP(AL99,CODEBOOK_CAP!$C$2:$D$212,2,FALSE),"")) -> 0322 - ESTRUTURAS, HOSPITAIS, CLÍNICAS | AN99: =IF(AL99="","",IFERROR(VLOOKUP(AL99,CODEBOOK_CAP!$C$2:$E$212,3,FALSE),"")) -> Observações relacionadas as estruturas do sistema de saúde, como a construção de hospitais, postos de saúde, construção de maternidades, laboratórios, centros de saúde avançado, SAMU, Ambulâncias, UTI Móveis, leitos, compra de equipamentos médicos, Raio X, Ultrasom, equipamentos de diálise, capacidade de atendimento, estrutura e funcionamento de equipamentos públicos de saúde. | AO99: 1 | AP99: Rua Boaventura, 1.900 - Liberdade | AQ99: 1 | AR99: 1 | AS99: Centro de Saúde Padre Joaquim Maia, localizado na Rua Boaventura, 1.900 - Liberdade | AT99: 0 | AX99: Pendente
A100: 2022_CLAUDIO_DO_MUNDO_NOVO_347_01 | B100: 2022 | C100: 4324 | D100: emendas_conslidadas(1).xlsx | E100: 2022_CLAUDIO_DO_MUNDO_NOVO | F100: 347 | G100: Concluída | H100: Cláudio do Mundo Novo | I100: PSD | J100: À compra de materiais permanentes, destinado ao Centro de Saúde Jardim Montanhês, localizado na Rua Padre Leopoldo Pereira, 407 - Jardim Montanhês; | K100: 2302.10.301.157.2690.449052 | L100: 2302 | M100: FUNDO MUNICIPAL DE SAÚDE | N100: 10 | O100: Saúde | P100: 301 | Q100: Atenção Básica | R100: 0157 | S100: Atenção Primária à Saúde | T100: 2690 | U100: Atenção Primária à Saúde | V100: 449052 | W100: Despesa de capital | X100: Investimentos | Z100: SMSA | AA100: 50000 | AB100: 31496 | AC100: 31496 | AD100: 31496 | AE100: COMERCIAL SILVESTRE LTDA IGM COMERCIO VAREJISTA DE PECAS E ACESSORIOS PARA VEICULOS LTDA DRIVE A INFORMATICA LTDA REPREMIG REPRESENTACAO E COMERCIO DE MINAS GERAIS LTDA ALFA MED SISTEMAS MEDICOS LTDA | AF100: 41823463000130 23140085000109 00677870000108 65149197000251 11405384000149 | AG100: PBH | AH100: Município de Belo Horizonte | AI100: 18715383000140 | AJ100: 1 | AK100: 1 | AL100: 0322 | AM100: =IF(AL100="","",AL100&" - "&IFERROR(VLOOKUP(AL100,CODEBOOK_CAP!$C$2:$D$212,2,FALSE),"")) -> 0322 - ESTRUTURAS, HOSPITAIS, CLÍNICAS | AN100: =IF(AL100="","",IFERROR(VLOOKUP(AL100,CODEBOOK_CAP!$C$2:$E$212,3,FALSE),"")) -> Observações relacionadas as estruturas do sistema de saúde, como a construção de hospitais, postos de saúde, construção de maternidades, laboratórios, centros de saúde avançado, SAMU, Ambulâncias, UTI Móveis, leitos, compra de equipamentos médicos, Raio X, Ultrasom, equipamentos de diálise, capacidade de atendimento, estrutura e funcionamento de equipamentos públicos de saúde. | AO100: 1 | AP100: Rua Padre Leopoldo Pereira, 407 - Jardim Montanhês | AQ100: 1 | AR100: 1 | AS100: Centro de Saúde Jardim Montanhês, localizado na Rua Padre Leopoldo Pereira, 407 - Jardim Montanhês | AT100: 0 | AX100: Pendente
...

Sheet CODEBOOK_CAP
A1: macro_codigo | B1: macro_tema | C1: subcodigo | D1: subtema | E1: definicao | F1: inclui | G1: nao_inclui | H1: exemplos | I1: observacao_local | J1: ativo
A2: 01 | B2: MACROECONOMIA | C2: 0100 | D2: GERAL | E2: Quando há combinação de diversos assuntos econômicos (subcódigos) em um mesmo dado. Menção de "economia" como assunto isolado, sem especificações. Código é usado em situações generalistas em que a questão macroeconômica aparece como política principal. Termos comuns são: Crescimento econômico, desenvolvimento econômico, política econômica, indicadores econômicos, recessão econômica, estagnação econômica, melhora da economia, plano econômico, condições econômicas, estado da economia, recuperação econômica, efeitos da economia, efeitos da recessão. | J2: 1
A3: 01 | B3: MACROECONOMIA | C3: 0101 | D3: INFLAÇÃO, TAXAS DE JUROS, CONTROLE DE PREÇOS | E3: Controle da inflação, políticas de combate a inflação, indicadores de inflação no Brasil, inflação comparada a outros países, estatísticas de sumento de preços, preço de alimentos e serviços, custo de vida, indicadores de preço e de reajustes, índices de reajuste de preço - Taxa SELIC, Índice de Preço ao Consumidor Amplo (IPCA), Índice de Preços ao Produtor Amplo (IPA), Índice de Preços ao Consumidor da Fipe (IPC-Fipe), Índice Nacional de Preços ao Consumidor (INPC), Índice Nacional de Custo da Construção (INCC), Índice Geral de Preços do Mercado (IGP-M), Índice Geral de Preços de Mercado (IGP-DI). Atuação do Comitê de Política Monetária do Banco Central (COPOM) para taxas de Juros. Políticas específicas para estabilização de preços devem ser codificadas no 110. (Quando há menção de preços, sem mencionar inflação) | J3: 1
A4: 01 | B4: MACROECONOMIA | C4: 0103 | D4: DESEMPREGO | E4: Indicador específico para tratar de Desemprego. Indicadores de taxa de emprego e taxa de desemprego, relatórios sobre taxas de desemprego, análises temporais e comparadas sobre taxa de desemprego. Não confundir com política de trabalho e emprego, Código 5. Impactos econômicos do desemprego usar o (100), Políticas gerais de trabalho e emprego usar o (500), formas de qualificação para emprego usar o (502), trabalho informal (505) | J4: 1
A5: 01 | B5: MACROECONOMIA | C5: 0104 | D5: POLÍTICA MONETÁRIA, BANCO CENTRAL E TESOURO NACIONAL | E5: Observações relacionadas a política monetária, atuação do Banco Central, reserva de ouro, certificados e títulos do tesouro, disponibilidade de crédito, oferta de moeda, taxas de câmbio, compra e venda de títulos públicos, política monetária expansiva, política monetária contracionista, redesconto, depósito compulsório. (Codificar guerra cambial, câmbio em 1808) | J5: 1
A6: 01 | B6: MACROECONOMIA | C6: 0105 | D6: ORÇAMENTO PÚBLICO E DÍVIDA PÚBLICA | E6: Questões relacionadas com a composição do orçamento público, execução orçamentária, déficit público, dívida pública, indicadores e avaliações do déficit ou superávit orçamentário, processo orçamentário, propostas orçamentárias anuais, ato e execução orçamentária, déficit e dívida federal, redução do déficit e propostas de gestão, projeções orçamentárias, aumento do limite da dívida pública, impacto das reduções orçamentárias nas indústrias, estados e comunidades, emissões de dívida pública, mudanças no status do exercício fiscal, resoluções orçamentárias, alterações da peça orçamentária anual. Consulta pública. Dívidas dos Estados e Municípios com a União. (Relações Federarativas do âmbito administrativo usar (2001). Questões de dívida entre entes federados usar (105) | J6: 1
A7: 01 | B7: MACROECONOMIA | C7: 0107 | D7: IMPOSTOS, POLÍTICA FISCAL E TRIBUTÁRIA | E7: Observações relacionadas à política tributária e política fiscal. Alterações tributárias específicas devem ser codificadas com base no assunto em questão. Somente deve ser utilizado em assuntos gerais de taxas, impostos e reformas tributária e fiscal que incluem mudanças em várias áreas substantivas. Quando a Taxa, Imposto ou tributo for sobre uma política ou área específica, usar o código da área (IPTU, por exemplo, usar código Habitação (1400), ou então IPI, que deve ser identificado pelo código Política Industrial (108) . Utilizar 107 em: Imposto de Renda, IRPF, tributação sobre a renda, esclarecimento do código tributário, reforma do código tributário, impostos sobre itens de luxo e de consumo, impostos sobre o alcool, impostos sobre tabaco, impostos sobre heranças e doações, imposto de renda corporativo, propostas de impostos administrativos, reforma do imposto de renda, código tributário federal reforma e simplificação, alterações fiscais gerais, incentivos fiscais, guerra fiscal. | J7: 1
A8: 01 | B8: MACROECONOMIA | C8: 0108 | D8: POLÍTICA INDUSTRIAL | E8: Informações exclusivas de promoção da política industrial. Reestruturação industrial, Desenvolvimento industrial, Subsídios industriais, Produtividade industrial, desempenho industrial, aumento da capacidade produtiva industrial, políticas de tecnologia industrial, centros industriais, parques industriais. alteracoes no valor do IPI. Quando a política for sobre um setor ou área específica, codificar na área. Indústria farmacêutica (321) Nao confundir com crescimento tecnológico geral, parques tecnológicos e ciência. (código 17) | J8: 1
A9: 01 | B9: MACROECONOMIA | C9: 0110 | D9: CONTROLE E ESTABILIZAÇÃO DE PREÇOS | E9: Políticas econômicas para controle e estabilização de preços gerais na economia. Programas de estabilização econômica de preços, Congelamento de preços, programas emergenciais de estabilização de preços. Codificar itens específicos em suas respectivas áreas. Por exemplo: controle de preços de alimentos (tomate, por exemplo) devem ser codificados no item Agricultura (4), preço de energia elétrica ou combustível nos subcódigos de Energia (8), controle do salário mínimo no código de Trabalho (5). | J9: 1
A10: 01 | B10: MACROECONOMIA | C10: 0199 | D10: OUTROS | E10: Observações que versam sobre a economia, mas que não se enquadram em nenhum dos itens acima. | J10: 1
A11: 02 | B11: DIREITOS CIVIS, POLÍTICOS, LIBERDADES E MINORIAS | C11: 0200 | D11: GERAL | E11: Quando há combinação de diversos assuntos relacionado aos direitos civis, liberdade e atores indetificados como minorias. Questões gerais e amplas tais como Comissões, violações de direitos sem especificação, criação ou modificação ou atuação de Ministérios, departamentos ou instituições gerais, direito a propriedade privada, violação e atentados contra direitos civis em geral, cotas gerais (quando existem várias linhas, nao apenas racial), coberturas jornalisticas, estatisticas sobre minorias e sobre direitos básicos, discriminações e preconceito gerais sobre múltiplos aspectos. Quando o tema abordado for sobre uma única parte (sexo ou raça ou idade ou deficiência, codificar nos subcódigos específicos. Geral somente quando há combinação de fatores. Quando aparecer DIREITOS HUMANOS e assuntos de direito civil internacional, codificar em 1925. | J11: 1
A12: 02 | B12: DIREITOS CIVIS, POLÍTICOS, LIBERDADES E MINORIAS | C12: 0201 | D12: DISCRIMINAÇÃO POR QUESTÕES ÉTNICO-RACIAIS | E12: Informações relacionadas exclusivamente a discriminação e questões sobre prevenção e proteção de etnia tais como populações indígenas, questões de raça e cor, discriminações relacionadas a raça e cor, racismo, grupos supremacistas raciais, tratamentos diferenciados, privilégios raciais e étnicos. Questões quaisquer de políticas de saude, de educacao, de terras, de assistencia social sobre populações tradicionais brasileiras usar o 2102. Politicas de cotas, usar o local onde elas sao usadas. Se Politicas de cotas nas universidades usar 601. Se política de cotas para acesso a concursos publicos usar 2004. | J12: 1
A13: 02 | B13: DIREITOS CIVIS, POLÍTICOS, LIBERDADES E MINORIAS | C13: 0202 | D13: DISCRIMINAÇÃO POR GÊNERO OU ORIENTAÇÃO SEXUAL (MISOGINIA E HOMOFOBIA) | E13: Políticas de promoção de igualdade de gênero e de igualdade de relações sociais relacionadas a gênero e orientação sexual. Misoginia, Homofobia, ataques homofóbicos, casamento homoafetivo, igualdade salarial para mulheres, igualdade de trabalho para mulheres, feminismo, Parada LGBT, LGBTQI, transexuais, homossexuais, bissexuais, travestis, relações de gênero com emprego ( tipos de posições, renda, promoção , salário) . VIOLÊNCIA DOMESTICA contra mulheres deve ser codificado em 1208 | J13: 1
... A212: 23 | B212: CULTURA, ESPORTE E LAZER | C212: 2300 | D212: GERAL | E212: Observações relativas as políticas de cultura, Lei rouanet, patrimônio cultural, imaterial, políticas de artes, incentivos fiscais para artes, promoção de eventos culturais, amostras, teatro, dança, artes plásticas, artes visuais, museus, galerias públicas, idioma, lingua portuguesa. Grandes eventos esportivos, Copa do Mundo, Olimpiadas, Esporte e Lazer. | J212: 1

Sheet VEREADOR_ANO
A1: ano | B1: id_vereador_ano | C1: parlamentar_original | D1: Sigla | E1: partido_base | F1: Estimativa ZUCCO POWER 2021 | G1: Estimativa ZUCCO POWER 2017 | H1: ideologia
A2: 2022 | B2: 2022_ALVARO_DAMIAO | C2: Álvaro Damião | D2: DEM | E2: Democratas | F2: 0.431 | H2: direita
A3: 2022 | B3: 2022_BELLA_GONCALVES | C3: Bella Gonçalves | D3: PSOL | E3: partido socialismo e liberdade | F3: -0.874 | H3: esquerda
A4: 2022 | B4: 2022_BIM_DA_AMBULANCIA | C4: Bim da Ambulância | D4: PSD | E4: partido social democratico | F4: 0.296 | H4: direita
A5: 2022 | B5: 2022_BRAULIO_LARA | C5: Braulio Lara | D5: NOVO | E5: partido novo | F5: 0.711 | H5: direita
A6: 2022 | B6: 2022_BRUNO_MIRANDA | C6: Bruno Miranda | D6: PDT | E6: partido democratico trabalhista | F6: -0.356 | H6: esquerda
A7: 2022 | B7: 2022_CIRO_PEREIRA | C7: Ciro Pereira | D7: PTB | E7: partido trabalhista brasileiro | F7: 0.455 | H7: direita
A8: 2022 | B8: 2022_CLAUDIO_DO_MUNDO_NOVO | C8: Cláudio do Mundo Novo | D8: PSD | E8: partido social democratico | F8: 0.296 | H8: direita
A9: 2022 | B9: 2022_DR_CELIO_FROIS | C9: Dr. Célio Frois | D9: CIDADANIA | E9: cidadania | F9: -0.014 | H9: centro
A10: 2022 | B10: 2022_DUDA_SALABERT | C10: Duda Salabert | D10: PDT | E10: partido democratico trabalhista | F10: -0.356 | H10: esquerda
A11: 2022 | B11: 2022_FERNANDA_PEREIRA_ALTOE | C11: Fernanda Pereira Altoé | D11: NOVO | E11: partido novo | F11: 0.711 | H11: direita
A12: 2022 | B12: 2022_FERNANDO_LUIZ | C12: Fernando Luiz | D12: PSD | E12: partido social democratico | F12: 0.296 | H12: direita
A13: 2022 | B13: 2022_FLAVIA_BORJA | C13: Flávia Borja | D13: AVANTE | E13: avante
A14: 2022 | B14: 2022_GILSON_GUIMARAES | C14: Gilson Guimarães | D14: REDE | E14: rede sustentabilidade | G14: -0.555 | H14: esquerda
A15: 2022 | B15: 2022_HELINHO_DA_FARMACIA | C15: Helinho da Farmácia | D15: PSD | E15: partido social democratico | F15: 0.296 | H15: direita
A16: 2022 | B16: 2022_HENRIQUE_BRAGA | C16: Henrique Braga | D16: PSDB | E16: partido da social democracia brasileira | F16: 0.157 | H16: centro
A17: 2022 | B17: 2022_IRLAN_MELO | C17: Irlan Melo | D17: PSD | E17: partido social democratico | F17: 0.296 | H17: direita
A18: 2022 | B18: 2022_IZA_LOURENCA | C18: Iza Lourença | D18: PSOL | E18: partido socialismo e liberdade | F18: -0.874 | H18: esquerda
A19: 2022 | B19: 2022_JORGE_SANTOS | C19: Jorge Santos | D19: REPUBLICANOS | E19: republicanos | F19: 0.550 | H19: direita
A20: 2022 | B20: 2022_JOSE_FERREIRA | C20: José Ferreira | D20: PP | E20: progressistas | F20: 0.510 | H20: direita
A21: 2022 | B21: 2022_JUNINHO_LOS_HERMANOS | C21: Juninho Los Hermanos | D21: AVANTE | E21: avante
A22: 2022 | B22: 2022_LEO | C22: Léo | D22: PSL | E22: Partido Social Liberal | F22: 0.803 | H22: direita
A23: 2022 | B23: 2022_MACAE_EVARISTO | C23: Macaé Evaristo | D23: PT | E23: partido dos trabalhadores | F23: -0.691 | H23: esquerda
A24: 2022 | B24: 2022_MARCELA_TROPIA | C24: Marcela Trópia | D24: NOVO | E24: partido novo | F24: 0.711 | H24: direita
A25: 2022 | B25: 2022_MARCOS_CRISPIM | C25: Marcos Crispim | D25: PSC | E25: partido social cristao | F25: 0.596 | H25: direita
A26: 2022 | B26: 2022_MARILDA_PORTELA | C26: Marilda Portela | D26: CIDADANIA | E26: cidadania | F26: -0.014 | H26: centro
A27: 2022 | B27: 2022_MILTINHO_CGE | C27: Miltinho CGE | D27: PDT | E27: partido democratico trabalhista | F27: -0.356 | H27: esquerda
A28: 2022 | B28: 2022_NELY_AQUINO | C28: Nely Aquino | D28: PODE | E28: podemos | F28: 0.386 | H28: direita
A29: 2022 | B29: 2022_NIKOLAS_FERREIRA | C29: Nikolas Ferreira | D29: PRTB | E29: Partido Renovador Trabalhista Brasileiro
A30: 2022 | B30: 2022_PEDRO_PATRUS | C30: Pedro Patrus | D30: PT | E30: partido dos trabalhadores | F30: -0.691 | H30: esquerda
A31: 2022 | B31: 2022_PROFESSORA_MARLI | C31: Professora Marli | D31: PP | E31: progressistas | F31: 0.510 | H31: direita
A32: 2022 | B32: 2022_PROFESSOR_CLAUDINEY_DULIM | C32: Professor Claudiney Dulim | D32: AVANTE | E32: avante
A33: 2022 | B33: 2022_PROFESSOR_JULIANO_LOPES | C33: Professor Juliano Lopes | D33: PTC | E33: Partido Trabalhista Comunitário
A34: 2022 | B34: 2022_RAMON_BIBIANO_DA_CASA_DE_APOIO | C34: Ramon Bibiano da Casa de Apoio | D34: PSD | E34: partido social democratico | F34: 0.296 | H34: direita
A35: 2022 | B35: 2022_REINALDO_GOMES_PRETO_SACOLAO | C35: Reinaldo Gomes Preto Sacolão | D35: MDB | E35: movimento democratico brasileiro | F35: 0.137 | H35: centro
A36: 2022 | B36: 2022_ROGERIO_ALKIMIM | C36: Rogerio Alkimim | D36: PMN | E36: partido da mobilizacao nacional
A37: 2022 | B37: 2022_RUBAO | C37: Rubão | D37: PP | E37: progressistas | F37: 0.510 | H37: direita
A38: 2022 | B38: 2022_WALTER_TOSTA | C38: Walter Tosta | D38: PL | E38: partido liberal | F38: 0.493 | H38: direita
A39: 2022 | B39: 2022_WANDERLEY_PORTO | C39: Wanderley Porto | D39: PATRIOTA | E39: patriota
A40: 2022 | B40: 2022_WESLEY | C40: Wesley | D40: PROS | E40: Partido Republicano da Ordem Social | F40: 0.032 | H40: centro
A41: 2022 | B41: 2022_WILSINHO_DA_TABU | C41: Wilsinho da Tabu | D41: PP | E41: progressistas | F41: 0.510 | H41: direita
A42: 2023 | B42: 2023_BELLA_GONCALVES | C42: Bella Gonçalves | D42: PSOL | E42: partido socialismo e liberdade | F42: -0.874 | H42: esquerda
A43: 2023 | B43: 2023_BIM_DA_AMBULANCIA | C43: Bim da Ambulância | D43: AVANTE | E43: avante
A44: 2023 | B44: 2023_BRAULIO_LARA | C44: Braulio Lara | D44: NOVO | E44: partido novo | F44: 0.711 | H44: direita
A45: 2023 | B45: 2023_BRUNO_MIRANDA | C45: Bruno Miranda | D45: PDT | E45: partido democratico trabalhista | F45: -0.356 | H45: esquerda
A46: 2023 | B46: 2023_CIRO_PEREIRA | C46: Ciro Pereira | D46: PTB | E46: partido trabalhista brasileiro | F46: 0.455 | H46: direita
A47: 2023 | B47: 2023_CLEITON_XAVIER | C47: Cleiton Xavier | D47: PMN | E47: partido da mobilizacao nacional
A48: 2023 | B48: 2023_CLAUDIO_DO_MUNDO_NOVO | C48: Cláudio do Mundo Novo | D48: PSD | E48: partido social democratico | F48: 0.296 | H48: direita
A49: 2023 | B49: 2023_CESAR_GORDIN | C49: César Gordin | D49: SD | E49: solidariedade | F49: 0.190 | H49: centro
A50: 2023 | B50: 2023_DR_CELIO_FROIS | C50: Dr. Célio Frois | D50: PSC | E50: partido social cristao | F50: 0.596 | H50: direita
A51: 2023 | B51: 2023_DUDA_SALABERT | C51: Duda Salabert | D51: PDT | E51: partido democratico trabalhista | F51: -0.356 | H51: esquerda
A52: 2023 | B52: 2023_FERNANDA_PEREIRA_ALTOE | C52: Fernanda Pereira Altoé | D52: NOVO | E52: partido novo | F52: 0.711 | H52: direita
A53: 2023 | B53: 2023_FERNANDO_LUIZ | C53: Fernando Luiz | D53: PSD | E53: partido social democratico | F53: 0.296 | H53: direita
A54: 2023 | B54: 2023_FLAVIA_BORJA | C54: Flávia Borja | D54: PP | E54: progressistas | F54: 0.510 | H54: direita
A55: 2023 | B55: 2023_GABRIEL | C55: Gabriel | D55: sem partido | E55: sem partido
A56: 2023 | B56: 2023_GILSON_GUIMARAES | C56: Gilson Guimarães | D56: REDE | E56: rede sustentabilidade | G56: -0.555 | H56: esquerda
A57: 2023 | B57: 2023_HELINHO_DA_FARMACIA | C57: Helinho da Farmácia | D57: PSD | E57: partido social democratico | F57: 0.296 | H57: direita
A58: 2023 | B58: 2023_HENRIQUE_BRAGA | C58: Henrique Braga | D58: PSDB | E58: partido da social democracia brasileira | F58: 0.157 | H58: centro
A59: 2023 | B59: 2023_IRLAN_MELO | C59: Irlan Melo | D59: PATRIOTA | E59: patriota
A60: 2023 | B60: 2023_IZA_LOURENCA | C60: Iza Lourença | D60: PSOL | E60: partido socialismo e liberdade | F60: -0.874 | H60: esquerda
A61: 2023 | B61: 2023_JANAINA_CARDOSO | C61: Janaina Cardoso | D61: UNIAO | E61: uniao brasil | F61: 0.660 | H61: direita
A62: 2023 | B62: 2023_JORGE_SANTOS | C62: Jorge Santos | D62: REPUBLICANOS | E62: republicanos | F62: 0.550 | H62: direita
A63: 2023 | B63: 2023_JOSE_FERREIRA | C63: José Ferreira | D63: PP | E63: progressistas | F63: 0.510 | H63: direita
A64: 2023 | B64: 2023_JUNINHO_LOS_HERMANOS | C64: Juninho Los Hermanos | D64: AVANTE | E64: avante
A65: 2023 | B65: 2023_LEO | C65: Léo | D65: UNIAO | E65: uniao brasil | F65: 0.660 | H65: direita
A66: 2023 | B66: 2023_MACAE_EVARISTO | C66: Macaé Evaristo | D66: PT | E66: partido dos trabalhadores | F66: -0.691 | H66: esquerda
A67: 2023 | B67: 2023_MARCELA_TROPIA | C67: Marcela Trópia | D67: NOVO | E67: partido novo | F67: 0.711 | H67: direita
A68: 2023 | B68: 2023_MARCOS_CRISPIM | C68: Marcos Crispim | D68: PP | E68: progressistas | F68: 0.510 | H68: direita
A69: 2023 | B69: 2023_MARILDA_PORTELA | C69: Marilda Portela | D69: CIDADANIA | E69: cidadania | F69: -0.014 | H69: centro
A70: 2023 | B70: 2023_MILTINHO_CGE | C70: Miltinho CGE | D70: PDT | E70: partido democratico trabalhista | F70: -0.356 | H70: esquerda
A71: 2023 | B71: 2023_NELY_AQUINO | C71: Nely Aquino | D71: PODE | E71: podemos | F71: 0.386 | H71: direita
A72: 2023 | B72: 2023_NIKOLAS_FERREIRA | C72: Nikolas Ferreira | D72: PL | E72: partido liberal | F72: 0.493 | H72: direita
A73: 2023 | B73: 2023_PEDRO_PATRUS | C73: Pedro Patrus | D73: PT | E73: partido dos trabalhadores | F73: -0.691 | H73: esquerda
A74: 2023 | B74: 2023_PROFESSOR_CLAUDINEY_DULIM | C74: Professor Claudiney Dulim | D74: AVANTE | E74: avante
A75: 2023 | B75: 2023_PROFESSOR_JULIANO_LOPES | C75: Professor Juliano Lopes | D75: AGIR | E75: agir
A76: 2023 | B76: 2023_PROFESSORA_MARLI | C76: Professora Marli | D76: PP | E76: progressistas | F76: 0.510 | H76: direita
A77: 2023 | B77: 2023_RAMON_BIBIANO_DA_CASA_DE_APOIO | C77: Ramon Bibiano da Casa de Apoio | D77: PSD | E77: partido social democratico | F77: 0.296 | H77: direita
A78: 2023 | B78: 2023_REINALDO_GOMES_PRETO_SACOLAO | C78: Reinaldo Gomes Preto Sacolão | D78: MDB | E78: movimento democratico brasileiro | F78: 0.137 | H78: centro
A79: 2023 | B79: 2023_RUBAO | C79: Rubão | D79: PP | E79: progressistas | F79: 0.510 | H79: direita
A80: 2023 | B80: 2023_SERGIO_FERNANDO_PINHO_TAVARES | C80: Sérgio Fernando Pinho Tavares | D80: PL | E80: partido liberal | F80: 0.493 | H80: direita
A81: 2023 | B81: 2023_WALTER_TOSTA | C81: Walter Tosta | D81: PL | E81: partido liberal | F81: 0.493 | H81: direita
A82: 2023 | B82: 2023_WANDERLEY_PORTO | C82: Wanderley Porto | D82: PATRIOTA | E82: patriota
A83: 2023 | B83: 2023_WESLEY | C83: Wesley | D83: PP | E83: progressistas | F83: 0.510 | H83: direita
A84: 2023 | B84: 2023_WILSINHO_DA_TABU | C84: Wilsinho da Tabu | D84: PP | E84: progressistas | F84: 0.510 | H84: direita
A85: 2023 | B85: 2023_ALVARO_DAMIAO | C85: Álvaro Damião | D85: UNIAO | E85: uniao brasil | F85: 0.660 | H85: direita
A86: 2024 | B86: 2024_BRAULIO_LARA | C86: Braulio Lara | D86: NOVO | E86: partido novo | F86: 0.711 | H86: direita
A87: 2024 | B87: 2024_BRUNO_MIRANDA | C87: Bruno Miranda | D87: PDT | E87: partido democratico trabalhista | F87: -0.356 | H87: esquerda
A88: 2024 | B88: 2024_BRUNO_PEDRALVA | C88: Bruno Pedralva | D88: PT | E88: partido dos trabalhadores | F88: -0.691 | H88: esquerda
A89: 2024 | B89: 2024_CIDA_FALABELLA | C89: Cida Falabella | D89: PSOL | E89: partido socialismo e liberdade | F89: -0.874 | H89: esquerda
A90: 2024 | B90: 2024_CIRO_PEREIRA | C90: Ciro Pereira | D90: PTB | E90: partido trabalhista brasileiro | F90: 0.455 | H90: direita
A91: 2024 | B91: 2024_CLEITON_XAVIER | C91: Cleiton Xavier | D91: PMN | E91: partido da mobilizacao nacional
A92: 2024 | B92: 2024_CLAUDIO_DO_MUNDO_NOVO | C92: Cláudio do Mundo Novo | D92: PSD | E92: partido social democratico | F92: 0.296 | H92: direita
A93: 2024 | B93: 2024_CESAR_GORDIN | C93: César Gordin | D93: SD | E93: solidariedade | F93: 0.190 | H93: centro
A94: 2024 | B94: 2024_DR_CELIO_FROIS | C94: Dr. Célio Frois | D94: PV | E94: partido verde | G94: -0.069 | H94: centro
A95: 2024 | B95: 2024_FERNANDA_PEREIRA_ALTOE | C95: Fernanda Pereira Altoé | D95: NOVO | E95: partido novo | F95: 0.711 | H95: direita
A96: 2024 | B96: 2024_FERNANDO_LUIZ | C96: Fernando Luiz | D96: PSD | E96: partido social democratico | F96: 0.296 | H96: direita
A97: 2024 | B97: 2024_FLAVIA_BORJA | C97: Flávia Borja | D97: PP | E97: progressistas | F97: 0.510 | H97: direita
A98: 2024 | B98: 2024_GABRIEL | C98: Gabriel | D98: sem partido | E98: sem partido
A99: 2024 | B99: 2024_GILSON_GUIMARAES | C99: Gilson Guimarães | D99: REDE | E99: rede sustentabilidade | G99: -0.555 | H99: esquerda
A100: 2024 | B100: 2024_HELINHO_DA_FARMACIA | C100: Helinho da Farmácia | D100: PSD | E100: partido social democratico | F100: 0.296 | H100: direita
...

Sheet LOCALIDADES_APRESENTACAO
A1: LOCALIDADE | B1: id_emenda | C1: endereco_padronizado | D1: bairro | E1: regional | F1: territorio | G1: logradouro | H1: numero | I1: cep | J1: latitude | K1: longitude | L1: coordenada_x | M1: coordenada_y
A2: 34º Batalhão da 1ª Região Policial Militar | B2: 2022_NIKOLAS_FERREIRA_793_01 | C2: Av. Américo Vespúcio, 2391, Caiçara | D2: Caicaras | E2: NOROESTE | F2: NO2 | G2: Avenida Américo Vespúcio | H2: 2391
