Workbook

Sheet EMENDAS_CODIFICACAO
A1: id_emenda | B1: ano | C1: linha_origem | D1: arquivo_origem | E1: id_vereador_ano | F1: numero_emenda | G1: status_original | H1: parlamentar_original | I1: partido_base | J1: objeto_emenda | K1: dotacao_original | L1: uo_dec | M1: nome_uo | N1: func_dec | O1: nome_funcao | P1: sub_dec | Q1: nome_subfuncao | R1: prog_dec | S1: nome_programa | T1: acao_dec | U1: nome_acao | V1: nat_dec | W1: categoria_economica | X1: grupo_despesa | Y1: fonte_dec | Z1: orgao_executor | AA1: valor_emenda | AB1: valor_empenhado | AC1: valor_liquidado | AD1: valor_pago | AE1: credor_original | AF1: saude_orcamentaria | AG1: saude_tematica | AH1: subcodigo_cap_final | AI1: subcodigo_cap | AJ1: subcodigo_cap_descricao | AK1: localidade_final | AL1: localidade_resumo | AM1: N_localidades | AN1: georreferenciavel | AO1: georreferenciacao | AP1: publico_alvo_final | AQ1: publico_alvo_resumo | AR1: credor_disponivel_final | AS1: credor_padronizado | AT1: status_codificacao | AU1: confianca | AV1: data_codificacao | AW1: regra_decisao_id | AX1: cultura_ou_esporte
A2: 2023_BELLA_GONCALVES_566_01 | B2: 2023 | C2: 358 | D2: emendas-2023-27-11-2025.xlsx | E2: 2023_BELLA_GONCALVES | F2: 566 | G2: ATOS PREPARATÓRIOS | H2: Bella Gonçalves | J2: à reforma dos Centros de Referência em Saúde Mental Noroeste (CERSAM Noroeste), Centros de Referência em Saúde Mental Infanto-Juvenil Noroeste (CERSAMi Noroeste) e Centros de Referência em Saúde Mental Infanto-Juvenil Centro-Sul (CERSAMi Centro-Sul/CEPAI) | K2: 2302.1012201171.216.449051.S.500 | L2: 2302 | M2: FUNDO MUNICIPAL DE SAÚDE | N2: 10 | O2: SAÚDE | P2: 122 | Q2: ADMINISTRAÇÃO GERAL | R2: 0117 | S2: GESTÃO DO SUS | T2: 1216 | U2: CONSTRUÇÃO, AMPLIAÇÃO E REFORMA DE UNIDADES DE SAÚDE | V2: 449051 | W2: Despesa de capital | X2: Investimentos | Y2: 500 | Z2: FMS/SMOBI | AA2: 1223854 | AB2: 813820.27 | AC2: 803820.27 | AD2: 803820.27 | AE2: VALESK CONSTRUCOES LTDA, | AF2: 1 | AG2: 1 | AH2: 0333 | AI2: =IF(AH2="","",IFERROR(RIGHT("0000"&AH2,4)&" - "&UPPER(_xlfn.XLOOKUP(RIGHT("0000"&AH2,4),CODEBOOK_CAP!$C$2:$C$212,CODEBOOK_CAP!$D$2:$D$212)),"Código CAP não encontrado")) -> 0333 - SAÚDE MENTAL | AJ2: =IF(AH2="","",IFERROR(_xlfn.XLOOKUP(RIGHT("0000"&AH2,4),CODEBOOK_CAP!$C$2:$C$212,CODEBOOK_CAP!$E$2:$E$212),"Código CAP não encontrado")) -> Serviços de atendimento a saúde mental e psico-social. CAPS, Controle de qualidade mental, esquizofrenia, bipolaridade, transtornos mentais, ansiedade, alucinançao, depressão, suicídio, CVV, atendimento psicológico e psiquiátrico, sanatório, manicomio. Não confundir com dependências de alcool (342) e drogas (343) | AK2: 0 | AM2: 3 | AN2: 1 | AO2: R. Camarugi, 10 - Padre Eustáquio, Belo Horizonte - MG, 30720-090; R. Manhumirim, 415 - Padre Eustáquio, Belo Horizonte - MG, 30720-070; R. Padre Marinho, 150 - Santa Efigênia, Belo Horizonte - MG, 30140-040 | AP2: 1 | AQ2: Infanto-Juvenil | AR2: 1 | AS2: VALESK CONSTRUCOES LTDA, | AT2: Revisado | AU2: Alta | AV2: 46214
A3: 2023_BELLA_GONCALVES_569_01 | B3: 2023 | C3: 361 | D3: emendas-2023-27-11-2025.xlsx | E3: 2023_BELLA_GONCALVES | F3: 569 | G3: CONCLUÍDO | H3: Bella Gonçalves | J3: à realização de eventos de formação com foco no público usuário dos serviços de saúde mental | K3: 2302.1030201142.891.339039.S.500 | L3: 2302 | M3: FUNDO MUNICIPAL DE SAÚDE | N3: 10 | O3: SAÚDE | P3: 302 | Q3: ASSISTÊNCIA HOSPITALAR E AMBULATORIAL | R3: 0114 | S3: ATENÇÃO SECUNDÁRIA E TERCIÁRIA À SAÚDE | T3: 2891 | U3: REDE ESPECIALIZADA | V3: 339039 | W3: Despesa corrente | X3: Outras despesas correntes | Y3: 500 | Z3: FMS | AA3: 104100 | AB3: 104100 | AC3: 104100 | AD3: 104100 | AF3: 1 | AG3: 1 | AH3: 0333 | AI3: =IF(AH3="","",IFERROR(RIGHT("0000"&AH3,4)&" - "&UPPER(_xlfn.XLOOKUP(RIGHT("0000"&AH3,4),CODEBOOK_CAP!$C$2:$C$212,CODEBOOK_CAP!$D$2:$D$212)),"Código CAP não encontrado")) -> 0333 - SAÚDE MENTAL | AJ3: =IF(AH3="","",IFERROR(_xlfn.XLOOKUP(RIGHT("0000"&AH3,4),CODEBOOK_CAP!$C$2:$C$212,CODEBOOK_CAP!$E$2:$E$212),"Código CAP não encontrado")) -> Serviços de atendimento a saúde mental e psico-social. CAPS, Controle de qualidade mental, esquizofrenia, bipolaridade, transtornos mentais, ansiedade, alucinançao, depressão, suicídio, CVV, atendimento psicológico e psiquiátrico, sanatório, manicomio. Não confundir com dependências de alcool (342) e drogas (343) | AK3: 0 | AM3: 0 | AN3: 0 | AP3: 0 | AR3: 0 | AT3: Revisado | AU3: Alta | AV3: 46214
A4: 2023_BELLA_GONCALVES_571_01 | B4: 2023 | C4: 363 | D4: emendas-2023-27-11-2025.xlsx | E4: 2023_BELLA_GONCALVES | F4: 571 | G4: CONCLUÍDO | H4: Bella Gonçalves | J4: à aquisição de material de apoio utilizado no atendimento das Equipes de Consultório na Rua. | K4: 2302.1030201142.891.335043.S.500 | L4: 2302 | M4: FUNDO MUNICIPAL DE SAÚDE | N4: 10 | O4: SAÚDE | P4: 302 | Q4: ASSISTÊNCIA HOSPITALAR E AMBULATORIAL | R4: 0114 | S4: ATENÇÃO SECUNDÁRIA E TERCIÁRIA À SAÚDE | T4: 2891 | U4: REDE ESPECIALIZADA | V4: 335043 | W4: Despesa corrente | X4: Outras despesas correntes | Y4: 500 | Z4: FMS | AA4: 112578 | AB4: 112578 | AC4: 112578 | AD4: 112578 | AF4: 1 | AG4: 1 | AH4: 0304 | AI4: =IF(AH4="","",IFERROR(RIGHT("0000"&AH4,4)&" - "&UPPER(_xlfn.XLOOKUP(RIGHT("0000"&AH4,4),CODEBOOK_CAP!$C$2:$C$212,CODEBOOK_CAP!$D$2:$D$212)),"Código CAP não encontrado")) -> 0304 - CUIDADOS PRIMARIOS E ATENÇÃO BÁSICA | AJ4: =IF(AH4="","",IFERROR(_xlfn.XLOOKUP(RIGHT("0000"&AH4,4),CODEBOOK_CAP!$C$2:$C$212,CODEBOOK_CAP!$E$2:$E$212),"Código CAP não encontrado")) -> Medicina da familia, cuidados básicos e informativos de saude, higiene pessoal e higiene alimentar. Normalmente vinculada a comunidades carentes e de exercício de práticas gerenciais e sanitárias democráticas, atuacao de trabalho em equipe, dirigidas a populações de territórios bem delimitados, pelas quais assume a responsabilidade sanitária, considerando a dinamicidade existente no território em que vivem essas populações. Programa saúde da família, Política Nacional de atenção básica, Equipes de Saúde da Família, Agentes comunitários de saúde. Mias médicos quando se tratar de inclusão regional, interiorização do atendimento. Quando tratar apenas de prevenção e promoção a saude, como campanhas específicas contra dengue, DSTs, codificar em (331) | AK4: 0 | AM4: 0 | AN4: 0 | AP4: 0 | AR4: 0 | AT4: Revisado | AU4: Alta | AV4: 46214
A5: 2023_BELLA_GONCALVES_574_01 | B5: 2023 | C5: 366 | D5: emendas-2023-27-11-2025.xlsx | E5: 2023_BELLA_GONCALVES | F5: 574 | G5: CONCLUÍDO | H5: Bella Gonçalves | J5: ao reforço de dotação orçamentária para qualificação no atendimento da população LGBT através do "Projeto BH de Mão Dadas Contra a Aids". | K5: 2302.1030500282.829.335043.S.500 | L5: 2302 | M5: FUNDO MUNICIPAL DE SAÚDE | N5: 10 | O5: SAÚDE | P5: 305 | Q5: VIGILÂNCIA EPIDEMIOLÓGICA | R5: 0028 | S5: VIGILÂNCIA EM SAÚDE | T5: 2829 | U5: VIGILÂNCIA EM SAÚDE | V5: 335043 | W5: Despesa corrente | X5: Outras despesas correntes | Y5: 500 | Z5: FMS | AA5: 72000 | AB5: 72000 | AC5: 72000 | AD5: 72000 | AF5: 1 | AG5: 1 | AH5: 0331 | AI5: =IF(AH5="","",IFERROR(RIGHT("0000"&AH5,4)&" - "&UPPER(_xlfn.XLOOKUP(RIGHT("0000"&AH5,4),CODEBOOK_CAP!$C$2:$C$212,CODEBOOK_CAP!$D$2:$D$212)),"Código CAP não encontrado")) -> 0331 - PREVENÇÃO, CAMPANHAS E PROMOÇÃO | AJ5: =IF(AH5="","",IFERROR(_xlfn.XLOOKUP(RIGHT("0000"&AH5,4),CODEBOOK_CAP!$C$2:$C$212,CODEBOOK_CAP!$E$2:$E$212),"Código CAP não encontrado")) -> Observações relacionadas a campanhas de promoção e de prevenção de saúde em adultos. Campanhas de vacinação de adultos, campanhas de prevenção de DSTs em adultos, campanhas para exames de câncer de mama, outubro rosa, Novembro azul, campanhas de valorização da vida, campanhas contra suicídio, Políticas de prevenção a diabetes, campanhas e politicas em pro de atividades esportivas para evitar problemas de pressão, publicacao de cartilhas, guias, informativos, educação sexual, campanhas e atuação de higiene bucal, higiene básica, prevenção contra anemia. Não confundir com acesso a alimentos (1302), pre-natal (332) ou tratamentos de doenças já existentes. Todas campanhas de prevenção que estejam relacionadas com gravidez, bebê e criança (332), | AK5: 0 | AM5: 0 | AN5: 0 | AP5: 1 | AQ5: LGBT | AR5: 0 | AT5: Revisado | AU5: Alta | AV5: 46214
A6: 2023_BELLA_GONCALVES_580_01 | B6: 2023 | C6: 372 | D6: emendas-2023-27-11-2025.xlsx | E6: 2023_BELLA_GONCALVES | F6: 580 | G6: CONCLUÍDO | H6: Bella Gonçalves | J6: ao reforço de dotação orçamentária para o Hospital Eduardo de Menezes, CNPJ 19.843.929/0011- 82, para a compra de hormônios e outras medicações utilizadas no ambulatório Anyky Lima. | K6: 2302.1030201142.894.339039.S.500 | L6: 2302 | M6: FUNDO MUNICIPAL DE SAÚDE | N6: 10 | O6: SAÚDE | P6: 302 | Q6: ASSISTÊNCIA HOSPITALAR E AMBULATORIAL | R6: 0114 | S6: ATENÇÃO SECUNDÁRIA E TERCIÁRIA À SAÚDE | T6: 2894 | U6: REDE HOSPITALAR | V6: 339039 | W6: Despesa corrente | X6: Outras despesas correntes | Y6: 500 | Z6: FMS | AA6: 100000 | AB6: 100000 | AC6: 100000 | AD6: 100000 | AF6: 1 | AG6: 1 | AH6: 0335 | AI6: =IF(AH6="","",IFERROR(RIGHT("0000"&AH6,4)&" - "&UPPER(_xlfn.XLOOKUP(RIGHT("0000"&AH6,4),CODEBOOK_CAP!$C$2:$C$212,CODEBOOK_CAP!$D$2:$D$212)),"Código CAP não encontrado")) -> 0335 - REGULAMENTAÇÃO DE FARMÁCIAS , COMPRA E CONSUMO DE MEDICAMENTOS | AJ6: =IF(AH6="","",IFERROR(_xlfn.XLOOKUP(RIGHT("0000"&AH6,4),CODEBOOK_CAP!$C$2:$C$212,CODEBOOK_CAP!$E$2:$E$212),"Código CAP não encontrado")) -> Assuntos relacionados a compra e venda de medicamentos em farmácias. Regulamentação de horário de funcionamento de farmácias, farmácia popular, farmácias de manipulação, organização e regras para funcionamento de farmácias, proibição de atendimento médico em farmácias, controle de receitas, acesso a compra de medicamentos de tarja vermelha e tarja preta. Preço de medicamentos e remedios. Distribuição de medicamentos gratuitos. Questões relacionadas sobre patentes de medicamentos no 1522. Não confundir com assuntos relacionados a Industria Farmaceutica (321) | AK6: 0 | AM6: 1 | AN6: 1 | AO6: R. Dr. Cristiano Rezende, 2213 - Bonsucesso, Belo Horizonte - MG, 30622-020 | AP6: 1 | AQ6: LGBT; trans e travestis | AR6: 0 | AT6: Revisado | AU6: Alta | AV6: 46214
A7: 2023_BELLA_GONCALVES_585_01 | B7: 2023 | C7: 377 | D7: emendas-2023-27-11-2025.xlsx | E7: 2023_BELLA_GONCALVES | F7: 585 | G7: CONCLUÍDO | H7: Bella Gonçalves | J7: à implantação e estruturação do projeto Cozinha-Escola para realização de atividades de formação, oficinas, e cursos, com foco na geração de trabalho, emprego e renda, destinados a público em situação de vulnerabilidade social e comunidades em situação de insegurança alimentar | K7: 2800.0412202172.853.339039.F.500 | L7: 2800 | M7: SECRETARIA MUNICIPAL DE DESENVOLVIMENTO ECONÔMICO | N7: 04 | O7: ADMINISTRAÇÃO | P7: 122 | Q7: ADMINISTRAÇÃO GERAL | R7: 0217 | S7: FOMENTO AO DESENVOLVIMENTO ECONÔMICO | T7: 2853 | U7: PROMOÇÃO E ATRAÇÃO DE INVESTIMENTOS E EMPREENDEDORISMO | V7: 339039 | W7: Despesa corrente | X7: Outras despesas correntes | Y7: 500 | Z7: SMDE | AA7: 600000 | AB7: 600000 | AC7: 600000 | AD7: 600000 | AF7: 0 | AG7: 0 | AH7: 0502 | AI7: =IF(AH7="","",IFERROR(RIGHT("0000"&AH7,4)&" - "&UPPER(_xlfn.XLOOKUP(RIGHT("0000"&AH7,4),CODEBOOK_CAP!$C$2:$C$212,CODEBOOK_CAP!$D$2:$D$212)),"Código CAP não encontrado")) -> 0502 - FORMAÇÃO E DESENVOLVIMENTO PROFISSIONAL | AJ7: =IF(AH7="","",IFERROR(_xlfn.XLOOKUP(RIGHT("0000"&AH7,4),CODEBOOK_CAP!$C$2:$C$212,CODEBOOK_CAP!$E$2:$E$212),"Código CAP não encontrado")) -> Programas de capacitação profissional, programas de incentivo ao emprego geral, reciclagem, realocação profissional em outra área, acordos e parcerias do estado com empresas privadas na capacitação, formação e treinamento profissional. | AK7: 0 | AM7: 0 | AN7: 0 | AP7: 0 | AR7: 0 | AT7: Revisado | AU7: Alta | AV7: 46214
A8: 2023_BELLA_GONCALVES_601_01 | B8: 2023 | C8: 393 | D8: emendas-2023-27-11-2025.xlsx | E8: 2023_BELLA_GONCALVES | F8: 601 | G8: CONCLUÍDO | H8: Bella Gonçalves | J8: ao reforço de dotação orçamentária da política municipal_ "Cultura Viva"_. | K8: 3100.1339201542.930.339036.F.500 | L8: 3100 | M8: SECRETARIA MUNICIPAL DE CULTURA | N8: 13 | O8: CULTURA | P8: 392 | Q8: DIFUSÃO CULTURAL | R8: 0154 | S8: PROMOÇÃO E ACESSO ÀS ARTES E À CULTURA | T8: 2930 | U8: PROMOÇÃO E DEMOCRATIZAÇÃO DO ACESSO À CULTURA | V8: 339036 | W8: Despesa corrente | X8: Outras despesas correntes | Y8: 500 | Z8: SMC | AA8: 300000 | AB8: 300000 | AC8: 300000 | AD8: 300000 | AF8: 0 | AG8: 0 | AH8: 2300 | AI8: =IF(AH8="","",IFERROR(RIGHT("0000"&AH8,4)&" - "&UPPER(_xlfn.XLOOKUP(RIGHT("0000"&AH8,4),CODEBOOK_CAP!$C$2:$C$212,CODEBOOK_CAP!$D$2:$D$212)),"Código CAP não encontrado")) -> 2300 - GERAL | AJ8: =IF(AH8="","",IFERROR(_xlfn.XLOOKUP(RIGHT("0000"&AH8,4),CODEBOOK_CAP!$C$2:$C$212,CODEBOOK_CAP!$E$2:$E$212),"Código CAP não encontrado")) -> Observações relativas as políticas de cultura, Lei rouanet, patrimônio cultural, imaterial, políticas de artes, incentivos fiscais para artes, promoção de eventos culturais, amostras, teatro, dança, artes plásticas, artes visuais, museus, galerias públicas, idioma, lingua portuguesa. Grandes eventos esportivos, Copa do Mundo, Olimpiadas, Esporte e Lazer. | AK8: 0 | AM8: 0 | AN8: 0 | AP8: 0 | AR8: 0 | AT8: Revisado | AU8: Alta | AV8: 46214 | AX8: cultura
A9: 2023_BELLA_GONCALVES_607_01 | B9: 2023 | C9: 399 | D9: emendas-2023-27-11-2025.xlsx | E9: 2023_BELLA_GONCALVES | F9: 607 | G9: CONCLUÍDO | H9: Bella Gonçalves | J9: ao atendimento das mulheres em situação de violência identificadas nos termos da Lei n° 11.166/2019 (Lei da Morada Segura) | K9: 2704.1648202262.792.339048.F.500 | L9: 2704 | M9: FUNDO MUNICIPAL DE HABITAÇÃO POPULAR | N9: 16 | O9: HABITAÇÃO | P9: 482 | Q9: HABITAÇÃO URBANA | R9: 0226 | S9: PROVISÃO HABITACIONAL | T9: 2792 | U9: BOLSA MORADIA / LOCAÇÃO SOCIAL | V9: 339048 | W9: Despesa corrente | X9: Outras despesas correntes | Y9: 500 | Z9: SMOBI | AA9: 300000 | AB9: 114779.32 | AC9: 114779.32 | AD9: 114779.32 | AF9: 0 | AG9: 0 | AH9: 1406 | AI9: =IF(AH9="","",IFERROR(RIGHT("0000"&AH9,4)&" - "&UPPER(_xlfn.XLOOKUP(RIGHT("0000"&AH9,4),CODEBOOK_CAP!$C$2:$C$212,CODEBOOK_CAP!$D$2:$D$212)),"Código CAP não encontrado")) -> 1406 - POLÍTICAS DE HABITAÇÃO SOCIAL | AJ9: =IF(AH9="","",IFERROR(_xlfn.XLOOKUP(RIGHT("0000"&AH9,4),CODEBOOK_CAP!$C$2:$C$212,CODEBOOK_CAP!$E$2:$E$212),"Código CAP não encontrado")) -> Políticas de habitação para classes sociais específicas. Minha Casa Minha Vida, Cingapura, COHAB, atuação direta governamental em subsídios ou mesmo em construção de mutirões, doação de casas, prédios não utilizados e cedidos pelos governos. Assuntos relacionados a Favelas, comunidades. Inclui questões relacionadas à habitação para veteranos militares e suas famílias, incluindo | AK9: 0 | AM9: 0 | AN9: 0 | AP9: 1 | AQ9: mulheres | AR9: 0 | AT9: Revisado | AU9: Alta | AV9: 46214
A10: 2023_BELLA_GONCALVES_619_01 | B10: 2023 | C10: 411 | D10: emendas-2023-27-11-2025.xlsx | E10: 2023_BELLA_GONCALVES | F10: 619 | G10: IMPEDIMENTO TÉCNICO | H10: Bella Gonçalves | J10: à implantação e/ou manutenção de equipamento de infraestrutura esportiva e de lazer em estrutura pública municipal | K10: 3000.2781201012.534.449052.F.500 3000.2781201012.534.339039.F.500 | L10: 3000 | M10: SECRETARIA MUNICIPAL DE ESPORTES E LAZER | N10: 27 | O10: DESPORTO E LAZER | P10: 812 | Q10: DESPORTO COMUNITÁRIO | R10: 0101 | S10: PROMOÇÃO E DEMOCRATIZAÇÃO DAS PRÁTICAS DE ESPORTES E LAZER | T10: 2534 | U10: IMPLANTAÇÃO, MANUTENÇÃO E RECUPERAÇAO DE INFRAESTRUTURA ESPORTIVA E DE LAZER | V10: 449052 | W10: Despesa de capital | X10: Investimentos | Y10: 500 | Z10: SMEL | AA10: 150000 | AB10: 0 | AC10: 0 | AD10: 0 | AF10: 0 | AG10: 0 | AH10: 2300 | AI10: =IF(AH10="","",IFERROR(RIGHT("0000"&AH10,4)&" - "&UPPER(_xlfn.XLOOKUP(RIGHT("0000"&AH10,4),CODEBOOK_CAP!$C$2:$C$212,CODEBOOK_CAP!$D$2:$D$212)),"Código CAP não encontrado")) -> 2300 - GERAL | AJ10: =IF(AH10="","",IFERROR(_xlfn.XLOOKUP(RIGHT("0000"&AH10,4),CODEBOOK_CAP!$C$2:$C$212,CODEBOOK_CAP!$E$2:$E$212),"Código CAP não encontrado")) -> Observações relativas as políticas de cultura, Lei rouanet, patrimônio cultural, imaterial, políticas de artes, incentivos fiscais para artes, promoção de eventos culturais, amostras, teatro, dança, artes plásticas, artes visuais, museus, galerias públicas, idioma, lingua portuguesa. Grandes eventos esportivos, Copa do Mundo, Olimpiadas, Esporte e Lazer. | AK10: 0 | AM10: 0 | AN10: 0 | AP10: 0 | AR10: 0 | AT10: Revisado | AU10: Alta | AV10: 46214 | AX10: esporte e lazer
A11: 2023_BELLA_GONCALVES_622_01 | B11: 2023 | C11: 414 | D11: emendas-2023-27-11-2025.xlsx | E11: 2023_BELLA_GONCALVES | F11: 622 | G11: CONCLUÍDO | H11: Bella Gonçalves | J11: ao reforço de dotação orçamentária para continuidade de projeto de capacitação profissionalizante e empreendedorismo voltado às comunidades quilombolas no contexto urbano de Belo Horizonte. | K11: 2800.0412202172.853.339039.F.500 | L11: 2800 | M11: SECRETARIA MUNICIPAL DE DESENVOLVIMENTO ECONÔMICO | N11: 04 | O11: ADMINISTRAÇÃO | P11: 122 | Q11: ADMINISTRAÇÃO GERAL | R11: 0217 | S11: FOMENTO AO DESENVOLVIMENTO ECONÔMICO | T11: 2853 | U11: PROMOÇÃO E ATRAÇÃO DE INVESTIMENTOS E EMPREENDEDORISMO | V11: 339039 | W11: Despesa corrente | X11: Outras despesas correntes | Y11: 500 | Z11: SMDE | AA11: 70000 | AB11: 70000 | AC11: 70000 | AD11: 70000 | AF11: 0 | AG11: 0 | AH11: 0502 | AI11: =IF(AH11="","",IFERROR(RIGHT("0000"&AH11,4)&" - "&UPPER(_xlfn.XLOOKUP(RIGHT("0000"&AH11,4),CODEBOOK_CAP!$C$2:$C$212,CODEBOOK_CAP!$D$2:$D$212)),"Código CAP não encontrado")) -> 0502 - FORMAÇÃO E DESENVOLVIMENTO PROFISSIONAL | AJ11: =IF(AH11="","",IFERROR(_xlfn.XLOOKUP(RIGHT("0000"&AH11,4),CODEBOOK_CAP!$C$2:$C$212,CODEBOOK_CAP!$E$2:$E$212),"Código CAP não encontrado")) -> Programas de capacitação profissional, programas de incentivo ao emprego geral, reciclagem, realocação profissional em outra área, acordos e parcerias do estado com empresas privadas na capacitação, formação e treinamento profissional. | AK11: 0 | AM11: 0 | AN11: 0 | AP11: 1 | AQ11: quilombolas | AR11: 0 | AT11: Revisado | AU11: Alta | AV11: 46214
A12: 2023_BELLA_GONCALVES_896_01 | B12: 2023 | C12: 674 | D12: emendas-2023-27-11-2025.xlsx | E12: 2023_BELLA_GONCALVES | F12: 896 | G12: IMPEDIMENTO TÉCNICO | H12: Bella Gonçalves | J12: à pavimentação de via urbana na Regional Oeste, especificamente na Ocupação Novo Paraíso, bairro Palmeiras | K12: 2700.1545100621.230.449051.F.500 | L12: 2700 | M12: SECRETARIA MUNICIPAL DE OBRAS E INFRAESTRUTURA | N12: 15 | O12: URBANISMO | P12: 451 | Q12: INFRA-ESTRUTURA URBANA | R12: 0062 | S12: GESTÃO DO SISTEMA VIÁRIO MUNICIPAL | T12: 1230 | U12: IMPLANTAÇÃO E RECONSTRUÇÃO DE VIAS PÚBLICAS | V12: 449051 | W12: Despesa de capital | X12: Investimentos | Y12: 500 | Z12: SMOBI | AA12: 192532 | AB12: 0 | AC12: 0 | AD12: 0 | AF12: 0 | AG12: 0 | AH12: 1002 | AI12: =IF(AH12="","",IFERROR(RIGHT("0000"&AH12,4)&" - "&UPPER(_xlfn.XLOOKUP(RIGHT("0000"&AH12,4),CODEBOOK_CAP!$C$2:$C$212,CODEBOOK_CAP!$D$2:$D$212)),"Código CAP não encontrado")) -> 1002 - CARROS, TRÂNSITO, CONSTRUÇÃO E MANUTENÇÃO DE RUAS E ESTRADAS | AJ12: =IF(AH12="","",IFERROR(_xlfn.XLOOKUP(RIGHT("0000"&AH12,4),CODEBOOK_CAP!$C$2:$C$212,CODEBOOK_CAP!$E$2:$E$212),"Código CAP não encontrado")) -> Construção, manutenção de ruas, avenidas, estradas. BRs, pedágios, privatizações, concessinárias, segurança nas estradas, leis de trânsito relacionadas a via, limite de velocidade, sinalização, recapeamento de ruas, pavimentação estradas de terra, não pavimentadas, acidentes e camapanhas de prevencao contra acidentes de transito. Observações sobre regulação de transportes não públicos de carros, veículos de passeio, uber, taxi, transporte de cargas terrestre, frete, trânsito em vias públicas, regulamentação de tipos de carteira de motorista, especificações para caminhoneiros, testes e exames de habilitação, exigências de carteira de habilitação, obrigatoriedade de itens em veículos (extintor, kit primeiros socorros, airbag, freios abs) Quando tratar de grandes obras de construções de rodovias, olhar codigo 1010 para ver qual se encaixa melhor. | AK12: 1 | AL12: Regional Oeste, Ocupação Novo Paraíso, bairro Palmeiras | AM12: 1 | AN12: 0 | AP12: 0 | AR12: 0 | AT12: Revisado | AU12: Alta | AV12: 46214
A13: 2023_BIM_DA_AMBULANCIA_1063_01 | B13: 2023 | C13: 841 | D13: emendas-2023-27-11-2025.xlsx | E13: 2023_BIM_DA_AMBULANCIA | F13: 1063 | G13: CONCLUÍDO | H13: Bim da Ambulância | J13: Ao reforço de dotação orçamentária para o Centro de Saúde Paraúna, situado à rua João Ferreira da Silva, 248 - Bairro Mantiqueira - Venda Nova | K13: 2302.1030101572.690.339037.S.500 | L13: 2302 | M13: FUNDO MUNICIPAL DE SAÚDE | N13: 10 | O13: SAÚDE | P13: 301 | Q13: ATENÇÃO BÁSICA | R13: 0157 | S13: ATENÇÃO PRIMÁRIA À SAÚDE | T13: 2690 | U13: ATENÇÃO PRIMÁRIA À SAÚDE | V13: 339037 | W13: Despesa corrente | X13: Outras despesas correntes | Y13: 500 | Z13: FMS | AA13: 60000 | AB13: 60000 | AC13: 113052.63 | AD13: 60000 | AF13: 1 | AG13: 1 | AH13: 0322 | AI13: =IF(AH13="","",IFERROR(RIGHT("0000"&AH13,4)&" - "&UPPER(_xlfn.XLOOKUP(RIGHT("0000"&AH13,4),CODEBOOK_CAP!$C$2:$C$212,CODEBOOK_CAP!$D$2:$D$212)),"Código CAP não encontrado")) -> 0322 - ESTRUTURAS, HOSPITAIS, CLÍNICAS | AJ13: =IF(AH13="","",IFERROR(_xlfn.XLOOKUP(RIGHT("0000"&AH13,4),CODEBOOK_CAP!$C$2:$C$212,CODEBOOK_CAP!$E$2:$E$212),"Código CAP não encontrado")) -> Observações relacionadas as estruturas do sistema de saúde, como a construção de hospitais, postos de saúde, construção de maternidades, laboratórios, centros de saúde avançado, SAMU, Ambulâncias, UTI Móveis, leitos, compra de equipamentos médicos, Raio X, Ultrasom, equipamentos de diálise, capacidade de atendimento, estrutura e funcionamento de equipamentos públicos de saúde. | AK13: 1 | AL13: rua João Ferreira da Silva, 248 - Bairro Mantiqueira - Venda Nova | AM13: 1 | AN13: 1 | AO13: Centro de Saúde Paraúna (Rua João Ferreira da Silva, 248 - Bairro Mantiqueira - Venda Nova) | AP13: 0 | AR13: 0 | AT13: Revisado | AU13: Alta | AV13: 46214
A14: 2023_BIM_DA_AMBULANCIA_744_01 | B14: 2023 | C14: 530 | D14: emendas-2023-27-11-2025.xlsx | E14: 2023_BIM_DA_AMBULANCIA | F14: 744 | G14: IMPEDIMENTO TÉCNICO | H14: Bim da Ambulância | J14: Ao reforço de dotação orçamentária para construção de vestiários no Campo do itatiaia, situado à rua Clóvis Salgado, 1300 - Bandeirantes | K14: 2700.2781201011.213.449051.F.500 | L14: 2700 | M14: SECRETARIA MUNICIPAL DE OBRAS E INFRAESTRUTURA | N14: 27 | O14: DESPORTO E LAZER | P14: 812 | Q14: DESPORTO COMUNITÁRIO | R14: 0101 | S14: PROMOÇÃO E DEMOCRATIZAÇÃO DAS PRÁTICAS DE ESPORTES E LAZER | T14: 1213 | U14: CONSTRUÇÃO, AMPLIAÇÃO E REFORMA DE EQUIPAMENTOS ESPORTIVOS E ÁREAS DE LAZER | V14: 449051 | W14: Despesa de capital | X14: Investimentos | Y14: 500 | Z14: SMOBI | AA14: 210000 | AB14: 0 | AC14: 0 | AD14: 0 | AF14: 0 | AG14: 0 | AH14: 2300 | AI14: =IF(AH14="","",IFERROR(RIGHT("0000"&AH14,4)&" - "&UPPER(_xlfn.XLOOKUP(RIGHT("0000"&AH14,4),CODEBOOK_CAP!$C$2:$C$212,CODEBOOK_CAP!$D$2:$D$212)),"Código CAP não encontrado")) -> 2300 - GERAL | AJ14: =IF(AH14="","",IFERROR(_xlfn.XLOOKUP(RIGHT("0000"&AH14,4),CODEBOOK_CAP!$C$2:$C$212,CODEBOOK_CAP!$E$2:$E$212),"Código CAP não encontrado")) -> Observações relativas as políticas de cultura, Lei rouanet, patrimônio cultural, imaterial, políticas de artes, incentivos fiscais para artes, promoção de eventos culturais, amostras, teatro, dança, artes plásticas, artes visuais, museus, galerias públicas, idioma, lingua portuguesa. Grandes eventos esportivos, Copa do Mundo, Olimpiadas, Esporte e Lazer. | AK14: 1 | AL14: rua Clóvis Salgado, 1300 - Bandeirantes | AM14: 1 | AN14: 1 | AO14: Campo do itatiaia (rua Clóvis Salgado, 1300 - Bandeirantes) | AP14: 0 | AR14: 0 | AT14: Revisado | AU14: Alta | AV14: 46214 | AX14: esporte e lazer
A15: 2023_BIM_DA_AMBULANCIA_752_01 | B15: 2023 | C15: 538 | D15: emendas-2023-27-11-2025.xlsx | E15: 2023_BIM_DA_AMBULANCIA | F15: 752 | G15: CONCLUÍDO | H15: Bim da Ambulância | J15: Construção do Vestiário Feminino do Campo Telê Santana situado à rua Augusto dos Anjos, Bairro SINIMBU - CEP 31.535-000 | K15: 2700.0412202331.219.449051.F.500 | L15: 2700 | M15: SECRETARIA MUNICIPAL DE OBRAS E INFRAESTRUTURA | N15: 04 | O15: ADMINISTRAÇÃO | P15: 122 | Q15: ADMINISTRAÇÃO GERAL | R15: 0233 | S15: MANUTENÇÃO DA CIDADE | T15: 1219 | U15: AQUISIÇÃO, CONSTRUÇÃO, REFORMA E READAPTAÇÃO DE IMÓVEIS | V15: 449051 | W15: Despesa de capital | X15: Investimentos | Y15: 500 | Z15: SMOBI | AA15: 140000 | AB15: 8004.73 | AC15: 8004.73 | AD15: 8004.73 | AF15: 0 | AG15: 0 | AH15: 2300 | AI15: =IF(AH15="","",IFERROR(RIGHT("0000"&AH15,4)&" - "&UPPER(_xlfn.XLOOKUP(RIGHT("0000"&AH15,4),CODEBOOK_CAP!$C$2:$C$212,CODEBOOK_CAP!$D$2:$D$212)),"Código CAP não encontrado")) -> 2300 - GERAL | AJ15: =IF(AH15="","",IFERROR(_xlfn.XLOOKUP(RIGHT("0000"&AH15,4),CODEBOOK_CAP!$C$2:$C$212,CODEBOOK_CAP!$E$2:$E$212),"Código CAP não encontrado")) -> Observações relativas as políticas de cultura, Lei rouanet, patrimônio cultural, imaterial, políticas de artes, incentivos fiscais para artes, promoção de eventos culturais, amostras, teatro, dança, artes plásticas, artes visuais, museus, galerias públicas, idioma, lingua portuguesa. Grandes eventos esportivos, Copa do Mundo, Olimpiadas, Esporte e Lazer. | AK15: 1 | AL15: rua Augusto dos Anjos, Bairro SINIMBU - CEP 31.535-000 | AM15: 1 | AN15: 1 | AO15: Campo Telê Santana (Rua Augusto dos Anjos, Bairro SINIMBU - CEP 31.535-000) | AP15: 1 | AQ15: mulheres | AR15: 0 | AT15: Revisado | AU15: Alta | AV15: 46214 | AX15: esporte e lazer
A16: 2023_BIM_DA_AMBULANCIA_753_01 | B16: 2023 | C16: 539 | D16: emendas-2023-27-11-2025.xlsx | E16: 2023_BIM_DA_AMBULANCIA | F16: 753 | G16: CONCLUÍDO | H16: Bim da Ambulância | J16: Reforma do Sine Venda Nova, situado à rua Padre Pedro Pinto, 1055 - Bairro Venda Nova | K16: 2700.0412202331.219.449051.F.500 | L16: 2700 | M16: SECRETARIA MUNICIPAL DE OBRAS E INFRAESTRUTURA | N16: 04 | O16: ADMINISTRAÇÃO | P16: 122 | Q16: ADMINISTRAÇÃO GERAL | R16: 0233 | S16: MANUTENÇÃO DA CIDADE | T16: 1219 | U16: AQUISIÇÃO, CONSTRUÇÃO, REFORMA E READAPTAÇÃO DE IMÓVEIS | V16: 449051 | W16: Despesa de capital | X16: Investimentos | Y16: 500 | Z16: SMOBI | AA16: 150000 | AB16: 40973.65 | AC16: 40973.65 | AD16: 40973.65 | AF16: 0 | AG16: 0 | AH16: 0599 | AI16: =IF(AH16="","",IFERROR(RIGHT("0000"&AH16,4)&" - "&UPPER(_xlfn.XLOOKUP(RIGHT("0000"&AH16,4),CODEBOOK_CAP!$C$2:$C$212,CODEBOOK_CAP!$D$2:$D$212)),"Código CAP não encontrado")) -> 0599 - OUTROS | AJ16: =IF(AH16="","",IFERROR(_xlfn.XLOOKUP(RIGHT("0000"&AH16,4),CODEBOOK_CAP!$C$2:$C$212,CODEBOOK_CAP!$E$2:$E$212),"Código CAP não encontrado")) -> Observações que versam sobre TRABALHO E EMPREGO, mas que não se enquadram em nenhum dos itens acima. | AK16: 1 | AL16: rua Padre Pedro Pinto, 1055 - Bairro Venda Nova | AM16: 1 | AN16: 1 | AO16: rua Padre Pedro Pinto, 1055 - Bairro Venda Nova | AP16: 0 | AR16: 0 | AT16: Revisado | AU16: Alta | AV16: 46214
A17: 2023_BIM_DA_AMBULANCIA_754_01 | B17: 2023 | C17: 540 | D17: emendas-2023-27-11-2025.xlsx | E17: 2023_BIM_DA_AMBULANCIA | F17: 754 | G17: CONCLUÍDO | H17: Bim da Ambulância | J17: Reforma do telhado da CARE Venda Nova, situado à Rua Padre Pedro Pinto, 1055 - Bairro Venda Nova | K17: 2700.0412202331.219.449051.F.500 | L17: 2700 | M17: SECRETARIA MUNICIPAL DE OBRAS E INFRAESTRUTURA | N17: 04 | O17: ADMINISTRAÇÃO | P17: 122 | Q17: ADMINISTRAÇÃO GERAL | R17: 0233 | S17: MANUTENÇÃO DA CIDADE | T17: 1219 | U17: AQUISIÇÃO, CONSTRUÇÃO, REFORMA E READAPTAÇÃO DE IMÓVEIS | V17: 449051 | W17: Despesa de capital | X17: Investimentos | Y17: 500 | Z17: SMOBI | AA17: 150000 | AB17: 0 | AC17: 0 | AD17: 0 | AF17: 0 | AG17: 0 | AH17: 2002 | AI17: =IF(AH17="","",IFERROR(RIGHT("0000"&AH17,4)&" - "&UPPER(_xlfn.XLOOKUP(RIGHT("0000"&AH17,4),CODEBOOK_CAP!$C$2:$C$212,CODEBOOK_CAP!$D$2:$D$212)),"Código CAP não encontrado")) -> 2002 - BUROCRACIA, EFICIÊNCIA E FUNCIONAMENTO DA ADMINISTRAÇÃO PÚBLICA | AJ17: =IF(AH17="","",IFERROR(_xlfn.XLOOKUP(RIGHT("0000"&AH17,4),CODEBOOK_CAP!$C$2:$C$212,CODEBOOK_CAP!$E$2:$E$212),"Código CAP não encontrado")) -> Assuntos relacionados aos modelos de administração pública, serviços público, burocracia, e eficiência dos serviços e do aparato público. Funcionamento e organização da administração Pública. Repartições, serviços. Atuação direta para o cidadão, POUPATEMPO, desburocratização da administração pública, informatização do setor público, oferta de serviços públicos online. | AK17: 1 | AL17: Rua Padre Pedro Pinto, 1055 - Bairro Venda Nova | AM17: 1 | AN17: 1 | AO17: Rua Padre Pedro Pinto, 1055 - Bairro Venda Nova | AP17: 0 | AR17: 0 | AT17: Revisado | AU17: Alta | AV17: 46214
A18: 2023_BIM_DA_AMBULANCIA_757_01 | B18: 2023 | C18: 541 | D18: emendas-2023-27-11-2025.xlsx | E18: 2023_BIM_DA_AMBULANCIA | F18: 757 | G18: IMPEDIMENTO TÉCNICO | H18: Bim da Ambulância | J18: À realização de ações de assistência social pela entidade: Associação Mineira de Educação Continuada - ASMEC CNPJ 05.263.848/0001-27 na qualificação profissional e inclusão produtiva. | K18: 1011.0824400192.308.339039.S.500 | L18: 1011 | M18: FUNDO MUNICIPAL DE ASSISTÊNCIA SOCIAL | N18: 08 | O18: ASSISTÊNCIA SOCIAL | P18: 244 | Q18: ASSISTÊNCIA COMUNITÁRIA | R18: 0019 | S18: PROTEÇÃO SOCIAL BÁSICA | T18: 2308 | U18: SERVIÇOS DE PROTEÇÃO SOCIAL BÁSICA | V18: 339039 | W18: Despesa corrente | X18: Outras despesas correntes | Y18: 500 | Z18: SMASDH | AA18: 806266 | AB18: 0 | AC18: 0 | AD18: 0 | AF18: 0 | AG18: 0 | AH18: 0502 | AI18: =IF(AH18="","",IFERROR(RIGHT("0000"&AH18,4)&" - "&UPPER(_xlfn.XLOOKUP(RIGHT("0000"&AH18,4),CODEBOOK_CAP!$C$2:$C$212,CODEBOOK_CAP!$D$2:$D$212)),"Código CAP não encontrado")) -> 0502 - FORMAÇÃO E DESENVOLVIMENTO PROFISSIONAL | AJ18: =IF(AH18="","",IFERROR(_xlfn.XLOOKUP(RIGHT("0000"&AH18,4),CODEBOOK_CAP!$C$2:$C$212,CODEBOOK_CAP!$E$2:$E$212),"Código CAP não encontrado")) -> Programas de capacitação profissional, programas de incentivo ao emprego geral, reciclagem, realocação profissional em outra área, acordos e parcerias do estado com empresas privadas na capacitação, formação e treinamento profissional. | AK18: 0 | AM18: 0 | AN18: 0 | AP18: 0 | AR18: 0 | AT18: Revisado | AU18: Alta | AV18: 46214
A19: 2023_BIM_DA_AMBULANCIA_758_01 | B19: 2023 | C19: 542 | D19: emendas-2023-27-11-2025.xlsx | E19: 2023_BIM_DA_AMBULANCIA | F19: 758 | G19: CONCLUÍDO | H19: Bim da Ambulância | J19: Manutenção de Rede de Drenagem da rua Edgard Torres - Minas Caixa - Venda Nova. | K19: 2700.1545102331.396.449051.F.500 | L19: 2700 | M19: SECRETARIA MUNICIPAL DE OBRAS E INFRAESTRUTURA | N19: 15 | O19: URBANISMO | P19: 451 | Q19: INFRA-ESTRUTURA URBANA | R19: 0233 | S19: MANUTENÇÃO DA CIDADE | T19: 1396 | U19: INFRAESTRUTURA URBANA | V19: 449051 | W19: Despesa de capital | X19: Investimentos | Y19: 500 | Z19: SMOBI | AA19: 30000 | AB19: 21000.67 | AC19: 21000.67 | AD19: 21000.67 | AF19: 0 | AG19: 0 | AH19: 0711 | AI19: =IF(AH19="","",IFERROR(RIGHT("0000"&AH19,4)&" - "&UPPER(_xlfn.XLOOKUP(RIGHT("0000"&AH19,4),CODEBOOK_CAP!$C$2:$C$212,CODEBOOK_CAP!$D$2:$D$212)),"Código CAP não encontrado")) -> 0711 - CONSERVAÇÃO DO SOLO, MAR, RIOS, PRAIAS E COSTAS | AJ19: =IF(AH19="","",IFERROR(_xlfn.XLOOKUP(RIGHT("0000"&AH19,4),CODEBOOK_CAP!$C$2:$C$212,CODEBOOK_CAP!$E$2:$E$212),"Código CAP não encontrado")) -> Poluição de oceanos, regulamentação de acesso e conservação da costa, ilhas, praias, mangues, e assuntos relacionados ao mar, oceanos e litoral. Erosão de terrenos, morros, promoção da qualidade do solo, conservação de rios, lagos e afluentes, questões vinculadas a enchentes, poluição urbana, margens, encostas de rios, chuvas, temporais, tempestades, terrenos contaminados, rios contamidados e poluidos, fertilizantes. Quando assunto for uso dos recursos naturais usar codigo 21. 2104 para recursos hídricos, 2103 para recursos naturais como minerais. Quando o assunto for tratamento de água potável, distribuição de água potável para residencias, 701. | AK19: 1 | AL19: rua Edgard Torres - Minas Caixa - Venda Nova. | AM19: 1 | AN19: 1 | AO19: rua Edgard Torres - Minas Caixa - Venda Nova. | AP19: 0 | AR19: 0 | AT19: Revisado | AU19: Alta | AV19: 46214
A20: 2023_BIM_DA_AMBULANCIA_759_01 | B20: 2023 | C20: 543 | D20: emendas-2023-27-11-2025.xlsx | E20: 2023_BIM_DA_AMBULANCIA | F20: 759 | G20: CONCLUÍDO | H20: Bim da Ambulância | J20: Revitalização da Praça São Caetano do Sul, situada entre as ruas Cyrene Bellonia e Hélio Pellegrino - São João Batista - Venda Nova | K20: 2700.1545102331.202.449051.F.500 | L20: 2700 | M20: SECRETARIA MUNICIPAL DE OBRAS E INFRAESTRUTURA | N20: 15 | O20: URBANISMO | P20: 451 | Q20: INFRA-ESTRUTURA URBANA | R20: 0233 | S20: MANUTENÇÃO DA CIDADE | T20: 1202 | U20: CONSTRUÇÃO, AMPLIAÇÃO E REFORMA DE PRAÇAS, PARQUES E CANTEIROS | V20: 449051 | W20: Despesa de capital | X20: Investimentos | Y20: 500 | Z20: SMOBI | AA20: 126266 | AB20: 112626.8 | AC20: 112626.8 | AD20: 112626.8 | AF20: 0 | AG20: 0 | AH20: 1403 | AI20: =IF(AH20="","",IFERROR(RIGHT("0000"&AH20,4)&" - "&UPPER(_xlfn.XLOOKUP(RIGHT("0000"&AH20,4),CODEBOOK_CAP!$C$2:$C$212,CODEBOOK_CAP!$D$2:$D$212)),"Código CAP não encontrado")) -> 1403 - REABILITAÇÃO URBANA, ECONOMIA URBANA | AJ20: =IF(AH20="","",IFERROR(_xlfn.XLOOKUP(RIGHT("0000"&AH20,4),CODEBOOK_CAP!$C$2:$C$212,CODEBOOK_CAP!$E$2:$E$212),"Código CAP não encontrado")) -> Reabilitação de áreas urbanas, revitalização urbana, modernização de áreas, mercados públicos, revitalização de praças, política urbana nacional, desenvolvimento urbano , desenvolvimento econômico de estados e cidades, modernização de espaços urbanos | AK20: 1 | AL20: Praça São Caetano do Sul, situada entre as ruas Cyrene Bellonia e Hélio Pellegrino - São João Batista - Venda Nova | AM20: 1 | AN20: 1 | AO20: Praça São Caetano do Sul, situada entre as ruas Cyrene Bellonia e Hélio Pellegrino - São João Batista - Venda Nova | AP20: 0 | AR20: 0 | AT20: Revisado | AU20: Alta | AV20: 46214
A21: 2023_BIM_DA_AMBULANCIA_803_01 | B21: 2023 | C21: 582 | D21: emendas-2023-27-11-2025.xlsx | E21: 2023_BIM_DA_AMBULANCIA | F21: 803 | G21: CONCLUÍDO | H21: Bim da Ambulância | J21: À aquisição de materiais permanentes para o Centro de Saúde Santo Antônio na Regional Venda Nova, situado à rua Irineu Pinto, 255 - São João Batista. | K21: 2302.1030101572.690.449052.S.500 | L21: 2302 | M21: FUNDO MUNICIPAL DE SAÚDE | N21: 10 | O21: SAÚDE | P21: 301 | Q21: ATENÇÃO BÁSICA | R21: 0157 | S21: ATENÇÃO PRIMÁRIA À SAÚDE | T21: 2690 | U21: ATENÇÃO PRIMÁRIA À SAÚDE | V21: 449052 | W21: Despesa de capital | X21: Investimentos | Y21: 500 | Z21: FMS | AA21: 7000 | AB21: 6706 | AC21: 6706 | AD21: 6706 | AF21: 1 | AG21: 1 | AH21: 0322 | AI21: =IF(AH21="","",IFERROR(RIGHT("0000"&AH21,4)&" - "&UPPER(_xlfn.XLOOKUP(RIGHT("0000"&AH21,4),CODEBOOK_CAP!$C$2:$C$212,CODEBOOK_CAP!$D$2:$D$212)),"Código CAP não encontrado")) -> 0322 - ESTRUTURAS, HOSPITAIS, CLÍNICAS | AJ21: =IF(AH21="","",IFERROR(_xlfn.XLOOKUP(RIGHT("0000"&AH21,4),CODEBOOK_CAP!$C$2:$C$212,CODEBOOK_CAP!$E$2:$E$212),"Código CAP não encontrado")) -> Observações relacionadas as estruturas do sistema de saúde, como a construção de hospitais, postos de saúde, construção de maternidades, laboratórios, centros de saúde avançado, SAMU, Ambulâncias, UTI Móveis, leitos, compra de equipamentos médicos, Raio X, Ultrasom, equipamentos de diálise, capacidade de atendimento, estrutura e funcionamento de equipamentos públicos de saúde. | AK21: 1 | AL21: Centro de Saúde Santo Antônio na Regional Venda Nova, situado à rua Irineu Pinto, 255 - São João Batista. | AM21: 1 | AN21: 1 | AO21: Centro de Saúde Santo Antônio na Regional Venda Nova, situado à rua Irineu Pinto, 255 - São João Batista. | AP21: 0 | AR21: 0 | AT21: Revisado | AU21: Alta | AV21: 46214
A22: 2023_BIM_DA_AMBULANCIA_810_01 | B22: 2023 | C22: 589 | D22: emendas-2023-27-11-2025.xlsx | E22: 2023_BIM_DA_AMBULANCIA | F22: 810 | G22: EM EXECUÇÃO | H22: Bim da Ambulância | J22: À aquisição de material permanente para o Centro de Saúde Minas Caixa na Regional Venda Nova, situado à rua Capitão Sérgio Pires, 226 - Bairro Minas Caixa. | K22: 2302.1030101572.690.449052.S.500 | L22: 2302 | M22: FUNDO MUNICIPAL DE SAÚDE | N22: 10 | O22: SAÚDE | P22: 301 | Q22: ATENÇÃO BÁSICA | R22: 0157 | S22: ATENÇÃO PRIMÁRIA À SAÚDE | T22: 2690 | U22: ATENÇÃO PRIMÁRIA À SAÚDE | V22: 449052 | W22: Despesa de capital | X22: Investimentos | Y22: 500 | Z22: FMS | AA22: 4000 | AB22: 2790.51 | AC22: 2013.11 | AD22: 2013.11 | AE22: INSMART COMERCIO DE EQUIPAMENTOS LTDA | AF22: 1 | AG22: 1 | AH22: 0322 | AI22: =IF(AH22="","",IFERROR(RIGHT("0000"&AH22,4)&" - "&UPPER(_xlfn.XLOOKUP(RIGHT("0000"&AH22,4),CODEBOOK_CAP!$C$2:$C$212,CODEBOOK_CAP!$D$2:$D$212)),"Código CAP não encontrado")) -> 0322 - ESTRUTURAS, HOSPITAIS, CLÍNICAS | AJ22: =IF(AH22="","",IFERROR(_xlfn.XLOOKUP(RIGHT("0000"&AH22,4),CODEBOOK_CAP!$C$2:$C$212,CODEBOOK_CAP!$E$2:$E$212),"Código CAP não encontrado")) -> Observações relacionadas as estruturas do sistema de saúde, como a construção de hospitais, postos de saúde, construção de maternidades, laboratórios, centros de saúde avançado, SAMU, Ambulâncias, UTI Móveis, leitos, compra de equipamentos médicos, Raio X, Ultrasom, equipamentos de diálise, capacidade de atendimento, estrutura e funcionamento de equipamentos públicos de saúde. | AK22: 1 | AL22: Centro de Saúde Minas Caixa na Regional Venda Nova, situado à rua Capitão Sérgio Pires, 226 - Bairro Minas Caixa. | AM22: 1 | AN22: 1 | AO22: Centro de Saúde Minas Caixa na Regional Venda Nova, situado à rua Capitão Sérgio Pires, 226 - Bairro Minas Caixa. | AP22: 0 | AR22: 1 | AS22: INSMART COMERCIO DE EQUIPAMENTOS LTDA | AT22: Revisado | AU22: Alta | AV22: 46214
A23: 2023_BIM_DA_AMBULANCIA_811_01 | B23: 2023 | C23: 590 | D23: emendas-2023-27-11-2025.xlsx | E23: 2023_BIM_DA_AMBULANCIA | F23: 811 | G23: EM EXECUÇÃO | H23: Bim da Ambulância | J23: À aquisição de materiais permanentes para o Centro de Saúde Andradas, na Regional Venda Nova, situado à rua Mariana Amélia de Azevedo, 21 - Bairro São João Batista | K23: 2302.1030101572.690.449052.S.500 | L23: 2302 | M23: FUNDO MUNICIPAL DE SAÚDE | N23: 10 | O23: SAÚDE | P23: 301 | Q23: ATENÇÃO BÁSICA | R23: 0157 | S23: ATENÇÃO PRIMÁRIA À SAÚDE | T23: 2690 | U23: ATENÇÃO PRIMÁRIA À SAÚDE | V23: 449052 | W23: Despesa de capital | X23: Investimentos | Y23: 500 | Z23: FMS | AA23: 45000 | AB23: 9518.4599999999991 | AC23: 8648.4599999999991 | AD23: 8648.4599999999991 | AE23: B. D. R. COMERCIO DE EQUIPAMENTOS LTDA | AF23: 1 | AG23: 1 | AH23: 0322 | AI23: =IF(AH23="","",IFERROR(RIGHT("0000"&AH23,4)&" - "&UPPER(_xlfn.XLOOKUP(RIGHT("0000"&AH23,4),CODEBOOK_CAP!$C$2:$C$212,CODEBOOK_CAP!$D$2:$D$212)),"Código CAP não encontrado")) -> 0322 - ESTRUTURAS, HOSPITAIS, CLÍNICAS | AJ23: =IF(AH23="","",IFERROR(_xlfn.XLOOKUP(RIGHT("0000"&AH23,4),CODEBOOK_CAP!$C$2:$C$212,CODEBOOK_CAP!$E$2:$E$212),"Código CAP não encontrado")) -> Observações relacionadas as estruturas do sistema de saúde, como a construção de hospitais, postos de saúde, construção de maternidades, laboratórios, centros de saúde avançado, SAMU, Ambulâncias, UTI Móveis, leitos, compra de equipamentos médicos, Raio X, Ultrasom, equipamentos de diálise, capacidade de atendimento, estrutura e funcionamento de equipamentos públicos de saúde. | AK23: 1 | AL23: Centro de Saúde Andradas, na Regional Venda Nova, situado à rua Mariana Amélia de Azevedo, 21 - Bairro São João Batista | AM23: 1 | AN23: 1 | AO23: Centro de Saúde Andradas, na Regional Venda Nova, situado à rua Mariana Amélia de Azevedo, 21 - Bairro São João Batista | AP23: 0 | AR23: 1 | AS23: B. D. R. COMERCIO DE EQUIPAMENTOS LTDA | AT23: Revisado | AU23: Alta | AV23: 46214
A24: 2023_BIM_DA_AMBULANCIA_812_01 | B24: 2023 | C24: 591 | D24: emendas-2023-27-11-2025.xlsx | E24: 2023_BIM_DA_AMBULANCIA | F24: 812 | G24: EM EXECUÇÃO | H24: Bim da Ambulância | J24: À aquisição de materiais permanentes para o Centro de Saúde Lagoa, na Regional Venda Nova, situado na rua José Sabino Maciel, 176 - Bairro Lagoa, CEP: 31578-060. | K24: 2302.1030101572.690.449052.S.500 | L24: 2302 | M24: FUNDO MUNICIPAL DE SAÚDE | N24: 10 | O24: SAÚDE | P24: 301 | Q24: ATENÇÃO BÁSICA | R24: 0157 | S24: ATENÇÃO PRIMÁRIA À SAÚDE | T24: 2690 | U24: ATENÇÃO PRIMÁRIA À SAÚDE | V24: 449052 | W24: Despesa de capital | X24: Investimentos | Y24: 500 | Z24: FMS | AA24: 35000 | AB24: 27776.400000000001 | AC24: 26036.400000000001 | AD24: 26036.400000000001 | AE24: B. D. R. COMERCIO DE EQUIPAMENTOS LTDA; SUPORTH CIRURGICA PONTA GROSSA LTDA | AF24: 1 | AG24: 1 | AH24: 0322 | AI24: =IF(AH24="","",IFERROR(RIGHT("0000"&AH24,4)&" - "&UPPER(_xlfn.XLOOKUP(RIGHT("0000"&AH24,4),CODEBOOK_CAP!$C$2:$C$212,CODEBOOK_CAP!$D$2:$D$212)),"Código CAP não encontrado")) -> 0322 - ESTRUTURAS, HOSPITAIS, CLÍNICAS | AJ24: =IF(AH24="","",IFERROR(_xlfn.XLOOKUP(RIGHT("0000"&AH24,4),CODEBOOK_CAP!$C$2:$C$212,CODEBOOK_CAP!$E$2:$E$212),"Código CAP não encontrado")) -> Observações relacionadas as estruturas do sistema de saúde, como a construção de hospitais, postos de saúde, construção de maternidades, laboratórios, centros de saúde avançado, SAMU, Ambulâncias, UTI Móveis, leitos, compra de equipamentos médicos, Raio X, Ultrasom, equipamentos de diálise, capacidade de atendimento, estrutura e funcionamento de equipamentos públicos de saúde. | AK24: 1 | AL24: Centro de Saúde Lagoa, na Regional Venda Nova, situado na rua José Sabino Maciel, 176 - Bairro Lagoa, CEP: 31578-060. | AM24: 1 | AN24: 1 | AO24: Centro de Saúde Lagoa, na Regional Venda Nova, situado na rua José Sabino Maciel, 176 - Bairro Lagoa, CEP: 31578-060. | AP24: 0 | AR24: 1 | AS24: B. D. R. COMERCIO DE EQUIPAMENTOS LTDA; SUPORTH CIRURGICA PONTA GROSSA LTDA | AT24: Revisado | AU24: Alta | AV24: 46214
A25: 2023_BIM_DA_AMBULANCIA_813_01 | B25: 2023 | C25: 592 | D25: emendas-2023-27-11-2025.xlsx | E25: 2023_BIM_DA_AMBULANCIA | F25: 813 | G25: EM EXECUÇÃO | H25: Bim da Ambulância | J25: À aquisição de materiais permanentes para o Centro de Assistência à Mulher na UPA Venda Nova, situado à rua Padre Pedro Pinto, 322 - Venda Nova - CEP: 31610-000 | K25: 2302.1030201142.893.449052.S.500 | L25: 2302 | M25: FUNDO MUNICIPAL DE SAÚDE | N25: 10 | O25: SAÚDE | P25: 302 | Q25: ASSISTÊNCIA HOSPITALAR E AMBULATORIAL | R25: 0114 | S25: ATENÇÃO SECUNDÁRIA E TERCIÁRIA À SAÚDE | T25: 2893 | U25: REDE DE URGÊNCIA E EMERGÊNCIA | V25: 449052 | W25: Despesa de capital | X25: Investimentos | Y25: 500 | Z25: FMS | AA25: 250000 | AB25: 195230 | AC25: 820 | AD25: 820 | AE25: ADEM DISTRIBUIDORA DE EQUIPAMENTOS MEDICOS LTDA; MARCENARIA SANTA CLARA LTDA; RJN COMERCIO DE MAQUINAS, APARELHOS E EQUIPAMENTOS LTDA; SENA E PRATES LTDA | AF25: 1 | AG25: 1 | AH25: 0322 | AI25: =IF(AH25="","",IFERROR(RIGHT("0000"&AH25,4)&" - "&UPPER(_xlfn.XLOOKUP(RIGHT("0000"&AH25,4),CODEBOOK_CAP!$C$2:$C$212,CODEBOOK_CAP!$D$2:$D$212)),"Código CAP não encontrado")) -> 0322 - ESTRUTURAS, HOSPITAIS, CLÍNICAS | AJ25: =IF(AH25="","",IFERROR(_xlfn.XLOOKUP(RIGHT("0000"&AH25,4),CODEBOOK_CAP!$C$2:$C$212,CODEBOOK_CAP!$E$2:$E$212),"Código CAP não encontrado")) -> Observações relacionadas as estruturas do sistema de saúde, como a construção de hospitais, postos de saúde, construção de maternidades, laboratórios, centros de saúde avançado, SAMU, Ambulâncias, UTI Móveis, leitos, compra de equipamentos médicos, Raio X, Ultrasom, equipamentos de diálise, capacidade de atendimento, estrutura e funcionamento de equipamentos públicos de saúde. | AK25: 1 | AL25: Centro de Assistência à Mulher na UPA Venda Nova, situado à rua Padre Pedro Pinto, 322 - Venda Nova - CEP: 31610-000 | AM25: 1 | AN25: 1 | AO25: Centro de Assistência à Mulher na UPA Venda Nova, situado à rua Padre Pedro Pinto, 322 - Venda Nova - CEP: 31610-000 | AP25: 1 | AQ25: mulheres | AR25: 1 | AS25: ADEM DISTRIBUIDORA DE EQUIPAMENTOS MEDICOS LTDA; MARCENARIA SANTA CLARA LTDA; RJN COMERCIO DE MAQUINAS, APARELHOS E EQUIPAMENTOS LTDA; SENA E PRATES LTDA | AT25: Revisado | AU25: Alta | AV25: 46214
A26: 2023_BIM_DA_AMBULANCIA_814_01 | B26: 2023 | C26: 593 | D26: emendas-2023-27-11-2025.xlsx | E26: 2023_BIM_DA_AMBULANCIA | F26: 814 | G26: CONCLUÍDO | H26: Bim da Ambulância | J26: Melhorias e Reformas para o Centro de Saúde Santo Antônio, localizado à rua Irineu pinto, 255 - Bairro São João Batista - Regional Venda Nova | K26: 2302.1012201171.216.449051.S.500 | L26: 2302 | M26: FUNDO MUNICIPAL DE SAÚDE | N26: 10 | O26: SAÚDE | P26: 122 | Q26: ADMINISTRAÇÃO GERAL | R26: 0117 | S26: GESTÃO DO SUS | T26: 1216 | U26: CONSTRUÇÃO, AMPLIAÇÃO E REFORMA DE UNIDADES DE SAÚDE | V26: 449051 | W26: Despesa de capital | X26: Investimentos | Y26: 500 | Z26: FMS/SMOBI | AA26: 120000 | AB26: 97682.11 | AC26: 97682.11 | AD26: 97682.11 | AF26: 1 | AG26: 1 | AH26: 0322 | AI26: =IF(AH26="","",IFERROR(RIGHT("0000"&AH26,4)&" - "&UPPER(_xlfn.XLOOKUP(RIGHT("0000"&AH26,4),CODEBOOK_CAP!$C$2:$C$212,CODEBOOK_CAP!$D$2:$D$212)),"Código CAP não encontrado")) -> 0322 - ESTRUTURAS, HOSPITAIS, CLÍNICAS | AJ26: =IF(AH26="","",IFERROR(_xlfn.XLOOKUP(RIGHT("0000"&AH26,4),CODEBOOK_CAP!$C$2:$C$212,CODEBOOK_CAP!$E$2:$E$212),"Código CAP não encontrado")) -> Observações relacionadas as estruturas do sistema de saúde, como a construção de hospitais, postos de saúde, construção de maternidades, laboratórios, centros de saúde avançado, SAMU, Ambulâncias, UTI Móveis, leitos, compra de equipamentos médicos, Raio X, Ultrasom, equipamentos de diálise, capacidade de atendimento, estrutura e funcionamento de equipamentos públicos de saúde. | AK26: 1 | AL26: Centro de Saúde Santo Antônio, localizado à rua Irineu pinto, 255 - Bairro São João Batista - Regional Venda Nova | AM26: 1 | AN26: 1 | AO26: Centro de Saúde Santo Antônio, localizado à rua Irineu pinto, 255 - Bairro São João Batista - Regional Venda Nova | AP26: 0 | AR26: 0 | AT26: Revisado | AU26: Alta | AV26: 46214
A27: 2023_BIM_DA_AMBULANCIA_815_01 | B27: 2023 | C27: 594 | D27: emendas-2023-27-11-2025.xlsx | E27: 2023_BIM_DA_AMBULANCIA | F27: 815 | G27: CONCLUÍDO | H27: Bim da Ambulância | J27: Reforço de dotação orçamentária para instalação de telhada no Centro de Saúde Jardim Europa, situado à Rua Edimburgo, 140 - Jardim Europa - Regional Venda Nova | K27: 2302.1012201171.216.449051.S.500 | L27: 2302 | M27: FUNDO MUNICIPAL DE SAÚDE | N27: 10 | O27: SAÚDE | P27: 122 | Q27: ADMINISTRAÇÃO GERAL | R27: 0117 | S27: GESTÃO DO SUS | T27: 1216 | U27: CONSTRUÇÃO, AMPLIAÇÃO E REFORMA DE UNIDADES DE SAÚDE | V27: 449051 | W27: Despesa de capital | X27: Investimentos | Y27: 500 | Z27: FMS/SMOBI | AA27: 12000 | AB27: 0 | AC27: 0 | AD27: 0 | AF27: 1 | AG27: 1 | AH27: 0322 | AI27: =IF(AH27="","",IFERROR(RIGHT("0000"&AH27,4)&" - "&UPPER(_xlfn.XLOOKUP(RIGHT("0000"&AH27,4),CODEBOOK_CAP!$C$2:$C$212,CODEBOOK_CAP!$D$2:$D$212)),"Código CAP não encontrado")) -> 0322 - ESTRUTURAS, HOSPITAIS, CLÍNICAS | AJ27: =IF(AH27="","",IFERROR(_xlfn.XLOOKUP(RIGHT("0000"&AH27,4),CODEBOOK_CAP!$C$2:$C$212,CODEBOOK_CAP!$E$2:$E$212),"Código CAP não encontrado")) -> Observações relacionadas as estruturas do sistema de saúde, como a construção de hospitais, postos de saúde, construção de maternidades, laboratórios, centros de saúde avançado, SAMU, Ambulâncias, UTI Móveis, leitos, compra de equipamentos médicos, Raio X, Ultrasom, equipamentos de diálise, capacidade de atendimento, estrutura e funcionamento de equipamentos públicos de saúde. | AK27: 1 | AL27: Rua Edimburgo, 140 - Jardim Europa - Regional Venda Nova | AM27: 1 | AN27: 1 | AO27: Centro de Saúde Jardim Europa (Rua Edimburgo, 140 - Jardim Europa - Regional Venda Nova) | AP27: 0 | AR27: 0 | AT27: Revisado | AU27: Alta | AV27: 46214
A28: 2023_BIM_DA_AMBULANCIA_816_01 | B28: 2023 | C28: 595 | D28: emendas-2023-27-11-2025.xlsx | E28: 2023_BIM_DA_AMBULANCIA | F28: 816 | G28: EM EXECUÇÃO | H28: Bim da Ambulância | J28: À aquisição de materiais permanentes para o centro de Saúde Jardim Europa na Regional Venda Nova, situado à rua Edimburgo, 149 - Bairro Jardim Europa. | K28: 2302.1030101572.690.449052.S.500 | L28: 2302 | M28: FUNDO MUNICIPAL DE SAÚDE | N28: 10 | O28: SAÚDE | P28: 301 | Q28: ATENÇÃO BÁSICA | R28: 0157 | S28: ATENÇÃO PRIMÁRIA À SAÚDE | T28: 2690 | U28: ATENÇÃO PRIMÁRIA À SAÚDE | V28: 449052 | W28: Despesa de capital | X28: Investimentos | Y28: 500 | Z28: FMS | AA28: 40000 | AB28: 27606.22 | AC28: 1521.22 | AD28: 1521.22 | AE28: UDILIFE COM IMPORTACAO E EXPORTACAO LTDA | AF28: 1 | AG28: 1 | AH28: 0322 | AI28: =IF(AH28="","",IFERROR(RIGHT("0000"&AH28,4)&" - "&UPPER(_xlfn.XLOOKUP(RIGHT("0000"&AH28,4),CODEBOOK_CAP!$C$2:$C$212,CODEBOOK_CAP!$D$2:$D$212)),"Código CAP não encontrado")) -> 0322 - ESTRUTURAS, HOSPITAIS, CLÍNICAS | AJ28: =IF(AH28="","",IFERROR(_xlfn.XLOOKUP(RIGHT("0000"&AH28,4),CODEBOOK_CAP!$C$2:$C$212,CODEBOOK_CAP!$E$2:$E$212),"Código CAP não encontrado")) -> Observações relacionadas as estruturas do sistema de saúde, como a construção de hospitais, postos de saúde, construção de maternidades, laboratórios, centros de saúde avançado, SAMU, Ambulâncias, UTI Móveis, leitos, compra de equipamentos médicos, Raio X, Ultrasom, equipamentos de diálise, capacidade de atendimento, estrutura e funcionamento de equipamentos públicos de saúde. | AK28: 1 | AL28: Regional Venda Nova, situado à rua Edimburgo, 149 - Bairro Jardim Europa. | AM28: 1 | AN28: 1 | AO28: centro de Saúde Jardim Europa (Regional Venda Nova, situado à rua Edimburgo, 149 - Bairro Jardim Europa.) | AP28: 0 | AR28: 1 | AS28: UDILIFE COM IMPORTACAO E EXPORTACAO LTDA | AT28: Revisado | AU28: Alta | AV28: 46214
A29: 2023_BIM_DA_AMBULANCIA_817_01 | B29: 2023 | C29: 596 | D29: emendas-2023-27-11-2025.xlsx | E29: 2023_BIM_DA_AMBULANCIA | F29: 817 | G29: IMPEDIMENTO TÉCNICO | H29: Bim da Ambulância | J29: Ampliação da Farmácia, Construção de Banheiro e Colocação de Calha para o Telhado do Centro de Saúde Minas Caixa, localizado à Rua capitão Sérgio Pires, 226 - Bairro Minas Caixa - Regional Venda Nova | K29: 2302.1012201171.216.449051.S.500 | L29: 2302 | M29: FUNDO MUNICIPAL DE SAÚDE | N29: 10 | O29: SAÚDE | P29: 122 | Q29: ADMINISTRAÇÃO GERAL | R29: 0117 | S29: GESTÃO DO SUS | T29: 1216 | U29: CONSTRUÇÃO, AMPLIAÇÃO E REFORMA DE UNIDADES DE SAÚDE | V29: 449051 | W29: Despesa de capital | X29: Investimentos | Y29: 500 | Z29: FMS/SMOBI | AA29: 90000 | AB29: 0 | AC29: 0 | AD29: 0 | AF29: 1 | AG29: 1 | AH29: 0322 | AI29: =IF(AH29="","",IFERROR(RIGHT("0000"&AH29,4)&" - "&UPPER(_xlfn.XLOOKUP(RIGHT("0000"&AH29,4),CODEBOOK_CAP!$C$2:$C$212,CODEBOOK_CAP!$D$2:$D$212)),"Código CAP não encontrado")) -> 0322 - ESTRUTURAS, HOSPITAIS, CLÍNICAS | AJ29: =IF(AH29="","",IFERROR(_xlfn.XLOOKUP(RIGHT("0000"&AH29,4),CODEBOOK_CAP!$C$2:$C$212,CODEBOOK_CAP!$E$2:$E$212),"Código CAP não encontrado")) -> Observações relacionadas as estruturas do sistema de saúde, como a construção de hospitais, postos de saúde, construção de maternidades, laboratórios, centros de saúde avançado, SAMU, Ambulâncias, UTI Móveis, leitos, compra de equipamentos médicos, Raio X, Ultrasom, equipamentos de diálise, capacidade de atendimento, estrutura e funcionamento de equipamentos públicos de saúde. | AK29: 1 | AL29: Rua capitão Sérgio Pires, 226 - Bairro Minas Caixa - Regional Venda Nova | AM29: 1 | AN29: 1 | AO29: Centro de Saúde Minas Caixa (Rua capitão Sérgio Pires, 226 - Bairro Minas Caixa - Regional Venda Nova) | AP29: 0 | AR29: 0 | AT29: Revisado | AU29: Alta | AV29: 46214
A30: 2023_BIM_DA_AMBULANCIA_818_01 | B30: 2023 | C30: 597 | D30: emendas-2023-27-11-2025.xlsx | E30: 2023_BIM_DA_AMBULANCIA | F30: 818 | G30: EM EXECUÇÃO | H30: Bim da Ambulância | J30: À aquisição de materiais permanentes para o Centro de Saúde Alameda dos Ipês, na Regional Venda Nova, situado à rua Ministro Oliveira Salazar, 1186 - Bairro Santa Mônica | K30: 2302.1030101572.690.449052.S.500 | L30: 2302 | M30: FUNDO MUNICIPAL DE SAÚDE | N30: 10 | O30: SAÚDE | P30: 301 | Q30: ATENÇÃO BÁSICA | R30: 0157 | S30: ATENÇÃO PRIMÁRIA À SAÚDE | T30: 2690 | U30: ATENÇÃO PRIMÁRIA À SAÚDE | V30: 449052 | W30: Despesa de capital | X30: Investimentos | Y30: 500 | Z30: FMS | AA30: 60000 | AB30: 51738.5 | AC30: 51738.5 | AD30: 51738.5 | AF30: 1 | AG30: 1 | AH30: 0322 | AI30: =IF(AH30="","",IFERROR(RIGHT("0000"&AH30,4)&" - "&UPPER(_xlfn.XLOOKUP(RIGHT("0000"&AH30,4),CODEBOOK_CAP!$C$2:$C$212,CODEBOOK_CAP!$D$2:$D$212)),"Código CAP não encontrado")) -> 0322 - ESTRUTURAS, HOSPITAIS, CLÍNICAS | AJ30: =IF(AH30="","",IFERROR(_xlfn.XLOOKUP(RIGHT("0000"&AH30,4),CODEBOOK_CAP!$C$2:$C$212,CODEBOOK_CAP!$E$2:$E$212),"Código CAP não encontrado")) -> Observações relacionadas as estruturas do sistema de saúde, como a construção de hospitais, postos de saúde, construção de maternidades, laboratórios, centros de saúde avançado, SAMU, Ambulâncias, UTI Móveis, leitos, compra de equipamentos médicos, Raio X, Ultrasom, equipamentos de diálise, capacidade de atendimento, estrutura e funcionamento de equipamentos públicos de saúde. | AK30: 1 | AL30: Regional Venda Nova, situado à rua Ministro Oliveira Salazar, 1186 - Bairro Santa Mônica | AM30: 1 | AN30: 1 | AO30: Centro de Saúde Alameda dos Ipês (Regional Venda Nova, situado à rua Ministro Oliveira Salazar, 1186 - Bairro Santa Mônica) | AP30: 0 | AR30: 0 | AT30: Revisado | AU30: Alta | AV30: 46214
A31: 2023_BIM_DA_AMBULANCIA_819_01 | B31: 2023 | C31: 598 | D31: emendas-2023-27-11-2025.xlsx | E31: 2023_BIM_DA_AMBULANCIA | F31: 819 | G31: IMPEDIMENTO TÉCNICO | H31: Bim da Ambulância | J31: Obra de Ampliação de Consultórios no Centro de Saúde Andradas, situado à Rua Mariana Amélia de Azevedo, 21 - Bairro São João Batista. | K31: 2302.1012201171.216.449051.S.500 | L31: 2302 | M31: FUNDO MUNICIPAL DE SAÚDE | N31: 10 | O31: SAÚDE | P31: 122 | Q31: ADMINISTRAÇÃO GERAL | R31: 0117 | S31: GESTÃO DO SUS | T31: 1216 | U31: CONSTRUÇÃO, AMPLIAÇÃO E REFORMA DE UNIDADES DE SAÚDE | V31: 449051 | W31: Despesa de capital | X31: Investimentos | Y31: 500 | Z31: FMS/SMOBI | AA31: 100000 | AB31: 0 | AC31: 0 | AD31: 0 | AF31: 1 | AG31: 1 | AH31: 0322 | AI31: =IF(AH31="","",IFERROR(RIGHT("0000"&AH31,4)&" - "&UPPER(_xlfn.XLOOKUP(RIGHT("0000"&AH31,4),CODEBOOK_CAP!$C$2:$C$212,CODEBOOK_CAP!$D$2:$D$212)),"Código CAP não encontrado")) -> 0322 - ESTRUTURAS, HOSPITAIS, CLÍNICAS | AJ31: =IF(AH31="","",IFERROR(_xlfn.XLOOKUP(RIGHT("0000"&AH31,4),CODEBOOK_CAP!$C$2:$C$212,CODEBOOK_CAP!$E$2:$E$212),"Código CAP não encontrado")) -> Observações relacionadas as estruturas do sistema de saúde, como a construção de hospitais, postos de saúde, construção de maternidades, laboratórios, centros de saúde avançado, SAMU, Ambulâncias, UTI Móveis, leitos, compra de equipamentos médicos, Raio X, Ultrasom, equipamentos de diálise, capacidade de atendimento, estrutura e funcionamento de equipamentos públicos de saúde. | AK31: 1 | AL31: Rua Mariana Amélia de Azevedo, 21 - Bairro São João Batista. | AM31: 1 | AN31: 1 | AO31: Centro de Saúde Andradas (Rua Mariana Amélia de Azevedo, 21 - Bairro São João Batista.) | AP31: 0 | AR31: 0 | AT31: Revisado | AU31: Alta | AV31: 46214
A32: 2023_BIM_DA_AMBULANCIA_820_01 | B32: 2023 | C32: 599 | D32: emendas-2023-27-11-2025.xlsx | E32: 2023_BIM_DA_AMBULANCIA | F32: 820 | G32: CONCLUÍDO | H32: Bim da Ambulância | J32: Recurso destinado para a Obra em andamento da reforma do Centro de Saúde Céu Azul, localizado à Rua Alice Marques, 187 - Bairro Céu Azul | K32: 2302.1012201171.216.449051.S.500 | L32: 2302 | M32: FUNDO MUNICIPAL DE SAÚDE | N32: 10 | O32: SAÚDE | P32: 122 | Q32: ADMINISTRAÇÃO GERAL | R32: 0117 | S32: GESTÃO DO SUS | T32: 1216 | U32: CONSTRUÇÃO, AMPLIAÇÃO E REFORMA DE UNIDADES DE SAÚDE | V32: 449051 | W32: Despesa de capital | X32: Investimentos | Y32: 500 | Z32: FMS/SMOBI | AA32: 50000 | AB32: 32708.75 | AC32: 32708.75 | AD32: 32708.75 | AF32: 1 | AG32: 1 | AH32: 0322 | AI32: =IF(AH32="","",IFERROR(RIGHT("0000"&AH32,4)&" - "&UPPER(_xlfn.XLOOKUP(RIGHT("0000"&AH32,4),CODEBOOK_CAP!$C$2:$C$212,CODEBOOK_CAP!$D$2:$D$212)),"Código CAP não encontrado")) -> 0322 - ESTRUTURAS, HOSPITAIS, CLÍNICAS | AJ32: =IF(AH32="","",IFERROR(_xlfn.XLOOKUP(RIGHT("0000"&AH32,4),CODEBOOK_CAP!$C$2:$C$212,CODEBOOK_CAP!$E$2:$E$212),"Código CAP não encontrado")) -> Observações relacionadas as estruturas do sistema de saúde, como a construção de hospitais, postos de saúde, construção de maternidades, laboratórios, centros de saúde avançado, SAMU, Ambulâncias, UTI Móveis, leitos, compra de equipamentos médicos, Raio X, Ultrasom, equipamentos de diálise, capacidade de atendimento, estrutura e funcionamento de equipamentos públicos de saúde. | AK32: 1 | AL32: Rua Alice Marques, 187 - Bairro Céu Azul | AM32: 1 | AN32: 1 | AO32: Centro de Saúde Céu Azul (Rua Alice Marques, 187 - Bairro Céu Azul) | AP32: 0 | AR32: 0 | AT32: Revisado | AU32: Alta | AV32: 46214
A33: 2023_BIM_DA_AMBULANCIA_822_01 | B33: 2023 | C33: 601 | D33: emendas-2023-27-11-2025.xlsx | E33: 2023_BIM_DA_AMBULANCIA | F33: 822 | G33: CONCLUÍDO | H33: Bim da Ambulância | J33: À aquisição de materiais permanentes para o Centro de Saúde Céu Azul, situado à rua: Alice Marques, 187 - Bairro Céu Azul | K33: 2302.1030101572.690.449052.S.500 | L33: 2302 | M33: FUNDO MUNICIPAL DE SAÚDE | N33: 10 | O33: SAÚDE | P33: 301 | Q33: ATENÇÃO BÁSICA | R33: 0157 | S33: ATENÇÃO PRIMÁRIA À SAÚDE | T33: 2690 | U33: ATENÇÃO PRIMÁRIA À SAÚDE | V33: 449052 | W33: Despesa de capital | X33: Investimentos | Y33: 500 | Z33: FMS | AA33: 20000 | AB33: 18930.98 | AC33: 18930.98 | AD33: 18930.98 | AF33: 1 | AG33: 1 | AH33: 0322 | AI33: =IF(AH33="","",IFERROR(RIGHT("0000"&AH33,4)&" - "&UPPER(_xlfn.XLOOKUP(RIGHT("0000"&AH33,4),CODEBOOK_CAP!$C$2:$C$212,CODEBOOK_CAP!$D$2:$D$212)),"Código CAP não encontrado")) -> 0322 - ESTRUTURAS, HOSPITAIS, CLÍNICAS | AJ33: =IF(AH33="","",IFERROR(_xlfn.XLOOKUP(RIGHT("0000"&AH33,4),CODEBOOK_CAP!$C$2:$C$212,CODEBOOK_CAP!$E$2:$E$212),"Código CAP não encontrado")) -> Observações relacionadas as estruturas do sistema de saúde, como a construção de hospitais, postos de saúde, construção de maternidades, laboratórios, centros de saúde avançado, SAMU, Ambulâncias, UTI Móveis, leitos, compra de equipamentos médicos, Raio X, Ultrasom, equipamentos de diálise, capacidade de atendimento, estrutura e funcionamento de equipamentos públicos de saúde. | AK33: 1 | AL33: rua: Alice Marques, 187 - Bairro Céu Azul | AM33: 1 | AN33: 1 | AO33: Centro de Saúde Céu Azul (rua: Alice Marques, 187 - Bairro Céu Azul) | AP33: 0 | AR33: 0 | AT33: Revisado | AU33: Alta | AV33: 46214
A34: 2023_BIM_DA_AMBULANCIA_823_01 | B34: 2023 | C34: 602 | D34: emendas-2023-27-11-2025.xlsx | E34: 2023_BIM_DA_AMBULANCIA | F34: 823 | G34: CONCLUÍDO | H34: Bim da Ambulância | J34: À aquisição de materiais permanentes para o Centro Especializado Odontológico, situado à rua Eugênio Volpíni, 143 - São João Batista. | K34: 2302.1030201142.891.449052.S.500 | L34: 2302 | M34: FUNDO MUNICIPAL DE SAÚDE | N34: 10 | O34: SAÚDE | P34: 302 | Q34: ASSISTÊNCIA HOSPITALAR E AMBULATORIAL | R34: 0114 | S34: ATENÇÃO SECUNDÁRIA E TERCIÁRIA À SAÚDE | T34: 2891 | U34: REDE ESPECIALIZADA | V34: 449052 | W34: Despesa de capital | X34: Investimentos | Y34: 500 | Z34: FMS | AA34: 50000 | AB34: 49319.6 | AC34: 49319.6 | AD34: 49319.6 | AF34: 1 | AG34: 1 | AH34: 0322 | AI34: =IF(AH34="","",IFERROR(RIGHT("0000"&AH34,4)&" - "&UPPER(_xlfn.XLOOKUP(RIGHT("0000"&AH34,4),CODEBOOK_CAP!$C$2:$C$212,CODEBOOK_CAP!$D$2:$D$212)),"Código CAP não encontrado")) -> 0322 - ESTRUTURAS, HOSPITAIS, CLÍNICAS | AJ34: =IF(AH34="","",IFERROR(_xlfn.XLOOKUP(RIGHT("0000"&AH34,4),CODEBOOK_CAP!$C$2:$C$212,CODEBOOK_CAP!$E$2:$E$212),"Código CAP não encontrado")) -> Observações relacionadas as estruturas do sistema de saúde, como a construção de hospitais, postos de saúde, construção de maternidades, laboratórios, centros de saúde avançado, SAMU, Ambulâncias, UTI Móveis, leitos, compra de equipamentos médicos, Raio X, Ultrasom, equipamentos de diálise, capacidade de atendimento, estrutura e funcionamento de equipamentos públicos de saúde. | AK34: 1 | AL34: rua Eugênio Volpíni, 143 - São João Batista. | AM34: 1 | AN34: 1 | AO34: Centro Especializado Odontológico (rua Eugênio Volpíni, 143 - São João Batista.) | AP34: 0 | AR34: 0 | AT34: Revisado | AU34: Alta | AV34: 46214
A35: 2023_BIM_DA_AMBULANCIA_824_01 | B35: 2023 | C35: 603 | D35: emendas-2023-27-11-2025.xlsx | E35: 2023_BIM_DA_AMBULANCIA | F35: 824 | G35: EM EXECUÇÃO | H35: Bim da Ambulância | J35: À Reforma, Adaptação e Manutenção de Telhado para o Centro Especializado Odontológico. que será situado à rua Padre Pedro Pinto, 322. Venda Nova | K35: 2302.1012201171.216.449051.S.500 | L35: 2302 | M35: FUNDO MUNICIPAL DE SAÚDE | N35: 10 | O35: SAÚDE | P35: 122 | Q35: ADMINISTRAÇÃO GERAL | R35: 0117 | S35: GESTÃO DO SUS | T35: 1216 | U35: CONSTRUÇÃO, AMPLIAÇÃO E REFORMA DE UNIDADES DE SAÚDE | V35: 449051 | W35: Despesa de capital | X35: Investimentos | Y35: 500 | Z35: FMS/SMOBI | AA35: 200000 | AB35: 200000 | AC35: 196894.67 | AD35: 196894.67 | AF35: 1 | AG35: 1 | AH35: 0322 | AI35: =IF(AH35="","",IFERROR(RIGHT("0000"&AH35,4)&" - "&UPPER(_xlfn.XLOOKUP(RIGHT("0000"&AH35,4),CODEBOOK_CAP!$C$2:$C$212,CODEBOOK_CAP!$D$2:$D$212)),"Código CAP não encontrado")) -> 0322 - ESTRUTURAS, HOSPITAIS, CLÍNICAS | AJ35: =IF(AH35="","",IFERROR(_xlfn.XLOOKUP(RIGHT("0000"&AH35,4),CODEBOOK_CAP!$C$2:$C$212,CODEBOOK_CAP!$E$2:$E$212),"Código CAP não encontrado")) -> Observações relacionadas as estruturas do sistema de saúde, como a construção de hospitais, postos de saúde, construção de maternidades, laboratórios, centros de saúde avançado, SAMU, Ambulâncias, UTI Móveis, leitos, compra de equipamentos médicos, Raio X, Ultrasom, equipamentos de diálise, capacidade de atendimento, estrutura e funcionamento de equipamentos públicos de saúde. | AK35: 1 | AL35: rua Padre Pedro Pinto, 322. Venda Nova | AM35: 1 | AN35: 1 | AO35: Centro Especializado Odontológico (rua Padre Pedro Pinto, 322. Venda Nova) | AP35: 0 | AR35: 0 | AT35: Revisado | AU35: Alta | AV35: 46214
A36: 2023_BIM_DA_AMBULANCIA_825_01 | B36: 2023 | C36: 604 | D36: emendas-2023-27-11-2025.xlsx | E36: 2023_BIM_DA_AMBULANCIA | F36: 825 | G36: CONCLUÍDO | H36: Bim da Ambulância | J36: Ao reforço de dotação orçamentária para atendimento ao Hospital Metropolitano Odilon Behrens | K36: 2302.1030201142.894.339139.S.500 | L36: 2302 | M36: FUNDO MUNICIPAL DE SAÚDE | N36: 10 | O36: SAÚDE | P36: 302 | Q36: ASSISTÊNCIA HOSPITALAR E AMBULATORIAL | R36: 0114 | S36: ATENÇÃO SECUNDÁRIA E TERCIÁRIA À SAÚDE | T36: 2894 | U36: REDE HOSPITALAR | V36: 339139 | W36: Despesa corrente | X36: Outras despesas correntes | Y36: 500 | Z36: FMS | AA36: 100000 | AB36: 100000 | AC36: 100000 | AD36: 100000 | AF36: 1 | AG36: 1 | AH36: 0322 | AI36: =IF(AH36="","",IFERROR(RIGHT("0000"&AH36,4)&" - "&UPPER(_xlfn.XLOOKUP(RIGHT("0000"&AH36,4),CODEBOOK_CAP!$C$2:$C$212,CODEBOOK_CAP!$D$2:$D$212)),"Código CAP não encontrado")) -> 0322 - ESTRUTURAS, HOSPITAIS, CLÍNICAS | AJ36: =IF(AH36="","",IFERROR(_xlfn.XLOOKUP(RIGHT("0000"&AH36,4),CODEBOOK_CAP!$C$2:$C$212,CODEBOOK_CAP!$E$2:$E$212),"Código CAP não encontrado")) -> Observações relacionadas as estruturas do sistema de saúde, como a construção de hospitais, postos de saúde, construção de maternidades, laboratórios, centros de saúde avançado, SAMU, Ambulâncias, UTI Móveis, leitos, compra de equipamentos médicos, Raio X, Ultrasom, equipamentos de diálise, capacidade de atendimento, estrutura e funcionamento de equipamentos públicos de saúde. | AK36: 0 | AM36: 1 | AN36: 1 | AO36: Hospital Odilon Behrens (R. Formiga, 50 - São Cristóvão, Belo Horizonte - MG, 31110-430) | AP36: 0 | AR36: 0 | AT36: Revisado | AU36: Alta | AV36: 46214
A37: 2023_BIM_DA_AMBULANCIA_831_01 | B37: 2023 | C37: 610 | D37: emendas-2023-27-11-2025.xlsx | E37: 2023_BIM_DA_AMBULANCIA | F37: 831 | G37: EM EXECUÇÃO | H37: Bim da Ambulância | J37: À aquisição de materiais permanentes para o Centro de Saúde Regina, situado à rua Aristolino Basílio de Oliveira, 467 - Bairro Regina - CEP: 30.692-000 | K37: 2302.1030101572.690.449052.S.500 | L37: 2302 | M37: FUNDO MUNICIPAL DE SAÚDE | N37: 10 | O37: SAÚDE | P37: 301 | Q37: ATENÇÃO BÁSICA | R37: 0157 | S37: ATENÇÃO PRIMÁRIA À SAÚDE | T37: 2690 | U37: ATENÇÃO PRIMÁRIA À SAÚDE | V37: 449052 | W37: Despesa de capital | X37: Investimentos | Y37: 500 | Z37: FMS | AA37: 40000 | AB37: 31739.13 | AC37: 28259.13 | AD37: 28259.13 | AE37: B. D. R. COMERCIO DE EQUIPAMENTOS LTDA; BOSCO FELIPE COMERCIO LTDA; BT COMERCIO INTELIGENTE LTDA; CB ELETRO E INFORMATICA LTDA; D3JF EMPREENDIMENTOS COMERCIAIS LTDA; FORMIGARI COMERCIO DE MOVEIS LTDA; INDUSTRIA FENIX CORTE A LASER LTDA; KIENTRO BRASIL LTDA | AF37: 1 | AG37: 1 | AH37: 0322 | AI37: =IF(AH37="","",IFERROR(RIGHT("0000"&AH37,4)&" - "&UPPER(_xlfn.XLOOKUP(RIGHT("0000"&AH37,4),CODEBOOK_CAP!$C$2:$C$212,CODEBOOK_CAP!$D$2:$D$212)),"Código CAP não encontrado")) -> 0322 - ESTRUTURAS, HOSPITAIS, CLÍNICAS | AJ37: =IF(AH37="","",IFERROR(_xlfn.XLOOKUP(RIGHT("0000"&AH37,4),CODEBOOK_CAP!$C$2:$C$212,CODEBOOK_CAP!$E$2:$E$212),"Código CAP não encontrado")) -> Observações relacionadas as estruturas do sistema de saúde, como a construção de hospitais, postos de saúde, construção de maternidades, laboratórios, centros de saúde avançado, SAMU, Ambulâncias, UTI Móveis, leitos, compra de equipamentos médicos, Raio X, Ultrasom, equipamentos de diálise, capacidade de atendimento, estrutura e funcionamento de equipamentos públicos de saúde. | AK37: 1 | AL37: rua Aristolino Basílio de Oliveira, 467 - Bairro Regina - CEP: 30.692-000 | AM37: 1 | AN37: 1 | AO37: Centro de Saúde Regina (rua Aristolino Basílio de Oliveira, 467 - Bairro Regina - CEP: 30.692-000) | AP37: 0 | AR37: 1 | AS37: B. D. R. COMERCIO DE EQUIPAMENTOS LTDA; BOSCO FELIPE COMERCIO LTDA; BT COMERCIO INTELIGENTE LTDA; CB ELETRO E INFORMATICA LTDA; D3JF EMPREENDIMENTOS COMERCIAIS LTDA; FORMIGARI COMERCIO DE MOVEIS LTDA; INDUSTRIA FENIX CORTE A LASER LTDA; KIENTRO BRASIL LTDA | AT37: Revisado | AU37: Alta | AV37: 46214
A38: 2023_BIM_DA_AMBULANCIA_839_01 | B38: 2023 | C38: 618 | D38: emendas-2023-27-11-2025.xlsx | E38: 2023_BIM_DA_AMBULANCIA | F38: 839 | G38: EM EXECUÇÃO | H38: Bim da Ambulância | J38: Objeto do gasto: À aquisição de materiais permanentes para o Centro de Saúde Paraúna, situado à rua João Ferreira da Silva, 248 - Bairro Mantiqueira - Venda Nova | K38: 2302.1030101572.690.449052.S.500 | L38: 2302 | M38: FUNDO MUNICIPAL DE SAÚDE | N38: 10 | O38: SAÚDE | P38: 301 | Q38: ATENÇÃO BÁSICA | R38: 0157 | S38: ATENÇÃO PRIMÁRIA À SAÚDE | T38: 2690 | U38: ATENÇÃO PRIMÁRIA À SAÚDE | V38: 449052 | W38: Despesa de capital | X38: Investimentos | Y38: 500 | Z38: FMS | AA38: 15000 | AB38: 3348.22 | AC38: 3348.22 | AD38: 3348.22 | AF38: 1 | AG38: 1 | AH38: 0322 | AI38: =IF(AH38="","",IFERROR(RIGHT("0000"&AH38,4)&" - "&UPPER(_xlfn.XLOOKUP(RIGHT("0000"&AH38,4),CODEBOOK_CAP!$C$2:$C$212,CODEBOOK_CAP!$D$2:$D$212)),"Código CAP não encontrado")) -> 0322 - ESTRUTURAS, HOSPITAIS, CLÍNICAS | AJ38: =IF(AH38="","",IFERROR(_xlfn.XLOOKUP(RIGHT("0000"&AH38,4),CODEBOOK_CAP!$C$2:$C$212,CODEBOOK_CAP!$E$2:$E$212),"Código CAP não encontrado")) -> Observações relacionadas as estruturas do sistema de saúde, como a construção de hospitais, postos de saúde, construção de maternidades, laboratórios, centros de saúde avançado, SAMU, Ambulâncias, UTI Móveis, leitos, compra de equipamentos médicos, Raio X, Ultrasom, equipamentos de diálise, capacidade de atendimento, estrutura e funcionamento de equipamentos públicos de saúde. | AK38: 1 | AL38: Centro de Saúde Paraúna, situado à rua João Ferreira da Silva, 248 - Bairro Mantiqueira - Venda Nova | AM38: 1 | AN38: 1 | AO38: Centro de Saúde Paraúna, situado à rua João Ferreira da Silva, 248 - Bairro Mantiqueira - Venda Nova | AP38: 0 | AR38: 0 | AT38: Revisado | AU38: Alta | AV38: 46214
A39: 2023_BIM_DA_AMBULANCIA_841_01 | B39: 2023 | C39: 619 | D39: emendas-2023-27-11-2025.xlsx | E39: 2023_BIM_DA_AMBULANCIA | F39: 841 | G39: EM EXECUÇÃO | H39: Bim da Ambulância | J39: À aquisição de material permanente para a UPA Barreira, situada à rua Aurélio Lopes, 20 - Bairro Diamante - Bairreiro | K39: 2302.1030201142.893.449052.S.500 | L39: 2302 | M39: FUNDO MUNICIPAL DE SAÚDE | N39: 10 | O39: SAÚDE | P39: 302 | Q39: ASSISTÊNCIA HOSPITALAR E AMBULATORIAL | R39: 0114 | S39: ATENÇÃO SECUNDÁRIA E TERCIÁRIA À SAÚDE | T39: 2893 | U39: REDE DE URGÊNCIA E EMERGÊNCIA | V39: 449052 | W39: Despesa de capital | X39: Investimentos | Y39: 500 | Z39: FMS | AA39: 15000 | AB39: 3998.75 | AC39: 3998.75 | AD39: 3998.75 | AF39: 1 | AG39: 1 | AH39: 0322 | AI39: =IF(AH39="","",IFERROR(RIGHT("0000"&AH39,4)&" - "&UPPER(_xlfn.XLOOKUP(RIGHT("0000"&AH39,4),CODEBOOK_CAP!$C$2:$C$212,CODEBOOK_CAP!$D$2:$D$212)),"Código CAP não encontrado")) -> 0322 - ESTRUTURAS, HOSPITAIS, CLÍNICAS | AJ39: =IF(AH39="","",IFERROR(_xlfn.XLOOKUP(RIGHT("0000"&AH39,4),CODEBOOK_CAP!$C$2:$C$212,CODEBOOK_CAP!$E$2:$E$212),"Código CAP não encontrado")) -> Observações relacionadas as estruturas do sistema de saúde, como a construção de hospitais, postos de saúde, construção de maternidades, laboratórios, centros de saúde avançado, SAMU, Ambulâncias, UTI Móveis, leitos, compra de equipamentos médicos, Raio X, Ultrasom, equipamentos de diálise, capacidade de atendimento, estrutura e funcionamento de equipamentos públicos de saúde. | AK39: 1 | AL39: UPA Barreira, situada à rua Aurélio Lopes, 20 - Bairro Diamante - Bairreiro | AM39: 1 | AN39: 1 | AO39: UPA Barreira, situada à rua Aurélio Lopes, 20 - Bairro Diamante - Bairreiro | AP39: 0 | AR39: 0 | AT39: Revisado | AU39: Alta | AV39: 46214
A40: 2023_BIM_DA_AMBULANCIA_844_01 | B40: 2023 | C40: 622 | D40: emendas-2023-27-11-2025.xlsx | E40: 2023_BIM_DA_AMBULANCIA | F40: 844 | G40: CONCLUÍDO | H40: Bim da Ambulância | J40: Ao reforço de dotação orçamentária para a Unidade de Pronto Atendimento - UPA Santa Terezinha, 515 | K40: 2302.1030201142.893.339039.S.500 | L40: 2302 | M40: FUNDO MUNICIPAL DE SAÚDE | N40: 10 | O40: SAÚDE | P40: 302 | Q40: ASSISTÊNCIA HOSPITALAR E AMBULATORIAL | R40: 0114 | S40: ATENÇÃO SECUNDÁRIA E TERCIÁRIA À SAÚDE | T40: 2893 | U40: REDE DE URGÊNCIA E EMERGÊNCIA | V40: 339039 | W40: Despesa corrente | X40: Outras despesas correntes | Y40: 500 | Z40: FMS | AA40: 100000 | AB40: 100000 | AC40: 188421.05 | AD40: 100000 | AF40: 1 | AG40: 1 | AH40: 0322 | AI40: =IF(AH40="","",IFERROR(RIGHT("0000"&AH40,4)&" - "&UPPER(_xlfn.XLOOKUP(RIGHT("0000"&AH40,4),CODEBOOK_CAP!$C$2:$C$212,CODEBOOK_CAP!$D$2:$D$212)),"Código CAP não encontrado")) -> 0322 - ESTRUTURAS, HOSPITAIS, CLÍNICAS | AJ40: =IF(AH40="","",IFERROR(_xlfn.XLOOKUP(RIGHT("0000"&AH40,4),CODEBOOK_CAP!$C$2:$C$212,CODEBOOK_CAP!$E$2:$E$212),"Código CAP não encontrado")) -> Observações relacionadas as estruturas do sistema de saúde, como a construção de hospitais, postos de saúde, construção de maternidades, laboratórios, centros de saúde avançado, SAMU, Ambulâncias, UTI Móveis, leitos, compra de equipamentos médicos, Raio X, Ultrasom, equipamentos de diálise, capacidade de atendimento, estrutura e funcionamento de equipamentos públicos de saúde. | AK40: 0 | AM40: 1 | AN40: 1 | AO40: Av. Santa Terezinha, 515 - Santa Terezinha, Belo Horizonte - MG, 31360-000, Brazil | AP40: 0 | AR40: 0 | AT40: Revisado | AU40: Alta | AV40: 46214
A41: 2023_BIM_DA_AMBULANCIA_847_01 | B41: 2023 | C41: 625 | D41: emendas-2023-27-11-2025.xlsx | E41: 2023_BIM_DA_AMBULANCIA | F41: 847 | G41: CONCLUÍDO | H41: Bim da Ambulância | J41: Ao reforço de dotação orçamentária para a Unidade de Pronto Atendimento - UPA Norte, situada à Avenida Risoleta Neves, 281 - Bairro Novo Aarão Reis. | K41: 2302.1030201142.893.339039.S.500 | L41: 2302 | M41: FUNDO MUNICIPAL DE SAÚDE | N41: 10 | O41: SAÚDE | P41: 302 | Q41: ASSISTÊNCIA HOSPITALAR E AMBULATORIAL | R41: 0114 | S41: ATENÇÃO SECUNDÁRIA E TERCIÁRIA À SAÚDE | T41: 2893 | U41: REDE DE URGÊNCIA E EMERGÊNCIA | V41: 339039 | W41: Despesa corrente | X41: Outras despesas correntes | Y41: 500 | Z41: FMS | AA41: 59000 | AB41: 59000 | AC41: 111168.42 | AD41: 59000 | AF41: 1 | AG41: 1 | AH41: 0322 | AI41: =IF(AH41="","",IFERROR(RIGHT("0000"&AH41,4)&" - "&UPPER(_xlfn.XLOOKUP(RIGHT("0000"&AH41,4),CODEBOOK_CAP!$C$2:$C$212,CODEBOOK_CAP!$D$2:$D$212)),"Código CAP não encontrado")) -> 0322 - ESTRUTURAS, HOSPITAIS, CLÍNICAS | AJ41: =IF(AH41="","",IFERROR(_xlfn.XLOOKUP(RIGHT("0000"&AH41,4),CODEBOOK_CAP!$C$2:$C$212,CODEBOOK_CAP!$E$2:$E$212),"Código CAP não encontrado")) -> Observações relacionadas as estruturas do sistema de saúde, como a construção de hospitais, postos de saúde, construção de maternidades, laboratórios, centros de saúde avançado, SAMU, Ambulâncias, UTI Móveis, leitos, compra de equipamentos médicos, Raio X, Ultrasom, equipamentos de diálise, capacidade de atendimento, estrutura e funcionamento de equipamentos públicos de saúde. | AK41: 1 | AL41: UPA Norte, situada à Avenida Risoleta Neves, 281 - Bairro Novo Aarão Reis. | AM41: 1 | AN41: 1 | AO41: UPA Norte, situada à Avenida Risoleta Neves, 281 - Bairro Novo Aarão Reis. | AP41: 0 | AR41: 0 | AT41: Revisado | AU41: Alta | AV41: 46214
A42: 2023_BIM_DA_AMBULANCIA_849_01 | B42: 2023 | C42: 627 | D42: emendas-2023-27-11-2025.xlsx | E42: 2023_BIM_DA_AMBULANCIA | F42: 849 | G42: EM EXECUÇÃO | H42: Bim da Ambulância | J42: Ao reforço de dotação orçamentária para a Unidade de Pronto Atendimento - UPA Venda Nova, situada à rua Padre Pedro Pinto, 175 - Venda Nova | K42: 2302.1030201142.893.449052.S.500 | L42: 2302 | M42: FUNDO MUNICIPAL DE SAÚDE | N42: 10 | O42: SAÚDE | P42: 302 | Q42: ASSISTÊNCIA HOSPITALAR E AMBULATORIAL | R42: 0114 | S42: ATENÇÃO SECUNDÁRIA E TERCIÁRIA À SAÚDE | T42: 2893 | U42: REDE DE URGÊNCIA E EMERGÊNCIA | V42: 449052 | W42: Despesa de capital | X42: Investimentos | Y42: 500 | Z42: FMS | AA42: 140532 | AB42: 80272.759999999995 | AC42: 80272.759999999995 | AD42: 80272.759999999995 | AE42: CONEXAO 5 DISTRIBUIDORA E SERVICOS LTDA; D3JF EMPREENDIMENTOS COMERCIAIS LTDA; DUMALE PRODUTOS PARA SAUDE LTDA; FABERMINAS COMERCIO DE MATERIAL HOSPITALAR E HIGIENE LTDA; KIENTRO BRASIL LTDA | AF42: 1 | AG42: 1 | AH42: 0322 | AI42: =IF(AH42="","",IFERROR(RIGHT("0000"&AH42,4)&" - "&UPPER(_xlfn.XLOOKUP(RIGHT("0000"&AH42,4),CODEBOOK_CAP!$C$2:$C$212,CODEBOOK_CAP!$D$2:$D$212)),"Código CAP não encontrado")) -> 0322 - ESTRUTURAS, HOSPITAIS, CLÍNICAS | AJ42: =IF(AH42="","",IFERROR(_xlfn.XLOOKUP(RIGHT("0000"&AH42,4),CODEBOOK_CAP!$C$2:$C$212,CODEBOOK_CAP!$E$2:$E$212),"Código CAP não encontrado")) -> Observações relacionadas as estruturas do sistema de saúde, como a construção de hospitais, postos de saúde, construção de maternidades, laboratórios, centros de saúde avançado, SAMU, Ambulâncias, UTI Móveis, leitos, compra de equipamentos médicos, Raio X, Ultrasom, equipamentos de diálise, capacidade de atendimento, estrutura e funcionamento de equipamentos públicos de saúde. | AK42: 1 | AL42: UPA Venda Nova, situada à rua Padre Pedro Pinto, 175 - Venda Nova | AM42: 1 | AN42: 1 | AO42: UPA Venda Nova, situada à rua Padre Pedro Pinto, 175 - Venda Nova | AP42: 0 | AR42: 1 | AS42: CONEXAO 5 DISTRIBUIDORA E SERVICOS LTDA; D3JF EMPREENDIMENTOS COMERCIAIS LTDA; DUMALE PRODUTOS PARA SAUDE LTDA; FABERMINAS COMERCIO DE MATERIAL HOSPITALAR E HIGIENE LTDA; KIENTRO BRASIL LTDA | AT42: Revisado | AU42: Alta | AV42: 46214
A43: 2023_BRAULIO_LARA_353_01 | B43: 2023 | C43: 166 | D43: emendas-2023-27-11-2025.xlsx | E43: 2023_BRAULIO_LARA | F43: 353 | G43: CONCLUÍDO | H43: Braulio Lara | J43: à manutenção e melhorias nos parques Aggeo Pio Sobrinho, Conjunto Estrela D'alva e Bandeirante Silva Ortiz, vinculados à Fundação de Parques Municipais e Zoobotanico | K43: 2700.1545102331.202.449051.F.500 | L43: 2700 | M43: SECRETARIA MUNICIPAL DE OBRAS E INFRAESTRUTURA | N43: 15 | O43: URBANISMO | P43: 451 | Q43: INFRA-ESTRUTURA URBANA | R43: 0233 | S43: MANUTENÇÃO DA CIDADE | T43: 1202 | U43: CONSTRUÇÃO, AMPLIAÇÃO E REFORMA DE PRAÇAS, PARQUES E CANTEIROS | V43: 449051 | W43: Despesa de capital | X43: Investimentos | Y43: 500 | Z43: SMOBI | AA43: 400000 | AB43: 253112.14 | AC43: 253112.14 | AD43: 253112.14 | AF43: 0 | AG43: 0 | AH43: 2101 | AI43: =IF(AH43="","",IFERROR(RIGHT("0000"&AH43,4)&" - "&UPPER(_xlfn.XLOOKUP(RIGHT("0000"&AH43,4),CODEBOOK_CAP!$C$2:$C$212,CODEBOOK_CAP!$D$2:$D$212)),"Código CAP não encontrado")) -> 2101 - PARQUES PÚBLICOS E RESERVAS DE PRESERVAÇÃO | AJ43: =IF(AH43="","",IFERROR(_xlfn.XLOOKUP(RIGHT("0000"&AH43,4),CODEBOOK_CAP!$C$2:$C$212,CODEBOOK_CAP!$E$2:$E$212),"Código CAP não encontrado")) -> Regulação, normas, orinetações, manutenção em território publico aberto, como parques, reservas ambientais, áreas protegidas e de preservação ambiental. Regulação de parques naturais e áreas protegidas. Utilização de bosques e florestas públicas | AK43: 0 | AM43: 3 | AN43: 1 | AO43: parques Aggeo Pio Sobrinho, Conjunto Estrela D'alva e Bandeirante Silva Ortiz | AP43: 0 | AR43: 0 | AT43: Revisado | AU43: Alta | AV43: 46214
A44: 2023_BRAULIO_LARA_354_01 | B44: 2023 | C44: 167 | D44: emendas-2023-27-11-2025.xlsx | E44: 2023_BRAULIO_LARA | F44: 354 | G44: IMPEDIMENTO TÉCNICO | H44: Braulio Lara | J44: à revitalização e melhoria da pista de caminhada na Av. Henrique Badaró Portugal, no bairro Buritis: alargamento, pintura e iluminação baixa | K44: 2700.2781201011.213.449051.F.500 | L44: 2700 | M44: SECRETARIA MUNICIPAL DE OBRAS E INFRAESTRUTURA | N44: 27 | O44: DESPORTO E LAZER | P44: 812 | Q44: DESPORTO COMUNITÁRIO | R44: 0101 | S44: PROMOÇÃO E DEMOCRATIZAÇÃO DAS PRÁTICAS DE ESPORTES E LAZER | T44: 1213 | U44: CONSTRUÇÃO, AMPLIAÇÃO E REFORMA DE EQUIPAMENTOS ESPORTIVOS E ÁREAS DE LAZER | V44: 449051 | W44: Despesa de capital | X44: Investimentos | Y44: 500 | Z44: SMOBI | AA44: 250000 | AB44: 0 | AC44: 0 | AD44: 0 | AF44: 0 | AG44: 0 | AH44: 2300 | AI44: =IF(AH44="","",IFERROR(RIGHT("0000"&AH44,4)&" - "&UPPER(_xlfn.XLOOKUP(RIGHT("0000"&AH44,4),CODEBOOK_CAP!$C$2:$C$212,CODEBOOK_CAP!$D$2:$D$212)),"Código CAP não encontrado")) -> 2300 - GERAL | AJ44: =IF(AH44="","",IFERROR(_xlfn.XLOOKUP(RIGHT("0000"&AH44,4),CODEBOOK_CAP!$C$2:$C$212,CODEBOOK_CAP!$E$2:$E$212),"Código CAP não encontrado")) -> Observações relativas as políticas de cultura, Lei rouanet, patrimônio cultural, imaterial, políticas de artes, incentivos fiscais para artes, promoção de eventos culturais, amostras, teatro, dança, artes plásticas, artes visuais, museus, galerias públicas, idioma, lingua portuguesa. Grandes eventos esportivos, Copa do Mundo, Olimpiadas, Esporte e Lazer. | AK44: 1 | AL44: Av. Henrique Badaró Portugal, no bairro Buritis: | AM44: 1 | AN44: 1 | AO44: Av. Henrique Badaró Portugal, no bairro Buritis | AP44: 0 | AR44: 0 | AT44: Revisado | AU44: Alta | AV44: 46214 | AX44: esporte e lazer
A45: 2023_BRAULIO_LARA_355_01 | B45: 2023 | C45: 168 | D45: emendas-2023-27-11-2025.xlsx | E45: 2023_BRAULIO_LARA | F45: 355 | G45: EM EXECUÇÃO | H45: Braulio Lara | J45: à Elaboração de projetos e orçamentos para implementação e revitalização das escadarias do bairro Buritis | K45: 2700.1545102331.396.449051.F.500 | L45: 2700 | M45: SECRETARIA MUNICIPAL DE OBRAS E INFRAESTRUTURA | N45: 15 | O45: URBANISMO | P45: 451 | Q45: INFRA-ESTRUTURA URBANA | R45: 0233 | S45: MANUTENÇÃO DA CIDADE | T45: 1396 | U45: INFRAESTRUTURA URBANA | V45: 449051 | W45: Despesa de capital | X45: Investimentos | Y45: 500 | Z45: SMOBI | AA45: 200000 | AB45: 0 | AC45: 0 | AD45: 0 | AF45: 0 | AG45: 0 | AH45: 1403 | AI45: =IF(AH45="","",IFERROR(RIGHT("0000"&AH45,4)&" - "&UPPER(_xlfn.XLOOKUP(RIGHT("0000"&AH45,4),CODEBOOK_CAP!$C$2:$C$212,CODEBOOK_CAP!$D$2:$D$212)),"Código CAP não encontrado")) -> 1403 - REABILITAÇÃO URBANA, ECONOMIA URBANA | AJ45: =IF(AH45="","",IFERROR(_xlfn.XLOOKUP(RIGHT("0000"&AH45,4),CODEBOOK_CAP!$C$2:$C$212,CODEBOOK_CAP!$E$2:$E$212),"Código CAP não encontrado")) -> Reabilitação de áreas urbanas, revitalização urbana, modernização de áreas, mercados públicos, revitalização de praças, política urbana nacional, desenvolvimento urbano , desenvolvimento econômico de estados e cidades, modernização de espaços urbanos | AK45: 1 | AL45: bairro Buritis | AM45: 1 | AN45: 0 | AP45: 0 | AR45: 0 | AT45: Revisado | AU45: Alta | AV45: 46214
A46: 2023_BRAULIO_LARA_356_01 | B46: 2023 | C46: 169 | D46: emendas-2023-27-11-2025.xlsx | E46: 2023_BRAULIO_LARA | F46: 356 | G46: IMPEDIMENTO TÉCNICO | H46: Braulio Lara | J46: à implantação de pista de caminhada na Rua Marco Aurélio de Miranda com Av. Protássio Oliveira Pena, no bairro Buritis | K46: 3303.1100.26452602.837.33903963.F.500 | L46: 3303 | M46: FUNDO MUNICIPAL DE MOBILIDADE URBANA | N46: 26 | O46: TRANSPORTE | P46: 452 | Q46: SERVIÇOS URBANOS | R46: 0060 | S46: GESTÃO DA MOBILIDADE URBANA | T46: 2837 | U46: GERENCIAMENTO DA MOBILIDADE URBANA MUNICIPAL | V46: 339039 | W46: Despesa corrente | X46: Outras despesas correntes | Y46: 500 | Z46: BHTRANS | AA46: 30000 | AB46: 0 | AC46: 0 | AD46: 0 | AF46: 0 | AG46: 0 | AH46: 2300 | AI46: =IF(AH46="","",IFERROR(RIGHT("0000"&AH46,4)&" - "&UPPER(_xlfn.XLOOKUP(RIGHT("0000"&AH46,4),CODEBOOK_CAP!$C$2:$C$212,CODEBOOK_CAP!$D$2:$D$212)),"Código CAP não encontrado")) -> 2300 - GERAL | AJ46: =IF(AH46="","",IFERROR(_xlfn.XLOOKUP(RIGHT("0000"&AH46,4),CODEBOOK_CAP!$C$2:$C$212,CODEBOOK_CAP!$E$2:$E$212),"Código CAP não encontrado")) -> Observações relativas as políticas de cultura, Lei rouanet, patrimônio cultural, imaterial, políticas de artes, incentivos fiscais para artes, promoção de eventos culturais, amostras, teatro, dança, artes plásticas, artes visuais, museus, galerias públicas, idioma, lingua portuguesa. Grandes eventos esportivos, Copa do Mundo, Olimpiadas, Esporte e Lazer. | AK46: 1 | AL46: Rua Marco Aurélio de Miranda com Av. Protássio Oliveira Pena, no bairro Buritis | AM46: 1 | AN46: 1 | AO46: Rua Marco Aurélio de Miranda com Av. Protássio Oliveira Pena, no bairro Buritis | AP46: 0 | AR46: 0 | AT46: Revisado | AU46: Alta | AV46: 46214 | AX46: esporte e lazer
A47: 2023_BRAULIO_LARA_357_01 | B47: 2023 | C47: 170 | D47: emendas-2023-27-11-2025.xlsx | E47: 2023_BRAULIO_LARA | F47: 357 | G47: CONCLUÍDO | H47: Braulio Lara | J47: à Sinalização na esquina da Rua Ernani Agrícola com a Rua Walter Guimarães Figueiredo: instalação de placa de pare e faixa de retenção na Ernani Agrícola | K47: 3303.2645200602.837.339039.F.500 | L47: 3303 | M47: FUNDO MUNICIPAL DE MOBILIDADE URBANA | N47: 26 | O47: TRANSPORTE | P47: 452 | Q47: SERVIÇOS URBANOS | R47: 0060 | S47: GESTÃO DA MOBILIDADE URBANA | T47: 2837 | U47: GERENCIAMENTO DA MOBILIDADE URBANA MUNICIPAL | V47: 339039 | W47: Despesa corrente | X47: Outras despesas correntes | Y47: 500 | Z47: BHTRANS | AA47: 3000 | AB47: 1325.41 | AC47: 1325.41 | AD47: 1325.41 | AF47: 0 | AG47: 0 | AH47: 1002 | AI47: =IF(AH47="","",IFERROR(RIGHT("0000"&AH47,4)&" - "&UPPER(_xlfn.XLOOKUP(RIGHT("0000"&AH47,4),CODEBOOK_CAP!$C$2:$C$212,CODEBOOK_CAP!$D$2:$D$212)),"Código CAP não encontrado")) -> 1002 - CARROS, TRÂNSITO, CONSTRUÇÃO E MANUTENÇÃO DE RUAS E ESTRADAS | AJ47: =IF(AH47="","",IFERROR(_xlfn.XLOOKUP(RIGHT("0000"&AH47,4),CODEBOOK_CAP!$C$2:$C$212,CODEBOOK_CAP!$E$2:$E$212),"Código CAP não encontrado")) -> Construção, manutenção de ruas, avenidas, estradas. BRs, pedágios, privatizações, concessinárias, segurança nas estradas, leis de trânsito relacionadas a via, limite de velocidade, sinalização, recapeamento de ruas, pavimentação estradas de terra, não pavimentadas, acidentes e camapanhas de prevencao contra acidentes de transito. Observações sobre regulação de transportes não públicos de carros, veículos de passeio, uber, taxi, transporte de cargas terrestre, frete, trânsito em vias públicas, regulamentação de tipos de carteira de motorista, especificações para caminhoneiros, testes e exames de habilitação, exigências de carteira de habilitação, obrigatoriedade de itens em veículos (extintor, kit primeiros socorros, airbag, freios abs) Quando tratar de grandes obras de construções de rodovias, olhar codigo 1010 para ver qual se encaixa melhor. | AK47: 1 | AL47: Rua Ernani Agrícola com a Rua Walter Guimarães Figueiredo | AM47: 1 | AN47: 1 | AO47: Rua Ernani Agrícola com a Rua Walter Guimarães Figueiredo | AP47: 0 | AR47: 0 | AT47: Revisado | AU47: Alta | AV47: 46214
A48: 2023_BRAULIO_LARA_358_01 | B48: 2023 | C48: 171 | D48: emendas-2023-27-11-2025.xlsx | E48: 2023_BRAULIO_LARA | F48: 358 | G48: CONCLUÍDO | H48: Braulio Lara | J48: ao desenvolvimento de Projeto operacional e ao arredondamento da quina da esquina da Rua Ernani Agrícola com a Rua Ulisses Marcondes Escobar (facilitar a melhoria da conversão) | K48: 3303.1100.26.452.60.2837.S.33903963.500 | L48: 3303 | M48: FUNDO MUNICIPAL DE MOBILIDADE URBANA | N48: 26 | O48: TRANSPORTE | P48: 452 | Q48: SERVIÇOS URBANOS | R48: 0060 | S48: GESTÃO DA MOBILIDADE URBANA | T48: 2837 | U48: GERENCIAMENTO DA MOBILIDADE URBANA MUNICIPAL | V48: 339039 | W48: Despesa corrente | X48: Outras despesas correntes | Y48: 500 | Z48: BHTRANS | AA48: 10000 | AB48: 9946.65 | AC48: 9946.65 | AD48: 9946.65 | AF48: 0 | AG48: 0 | AH48: 1002 | AI48: =IF(AH48="","",IFERROR(RIGHT("0000"&AH48,4)&" - "&UPPER(_xlfn.XLOOKUP(RIGHT("0000"&AH48,4),CODEBOOK_CAP!$C$2:$C$212,CODEBOOK_CAP!$D$2:$D$212)),"Código CAP não encontrado")) -> 1002 - CARROS, TRÂNSITO, CONSTRUÇÃO E MANUTENÇÃO DE RUAS E ESTRADAS | AJ48: =IF(AH48="","",IFERROR(_xlfn.XLOOKUP(RIGHT("0000"&AH48,4),CODEBOOK_CAP!$C$2:$C$212,CODEBOOK_CAP!$E$2:$E$212),"Código CAP não encontrado")) -> Construção, manutenção de ruas, avenidas, estradas. BRs, pedágios, privatizações, concessinárias, segurança nas estradas, leis de trânsito relacionadas a via, limite de velocidade, sinalização, recapeamento de ruas, pavimentação estradas de terra, não pavimentadas, acidentes e camapanhas de prevencao contra acidentes de transito. Observações sobre regulação de transportes não públicos de carros, veículos de passeio, uber, taxi, transporte de cargas terrestre, frete, trânsito em vias públicas, regulamentação de tipos de carteira de motorista, especificações para caminhoneiros, testes e exames de habilitação, exigências de carteira de habilitação, obrigatoriedade de itens em veículos (extintor, kit primeiros socorros, airbag, freios abs) Quando tratar de grandes obras de construções de rodovias, olhar codigo 1010 para ver qual se encaixa melhor. | AK48: 1 | AL48: Rua Ernani Agrícola com a Rua Ulisses Marcondes Escobar | AM48: 1 | AN48: 1 | AO48: Rua Ernani Agrícola com a Rua Ulisses Marcondes Escobar | AP48: 0 | AR48: 0 | AT48: Revisado | AU48: Alta | AV48: 46214
A49: 2023_BRAULIO_LARA_359_01 | B49: 2023 | C49: 172 | D49: emendas-2023-27-11-2025.xlsx | E49: 2023_BRAULIO_LARA | F49: 359 | G49: CONCLUÍDO | H49: Braulio Lara | J49: à melhoria de sinalização de trânsito na Rua Lauro Ferreira | K49: 3303.2645200602.837.339039.F.500 | L49: 3303 | M49: FUNDO MUNICIPAL DE MOBILIDADE URBANA | N49: 26 | O49: TRANSPORTE | P49: 452 | Q49: SERVIÇOS URBANOS | R49: 0060 | S49: GESTÃO DA MOBILIDADE URBANA | T49: 2837 | U49: GERENCIAMENTO DA MOBILIDADE URBANA MUNICIPAL | V49: 339039 | W49: Despesa corrente | X49: Outras despesas correntes | Y49: 500 | Z49: BHTRANS | AA49: 2000 | AB49: 1234 | AC49: 1234 | AD49: 1234 | AF49: 0 | AG49: 0 | AH49: 1002 | AI49: =IF(AH49="","",IFERROR(RIGHT("0000"&AH49,4)&" - "&UPPER(_xlfn.XLOOKUP(RIGHT("0000"&AH49,4),CODEBOOK_CAP!$C$2:$C$212,CODEBOOK_CAP!$D$2:$D$212)),"Código CAP não encontrado")) -> 1002 - CARROS, TRÂNSITO, CONSTRUÇÃO E MANUTENÇÃO DE RUAS E ESTRADAS | AJ49: =IF(AH49="","",IFERROR(_xlfn.XLOOKUP(RIGHT("0000"&AH49,4),CODEBOOK_CAP!$C$2:$C$212,CODEBOOK_CAP!$E$2:$E$212),"Código CAP não encontrado")) -> Construção, manutenção de ruas, avenidas, estradas. BRs, pedágios, privatizações, concessinárias, segurança nas estradas, leis de trânsito relacionadas a via, limite de velocidade, sinalização, recapeamento de ruas, pavimentação estradas de terra, não pavimentadas, acidentes e camapanhas de prevencao contra acidentes de transito. Observações sobre regulação de transportes não públicos de carros, veículos de passeio, uber, taxi, transporte de cargas terrestre, frete, trânsito em vias públicas, regulamentação de tipos de carteira de motorista, especificações para caminhoneiros, testes e exames de habilitação, exigências de carteira de habilitação, obrigatoriedade de itens em veículos (extintor, kit primeiros socorros, airbag, freios abs) Quando tratar de grandes obras de construções de rodovias, olhar codigo 1010 para ver qual se encaixa melhor. | AK49: 1 | AL49: Rua Lauro Ferreira | AM49: 1 | AN49: 1 | AO49: Rua Lauro Ferreira | AP49: 0 | AR49: 0 | AT49: Revisado | AU49: Alta | AV49: 46214
A50: 2023_BRAULIO_LARA_360_01 | B50: 2023 | C50: 173 | D50: emendas-2023-27-11-2025.xlsx | E50: 2023_BRAULIO_LARA | F50: 360 | G50: CONCLUÍDO | H50: Braulio Lara | J50: à sinalização e implementação de faixa de pedestres na Rua Fidélis Martins com Rua Ulisses Marcondes Escobar: pintura de sinalização e reposicionamento de placa escondida atrás de árvore | K50: 3303.2645200602.837.339039.F.500 | L50: 3303 | M50: FUNDO MUNICIPAL DE MOBILIDADE URBANA | N50: 26 | O50: TRANSPORTE | P50: 452 | Q50: SERVIÇOS URBANOS | R50: 0060 | S50: GESTÃO DA MOBILIDADE URBANA | T50: 2837 | U50: GERENCIAMENTO DA MOBILIDADE URBANA MUNICIPAL | V50: 339039 | W50: Despesa corrente | X50: Outras despesas correntes | Y50: 500 | Z50: BHTRANS | AA50: 3500 | AB50: 1231.92 | AC50: 1231.92 | AD50: 1231.92 | AF50: 0 | AG50: 0 | AH50: 1002 | AI50: =IF(AH50="","",IFERROR(RIGHT("0000"&AH50,4)&" - "&UPPER(_xlfn.XLOOKUP(RIGHT("0000"&AH50,4),CODEBOOK_CAP!$C$2:$C$212,CODEBOOK_CAP!$D$2:$D$212)),"Código CAP não encontrado")) -> 1002 - CARROS, TRÂNSITO, CONSTRUÇÃO E MANUTENÇÃO DE RUAS E ESTRADAS | AJ50: =IF(AH50="","",IFERROR(_xlfn.XLOOKUP(RIGHT("0000"&AH50,4),CODEBOOK_CAP!$C$2:$C$212,CODEBOOK_CAP!$E$2:$E$212),"Código CAP não encontrado")) -> Construção, manutenção de ruas, avenidas, estradas. BRs, pedágios, privatizações, concessinárias, segurança nas estradas, leis de trânsito relacionadas a via, limite de velocidade, sinalização, recapeamento de ruas, pavimentação estradas de terra, não pavimentadas, acidentes e camapanhas de prevencao contra acidentes de transito. Observações sobre regulação de transportes não públicos de carros, veículos de passeio, uber, taxi, transporte de cargas terrestre, frete, trânsito em vias públicas, regulamentação de tipos de carteira de motorista, especificações para caminhoneiros, testes e exames de habilitação, exigências de carteira de habilitação, obrigatoriedade de itens em veículos (extintor, kit primeiros socorros, airbag, freios abs) Quando tratar de grandes obras de construções de rodovias, olhar codigo 1010 para ver qual se encaixa melhor. | AK50: 1 | AL50: Rua Fidélis Martins com Rua Ulisses Marcondes Escobar | AM50: 1 | AN50: 1 | AO50: Rua Fidélis Martins com Rua Ulisses Marcondes Escobar | AP50: 0 | AR50: 0 | AT50: Revisado | AU50: Alta | AV50: 46214
A51: 2023_BRAULIO_LARA_361_01 | B51: 2023 | C51: 174 | D51: emendas-2023-27-11-2025.xlsx | E51: 2023_BRAULIO_LARA | F51: 361 | G51: CONCLUÍDO | H51: Braulio Lara | J51: ao projeto e criação de ilha (triangular) para melhoria da travessia de pedestres na Rua José Amaury Ferrara com Rua Engenheiro Aluísio Rocha: criação de ilha e sinalização vertical e horizontal | K51: 3303.1100.26.452.60.2837.S.33903963.500 | L51: 3303 | M51: FUNDO MUNICIPAL DE MOBILIDADE URBANA | N51: 26 | O51: TRANSPORTE | P51: 452 | Q51: SERVIÇOS URBANOS | R51: 0060 | S51: GESTÃO DA MOBILIDADE URBANA | T51: 2837 | U51: GERENCIAMENTO DA MOBILIDADE URBANA MUNICIPAL | V51: 339039 | W51: Despesa corrente | X51: Outras despesas correntes | Y51: 500 | Z51: BHTRANS | AA51: 10000 | AB51: 4241.4399999999996 | AC51: 4241.4399999999996 | AD51: 4241.4399999999996 | AF51: 0 | AG51: 0 | AH51: 1002 | AI51: =IF(AH51="","",IFERROR(RIGHT("0000"&AH51,4)&" - "&UPPER(_xlfn.XLOOKUP(RIGHT("0000"&AH51,4),CODEBOOK_CAP!$C$2:$C$212,CODEBOOK_CAP!$D$2:$D$212)),"Código CAP não encontrado")) -> 1002 - CARROS, TRÂNSITO, CONSTRUÇÃO E MANUTENÇÃO DE RUAS E ESTRADAS | AJ51: =IF(AH51="","",IFERROR(_xlfn.XLOOKUP(RIGHT("0000"&AH51,4),CODEBOOK_CAP!$C$2:$C$212,CODEBOOK_CAP!$E$2:$E$212),"Código CAP não encontrado")) -> Construção, manutenção de ruas, avenidas, estradas. BRs, pedágios, privatizações, concessinárias, segurança nas estradas, leis de trânsito relacionadas a via, limite de velocidade, sinalização, recapeamento de ruas, pavimentação estradas de terra, não pavimentadas, acidentes e camapanhas de prevencao contra acidentes de transito. Observações sobre regulação de transportes não públicos de carros, veículos de passeio, uber, taxi, transporte de cargas terrestre, frete, trânsito em vias públicas, regulamentação de tipos de carteira de motorista, especificações para caminhoneiros, testes e exames de habilitação, exigências de carteira de habilitação, obrigatoriedade de itens em veículos (extintor, kit primeiros socorros, airbag, freios abs) Quando tratar de grandes obras de construções de rodovias, olhar codigo 1010 para ver qual se encaixa melhor. | AK51: 1 | AL51: Rua José Amaury Ferrara com Rua Engenheiro Aluísio Rocha | AM51: 1 | AN51: 1 | AO51: Rua José Amaury Ferrara com Rua Engenheiro Aluísio Rocha: | AP51: 0 | AR51: 0 | AT51: Revisado | AU51: Alta | AV51: 46214
A52: 2023_BRAULIO_LARA_362_01 | B52: 2023 | C52: 175 | D52: emendas-2023-27-11-2025.xlsx | E52: 2023_BRAULIO_LARA | F52: 362 | G52: CONCLUÍDO | H52: Braulio Lara | J52: ao projeto e implantação de redutor de velocidade na Rua José Amaury Ferrara no meio do quarteirão (onde a inclinação é favorável) entre as Ruas Engenheiro Aluísio Rocha e Alessandra Salum Cadar | K52: 3303.1100.26.452.60.2837.S.33903963.500 | L52: 3303 | M52: FUNDO MUNICIPAL DE MOBILIDADE URBANA | N52: 26 | O52: TRANSPORTE | P52: 452 | Q52: SERVIÇOS URBANOS | R52: 0060 | S52: GESTÃO DA MOBILIDADE URBANA | T52: 2837 | U52: GERENCIAMENTO DA MOBILIDADE URBANA MUNICIPAL | V52: 339039 | W52: Despesa corrente | X52: Outras despesas correntes | Y52: 500 | Z52: BHTRANS | AA52: 6150 | AB52: 5782.37 | AC52: 5782.37 | AD52: 5782.37 | AF52: 0 | AG52: 0 | AH52: 1002 | AI52: =IF(AH52="","",IFERROR(RIGHT("0000"&AH52,4)&" - "&UPPER(_xlfn.XLOOKUP(RIGHT("0000"&AH52,4),CODEBOOK_CAP!$C$2:$C$212,CODEBOOK_CAP!$D$2:$D$212)),"Código CAP não encontrado")) -> 1002 - CARROS, TRÂNSITO, CONSTRUÇÃO E MANUTENÇÃO DE RUAS E ESTRADAS | AJ52: =IF(AH52="","",IFERROR(_xlfn.XLOOKUP(RIGHT("0000"&AH52,4),CODEBOOK_CAP!$C$2:$C$212,CODEBOOK_CAP!$E$2:$E$212),"Código CAP não encontrado")) -> Construção, manutenção de ruas, avenidas, estradas. BRs, pedágios, privatizações, concessinárias, segurança nas estradas, leis de trânsito relacionadas a via, limite de velocidade, sinalização, recapeamento de ruas, pavimentação estradas de terra, não pavimentadas, acidentes e camapanhas de prevencao contra acidentes de transito. Observações sobre regulação de transportes não públicos de carros, veículos de passeio, uber, taxi, transporte de cargas terrestre, frete, trânsito em vias públicas, regulamentação de tipos de carteira de motorista, especificações para caminhoneiros, testes e exames de habilitação, exigências de carteira de habilitação, obrigatoriedade de itens em veículos (extintor, kit primeiros socorros, airbag, freios abs) Quando tratar de grandes obras de construções de rodovias, olhar codigo 1010 para ver qual se encaixa melhor. | AK52: 1 | AL52: Rua José Amaury Ferrara no meio do quarteirão (onde a inclinação é favorável) entre as Ruas Engenheiro Aluísio Rocha e Alessandra Salum Cadar | AM52: 1 | AN52: 1 | AO52: Rua José Amaury Ferrara no meio do quarteirão (onde a inclinação é favorável) entre as Ruas Engenheiro Aluísio Rocha e Alessandra Salum Cadar | AP52: 0 | AR52: 0 | AT52: Revisado | AU52: Alta | AV52: 46214
A53: 2023_BRAULIO_LARA_363_01 | B53: 2023 | C53: 176 | D53: emendas-2023-27-11-2025.xlsx | E53: 2023_BRAULIO_LARA | F53: 363 | G53: CONCLUÍDO | H53: Braulio Lara | J53: ao projeto e redução do canteiro da Mário Werneck com Rua Engenheiro Aluísio Rocha | K53: 3303.1100.26.452.60.2837.S.33903963.500 | L53: 3303 | M53: FUNDO MUNICIPAL DE MOBILIDADE URBANA | N53: 26 | O53: TRANSPORTE | P53: 452 | Q53: SERVIÇOS URBANOS | R53: 0060 | S53: GESTÃO DA MOBILIDADE URBANA | T53: 2837 | U53: GERENCIAMENTO DA MOBILIDADE URBANA MUNICIPAL | V53: 339039 | W53: Despesa corrente | X53: Outras despesas correntes | Y53: 500 | Z53: BHTRANS | AA53: 10000 | AB53: 9763.5 | AC53: 9763.5 | AD53: 9763.5 | AF53: 0 | AG53: 0 | AH53: 1002 | AI53: =IF(AH53="","",IFERROR(RIGHT("0000"&AH53,4)&" - "&UPPER(_xlfn.XLOOKUP(RIGHT("0000"&AH53,4),CODEBOOK_CAP!$C$2:$C$212,CODEBOOK_CAP!$D$2:$D$212)),"Código CAP não encontrado")) -> 1002 - CARROS, TRÂNSITO, CONSTRUÇÃO E MANUTENÇÃO DE RUAS E ESTRADAS | AJ53: =IF(AH53="","",IFERROR(_xlfn.XLOOKUP(RIGHT("0000"&AH53,4),CODEBOOK_CAP!$C$2:$C$212,CODEBOOK_CAP!$E$2:$E$212),"Código CAP não encontrado")) -> Construção, manutenção de ruas, avenidas, estradas. BRs, pedágios, privatizações, concessinárias, segurança nas estradas, leis de trânsito relacionadas a via, limite de velocidade, sinalização, recapeamento de ruas, pavimentação estradas de terra, não pavimentadas, acidentes e camapanhas de prevencao contra acidentes de transito. Observações sobre regulação de transportes não públicos de carros, veículos de passeio, uber, taxi, transporte de cargas terrestre, frete, trânsito em vias públicas, regulamentação de tipos de carteira de motorista, especificações para caminhoneiros, testes e exames de habilitação, exigências de carteira de habilitação, obrigatoriedade de itens em veículos (extintor, kit primeiros socorros, airbag, freios abs) Quando tratar de grandes obras de construções de rodovias, olhar codigo 1010 para ver qual se encaixa melhor. | AK53: 1 | AL53: Mário Werneck com Rua Engenheiro Aluísio Rocha | AM53: 1 | AN53: 1 | AO53: Mário Werneck com Rua Engenheiro Aluísio Rocha | AP53: 0 | AR53: 0 | AT53: Revisado | AU53: Alta | AV53: 46214
A54: 2023_BRAULIO_LARA_364_01 | B54: 2023 | C54: 177 | D54: emendas-2023-27-11-2025.xlsx | E54: 2023_BRAULIO_LARA | F54: 364 | G54: CONCLUÍDO | H54: Braulio Lara | J54: ao projeto operacional para criação de faixa de proibido estacionar na Av. Aggeo Pio Sobrinho até o alinhamento da Rua Rubens Rua Caporali, no sentido Palmeiras, com vistas a manter duas faixas livres de trânsito para facilitar o fluxo visto que os veículos que tentam fazer a conversão à esquerda na Rua Rubens Caporali precisam aguardar em fila | K54: 3303.2645200602.837.339039.F.500 | L54: 3303 | M54: FUNDO MUNICIPAL DE MOBILIDADE URBANA | N54: 26 | O54: TRANSPORTE | P54: 452 | Q54: SERVIÇOS URBANOS | R54: 0060 | S54: GESTÃO DA MOBILIDADE URBANA | T54: 2837 | U54: GERENCIAMENTO DA MOBILIDADE URBANA MUNICIPAL | V54: 339039 | W54: Despesa corrente | X54: Outras despesas correntes | Y54: 500 | Z54: BHTRANS | AA54: 700 | AB54: 636.69000000000005 | AC54: 1247.58 | AD54: 636.69000000000005 | AF54: 0 | AG54: 0 | AH54: 1002 | AI54: =IF(AH54="","",IFERROR(RIGHT("0000"&AH54,4)&" - "&UPPER(_xlfn.XLOOKUP(RIGHT("0000"&AH54,4),CODEBOOK_CAP!$C$2:$C$212,CODEBOOK_CAP!$D$2:$D$212)),"Código CAP não encontrado")) -> 1002 - CARROS, TRÂNSITO, CONSTRUÇÃO E MANUTENÇÃO DE RUAS E ESTRADAS | AJ54: =IF(AH54="","",IFERROR(_xlfn.XLOOKUP(RIGHT("0000"&AH54,4),CODEBOOK_CAP!$C$2:$C$212,CODEBOOK_CAP!$E$2:$E$212),"Código CAP não encontrado")) -> Construção, manutenção de ruas, avenidas, estradas. BRs, pedágios, privatizações, concessinárias, segurança nas estradas, leis de trânsito relacionadas a via, limite de velocidade, sinalização, recapeamento de ruas, pavimentação estradas de terra, não pavimentadas, acidentes e camapanhas de prevencao contra acidentes de transito. Observações sobre regulação de transportes não públicos de carros, veículos de passeio, uber, taxi, transporte de cargas terrestre, frete, trânsito em vias públicas, regulamentação de tipos de carteira de motorista, especificações para caminhoneiros, testes e exames de habilitação, exigências de carteira de habilitação, obrigatoriedade de itens em veículos (extintor, kit primeiros socorros, airbag, freios abs) Quando tratar de grandes obras de construções de rodovias, olhar codigo 1010 para ver qual se encaixa melhor. | AK54: 1 | AL54: Av. Aggeo Pio Sobrinho até o alinhamento da Rua Rubens Rua Caporali, no sentido Palmeira | AM54: 1 | AN54: 1 | AO54: Av. Aggeo Pio Sobrinho até o alinhamento da Rua Rubens Rua Caporali, no sentido Palmeira | AP54: 0 | AR54: 0 | AT54: Revisado | AU54: Alta | AV54: 46214
A55: 2023_BRAULIO_LARA_365_01 | B55: 2023 | C55: 178 | D55: emendas-2023-27-11-2025.xlsx | E55: 2023_BRAULIO_LARA | F55: 365 | G55: CONCLUÍDO | H55: Braulio Lara | J55: ao projeto e implantação de 4 faixas de pedestre com ilha de segurança, na Avenida Aggeo Pio Sobrinho, no trecho entre as ruas Rubens Caporali Ribeiro e Deputado Sebastião Nascimento | K55: 3303.2645200602.837.339039.F.500 | L55: 3303 | M55: FUNDO MUNICIPAL DE MOBILIDADE URBANA | N55: 26 | O55: TRANSPORTE | P55: 452 | Q55: SERVIÇOS URBANOS | R55: 0060 | S55: GESTÃO DA MOBILIDADE URBANA | T55: 2837 | U55: GERENCIAMENTO DA MOBILIDADE URBANA MUNICIPAL | V55: 339039 | W55: Despesa corrente | X55: Outras despesas correntes | Y55: 500 | Z55: BHTRANS | AA55: 20000 | AB55: 9200.69 | AC55: 9200.69 | AD55: 9200.69 | AF55: 0 | AG55: 0 | AH55: 1002 | AI55: =IF(AH55="","",IFERROR(RIGHT("0000"&AH55,4)&" - "&UPPER(_xlfn.XLOOKUP(RIGHT("0000"&AH55,4),CODEBOOK_CAP!$C$2:$C$212,CODEBOOK_CAP!$D$2:$D$212)),"Código CAP não encontrado")) -> 1002 - CARROS, TRÂNSITO, CONSTRUÇÃO E MANUTENÇÃO DE RUAS E ESTRADAS | AJ55: =IF(AH55="","",IFERROR(_xlfn.XLOOKUP(RIGHT("0000"&AH55,4),CODEBOOK_CAP!$C$2:$C$212,CODEBOOK_CAP!$E$2:$E$212),"Código CAP não encontrado")) -> Construção, manutenção de ruas, avenidas, estradas. BRs, pedágios, privatizações, concessinárias, segurança nas estradas, leis de trânsito relacionadas a via, limite de velocidade, sinalização, recapeamento de ruas, pavimentação estradas de terra, não pavimentadas, acidentes e camapanhas de prevencao contra acidentes de transito. Observações sobre regulação de transportes não públicos de carros, veículos de passeio, uber, taxi, transporte de cargas terrestre, frete, trânsito em vias públicas, regulamentação de tipos de carteira de motorista, especificações para caminhoneiros, testes e exames de habilitação, exigências de carteira de habilitação, obrigatoriedade de itens em veículos (extintor, kit primeiros socorros, airbag, freios abs) Quando tratar de grandes obras de construções de rodovias, olhar codigo 1010 para ver qual se encaixa melhor. | AK55: 1 | AL55: Avenida Aggeo Pio Sobrinho, no trecho entre as ruas Rubens Caporali Ribeiro e Deputado Sebastião Nascimento | AM55: 1 | AN55: 1 | AO55: Avenida Aggeo Pio Sobrinho, no trecho entre as ruas Rubens Caporali Ribeiro e Deputado Sebastião Nascimento | AP55: 0 | AR55: 0 | AT55: Revisado | AU55: Alta | AV55: 46214
A56: 2023_BRAULIO_LARA_366_01 | B56: 2023 | C56: 179 | D56: emendas-2023-27-11-2025.xlsx | E56: 2023_BRAULIO_LARA | F56: 366 | G56: CONCLUÍDO | H56: Braulio Lara | J56: ao projeto operacional e sinalização de faixa contínua e faixas de pedestre na extensão da Rua Rubens Caporali Ribeiro, no trecho entre Rua Senador José Augusto e Aggeo Pio Sobrinho | K56: 3303.2645200602.837.339039.F.500 | L56: 3303 | M56: FUNDO MUNICIPAL DE MOBILIDADE URBANA | N56: 26 | O56: TRANSPORTE | P56: 452 | Q56: SERVIÇOS URBANOS | R56: 0060 | S56: GESTÃO DA MOBILIDADE URBANA | T56: 2837 | U56: GERENCIAMENTO DA MOBILIDADE URBANA MUNICIPAL | V56: 339039 | W56: Despesa corrente | X56: Outras despesas correntes | Y56: 500 | Z56: BHTRANS | AA56: 14200 | AB56: 13005.9 | AC56: 13005.9 | AD56: 13005.9 | AF56: 0 | AG56: 0 | AH56: 1002 | AI56: =IF(AH56="","",IFERROR(RIGHT("0000"&AH56,4)&" - "&UPPER(_xlfn.XLOOKUP(RIGHT("0000"&AH56,4),CODEBOOK_CAP!$C$2:$C$212,CODEBOOK_CAP!$D$2:$D$212)),"Código CAP não encontrado")) -> 1002 - CARROS, TRÂNSITO, CONSTRUÇÃO E MANUTENÇÃO DE RUAS E ESTRADAS | AJ56: =IF(AH56="","",IFERROR(_xlfn.XLOOKUP(RIGHT("0000"&AH56,4),CODEBOOK_CAP!$C$2:$C$212,CODEBOOK_CAP!$E$2:$E$212),"Código CAP não encontrado")) -> Construção, manutenção de ruas, avenidas, estradas. BRs, pedágios, privatizações, concessinárias, segurança nas estradas, leis de trânsito relacionadas a via, limite de velocidade, sinalização, recapeamento de ruas, pavimentação estradas de terra, não pavimentadas, acidentes e camapanhas de prevencao contra acidentes de transito. Observações sobre regulação de transportes não públicos de carros, veículos de passeio, uber, taxi, transporte de cargas terrestre, frete, trânsito em vias públicas, regulamentação de tipos de carteira de motorista, especificações para caminhoneiros, testes e exames de habilitação, exigências de carteira de habilitação, obrigatoriedade de itens em veículos (extintor, kit primeiros socorros, airbag, freios abs) Quando tratar de grandes obras de construções de rodovias, olhar codigo 1010 para ver qual se encaixa melhor. | AK56: 1 | AL56: Rua Rubens Caporali Ribeiro, no trecho entre Rua Senador José Augusto e Aggeo Pio Sobrinho | AM56: 1 | AN56: 1 | AO56: Rua Rubens Caporali Ribeiro, no trecho entre Rua Senador José Augusto e Aggeo Pio Sobrinho | AP56: 0 | AR56: 0 | AT56: Revisado | AU56: Alta | AV56: 46214
A57: 2023_BRAULIO_LARA_367_01 | B57: 2023 | C57: 180 | D57: emendas-2023-27-11-2025.xlsx | E57: 2023_BRAULIO_LARA | F57: 367 | G57: CONCLUÍDO | H57: Braulio Lara | J57: à Implantação do projeto de restrição de circulação de caminhões pesados no bairro Buritis, Via Anel Rodoviário, nas imediações na Rua Moises Kalil | K57: 3303.2645200602.837.339039.F.500 | L57: 3303 | M57: FUNDO MUNICIPAL DE MOBILIDADE URBANA | N57: 26 | O57: TRANSPORTE | P57: 452 | Q57: SERVIÇOS URBANOS | R57: 0060 | S57: GESTÃO DA MOBILIDADE URBANA | T57: 2837 | U57: GERENCIAMENTO DA MOBILIDADE URBANA MUNICIPAL | V57: 339039 | W57: Despesa corrente | X57: Outras despesas correntes | Y57: 500 | Z57: BHTRANS | AA57: 40000 | AB57: 38507.129999999997 | AC57: 75477.960000000006 | AD57: 38507.129999999997 | AF57: 0 | AG57: 0 | AH57: 1002 | AI57: =IF(AH57="","",IFERROR(RIGHT("0000"&AH57,4)&" - "&UPPER(_xlfn.XLOOKUP(RIGHT("0000"&AH57,4),CODEBOOK_CAP!$C$2:$C$212,CODEBOOK_CAP!$D$2:$D$212)),"Código CAP não encontrado")) -> 1002 - CARROS, TRÂNSITO, CONSTRUÇÃO E MANUTENÇÃO DE RUAS E ESTRADAS | AJ57: =IF(AH57="","",IFERROR(_xlfn.XLOOKUP(RIGHT("0000"&AH57,4),CODEBOOK_CAP!$C$2:$C$212,CODEBOOK_CAP!$E$2:$E$212),"Código CAP não encontrado")) -> Construção, manutenção de ruas, avenidas, estradas. BRs, pedágios, privatizações, concessinárias, segurança nas estradas, leis de trânsito relacionadas a via, limite de velocidade, sinalização, recapeamento de ruas, pavimentação estradas de terra, não pavimentadas, acidentes e camapanhas de prevencao contra acidentes de transito. Observações sobre regulação de transportes não públicos de carros, veículos de passeio, uber, taxi, transporte de cargas terrestre, frete, trânsito em vias públicas, regulamentação de tipos de carteira de motorista, especificações para caminhoneiros, testes e exames de habilitação, exigências de carteira de habilitação, obrigatoriedade de itens em veículos (extintor, kit primeiros socorros, airbag, freios abs) Quando tratar de grandes obras de construções de rodovias, olhar codigo 1010 para ver qual se encaixa melhor. | AK57: 1 | AL57: Anel Rodoviário nas imediações da Rua Moisés Kalil | AM57: 1 | AN57: 1 | AO57: Via Anel Rodoviário, nas imediações da Rua Moisés Kalil - Buritis | AP57: 0 | AR57: 0 | AT57: Revisado | AU57: Alta | AV57: 46214
A58: 2023_BRAULIO_LARA_368_01 | B58: 2023 | C58: 181 | D58: emendas-2023-27-11-2025.xlsx | E58: 2023_BRAULIO_LARA | F58: 368 | G58: CONCLUÍDO | H58: Braulio Lara | J58: à construção, reforma e implantação de escadarias no bairro Buritis e complementação dos recursos destinados na emenda 741, da LOA 2022 | K58: 2700.1545102331.396.449051.F.500 | L58: 2700 | M58: SECRETARIA MUNICIPAL DE OBRAS E INFRAESTRUTURA | N58: 15 | O58: URBANISMO | P58: 451 | Q58: INFRA-ESTRUTURA URBANA | R58: 0233 | S58: MANUTENÇÃO DA CIDADE | T58: 1396 | U58: INFRAESTRUTURA URBANA | V58: 449051 | W58: Despesa de capital | X58: Investimentos | Y58: 500 | Z58: SMOBI | AA58: 225000 | AB58: 0 | AC58: 0 | AD58: 0 | AF58: 0 | AG58: 0 | AH58: 1403 | AI58: =IF(AH58="","",IFERROR(RIGHT("0000"&AH58,4)&" - "&UPPER(_xlfn.XLOOKUP(RIGHT("0000"&AH58,4),CODEBOOK_CAP!$C$2:$C$212,CODEBOOK_CAP!$D$2:$D$212)),"Código CAP não encontrado")) -> 1403 - REABILITAÇÃO URBANA, ECONOMIA URBANA | AJ58: =IF(AH58="","",IFERROR(_xlfn.XLOOKUP(RIGHT("0000"&AH58,4),CODEBOOK_CAP!$C$2:$C$212,CODEBOOK_CAP!$E$2:$E$212),"Código CAP não encontrado")) -> Reabilitação de áreas urbanas, revitalização urbana, modernização de áreas, mercados públicos, revitalização de praças, política urbana nacional, desenvolvimento urbano , desenvolvimento econômico de estados e cidades, modernização de espaços urbanos | AK58: 1 | AL58: bairro Buritis | AM58: 1 | AN58: 0 | AP58: 0 | AR58: 0 | AT58: Revisado | AU58: Alta | AV58: 46214
A59: 2023_BRAULIO_LARA_369_01 | B59: 2023 | C59: 182 | D59: emendas-2023-27-11-2025.xlsx | E59: 2023_BRAULIO_LARA | F59: 369 | G59: CONCLUÍDO | H59: Braulio Lara | J59: à instalação de corrimão e revitalização de passeios na Rua Paulo Diniz Carneiro com Rua Deputado Sebastião Nascimento nas imediações do Centro de Saúde Havaí | K59: 2700.1545102331.396.449051.F.500 | L59: 2700 | M59: SECRETARIA MUNICIPAL DE OBRAS E INFRAESTRUTURA | N59: 15 | O59: URBANISMO | P59: 451 | Q59: INFRA-ESTRUTURA URBANA | R59: 0233 | S59: MANUTENÇÃO DA CIDADE | T59: 1396 | U59: INFRAESTRUTURA URBANA | V59: 449051 | W59: Despesa de capital | X59: Investimentos | Y59: 500 | Z59: SMOBI | AA59: 41716 | AB59: 16716 | AC59: 16716 | AD59: 16716 | AF59: 0 | AG59: 0 | AH59: 1403 | AI59: =IF(AH59="","",IFERROR(RIGHT("0000"&AH59,4)&" - "&UPPER(_xlfn.XLOOKUP(RIGHT("0000"&AH59,4),CODEBOOK_CAP!$C$2:$C$212,CODEBOOK_CAP!$D$2:$D$212)),"Código CAP não encontrado")) -> 1403 - REABILITAÇÃO URBANA, ECONOMIA URBANA | AJ59: =IF(AH59="","",IFERROR(_xlfn.XLOOKUP(RIGHT("0000"&AH59,4),CODEBOOK_CAP!$C$2:$C$212,CODEBOOK_CAP!$E$2:$E$212),"Código CAP não encontrado")) -> Reabilitação de áreas urbanas, revitalização urbana, modernização de áreas, mercados públicos, revitalização de praças, política urbana nacional, desenvolvimento urbano , desenvolvimento econômico de estados e cidades, modernização de espaços urbanos | AK59: 1 | AL59: Rua Paulo Diniz Carneiro com Rua Deputado Sebastião Nascimento nas imediações do Centro de Saúde Havaí | AM59: 1 | AN59: 1 | AO59: Rua Paulo Diniz Carneiro com Rua Deputado Sebastião Nascimento nas imediações do Centro de Saúde Havaí | AP59: 0 | AR59: 0 | AT59: Revisado | AU59: Alta | AV59: 46214
A60: 2023_BRAULIO_LARA_370_01 | B60: 2023 | C60: 183 | D60: emendas-2023-27-11-2025.xlsx | E60: 2023_BRAULIO_LARA | F60: 370 | G60: ATOS PREPARATÓRIOS | H60: Braulio Lara | J60: ao reforço de dotação orçamentária para as unidades de atendimento à saúde, dos centros de saúde Palmeiras, Vila Leonina, Salgado Filho, Betânia, Amilcar Vianna Martins, Noraldino de Lima, Waldomiro Lobo, Vila Imperial e Pilar Olhos D’água, da Regional Oeste. | K60: 2302.1030101571.216449051.S.500 | L60: 2302 | M60: FUNDO MUNICIPAL DE SAÚDE | N60: 10 | O60: SAÚDE | P60: 301 | Q60: ATENÇÃO BÁSICA | R60: 0157 | S60: ATENÇÃO PRIMÁRIA À SAÚDE | T60: 1216 | U60: CONSTRUÇÃO, AMPLIAÇÃO E REFORMA DE UNIDADES DE SAÚDE | V60: 449051 | W60: Despesa de capital | X60: Investimentos | Y60: 500 | Z60: FMS | AA60: 640000 | AB60: 225462.86 | AC60: 215648.98 | AD60: 215648.98 | AE60: 3S CONSTRUCOES LTDA; MLQ ENGENHARIA LTDA | AF60: 1 | AG60: 1 | AH60: 0322 | AI60: =IF(AH60="","",IFERROR(RIGHT("0000"&AH60,4)&" - "&UPPER(_xlfn.XLOOKUP(RIGHT("0000"&AH60,4),CODEBOOK_CAP!$C$2:$C$212,CODEBOOK_CAP!$D$2:$D$212)),"Código CAP não encontrado")) -> 0322 - ESTRUTURAS, HOSPITAIS, CLÍNICAS | AJ60: =IF(AH60="","",IFERROR(_xlfn.XLOOKUP(RIGHT("0000"&AH60,4),CODEBOOK_CAP!$C$2:$C$212,CODEBOOK_CAP!$E$2:$E$212),"Código CAP não encontrado")) -> Observações relacionadas as estruturas do sistema de saúde, como a construção de hospitais, postos de saúde, construção de maternidades, laboratórios, centros de saúde avançado, SAMU, Ambulâncias, UTI Móveis, leitos, compra de equipamentos médicos, Raio X, Ultrasom, equipamentos de diálise, capacidade de atendimento, estrutura e funcionamento de equipamentos públicos de saúde. | AK60: 0 | AM60: 9 | AN60: 1 | AO60: centros de saúde Palmeiras, Vila Leonina, Salgado Filho, Betânia, Amilcar Vianna Martins, Noraldino de Lima, Waldomiro Lobo, Vila Imperial e Pilar Olhos D’água, da Regional Oeste. | AP60: 0 | AR60: 1 | AS60: 3S CONSTRUCOES LTDA; MLQ ENGENHARIA LTDA | AT60: Revisado | AU60: Alta | AV60: 46214
A61: 2023_BRAULIO_LARA_371_01 | B61: 2023 | C61: 184 | D61: emendas-2023-27-11-2025.xlsx | E61: 2023_BRAULIO_LARA | F61: 371 | G61: CONCLUÍDO | H61: Braulio Lara | J61: ao aprimoramento das atividades desenvolvidas no âmbito do SUS pelo Hospital Mario Penna, Associação Mario Penna, 17.513.235/0001-80 | K61: 2302.1030201142.894.339039.S.500 | L61: 2302 | M61: FUNDO MUNICIPAL DE SAÚDE | N61: 10 | O61: SAÚDE | P61: 302 | Q61: ASSISTÊNCIA HOSPITALAR E AMBULATORIAL | R61: 0114 | S61: ATENÇÃO SECUNDÁRIA E TERCIÁRIA À SAÚDE | T61: 2894 | U61: REDE HOSPITALAR | V61: 339039 | W61: Despesa corrente | X61: Outras despesas correntes | Y61: 500 | Z61: FMS | AA61: 80000 | AB61: 80000 | AC61: 80000 | AD61: 80000 | AF61: 1 | AG61: 1 | AH61: 0323 | AI61: =IF(AH61="","",IFERROR(RIGHT("0000"&AH61,4)&" - "&UPPER(_xlfn.XLOOKUP(RIGHT("0000"&AH61,4),CODEBOOK_CAP!$C$2:$C$212,CODEBOOK_CAP!$D$2:$D$212)),"Código CAP não encontrado")) -> 0323 - ACORDOS | AJ61: =IF(AH61="","",IFERROR(_xlfn.XLOOKUP(RIGHT("0000"&AH61,4),CODEBOOK_CAP!$C$2:$C$212,CODEBOOK_CAP!$E$2:$E$212),"Código CAP não encontrado")) -> Questões relacionadas a Acordos nacionais e internacionais na saúde. Parcerias público privadas em saúde. Vagas do SUS em hospitais privados, acordos e parcerias. Somente utilizar esse código quando há acordos e parcerias entre instituições com o SUS. Não confundir com regulação e alternativas de saúde particular (302). | AK61: 0 | AM61: 1 | AN61: 1 | AO61: Hospital Mario Penna (R. Joaquim Cândido Filho, 91 - Luxemburgo, Belo Horizonte - MG, 30380-420, Brazil) | AP61: 0 | AR61: 0 | AT61: Revisado | AU61: Média | AV61: 46214
A62: 2023_BRAULIO_LARA_372_01 | B62: 2023 | C62: 185 | D62: emendas-2023-27-11-2025.xlsx | E62: 2023_BRAULIO_LARA | F62: 372 | G62: CONCLUÍDO | H62: Braulio Lara | J62: ao reforço de dotação orçamentária para as unidades de atendimento à saúde, dos centros de saúde Ouro Preto e Santa Terezinha, da Regional Noroeste/Pampulha. | K62: 2302.1030101571.216449051.S.501 | L62: 2302 | M62: FUNDO MUNICIPAL DE SAÚDE | N62: 10 | O62: SAÚDE | P62: 301 | Q62: ATENÇÃO BÁSICA | R62: 0157 | S62: ATENÇÃO PRIMÁRIA À SAÚDE | T62: 1216 | U62: CONSTRUÇÃO, AMPLIAÇÃO E REFORMA DE UNIDADES DE SAÚDE | V62: 449051 | W62: Despesa de capital | X62: Investimentos | Y62: 501 | Z62: FMS | AA62: 120000 | AB62: 0 | AC62: 0 | AD62: 0 | AF62: 1 | AG62: 1 | AH62: 0322 | AI62: =IF(AH62="","",IFERROR(RIGHT("0000"&AH62,4)&" - "&UPPER(_xlfn.XLOOKUP(RIGHT("0000"&AH62,4),CODEBOOK_CAP!$C$2:$C$212,CODEBOOK_CAP!$D$2:$D$212)),"Código CAP não encontrado")) -> 0322 - ESTRUTURAS, HOSPITAIS, CLÍNICAS | AJ62: =IF(AH62="","",IFERROR(_xlfn.XLOOKUP(RIGHT("0000"&AH62,4),CODEBOOK_CAP!$C$2:$C$212,CODEBOOK_CAP!$E$2:$E$212),"Código CAP não encontrado")) -> Observações relacionadas as estruturas do sistema de saúde, como a construção de hospitais, postos de saúde, construção de maternidades, laboratórios, centros de saúde avançado, SAMU, Ambulâncias, UTI Móveis, leitos, compra de equipamentos médicos, Raio X, Ultrasom, equipamentos de diálise, capacidade de atendimento, estrutura e funcionamento de equipamentos públicos de saúde. | AK62: 1 | AL62: Regional Noroeste/Pampulha | AM62: 2 | AN62: 1 | AO62: centros de saúde Ouro Preto e Santa Terezinha, da Regional Noroeste/Pampulha. (Rua Jonas Jean, 77 - Ouro Preto; Rua Senador Virgílio Távora, 157 - Santa Terezinha, Belo Horizonte - MG, 31360-220, Brazil) | AP62: 0 | AR62: 0 | AT62: Revisado | AU62: Alta | AV62: 46214
A63: 2023_BRAULIO_LARA_373_01 | B63: 2023 | C63: 186 | D63: emendas-2023-27-11-2025.xlsx | E63: 2023_BRAULIO_LARA | F63: 373 | G63: CONCLUÍDO | H63: Braulio Lara | J63: ao reforço de dotação orçamentária para as unidades de atendimento à saúde da UPA Oeste | K63: 2302.1030201142.893.339039.S.500 | L63: 2302 | M63: FUNDO MUNICIPAL DE SAÚDE | N63: 10 | O63: SAÚDE | P63: 302 | Q63: ASSISTÊNCIA HOSPITALAR E AMBULATORIAL | R63: 0114 | S63: ATENÇÃO SECUNDÁRIA E TERCIÁRIA À SAÚDE | T63: 2893 | U63: REDE DE URGÊNCIA E EMERGÊNCIA | V63: 339039 | W63: Despesa corrente | X63: Outras despesas correntes | Y63: 500 | Z63: FMS | AA63: 122532 | AB63: 122532 | AC63: 230876.08 | AD63: 122532 | AF63: 1 | AG63: 1 | AH63: 0322 | AI63: =IF(AH63="","",IFERROR(RIGHT("0000"&AH63,4)&" - "&UPPER(_xlfn.XLOOKUP(RIGHT("0000"&AH63,4),CODEBOOK_CAP!$C$2:$C$212,CODEBOOK_CAP!$D$2:$D$212)),"Código CAP não encontrado")) -> 0322 - ESTRUTURAS, HOSPITAIS, CLÍNICAS | AJ63: =IF(AH63="","",IFERROR(_xlfn.XLOOKUP(RIGHT("0000"&AH63,4),CODEBOOK_CAP!$C$2:$C$212,CODEBOOK_CAP!$E$2:$E$212),"Código CAP não encontrado")) -> Observações relacionadas as estruturas do sistema de saúde, como a construção de hospitais, postos de saúde, construção de maternidades, laboratórios, centros de saúde avançado, SAMU, Ambulâncias, UTI Móveis, leitos, compra de equipamentos médicos, Raio X, Ultrasom, equipamentos de diálise, capacidade de atendimento, estrutura e funcionamento de equipamentos públicos de saúde. | AK63: 0 | AM63: 1 | AN63: 1 | AO63: UPA OESTE (R. Santa Cruz, 137 - Alto Barroca, Belo Horizonte - MG, 30431-045) | AP63: 0 | AR63: 0 | AT63: Revisado | AU63: Alta | AV63: 46214
A64: 2023_BRAULIO_LARA_374_01 | B64: 2023 | C64: 187 | D64: emendas-2023-27-11-2025.xlsx | E64: 2023_BRAULIO_LARA | F64: 374 | G64: ATOS PREPARATÓRIOS | H64: Braulio Lara | J64: ao desenvolvimento de projeto e implementação de praça na Rua José Rodrigues Pereira, em frente à esquina da Rua Desembargador Edésio Fernandes, no Bairro Buritis | K64: 2700.1545102331.396.449051.F.500 | L64: 2700 | M64: SECRETARIA MUNICIPAL DE OBRAS E INFRAESTRUTURA | N64: 15 | O64: URBANISMO | P64: 451 | Q64: INFRA-ESTRUTURA URBANA | R64: 0233 | S64: MANUTENÇÃO DA CIDADE | T64: 1396 | U64: INFRAESTRUTURA URBANA | V64: 449051 | W64: Despesa de capital | X64: Investimentos | Y64: 500 | Z64: SMOBI | AA64: 160000 | AB64: 0 | AC64: 0 | AD64: 0 | AF64: 0 | AG64: 0 | AH64: 1403 | AI64: =IF(AH64="","",IFERROR(RIGHT("0000"&AH64,4)&" - "&UPPER(_xlfn.XLOOKUP(RIGHT("0000"&AH64,4),CODEBOOK_CAP!$C$2:$C$212,CODEBOOK_CAP!$D$2:$D$212)),"Código CAP não encontrado")) -> 1403 - REABILITAÇÃO URBANA, ECONOMIA URBANA | AJ64: =IF(AH64="","",IFERROR(_xlfn.XLOOKUP(RIGHT("0000"&AH64,4),CODEBOOK_CAP!$C$2:$C$212,CODEBOOK_CAP!$E$2:$E$212),"Código CAP não encontrado")) -> Reabilitação de áreas urbanas, revitalização urbana, modernização de áreas, mercados públicos, revitalização de praças, política urbana nacional, desenvolvimento urbano , desenvolvimento econômico de estados e cidades, modernização de espaços urbanos | AK64: 1 | AL64: Rua José Rodrigues Pereira, em frente à esquina da Rua Desembargador Edésio Fernandes, no Bairro Buritis | AM64: 1 | AN64: 1 | AO64: Rua José Rodrigues Pereira, em frente à esquina da Rua Desembargador Edésio Fernandes, no Bairro Buritis | AP64: 0 | AR64: 0 | AT64: Revisado | AU64: Alta | AV64: 46214
A65: 2023_BRAULIO_LARA_375_01 | B65: 2023 | C65: 188 | D65: emendas-2023-27-11-2025.xlsx | E65: 2023_BRAULIO_LARA | F65: 375 | G65: EM EXECUÇÃO | H65: Braulio Lara | J65: ao Instituto Pedra Viva, CNPJ 08.878.503/0001-76, para desenvolvimento de projetos | K65: 1011.0824400192.308.339039.S.500 | L65: 1011 | M65: FUNDO MUNICIPAL DE ASSISTÊNCIA SOCIAL | N65: 08 | O65: ASSISTÊNCIA SOCIAL | P65: 244 | Q65: ASSISTÊNCIA COMUNITÁRIA | R65: 0019 | S65: PROTEÇÃO SOCIAL BÁSICA | T65: 2308 | U65: SERVIÇOS DE PROTEÇÃO SOCIAL BÁSICA | V65: 339039 | W65: Despesa corrente | X65: Outras despesas correntes | Y65: 500 | Z65: SMASDH | AA65: 76266 | AB65: 76266 | AC65: 76266 | AD65: 76266 | AF65: 0 | AG65: 0 | AH65: 1300 | AI65: =IF(AH65="","",IFERROR(RIGHT("0000"&AH65,4)&" - "&UPPER(_xlfn.XLOOKUP(RIGHT("0000"&AH65,4),CODEBOOK_CAP!$C$2:$C$212,CODEBOOK_CAP!$D$2:$D$212)),"Código CAP não encontrado")) -> 1300 - GERAL | AJ65: =IF(AH65="","",IFERROR(_xlfn.XLOOKUP(RIGHT("0000"&AH65,4),CODEBOOK_CAP!$C$2:$C$212,CODEBOOK_CAP!$E$2:$E$212),"Código CAP não encontrado")) -> Observações gerais sobre políticas sociais que envolvam mais de um casos dos subtópicos, políticas gerais de assistência social, welfare state, bem estar social, Ministérios e orcamentos como do Desenvolvimento social e combate e fome, desenvolvimento social, sistemas de gestão de políticas de assistencia, CAD UNICO, cadastros, sistemas computacionais para desenvolvimento de ações e políticas sociais, BPC - Benefício de Prestação Continuada geral para idosos e deficientes. NÃO CONFUNDIR POLÍTICAS SOCIAIS COM POLÍTICA DE EMPREGO E RENDA. Todas as questões, direitos, políticas que se relacionem com o TRABALHO como contrapartida, estão no código 5. Maternidade, Paternidade aposentadoria por tempo de serviço, INSS. | AK65: 0 | AM65: 0 | AN65: 0 | AP65: 0 | AR65: 0 | AT65: Revisado | AU65: Alta | AV65: 46214
A66: 2023_BRAULIO_LARA_376_01 | B66: 2023 | C66: 189 | D66: emendas-2023-27-11-2025.xlsx | E66: 2023_BRAULIO_LARA | F66: 376 | G66: CONCLUÍDO | H66: Braulio Lara | J66: ao reforço de dotação orçamentária para atendimento ao Hospital da Baleia, CNPJ 17.200.429/0001-25 | K66: 2302.1030201142.894.339039.S.500 | L66: 2302 | M66: FUNDO MUNICIPAL DE SAÚDE | N66: 10 | O66: SAÚDE | P66: 302 | Q66: ASSISTÊNCIA HOSPITALAR E AMBULATORIAL | R66: 0114 | S66: ATENÇÃO SECUNDÁRIA E TERCIÁRIA À SAÚDE | T66: 2894 | U66: REDE HOSPITALAR | V66: 339039 | W66: Despesa corrente | X66: Outras despesas correntes | Y66: 500 | Z66: FMS | AA66: 125000 | AB66: 125000 | AC66: 125000 | AD66: 125000 | AF66: 1 | AG66: 1 | AH66: 0322 | AI66: =IF(AH66="","",IFERROR(RIGHT("0000"&AH66,4)&" - "&UPPER(_xlfn.XLOOKUP(RIGHT("0000"&AH66,4),CODEBOOK_CAP!$C$2:$C$212,CODEBOOK_CAP!$D$2:$D$212)),"Código CAP não encontrado")) -> 0322 - ESTRUTURAS, HOSPITAIS, CLÍNICAS | AJ66: =IF(AH66="","",IFERROR(_xlfn.XLOOKUP(RIGHT("0000"&AH66,4),CODEBOOK_CAP!$C$2:$C$212,CODEBOOK_CAP!$E$2:$E$212),"Código CAP não encontrado")) -> Observações relacionadas as estruturas do sistema de saúde, como a construção de hospitais, postos de saúde, construção de maternidades, laboratórios, centros de saúde avançado, SAMU, Ambulâncias, UTI Móveis, leitos, compra de equipamentos médicos, Raio X, Ultrasom, equipamentos de diálise, capacidade de atendimento, estrutura e funcionamento de equipamentos públicos de saúde. | AK66: 0 | AM66: 1 | AN66: 1 | AO66: Hospital da Baleia (R. Juramento, 1464 - Saudade, Belo Horizonte - MG, 30285-408) | AP66: 0 | AR66: 0 | AT66: Revisado | AU66: Alta | AV66: 46214
A67: 2023_BRAULIO_LARA_377_01 | B67: 2023 | C67: 190 | D67: emendas-2023-27-11-2025.xlsx | E67: 2023_BRAULIO_LARA | F67: 377 | G67: CONCLUÍDO | H67: Braulio Lara | J67: ao reforço de dotação orçamentária para atendimento ao Hospital Metropolitano Doutor Célio de Castro, CNPJ 22.012.907/0001-03 | K67: 2302.1030201142.894.339039.S.500 | L67: 2302 | M67: FUNDO MUNICIPAL DE SAÚDE | N67: 10 | O67: SAÚDE | P67: 302 | Q67: ASSISTÊNCIA HOSPITALAR E AMBULATORIAL | R67: 0114 | S67: ATENÇÃO SECUNDÁRIA E TERCIÁRIA À SAÚDE | T67: 2894 | U67: REDE HOSPITALAR | V67: 339039 | W67: Despesa corrente | X67: Outras despesas correntes | Y67: 500 | Z67: FMS | AA67: 80000 | AB67: 80000 | AC67: 80000 | AD67: 80000 | AF67: 1 | AG67: 1 | AH67: 0322 | AI67: =IF(AH67="","",IFERROR(RIGHT("0000"&AH67,4)&" - "&UPPER(_xlfn.XLOOKUP(RIGHT("0000"&AH67,4),CODEBOOK_CAP!$C$2:$C$212,CODEBOOK_CAP!$D$2:$D$212)),"Código CAP não encontrado")) -> 0322 - ESTRUTURAS, HOSPITAIS, CLÍNICAS | AJ67: =IF(AH67="","",IFERROR(_xlfn.XLOOKUP(RIGHT("0000"&AH67,4),CODEBOOK_CAP!$C$2:$C$212,CODEBOOK_CAP!$E$2:$E$212),"Código CAP não encontrado")) -> Observações relacionadas as estruturas do sistema de saúde, como a construção de hospitais, postos de saúde, construção de maternidades, laboratórios, centros de saúde avançado, SAMU, Ambulâncias, UTI Móveis, leitos, compra de equipamentos médicos, Raio X, Ultrasom, equipamentos de diálise, capacidade de atendimento, estrutura e funcionamento de equipamentos públicos de saúde. | AK67: 0 | AM67: 1 | AN67: 1 | AO67: Hospital Metrepolitano Doutor Célio de Castro (Rua Dona Luiza, 311 - Milionários, Belo Horizonte - MG, 30620-090) | AP67: 0 | AR67: 0 | AT67: Revisado | AU67: Alta | AV67: 46214
A68: 2023_BRAULIO_LARA_378_01 | B68: 2023 | C68: 191 | D68: emendas-2023-27-11-2025.xlsx | E68: 2023_BRAULIO_LARA | F68: 378 | G68: CONCLUÍDO | H68: Braulio Lara | J68: ao reforço de dotação orçamentária para atendimento ao Hospital Sofia Feldman, CNPJ 25.459.256/0001-92 | K68: 2302.1030201142.894.339039.S.500 | L68: 2302 | M68: FUNDO MUNICIPAL DE SAÚDE | N68: 10 | O68: SAÚDE | P68: 302 | Q68: ASSISTÊNCIA HOSPITALAR E AMBULATORIAL | R68: 0114 | S68: ATENÇÃO SECUNDÁRIA E TERCIÁRIA À SAÚDE | T68: 2894 | U68: REDE HOSPITALAR | V68: 339039 | W68: Despesa corrente | X68: Outras despesas correntes | Y68: 500 | Z68: FMS | AA68: 80000 | AB68: 80000 | AC68: 80000 | AD68: 80000 | AF68: 1 | AG68: 1 | AH68: 0332 | AI68: =IF(AH68="","",IFERROR(RIGHT("0000"&AH68,4)&" - "&UPPER(_xlfn.XLOOKUP(RIGHT("0000"&AH68,4),CODEBOOK_CAP!$C$2:$C$212,CODEBOOK_CAP!$D$2:$D$212)),"Código CAP não encontrado")) -> 0332 - SAÚDE INFANTIL, GRAVIDEZ E PRÉ-NATAL | AJ68: =IF(AH68="","",IFERROR(_xlfn.XLOOKUP(RIGHT("0000"&AH68,4),CODEBOOK_CAP!$C$2:$C$212,CODEBOOK_CAP!$E$2:$E$212),"Código CAP não encontrado")) -> Questões relacionadas a saúde da mãe, bebê e criança desde a gravidez. Campanhas de prevenção de gravidez indesejada, gravidez na adolescencia, Vacinação infantil ou vacina para doenças já existentes, atendimento pediátrico, atendimento obstétrico, parto, parto normal, cesariana, parto natural, pré-natal, consultas e exames pré-natal, atividades relacionadas a gravidez, saúde da mãe e do bebê, cuidados dentários infantís. Quando a política de prevenção for sobre crianças ou gravidez, codificar aqui 332. | AK68: 0 | AM68: 1 | AN68: 1 | AO68: Hospital Sofia Feldman (Rua Antônio Bandeira, 1060 - Tupi, Belo Horizonte - MG, 31844-130) | AP68: 1 | AQ68: gestantes, parturientes e puérperas; recém-nascidos | AR68: 0 | AT68: Revisado | AU68: Alta | AV68: 46214
A69: 2023_BRAULIO_LARA_379_01 | B69: 2023 | C69: 192 | D69: emendas-2023-27-11-2025.xlsx | E69: 2023_BRAULIO_LARA | F69: 379 | G69: CONCLUÍDO | H69: Braulio Lara | J69: ao reforço de dotação orçamentária para atendimento ao Hospital Madre Tereza, CNPJ 60.194.990/0008-44 | K69: 2302.1030201142.894.339039.S.500 | L69: 2302 | M69: FUNDO MUNICIPAL DE SAÚDE | N69: 10 | O69: SAÚDE | P69: 302 | Q69: ASSISTÊNCIA HOSPITALAR E AMBULATORIAL | R69: 0114 | S69: ATENÇÃO SECUNDÁRIA E TERCIÁRIA À SAÚDE | T69: 2894 | U69: REDE HOSPITALAR | V69: 339039 | W69: Despesa corrente | X69: Outras despesas correntes | Y69: 500 | Z69: FMS | AA69: 80000 | AB69: 80000 | AC69: 80000 | AD69: 80000 | AF69: 1 | AG69: 1 | AH69: 0322 | AI69: =IF(AH69="","",IFERROR(RIGHT("0000"&AH69,4)&" - "&UPPER(_xlfn.XLOOKUP(RIGHT("0000"&AH69,4),CODEBOOK_CAP!$C$2:$C$212,CODEBOOK_CAP!$D$2:$D$212)),"Código CAP não encontrado")) -> 0322 - ESTRUTURAS, HOSPITAIS, CLÍNICAS | AJ69: =IF(AH69="","",IFERROR(_xlfn.XLOOKUP(RIGHT("0000"&AH69,4),CODEBOOK_CAP!$C$2:$C$212,CODEBOOK_CAP!$E$2:$E$212),"Código CAP não encontrado")) -> Observações relacionadas as estruturas do sistema de saúde, como a construção de hospitais, postos de saúde, construção de maternidades, laboratórios, centros de saúde avançado, SAMU, Ambulâncias, UTI Móveis, leitos, compra de equipamentos médicos, Raio X, Ultrasom, equipamentos de diálise, capacidade de atendimento, estrutura e funcionamento de equipamentos públicos de saúde. | AK69: 0 | AM69: 1 | AN69: 1 | AO69: Hospital Madre Tereza (Avenida Raja Gabáglia, 1002 Av. Raja Gabáglia, 1093 - Luxemburgo - Gutierrez, Belo Horizonte - MG, 30441-070) | AP69: 0 | AR69: 0 | AT69: Revisado | AU69: Alta | AV69: 46214
A70: 2023_BRAULIO_LARA_380_01 | B70: 2023 | C70: 193 | D70: emendas-2023-27-11-2025.xlsx | E70: 2023_BRAULIO_LARA | F70: 380 | G70: CONCLUÍDO | H70: Braulio Lara | J70: ao reforço de dotação orçamentária para atendimento ao Hospital Santa Casa de Belo Horizonte, CNPJ 17.209.891/0001-93 | K70: 2302.1030201142.894.339039.S.500 | L70: 2302 | M70: FUNDO MUNICIPAL DE SAÚDE | N70: 10 | O70: SAÚDE | P70: 302 | Q70: ASSISTÊNCIA HOSPITALAR E AMBULATORIAL | R70: 0114 | S70: ATENÇÃO SECUNDÁRIA E TERCIÁRIA À SAÚDE | T70: 2894 | U70: REDE HOSPITALAR | V70: 339039 | W70: Despesa corrente | X70: Outras despesas correntes | Y70: 500 | Z70: FMS | AA70: 125000 | AB70: 125000 | AC70: 125000 | AD70: 125000 | AF70: 1 | AG70: 1 | AH70: 0322 | AI70: =IF(AH70="","",IFERROR(RIGHT("0000"&AH70,4)&" - "&UPPER(_xlfn.XLOOKUP(RIGHT("0000"&AH70,4),CODEBOOK_CAP!$C$2:$C$212,CODEBOOK_CAP!$D$2:$D$212)),"Código CAP não encontrado")) -> 0322 - ESTRUTURAS, HOSPITAIS, CLÍNICAS | AJ70: =IF(AH70="","",IFERROR(_xlfn.XLOOKUP(RIGHT("0000"&AH70,4),CODEBOOK_CAP!$C$2:$C$212,CODEBOOK_CAP!$E$2:$E$212),"Código CAP não encontrado")) -> Observações relacionadas as estruturas do sistema de saúde, como a construção de hospitais, postos de saúde, construção de maternidades, laboratórios, centros de saúde avançado, SAMU, Ambulâncias, UTI Móveis, leitos, compra de equipamentos médicos, Raio X, Ultrasom, equipamentos de diálise, capacidade de atendimento, estrutura e funcionamento de equipamentos públicos de saúde. | AK70: 0 | AM70: 1 | AN70: 1 | AO70: Hospital Santa Casa de Belo Horizonte (Av. Francisco Sales, 1111 - Santa Efigênia, Belo Horizonte - MG, 30150-223) | AP70: 0 | AR70: 0 | AT70: Revisado | AU70: Alta | AV70: 46214
A71: 2023_BRAULIO_LARA_381_01 | B71: 2023 | C71: 194 | D71: emendas-2023-27-11-2025.xlsx | E71: 2023_BRAULIO_LARA | F71: 381 | G71: CANCELADA | H71: Braulio Lara | AI71: =IF(AH71="","",IFERROR(RIGHT("0000"&AH71,4)&" - "&UPPER(_xlfn.XLOOKUP(RIGHT("0000"&AH71,4),CODEBOOK_CAP!$C$2:$C$212,CODEBOOK_CAP!$D$2:$D$212)),"Código CAP não encontrado")) | AJ71: =IF(AH71="","",IFERROR(_xlfn.XLOOKUP(RIGHT("0000"&AH71,4),CODEBOOK_CAP!$C$2:$C$212,CODEBOOK_CAP!$E$2:$E$212),"Código CAP não encontrado")) | AT71: Codificado | AV71: 46214
A72: 2023_BRAULIO_LARA_382_01 | B72: 2023 | C72: 195 | D72: emendas-2023-27-11-2025.xlsx | E72: 2023_BRAULIO_LARA | F72: 382 | G72: CONCLUÍDO | H72: Braulio Lara | J72: ao reforço de dotação orçamentária para atendimento ao Hospital Evangélico de Belo Horizonte, CNPJ 17.214.743/0001-67 | K72: 2302.1030201142.894.339039.S.500 | L72: 2302 | M72: FUNDO MUNICIPAL DE SAÚDE | N72: 10 | O72: SAÚDE | P72: 302 | Q72: ASSISTÊNCIA HOSPITALAR E AMBULATORIAL | R72: 0114 | S72: ATENÇÃO SECUNDÁRIA E TERCIÁRIA À SAÚDE | T72: 2894 | U72: REDE HOSPITALAR | V72: 339039 | W72: Despesa corrente | X72: Outras despesas correntes | Y72: 500 | Z72: FMS | AA72: 80000 | AB72: 80000 | AC72: 80000 | AD72: 80000 | AF72: 1 | AG72: 1 | AH72: 0322 | AI72: =IF(AH72="","",IFERROR(RIGHT("0000"&AH72,4)&" - "&UPPER(_xlfn.XLOOKUP(RIGHT("0000"&AH72,4),CODEBOOK_CAP!$C$2:$C$212,CODEBOOK_CAP!$D$2:$D$212)),"Código CAP não encontrado")) -> 0322 - ESTRUTURAS, HOSPITAIS, CLÍNICAS | AJ72: =IF(AH72="","",IFERROR(_xlfn.XLOOKUP(RIGHT("0000"&AH72,4),CODEBOOK_CAP!$C$2:$C$212,CODEBOOK_CAP!$E$2:$E$212),"Código CAP não encontrado")) -> Observações relacionadas as estruturas do sistema de saúde, como a construção de hospitais, postos de saúde, construção de maternidades, laboratórios, centros de saúde avançado, SAMU, Ambulâncias, UTI Móveis, leitos, compra de equipamentos médicos, Raio X, Ultrasom, equipamentos de diálise, capacidade de atendimento, estrutura e funcionamento de equipamentos públicos de saúde. | AK72: 0 | AM72: 1 | AN72: 1 | AO72: Hospital Evangélico de Belo Horizonte (R. Doutor Alípio Goulart, 25 - Serra, Belo Horizonte - MG, 30220-330) | AP72: 0 | AR72: 0 | AT72: Revisado | AU72: Alta | AV72: 46214
A73: 2023_BRAULIO_LARA_383_01 | B73: 2023 | C73: 196 | D73: emendas-2023-27-11-2025.xlsx | E73: 2023_BRAULIO_LARA | F73: 383 | G73: CONCLUÍDO | H73: Braulio Lara | J73: ao reforço de dotação orçamentária para atendimento ao Complexo Hospitalar São Francisco de Assis, CNPJ 13.025.354/0002-13 | K73: 2302.1030201142.894.339039.S.500 | L73: 2302 | M73: FUNDO MUNICIPAL DE SAÚDE | N73: 10 | O73: SAÚDE | P73: 302 | Q73: ASSISTÊNCIA HOSPITALAR E AMBULATORIAL | R73: 0114 | S73: ATENÇÃO SECUNDÁRIA E TERCIÁRIA À SAÚDE | T73: 2894 | U73: REDE HOSPITALAR | V73: 339039 | W73: Despesa corrente | X73: Outras despesas correntes | Y73: 500 | Z73: FMS | AA73: 80000 | AB73: 80000 | AC73: 80000 | AD73: 80000 | AF73: 1 | AG73: 1 | AH73: 0322 | AI73: =IF(AH73="","",IFERROR(RIGHT("0000"&AH73,4)&" - "&UPPER(_xlfn.XLOOKUP(RIGHT("0000"&AH73,4),CODEBOOK_CAP!$C$2:$C$212,CODEBOOK_CAP!$D$2:$D$212)),"Código CAP não encontrado")) -> 0322 - ESTRUTURAS, HOSPITAIS, CLÍNICAS | AJ73: =IF(AH73="","",IFERROR(_xlfn.XLOOKUP(RIGHT("0000"&AH73,4),CODEBOOK_CAP!$C$2:$C$212,CODEBOOK_CAP!$E$2:$E$212),"Código CAP não encontrado")) -> Observações relacionadas as estruturas do sistema de saúde, como a construção de hospitais, postos de saúde, construção de maternidades, laboratórios, centros de saúde avançado, SAMU, Ambulâncias, UTI Móveis, leitos, compra de equipamentos médicos, Raio X, Ultrasom, equipamentos de diálise, capacidade de atendimento, estrutura e funcionamento de equipamentos públicos de saúde. | AK73: 0 | AM73: 1 | AN73: 1 | AO73: Complexo Hospitalar São Francisco de Assis | AP73: 0 | AR73: 0 | AT73: Revisado | AU73: Alta | AV73: 46214
A74: 2023_BRAULIO_LARA_385_01 | B74: 2023 | C74: 197 | D74: emendas-2023-27-11-2025.xlsx | E74: 2023_BRAULIO_LARA | F74: 385 | G74: CONCLUÍDO | H74: Braulio Lara | J74: à pintura e revitalização das quadras da Vila Leonina, na Praça do Ensino, Rua Onze de Abril | K74: 2700.1545102331.396.449051.F.500 | L74: 2700 | M74: SECRETARIA MUNICIPAL DE OBRAS E INFRAESTRUTURA | N74: 15 | O74: URBANISMO | P74: 451 | Q74: INFRA-ESTRUTURA URBANA | R74: 0233 | S74: MANUTENÇÃO DA CIDADE | T74: 1396 | U74: INFRAESTRUTURA URBANA | V74: 449051 | W74: Despesa de capital | X74: Investimentos | Y74: 500 | Z74: SMOBI | AA74: 40000 | AB74: 37680.22 | AC74: 37680.22 | AD74: 37680.22 | AF74: 0 | AG74: 0 | AH74: 2300 | AI74: =IF(AH74="","",IFERROR(RIGHT("0000"&AH74,4)&" - "&UPPER(_xlfn.XLOOKUP(RIGHT("0000"&AH74,4),CODEBOOK_CAP!$C$2:$C$212,CODEBOOK_CAP!$D$2:$D$212)),"Código CAP não encontrado")) -> 2300 - GERAL | AJ74: =IF(AH74="","",IFERROR(_xlfn.XLOOKUP(RIGHT("0000"&AH74,4),CODEBOOK_CAP!$C$2:$C$212,CODEBOOK_CAP!$E$2:$E$212),"Código CAP não encontrado")) -> Observações relativas as políticas de cultura, Lei rouanet, patrimônio cultural, imaterial, políticas de artes, incentivos fiscais para artes, promoção de eventos culturais, amostras, teatro, dança, artes plásticas, artes visuais, museus, galerias públicas, idioma, lingua portuguesa. Grandes eventos esportivos, Copa do Mundo, Olimpiadas, Esporte e Lazer. | AK74: 1 | AL74: quadras da Vila Leonina, na Praça do Ensino, Rua Onze de Abril | AM74: 1 | AN74: 1 | AO74: quadras da Vila Leonina, na Praça do Ensino, Rua Onze de Abril | AP74: 0 | AR74: 0 | AT74: Revisado | AU74: Alta | AV74: 46214 | AX74: esporte e lazer
A75: 2023_BRAULIO_LARA_386_01 | B75: 2023 | C75: 198 | D75: emendas-2023-27-11-2025.xlsx | E75: 2023_BRAULIO_LARA | F75: 386 | G75: CANCELADA | H75: Braulio Lara | AB75: 0 | AC75: 0 | AD75: 0 | AI75: =IF(AH75="","",IFERROR(RIGHT("0000"&AH75,4)&" - "&UPPER(_xlfn.XLOOKUP(RIGHT("0000"&AH75,4),CODEBOOK_CAP!$C$2:$C$212,CODEBOOK_CAP!$D$2:$D$212)),"Código CAP não encontrado")) | AJ75: =IF(AH75="","",IFERROR(_xlfn.XLOOKUP(RIGHT("0000"&AH75,4),CODEBOOK_CAP!$C$2:$C$212,CODEBOOK_CAP!$E$2:$E$212),"Código CAP não encontrado")) | AT75: Revisado | AV75: 46214
A76: 2023_BRAULIO_LARA_387_01 | B76: 2023 | C76: 199 | D76: emendas-2023-27-11-2025.xlsx | E76: 2023_BRAULIO_LARA | F76: 387 | G76: IMPEDIMENTO TÉCNICO | H76: Braulio Lara | J76: à implantação de pista de caminhada na Av. Senador Lima Guimarães, no bairro Buritis | K76: 3303.1100.26452602.837.33903963.F.500 | L76: 3303 | M76: FUNDO MUNICIPAL DE MOBILIDADE URBANA | N76: 26 | O76: TRANSPORTE | P76: 452 | Q76: SERVIÇOS URBANOS | R76: 0060 | S76: GESTÃO DA MOBILIDADE URBANA | T76: 2837 | U76: GERENCIAMENTO DA MOBILIDADE URBANA MUNICIPAL | V76: 339039 | W76: Despesa corrente | X76: Outras despesas correntes | Y76: 500 | Z76: BHTRANS | AA76: 30000 | AB76: 0 | AC76: 0 | AD76: 0 | AF76: 0 | AG76: 0 | AH76: 2300 | AI76: =IF(AH76="","",IFERROR(RIGHT("0000"&AH76,4)&" - "&UPPER(_xlfn.XLOOKUP(RIGHT("0000"&AH76,4),CODEBOOK_CAP!$C$2:$C$212,CODEBOOK_CAP!$D$2:$D$212)),"Código CAP não encontrado")) -> 2300 - GERAL | AJ76: =IF(AH76="","",IFERROR(_xlfn.XLOOKUP(RIGHT("0000"&AH76,4),CODEBOOK_CAP!$C$2:$C$212,CODEBOOK_CAP!$E$2:$E$212),"Código CAP não encontrado")) -> Observações relativas as políticas de cultura, Lei rouanet, patrimônio cultural, imaterial, políticas de artes, incentivos fiscais para artes, promoção de eventos culturais, amostras, teatro, dança, artes plásticas, artes visuais, museus, galerias públicas, idioma, lingua portuguesa. Grandes eventos esportivos, Copa do Mundo, Olimpiadas, Esporte e Lazer. | AK76: 1 | AL76: Av. Senador Lima Guimarães, no bairro Buritis | AM76: 1 | AN76: 1 | AO76: Av. Senador Lima Guimarães, no bairro Buritis | AP76: 0 | AR76: 0 | AT76: Revisado | AU76: Alta | AV76: 46214 | AX76: esporte e lazer
A77: 2023_BRAULIO_LARA_388_01 | B77: 2023 | C77: 200 | D77: emendas-2023-27-11-2025.xlsx | E77: 2023_BRAULIO_LARA | F77: 388 | G77: CONCLUÍDO | H77: Braulio Lara | J77: à revitalização da praça Aroldo Tenuta, no bairro Buritis | K77: 2702.1854102332.811.339039.F.500 | L77: 2702 | M77: SUPERINTENDÊNCIA DE DESENVOLVIMENTO DA CAPITAL | N77: 18 | O77: GESTÃO AMBIENTAL | P77: 541 | Q77: PRESERVAÇÃO E CONSERVAÇÃO AMBIENTAL | R77: 0233 | S77: MANUTENÇÃO DA CIDADE | T77: 2811 | U77: SERVIÇOS DE MANUTENÇÃO DE PRAÇAS, JARDINS E ARBORIZAÇÃO DA CIDADE | V77: 339039 | W77: Despesa corrente | X77: Outras despesas correntes | Y77: 500 | Z77: SMOBI | AA77: 20000 | AB77: 18994.490000000002 | AC77: 18994.490000000002 | AD77: 18994.490000000002 | AF77: 0 | AG77: 0 | AH77: 1403 | AI77: =IF(AH77="","",IFERROR(RIGHT("0000"&AH77,4)&" - "&UPPER(_xlfn.XLOOKUP(RIGHT("0000"&AH77,4),CODEBOOK_CAP!$C$2:$C$212,CODEBOOK_CAP!$D$2:$D$212)),"Código CAP não encontrado")) -> 1403 - REABILITAÇÃO URBANA, ECONOMIA URBANA | AJ77: =IF(AH77="","",IFERROR(_xlfn.XLOOKUP(RIGHT("0000"&AH77,4),CODEBOOK_CAP!$C$2:$C$212,CODEBOOK_CAP!$E$2:$E$212),"Código CAP não encontrado")) -> Reabilitação de áreas urbanas, revitalização urbana, modernização de áreas, mercados públicos, revitalização de praças, política urbana nacional, desenvolvimento urbano , desenvolvimento econômico de estados e cidades, modernização de espaços urbanos | AK77: 1 | AL77: praça Aroldo Tenuta, no bairro Buritis | AM77: 1 | AN77: 1 | AO77: praça Aroldo Tenuta, no bairro Buritis | AP77: 0 | AR77: 0 | AT77: Revisado | AU77: Alta | AV77: 46214
A78: 2023_BRAULIO_LARA_389_01 | B78: 2023 | C78: 201 | D78: emendas-2023-27-11-2025.xlsx | E78: 2023_BRAULIO_LARA | F78: 389 | G78: CONCLUÍDO | H78: Braulio Lara | J78: ao desenvolvimento de projeto operacional e ao arredondamento da quina da esquina da esquina da Rua Maria Heilbuth Surette com a esquina da Rua Moacyr José Bernardes (facilitar a melhoria da conversão) | K78: 3303.1100.26.452.60.2837.S.33903963.500 | L78: 3303 | M78: FUNDO MUNICIPAL DE MOBILIDADE URBANA | N78: 26 | O78: TRANSPORTE | P78: 452 | Q78: SERVIÇOS URBANOS | R78: 0060 | S78: GESTÃO DA MOBILIDADE URBANA | T78: 2837 | U78: GERENCIAMENTO DA MOBILIDADE URBANA MUNICIPAL | V78: 339039 | W78: Despesa corrente | X78: Outras despesas correntes | Y78: 500 | Z78: BHTRANS | AA78: 10000 | AB78: 9964.1 | AC78: 9964.1 | AD78: 9964.1 | AF78: 0 | AG78: 0 | AH78: 1002 | AI78: =IF(AH78="","",IFERROR(RIGHT("0000"&AH78,4)&" - "&UPPER(_xlfn.XLOOKUP(RIGHT("0000"&AH78,4),CODEBOOK_CAP!$C$2:$C$212,CODEBOOK_CAP!$D$2:$D$212)),"Código CAP não encontrado")) -> 1002 - CARROS, TRÂNSITO, CONSTRUÇÃO E MANUTENÇÃO DE RUAS E ESTRADAS | AJ78: =IF(AH78="","",IFERROR(_xlfn.XLOOKUP(RIGHT("0000"&AH78,4),CODEBOOK_CAP!$C$2:$C$212,CODEBOOK_CAP!$E$2:$E$212),"Código CAP não encontrado")) -> Construção, manutenção de ruas, avenidas, estradas. BRs, pedágios, privatizações, concessinárias, segurança nas estradas, leis de trânsito relacionadas a via, limite de velocidade, sinalização, recapeamento de ruas, pavimentação estradas de terra, não pavimentadas, acidentes e camapanhas de prevencao contra acidentes de transito. Observações sobre regulação de transportes não públicos de carros, veículos de passeio, uber, taxi, transporte de cargas terrestre, frete, trânsito em vias públicas, regulamentação de tipos de carteira de motorista, especificações para caminhoneiros, testes e exames de habilitação, exigências de carteira de habilitação, obrigatoriedade de itens em veículos (extintor, kit primeiros socorros, airbag, freios abs) Quando tratar de grandes obras de construções de rodovias, olhar codigo 1010 para ver qual se encaixa melhor. | AK78: 1 | AL78: quina da esquina da esquina da Rua Maria Heilbuth Surette com a esquina da Rua Moacyr José Bernardes | AM78: 1 | AN78: 1 | AO78: quina da esquina da esquina da Rua Maria Heilbuth Surette com a esquina da Rua Moacyr José Bernardes | AP78: 0 | AR78: 0 | AT78: Revisado | AU78: Alta | AV78: 46214
A79: 2023_BRAULIO_LARA_390_01 | B79: 2023 | C79: 202 | D79: emendas-2023-27-11-2025.xlsx | E79: 2023_BRAULIO_LARA | F79: 390 | G79: IMPEDIMENTO TÉCNICO | H79: Braulio Lara | J79: ao desenvolvimento de projeto operacional e ao arredondamento da quina da esquina da esquina da Rua Moacyr José Bernardes com a Rua Eduardo Frieiro (facilitar a melhoria da conversão) | K79: 3303.1100.26.452.60.2837.S.33903963.500 | L79: 3303 | M79: FUNDO MUNICIPAL DE MOBILIDADE URBANA | N79: 26 | O79: TRANSPORTE | P79: 452 | Q79: SERVIÇOS URBANOS | R79: 0060 | S79: GESTÃO DA MOBILIDADE URBANA | T79: 2837 | U79: GERENCIAMENTO DA MOBILIDADE URBANA MUNICIPAL | V79: 339039 | W79: Despesa corrente | X79: Outras despesas correntes | Y79: 500 | Z79: BHTRANS | AA79: 10000 | AB79: 0 | AC79: 0 | AD79: 0 | AF79: 0 | AG79: 0 | AH79: 1002 | AI79: =IF(AH79="","",IFERROR(RIGHT("0000"&AH79,4)&" - "&UPPER(_xlfn.XLOOKUP(RIGHT("0000"&AH79,4),CODEBOOK_CAP!$C$2:$C$212,CODEBOOK_CAP!$D$2:$D$212)),"Código CAP não encontrado")) -> 1002 - CARROS, TRÂNSITO, CONSTRUÇÃO E MANUTENÇÃO DE RUAS E ESTRADAS | AJ79: =IF(AH79="","",IFERROR(_xlfn.XLOOKUP(RIGHT("0000"&AH79,4),CODEBOOK_CAP!$C$2:$C$212,CODEBOOK_CAP!$E$2:$E$212),"Código CAP não encontrado")) -> Construção, manutenção de ruas, avenidas, estradas. BRs, pedágios, privatizações, concessinárias, segurança nas estradas, leis de trânsito relacionadas a via, limite de velocidade, sinalização, recapeamento de ruas, pavimentação estradas de terra, não pavimentadas, acidentes e camapanhas de prevencao contra acidentes de transito. Observações sobre regulação de transportes não públicos de carros, veículos de passeio, uber, taxi, transporte de cargas terrestre, frete, trânsito em vias públicas, regulamentação de tipos de carteira de motorista, especificações para caminhoneiros, testes e exames de habilitação, exigências de carteira de habilitação, obrigatoriedade de itens em veículos (extintor, kit primeiros socorros, airbag, freios abs) Quando tratar de grandes obras de construções de rodovias, olhar codigo 1010 para ver qual se encaixa melhor. | AK79: 1 | AL79: quina da esquina da esquina da Rua Moacyr José Bernardes com a Rua Eduardo Frieiro | AM79: 1 | AN79: 1 | AO79: quina da esquina da esquina da Rua Moacyr José Bernardes com a Rua Eduardo Frieiro | AP79: 0 | AR79: 0 | AT79: Revisado | AU79: Alta | AV79: 46214
A80: 2023_BRUNO_MIRANDA_1091_01 | B80: 2023 | C80: 870 | D80: emendas-2023-27-11-2025.xlsx | E80: 2023_BRUNO_MIRANDA | F80: 1091 | G80: CONCLUÍDO | H80: Bruno Miranda | J80: ao reforço de dotação orçamentária destinado à realização de rua de lazer. | K80: 3000.2781301012.545.339039.F.500 | L80: 3000 | M80: SECRETARIA MUNICIPAL DE ESPORTES E LAZER | N80: 27 | O80: DESPORTO E LAZER | P80: 813 | Q80: LAZER | R80: 0101 | S80: PROMOÇÃO E DEMOCRATIZAÇÃO DAS PRÁTICAS DE ESPORTES E LAZER | T80: 2545 | U80: PROMOÇÃO DE EVENTOS ESPORTIVOS E DE LAZER | V80: 339039 | W80: Despesa corrente | X80: Outras despesas correntes | Y80: 500 | Z80: SMEL | AA80: 65000 | AB80: 33039.379999999997 | AC80: 33039.379999999997 | AD80: 33039.379999999997 | AF80: 0 | AG80: 0 | AH80: 2300 | AI80: =IF(AH80="","",IFERROR(RIGHT("0000"&AH80,4)&" - "&UPPER(_xlfn.XLOOKUP(RIGHT("0000"&AH80,4),CODEBOOK_CAP!$C$2:$C$212,CODEBOOK_CAP!$D$2:$D$212)),"Código CAP não encontrado")) -> 2300 - GERAL | AJ80: =IF(AH80="","",IFERROR(_xlfn.XLOOKUP(RIGHT("0000"&AH80,4),CODEBOOK_CAP!$C$2:$C$212,CODEBOOK_CAP!$E$2:$E$212),"Código CAP não encontrado")) -> Observações relativas as políticas de cultura, Lei rouanet, patrimônio cultural, imaterial, políticas de artes, incentivos fiscais para artes, promoção de eventos culturais, amostras, teatro, dança, artes plásticas, artes visuais, museus, galerias públicas, idioma, lingua portuguesa. Grandes eventos esportivos, Copa do Mundo, Olimpiadas, Esporte e Lazer. | AK80: 0 | AM80: 0 | AN80: 0 | AP80: 0 | AR80: 0 | AT80: Revisado | AU80: Alta | AV80: 46214 | AX80: esporte e lazer
A81: 2023_BRUNO_MIRANDA_1092_01 | B81: 2023 | C81: 871 | D81: emendas-2023-27-11-2025.xlsx | E81: 2023_BRUNO_MIRANDA | F81: 1092 | G81: CONCLUÍDO | H81: Bruno Miranda | J81: ao reforço de dotação orçamentária destinado à manutenção em equipamentos esportivos de lazer (play ground) em praças e parques. | K81: 3000.2781201012.534.449052.F.500 3000.2781201012.534.339039.F.500 | L81: 3000 | M81: SECRETARIA MUNICIPAL DE ESPORTES E LAZER | N81: 27 | O81: DESPORTO E LAZER | P81: 812 | Q81: DESPORTO COMUNITÁRIO | R81: 0101 | S81: PROMOÇÃO E DEMOCRATIZAÇÃO DAS PRÁTICAS DE ESPORTES E LAZER | T81: 2534 | U81: IMPLANTAÇÃO, MANUTENÇÃO E RECUPERAÇAO DE INFRAESTRUTURA ESPORTIVA E DE LAZER | V81: 449052 | W81: Despesa de capital | X81: Investimentos | Y81: 500 | Z81: SMEL | AA81: 65000 | AB81: 29748.74 | AC81: 29748.74 | AD81: 29748.74 | AF81: 0 | AG81: 0 | AH81: 2300 | AI81: =IF(AH81="","",IFERROR(RIGHT("0000"&AH81,4)&" - "&UPPER(_xlfn.XLOOKUP(RIGHT("0000"&AH81,4),CODEBOOK_CAP!$C$2:$C$212,CODEBOOK_CAP!$D$2:$D$212)),"Código CAP não encontrado")) -> 2300 - GERAL | AJ81: =IF(AH81="","",IFERROR(_xlfn.XLOOKUP(RIGHT("0000"&AH81,4),CODEBOOK_CAP!$C$2:$C$212,CODEBOOK_CAP!$E$2:$E$212),"Código CAP não encontrado")) -> Observações relativas as políticas de cultura, Lei rouanet, patrimônio cultural, imaterial, políticas de artes, incentivos fiscais para artes, promoção de eventos culturais, amostras, teatro, dança, artes plásticas, artes visuais, museus, galerias públicas, idioma, lingua portuguesa. Grandes eventos esportivos, Copa do Mundo, Olimpiadas, Esporte e Lazer. | AK81: 0 | AM81: 0 | AN81: 0 | AP81: 0 | AR81: 0 | AT81: Revisado | AU81: Alta | AV81: 46214 | AX81: esporte e lazer
A82: 2023_BRUNO_MIRANDA_1093_01 | B82: 2023 | C82: 872 | D82: emendas-2023-27-11-2025.xlsx | E82: 2023_BRUNO_MIRANDA | F82: 1093 | G82: CONCLUÍDO | H82: Bruno Miranda | J82: ao reforço de dotação orçamentária destinado à iluminação e revitalização do Campo Taça de Ouro. | K82: 2700.2781201011.213.449051.F.500 | L82: 2700 | M82: SECRETARIA MUNICIPAL DE OBRAS E INFRAESTRUTURA | N82: 27 | O82: DESPORTO E LAZER | P82: 812 | Q82: DESPORTO COMUNITÁRIO | R82: 0101 | S82: PROMOÇÃO E DEMOCRATIZAÇÃO DAS PRÁTICAS DE ESPORTES E LAZER | T82: 1213 | U82: CONSTRUÇÃO, AMPLIAÇÃO E REFORMA DE EQUIPAMENTOS ESPORTIVOS E ÁREAS DE LAZER | V82: 449051 | W82: Despesa de capital | X82: Investimentos | Y82: 500 | Z82: SMOBI | AA82: 20000 | AB82: 16076.25 | AC82: 16076.25 | AD82: 16076.25 | AF82: 0 | AG82: 0 | AH82: 2300 | AI82: =IF(AH82="","",IFERROR(RIGHT("0000"&AH82,4)&" - "&UPPER(_xlfn.XLOOKUP(RIGHT("0000"&AH82,4),CODEBOOK_CAP!$C$2:$C$212,CODEBOOK_CAP!$D$2:$D$212)),"Código CAP não encontrado")) -> 2300 - GERAL | AJ82: =IF(AH82="","",IFERROR(_xlfn.XLOOKUP(RIGHT("0000"&AH82,4),CODEBOOK_CAP!$C$2:$C$212,CODEBOOK_CAP!$E$2:$E$212),"Código CAP não encontrado")) -> Observações relativas as políticas de cultura, Lei rouanet, patrimônio cultural, imaterial, políticas de artes, incentivos fiscais para artes, promoção de eventos culturais, amostras, teatro, dança, artes plásticas, artes visuais, museus, galerias públicas, idioma, lingua portuguesa. Grandes eventos esportivos, Copa do Mundo, Olimpiadas, Esporte e Lazer. | AK82: 0 | AM82: 1 | AN82: 1 | AO82: Campo Taça de Ouro | AP82: 0 | AR82: 0 | AT82: Revisado | AU82: Alta | AV82: 46214 | AX82: esporte e lazer
A83: 2023_BRUNO_MIRANDA_603_01 | B83: 2023 | C83: 395 | D83: emendas-2023-27-11-2025.xlsx | E83: 2023_BRUNO_MIRANDA | F83: 603 | G83: CONCLUÍDO | H83: Bruno Miranda | J83: ao reforço de dotação orçamentária para Incentivo ao Programa Estamos Juntos. | K83: 2810.1133402372.404.339039.F.500 | L83: 2810 | M83: FUNDO MUNICIPAL DO TRABALHO | N83: 11 | O83: TRABALHO | P83: 334 | Q83: FOMENTO AO TRABALHO | R83: 0237 | S83: QUALIFICAÇÃO, PROFISSIONALIZAÇÃO E EMPREGO | T83: 2404 | U83: AÇÕES DE QUALIFICAÇÃO, PROFISSIONALIZAÇÃO E EMPREGO | V83: 339039 | W83: Despesa corrente | X83: Outras despesas correntes | Y83: 500 | Z83: SMDE | AA83: 150000 | AB83: 150000 | AC83: 150000 | AD83: 150000 | AF83: 0 | AG83: 0 | AH83: 0502 | AI83: =IF(AH83="","",IFERROR(RIGHT("0000"&AH83,4)&" - "&UPPER(_xlfn.XLOOKUP(RIGHT("0000"&AH83,4),CODEBOOK_CAP!$C$2:$C$212,CODEBOOK_CAP!$D$2:$D$212)),"Código CAP não encontrado")) -> 0502 - FORMAÇÃO E DESENVOLVIMENTO PROFISSIONAL | AJ83: =IF(AH83="","",IFERROR(_xlfn.XLOOKUP(RIGHT("0000"&AH83,4),CODEBOOK_CAP!$C$2:$C$212,CODEBOOK_CAP!$E$2:$E$212),"Código CAP não encontrado")) -> Programas de capacitação profissional, programas de incentivo ao emprego geral, reciclagem, realocação profissional em outra área, acordos e parcerias do estado com empresas privadas na capacitação, formação e treinamento profissional. | AK83: 0 | AM83: 0 | AN83: 0 | AP83: 1 | AQ83: pessoas em situação de rua | AR83: 0 | AT83: Revisado | AU83: Alta | AV83: 46214
A84: 2023_BRUNO_MIRANDA_610_01 | B84: 2023 | C84: 402 | D84: emendas-2023-27-11-2025.xlsx | E84: 2023_BRUNO_MIRANDA | F84: 610 | G84: CONCLUÍDO | H84: Bruno Miranda | J84: ao reforço de dotação orçamentária para suporte, conservação e manutenção das Unidades e Serviços da Rede de Saúde Mental. | K84: 2302.1030201142.891.339039.S.500 | L84: 2302 | M84: FUNDO MUNICIPAL DE SAÚDE | N84: 10 | O84: SAÚDE | P84: 302 | Q84: ASSISTÊNCIA HOSPITALAR E AMBULATORIAL | R84: 0114 | S84: ATENÇÃO SECUNDÁRIA E TERCIÁRIA À SAÚDE | T84: 2891 | U84: REDE ESPECIALIZADA | V84: 339039 | W84: Despesa corrente | X84: Outras despesas correntes | Y84: 500 | Z84: FMS | AA84: 200000 | AB84: 200000 | AC84: 200000 | AD84: 200000 | AF84: 1 | AG84: 1 | AH84: 0333 | AI84: =IF(AH84="","",IFERROR(RIGHT("0000"&AH84,4)&" - "&UPPER(_xlfn.XLOOKUP(RIGHT("0000"&AH84,4),CODEBOOK_CAP!$C$2:$C$212,CODEBOOK_CAP!$D$2:$D$212)),"Código CAP não encontrado")) -> 0333 - SAÚDE MENTAL | AJ84: =IF(AH84="","",IFERROR(_xlfn.XLOOKUP(RIGHT("0000"&AH84,4),CODEBOOK_CAP!$C$2:$C$212,CODEBOOK_CAP!$E$2:$E$212),"Código CAP não encontrado")) -> Serviços de atendimento a saúde mental e psico-social. CAPS, Controle de qualidade mental, esquizofrenia, bipolaridade, transtornos mentais, ansiedade, alucinançao, depressão, suicídio, CVV, atendimento psicológico e psiquiátrico, sanatório, manicomio. Não confundir com dependências de alcool (342) e drogas (343) | AK84: 0 | AM84: 0 | AN84: 0 | AP84: 0 | AR84: 0 | AT84: Revisado | AU84: Alta | AV84: 46214
A85: 2023_BRUNO_MIRANDA_612_01 | B85: 2023 | C85: 404 | D85: emendas-2023-27-11-2025.xlsx | E85: 2023_BRUNO_MIRANDA | F85: 612 | G85: CANCELADA | H85: Bruno Miranda | AI85: =IF(AH85="","",IFERROR(RIGHT("0000"&AH85,4)&" - "&UPPER(_xlfn.XLOOKUP(RIGHT("0000"&AH85,4),CODEBOOK_CAP!$C$2:$C$212,CODEBOOK_CAP!$D$2:$D$212)),"Código CAP não encontrado")) | AJ85: =IF(AH85="","",IFERROR(_xlfn.XLOOKUP(RIGHT("0000"&AH85,4),CODEBOOK_CAP!$C$2:$C$212,CODEBOOK_CAP!$E$2:$E$212),"Código CAP não encontrado")) | AT85: Revisado | AV85: 46214
A86: 2023_BRUNO_MIRANDA_617_01 | B86: 2023 | C86: 409 | D86: emendas-2023-27-11-2025.xlsx | E86: 2023_BRUNO_MIRANDA | F86: 617 | G86: CONCLUÍDO | H86: Bruno Miranda | J86: ao reforço de dotação orçamentária para instalação de pontos de videomonitoramento na cidade. | K86: 2100.0612203021.334.339039.F.500 | L86: 2100 | M86: SECRETARIA MUNICIPAL DE SEGURANÇA E PREVENÇÃO | N86: 06 | O86: SEGURANÇA PÚBLICA | P86: 122 | Q86: ADMINISTRAÇÃO GERAL | R86: 0302 | S86: BELO HORIZONTE CIDADE INTELIGENTE | T86: 1334 | U86: VIDEOMONITORAMENTO | V86: 339039 | W86: Despesa corrente | X86: Outras despesas correntes | Y86: 500 | Z86: SMSP | AA86: 200000 | AB86: 199995.51999999999 | AC86: 199995.51999999999 | AD86: 199995.51999999999 | AF86: 0 | AG86: 0 | AH86: 1211 | AI86: =IF(AH86="","",IFERROR(RIGHT("0000"&AH86,4)&" - "&UPPER(_xlfn.XLOOKUP(RIGHT("0000"&AH86,4),CODEBOOK_CAP!$C$2:$C$212,CODEBOOK_CAP!$D$2:$D$212)),"Código CAP não encontrado")) -> 1211 - CRIME COMUM , VIOLÊNCIA E PREVENÇÃO | AJ86: =IF(AH86="","",IFERROR(_xlfn.XLOOKUP(RIGHT("0000"&AH86,4),CODEBOOK_CAP!$C$2:$C$212,CODEBOOK_CAP!$E$2:$E$212),"Código CAP não encontrado")) -> Crime comum, roubo, furto, estelionato, assassinatos. Programas de prevenção de crimes gerais, que não sejam crimes específicos listados acima. Programas de prevenção, anuncios, panfletos sobre roubo, furto, violência e crimes. | AK86: 0 | AM86: 0 | AN86: 0 | AP86: 0 | AR86: 0 | AT86: Revisado | AU86: Alta | AV86: 46214
A87: 2023_BRUNO_MIRANDA_620_01 | B87: 2023 | C87: 412 | D87: emendas-2023-27-11-2025.xlsx | E87: 2023_BRUNO_MIRANDA | F87: 620 | G87: CONCLUÍDO | H87: Bruno Miranda | J87: ao reforço de dotação orçamentária para fomento à Rua é Nossa. | K87: 3000.2781301012.545.339039.F.500 | L87: 3000 | M87: SECRETARIA MUNICIPAL DE ESPORTES E LAZER | N87: 27 | O87: DESPORTO E LAZER | P87: 813 | Q87: LAZER | R87: 0101 | S87: PROMOÇÃO E DEMOCRATIZAÇÃO DAS PRÁTICAS DE ESPORTES E LAZER | T87: 2545 | U87: PROMOÇÃO DE EVENTOS ESPORTIVOS E DE LAZER | V87: 339039 | W87: Despesa corrente | X87: Outras despesas correntes | Y87: 500 | Z87: SMEL | AA87: 150000 | AB87: 98834 | AC87: 98834 | AD87: 98834 | AF87: 0 | AG87: 0 | AH87: 2300 | AI87: =IF(AH87="","",IFERROR(RIGHT("0000"&AH87,4)&" - "&UPPER(_xlfn.XLOOKUP(RIGHT("0000"&AH87,4),CODEBOOK_CAP!$C$2:$C$212,CODEBOOK_CAP!$D$2:$D$212)),"Código CAP não encontrado")) -> 2300 - GERAL | AJ87: =IF(AH87="","",IFERROR(_xlfn.XLOOKUP(RIGHT("0000"&AH87,4),CODEBOOK_CAP!$C$2:$C$212,CODEBOOK_CAP!$E$2:$E$212),"Código CAP não encontrado")) -> Observações relativas as políticas de cultura, Lei rouanet, patrimônio cultural, imaterial, políticas de artes, incentivos fiscais para artes, promoção de eventos culturais, amostras, teatro, dança, artes plásticas, artes visuais, museus, galerias públicas, idioma, lingua portuguesa. Grandes eventos esportivos, Copa do Mundo, Olimpiadas, Esporte e Lazer. | AK87: 0 | AM87: 0 | AN87: 0 | AP87: 0 | AR87: 0 | AT87: Revisado | AU87: Alta | AV87: 46214 | AX87: esporte e lazer
A88: 2023_BRUNO_MIRANDA_623_01 | B88: 2023 | C88: 415 | D88: emendas-2023-27-11-2025.xlsx | E88: 2023_BRUNO_MIRANDA | F88: 623 | G88: CONCLUÍDO | H88: Bruno Miranda | J88: ao reforço de dotação orçamentária para atendimento ao Hospital Mario Penna/Luxemburgo. CNPJ: 17.513.235/0001-80 | K88: 2302.1030201142.894.339039.S.500 | L88: 2302 | M88: FUNDO MUNICIPAL DE SAÚDE | N88: 10 | O88: SAÚDE | P88: 302 | Q88: ASSISTÊNCIA HOSPITALAR E AMBULATORIAL | R88: 0114 | S88: ATENÇÃO SECUNDÁRIA E TERCIÁRIA À SAÚDE | T88: 2894 | U88: REDE HOSPITALAR | V88: 339039 | W88: Despesa corrente | X88: Outras despesas correntes | Y88: 500 | Z88: FMS | AA88: 170000 | AB88: 170000 | AC88: 170000 | AD88: 170000 | AF88: 1 | AG88: 1 | AH88: 0322 | AI88: =IF(AH88="","",IFERROR(RIGHT("0000"&AH88,4)&" - "&UPPER(_xlfn.XLOOKUP(RIGHT("0000"&AH88,4),CODEBOOK_CAP!$C$2:$C$212,CODEBOOK_CAP!$D$2:$D$212)),"Código CAP não encontrado")) -> 0322 - ESTRUTURAS, HOSPITAIS, CLÍNICAS | AJ88: =IF(AH88="","",IFERROR(_xlfn.XLOOKUP(RIGHT("0000"&AH88,4),CODEBOOK_CAP!$C$2:$C$212,CODEBOOK_CAP!$E$2:$E$212),"Código CAP não encontrado")) -> Observações relacionadas as estruturas do sistema de saúde, como a construção de hospitais, postos de saúde, construção de maternidades, laboratórios, centros de saúde avançado, SAMU, Ambulâncias, UTI Móveis, leitos, compra de equipamentos médicos, Raio X, Ultrasom, equipamentos de diálise, capacidade de atendimento, estrutura e funcionamento de equipamentos públicos de saúde. | AK88: 0 | AM88: 1 | AN88: 1 | AO88: Hospital Mario Penna/Luxemburgo | AP88: 0 | AR88: 0 | AT88: Revisado | AU88: Alta | AV88: 46214
A89: 2023_BRUNO_MIRANDA_633_01 | B89: 2023 | C89: 423 | D89: emendas-2023-27-11-2025.xlsx | E89: 2023_BRUNO_MIRANDA | F89: 633 | G89: CONCLUÍDO | H89: Bruno Miranda | J89: ao reforço de dotação orçamentária para atendimento ao Hospital Sofia Feldman. CNPJ: 25.459.256/0001-92 | K89: 2302.1030201142.894.339039.S.500 | L89: 2302 | M89: FUNDO MUNICIPAL DE SAÚDE | N89: 10 | O89: SAÚDE | P89: 302 | Q89: ASSISTÊNCIA HOSPITALAR E AMBULATORIAL | R89: 0114 | S89: ATENÇÃO SECUNDÁRIA E TERCIÁRIA À SAÚDE | T89: 2894 | U89: REDE HOSPITALAR | V89: 339039 | W89: Despesa corrente | X89: Outras despesas correntes | Y89: 500 | Z89: FMS | AA89: 200000 | AB89: 200000 | AC89: 200000 | AD89: 200000 | AF89: 1 | AG89: 1 | AH89: 0332 | AI89: =IF(AH89="","",IFERROR(RIGHT("0000"&AH89,4)&" - "&UPPER(_xlfn.XLOOKUP(RIGHT("0000"&AH89,4),CODEBOOK_CAP!$C$2:$C$212,CODEBOOK_CAP!$D$2:$D$212)),"Código CAP não encontrado")) -> 0332 - SAÚDE INFANTIL, GRAVIDEZ E PRÉ-NATAL | AJ89: =IF(AH89="","",IFERROR(_xlfn.XLOOKUP(RIGHT("0000"&AH89,4),CODEBOOK_CAP!$C$2:$C$212,CODEBOOK_CAP!$E$2:$E$212),"Código CAP não encontrado")) -> Questões relacionadas a saúde da mãe, bebê e criança desde a gravidez. Campanhas de prevenção de gravidez indesejada, gravidez na adolescencia, Vacinação infantil ou vacina para doenças já existentes, atendimento pediátrico, atendimento obstétrico, parto, parto normal, cesariana, parto natural, pré-natal, consultas e exames pré-natal, atividades relacionadas a gravidez, saúde da mãe e do bebê, cuidados dentários infantís. Quando a política de prevenção for sobre crianças ou gravidez, codificar aqui 332. | AK89: 0 | AM89: 1 | AN89: 1 | AO89: Rua Antônio Bandeira, 1060 - Tupi, Belo Horizonte - MG, 31844-130 | AP89: 1 | AQ89: gestantes, parturientes e puérperas; recém-nascidos | AR89: 0 | AT89: Revisado | AU89: Alta | AV89: 46214
A90: 2023_BRUNO_MIRANDA_635_01 | B90: 2023 | C90: 425 | D90: emendas-2023-27-11-2025.xlsx | E90: 2023_BRUNO_MIRANDA | F90: 635 | G90: IMPEDIMENTO TÉCNICO | H90: Bruno Miranda | J90: ao reforço de dotação orçamentária para ampliação do atendimento de adolescentes residentes em vilas e favelas que realizarão cursos de qualificação profissional a serem elaborados e implementados pela Associação Mineira de Educação Continuada - ASMEC. CNPJ: 05.263.848/0001-27 | K90: 1011.0824300192.647.339039.S.500 | L90: 1011 | M90: FUNDO MUNICIPAL DE ASSISTÊNCIA SOCIAL | N90: 08 | O90: ASSISTÊNCIA SOCIAL | P90: 243 | Q90: ASSISTÊNCIA À CRIANÇA E AO ADOLESCENTE | R90: 0019 | S90: PROTEÇÃO SOCIAL BÁSICA | T90: 2647 | U90: PROGRAMAS E PROJETOS DE PROTEÇÃO SOCIAL BÁSICA | V90: 339039 | W90: Despesa corrente | X90: Outras despesas correntes | Y90: 500 | Z90: SMASDH | AA90: 376000 | AB90: 0 | AC90: 0 | AD90: 0 | AF90: 0 | AG90: 0 | AH90: 0502 | AI90: =IF(AH90="","",IFERROR(RIGHT("0000"&AH90,4)&" - "&UPPER(_xlfn.XLOOKUP(RIGHT("0000"&AH90,4),CODEBOOK_CAP!$C$2:$C$212,CODEBOOK_CAP!$D$2:$D$212)),"Código CAP não encontrado")) -> 0502 - FORMAÇÃO E DESENVOLVIMENTO PROFISSIONAL | AJ90: =IF(AH90="","",IFERROR(_xlfn.XLOOKUP(RIGHT("0000"&AH90,4),CODEBOOK_CAP!$C$2:$C$212,CODEBOOK_CAP!$E$2:$E$212),"Código CAP não encontrado")) -> Programas de capacitação profissional, programas de incentivo ao emprego geral, reciclagem, realocação profissional em outra área, acordos e parcerias do estado com empresas privadas na capacitação, formação e treinamento profissional. | AK90: 0 | AM90: 0 | AN90: 0 | AP90: 1 | AQ90: adolescentes | AR90: 0 | AT90: Revisado | AU90: Alta | AV90: 46214
A91: 2023_BRUNO_MIRANDA_636_01 | B91: 2023 | C91: 426 | D91: emendas-2023-27-11-2025.xlsx | E91: 2023_BRUNO_MIRANDA | F91: 636 | G91: CONCLUÍDO | H91: Bruno Miranda | J91: ao reforço de dotação orçamentária para fomento da aprendizagem de instrumentos de percussão e bateria para pessoas em vulnerabilidade social nas regiões Norte e Pampulha. | K91: 3103.1339201542.371.339039.F.500 | L91: 3103 | M91: FUNDAÇÃO MUNICIPAL DE CULTURA | N91: 13 | O91: CULTURA | P91: 392 | Q91: DIFUSÃO CULTURAL | R91: 0154 | S91: PROMOÇÃO E ACESSO ÀS ARTES E À CULTURA | T91: 2371 | U91: DEMOCRATIZAÇÃO DAS ARTES E DAS CULTURAS | V91: 339039 | W91: Despesa corrente | X91: Outras despesas correntes | Y91: 500 | Z91: FMC | AA91: 126000 | AB91: 126000 | AC91: 126000 | AD91: 126000 | AF91: 0 | AG91: 0 | AH91: 2300 | AI91: =IF(AH91="","",IFERROR(RIGHT("0000"&AH91,4)&" - "&UPPER(_xlfn.XLOOKUP(RIGHT("0000"&AH91,4),CODEBOOK_CAP!$C$2:$C$212,CODEBOOK_CAP!$D$2:$D$212)),"Código CAP não encontrado")) -> 2300 - GERAL | AJ91: =IF(AH91="","",IFERROR(_xlfn.XLOOKUP(RIGHT("0000"&AH91,4),CODEBOOK_CAP!$C$2:$C$212,CODEBOOK_CAP!$E$2:$E$212),"Código CAP não encontrado")) -> Observações relativas as políticas de cultura, Lei rouanet, patrimônio cultural, imaterial, políticas de artes, incentivos fiscais para artes, promoção de eventos culturais, amostras, teatro, dança, artes plásticas, artes visuais, museus, galerias públicas, idioma, lingua portuguesa. Grandes eventos esportivos, Copa do Mundo, Olimpiadas, Esporte e Lazer. | AK91: 1 | AL91: regiões Norte e Pampulha | AM91: 2 | AN91: 0 | AP91: 0 | AR91: 0 | AT91: Revisado | AU91: Alta | AV91: 46214 | AX91: cultura
A92: 2023_BRUNO_MIRANDA_651_01 | B92: 2023 | C92: 441 | D92: emendas-2023-27-11-2025.xlsx | E92: 2023_BRUNO_MIRANDA | F92: 651 | G92: EM EXECUÇÃO | H92: Bruno Miranda | J92: à aquisição de equipamentos e material permanente para o Centro de Saúde Leopoldo Chrisóstomo de Castro. | K92: 2302.1030101572.690.449052.S.500 | L92: 2302 | M92: FUNDO MUNICIPAL DE SAÚDE | N92: 10 | O92: SAÚDE | P92: 301 | Q92: ATENÇÃO BÁSICA | R92: 0157 | S92: ATENÇÃO PRIMÁRIA À SAÚDE | T92: 2690 | U92: ATENÇÃO PRIMÁRIA À SAÚDE | V92: 449052 | W92: Despesa de capital | X92: Investimentos | Y92: 500 | Z92: FMS | AA92: 20000 | AB92: 17929.61 | AC92: 13579.61 | AD92: 13579.61 | AE92: B. D. R. COMERCIO DE EQUIPAMENTOS LTDA; INSMART COMERCIO DE EQUIPAMENTOS LTDA; SUPORTH CIRURGICA PONTA GROSSA LTDA | AF92: 1 | AG92: 1 | AH92: 0322 | AI92: =IF(AH92="","",IFERROR(RIGHT("0000"&AH92,4)&" - "&UPPER(_xlfn.XLOOKUP(RIGHT("0000"&AH92,4),CODEBOOK_CAP!$C$2:$C$212,CODEBOOK_CAP!$D$2:$D$212)),"Código CAP não encontrado")) -> 0322 - ESTRUTURAS, HOSPITAIS, CLÍNICAS | AJ92: =IF(AH92="","",IFERROR(_xlfn.XLOOKUP(RIGHT("0000"&AH92,4),CODEBOOK_CAP!$C$2:$C$212,CODEBOOK_CAP!$E$2:$E$212),"Código CAP não encontrado")) -> Observações relacionadas as estruturas do sistema de saúde, como a construção de hospitais, postos de saúde, construção de maternidades, laboratórios, centros de saúde avançado, SAMU, Ambulâncias, UTI Móveis, leitos, compra de equipamentos médicos, Raio X, Ultrasom, equipamentos de diálise, capacidade de atendimento, estrutura e funcionamento de equipamentos públicos de saúde. | AK92: 0 | AM92: 1 | AN92: 1 | AO92: Centro de Saúde Leopoldo Chrisóstomo de Castro | AP92: 0 | AR92: 1 | AS92: B. D. R. COMERCIO DE EQUIPAMENTOS LTDA; INSMART COMERCIO DE EQUIPAMENTOS LTDA; SUPORTH CIRURGICA PONTA GROSSA LTDA | AT92: Revisado | AU92: Alta | AV92: 46214
A93: 2023_BRUNO_MIRANDA_652_01 | B93: 2023 | C93: 442 | D93: emendas-2023-27-11-2025.xlsx | E93: 2023_BRUNO_MIRANDA | F93: 652 | G93: EM EXECUÇÃO | H93: Bruno Miranda | J93: ao reforço de dotação orçamentária para aquisição de equipamento para o Centro de Saúde Dom Joaquim. | K93: 2302.1030101572.690.449052.S.500 | L93: 2302 | M93: FUNDO MUNICIPAL DE SAÚDE | N93: 10 | O93: SAÚDE | P93: 301 | Q93: ATENÇÃO BÁSICA | R93: 0157 | S93: ATENÇÃO PRIMÁRIA À SAÚDE | T93: 2690 | U93: ATENÇÃO PRIMÁRIA À SAÚDE | V93: 449052 | W93: Despesa de capital | X93: Investimentos | Y93: 500 | Z93: FMS | AA93: 22000 | AB93: 18711.82 | AC93: 18711.82 | AD93: 18711.82 | AE93: BOSCO FELIPE COMERCIO LTDA; INSMART COMERCIO DE EQUIPAMENTOS LTDA; SUPORTH CIRURGICA PONTA GROSSA LTDA | AF93: 1 | AG93: 1 | AH93: 0322 | AI93: =IF(AH93="","",IFERROR(RIGHT("0000"&AH93,4)&" - "&UPPER(_xlfn.XLOOKUP(RIGHT("0000"&AH93,4),CODEBOOK_CAP!$C$2:$C$212,CODEBOOK_CAP!$D$2:$D$212)),"Código CAP não encontrado")) -> 0322 - ESTRUTURAS, HOSPITAIS, CLÍNICAS | AJ93: =IF(AH93="","",IFERROR(_xlfn.XLOOKUP(RIGHT("0000"&AH93,4),CODEBOOK_CAP!$C$2:$C$212,CODEBOOK_CAP!$E$2:$E$212),"Código CAP não encontrado")) -> Observações relacionadas as estruturas do sistema de saúde, como a construção de hospitais, postos de saúde, construção de maternidades, laboratórios, centros de saúde avançado, SAMU, Ambulâncias, UTI Móveis, leitos, compra de equipamentos médicos, Raio X, Ultrasom, equipamentos de diálise, capacidade de atendimento, estrutura e funcionamento de equipamentos públicos de saúde. | AK93: 0 | AM93: 1 | AN93: 1 | AO93: Centro de Saúde Dom Joaquim. | AP93: 0 | AR93: 1 | AS93: BOSCO FELIPE COMERCIO LTDA; INSMART COMERCIO DE EQUIPAMENTOS LTDA; SUPORTH CIRURGICA PONTA GROSSA LTDA | AT93: Revisado | AU93: Alta | AV93: 46214
A94: 2023_BRUNO_MIRANDA_653_01 | B94: 2023 | C94: 443 | D94: emendas-2023-27-11-2025.xlsx | E94: 2023_BRUNO_MIRANDA | F94: 653 | G94: CONCLUÍDO | H94: Bruno Miranda | J94: ao reforço de dotação orçamentária destinado à realização de Campo de Futebol Monte Azul. | K94: 2200.0600.12.365.169.2.046 44504201.1.500.000 | L94: 2200 | M94: SECRETARIA MUNICIPAL DE EDUCAÇÃO | N94: 12 | O94: EDUCAÇÃO | P94: 365 | Q94: EDUCAÇÃO INFANTIL | R94: 0169 | S94: GESTÃO DA POLÍTICA DE EDUCAÇÃO INFANTIL | T94: 2046 | U94: GESTÃO DESCENTRALIZADA DA EDUCAÇÃO | Z94: SMED | AA94: 400000 | AB94: 400000 | AC94: 800000 | AD94: 400000 | AF94: 0 | AG94: 0 | AH94: 2300 | AI94: =IF(AH94="","",IFERROR(RIGHT("0000"&AH94,4)&" - "&UPPER(_xlfn.XLOOKUP(RIGHT("0000"&AH94,4),CODEBOOK_CAP!$C$2:$C$212,CODEBOOK_CAP!$D$2:$D$212)),"Código CAP não encontrado")) -> 2300 - GERAL | AJ94: =IF(AH94="","",IFERROR(_xlfn.XLOOKUP(RIGHT("0000"&AH94,4),CODEBOOK_CAP!$C$2:$C$212,CODEBOOK_CAP!$E$2:$E$212),"Código CAP não encontrado")) -> Observações relativas as políticas de cultura, Lei rouanet, patrimônio cultural, imaterial, políticas de artes, incentivos fiscais para artes, promoção de eventos culturais, amostras, teatro, dança, artes plásticas, artes visuais, museus, galerias públicas, idioma, lingua portuguesa. Grandes eventos esportivos, Copa do Mundo, Olimpiadas, Esporte e Lazer. | AK94: 1 | AL94: Campo de Futebol Monte Azul | AM94: 1 | AN94: 1 | AO94: Campo de Futebol Monte Azul | AP94: 0 | AR94: 0 | AT94: Revisado | AU94: Alta | AV94: 46214 | AX94: esporte e lazer
A95: 2023_BRUNO_MIRANDA_656_01 | B95: 2023 | C95: 444 | D95: emendas-2023-27-11-2025.xlsx | E95: 2023_BRUNO_MIRANDA | F95: 656 | G95: CONCLUÍDO | H95: Bruno Miranda | J95: ao reforço orçamentário para a garantia do atendimento e transporte de pacientes agudos e crônicos - Transporte e Hemodiálise | K95: 2302.1030201142.893.339039.S.500 | L95: 2302 | M95: FUNDO MUNICIPAL DE SAÚDE | N95: 10 | O95: SAÚDE | P95: 302 | Q95: ASSISTÊNCIA HOSPITALAR E AMBULATORIAL | R95: 0114 | S95: ATENÇÃO SECUNDÁRIA E TERCIÁRIA À SAÚDE | T95: 2893 | U95: REDE DE URGÊNCIA E EMERGÊNCIA | V95: 339039 | W95: Despesa corrente | X95: Outras despesas correntes | Y95: 500 | Z95: FMS | AA95: 300000 | AB95: 300000 | AC95: 300000 | AD95: 300000 | AF95: 1 | AG95: 1 | AH95: 0334 | AI95: =IF(AH95="","",IFERROR(RIGHT("0000"&AH95,4)&" - "&UPPER(_xlfn.XLOOKUP(RIGHT("0000"&AH95,4),CODEBOOK_CAP!$C$2:$C$212,CODEBOOK_CAP!$D$2:$D$212)),"Código CAP não encontrado")) -> 0334 - TRATAMENTOS, CIRUGIAS, ATENDIMENTOS, DOENÇAS E REABILITAÇÃO | AJ95: =IF(AH95="","",IFERROR(_xlfn.XLOOKUP(RIGHT("0000"&AH95,4),CODEBOOK_CAP!$C$2:$C$212,CODEBOOK_CAP!$E$2:$E$212),"Código CAP não encontrado")) -> Questões gerais sobre atendimentos emergenciais, cirurgias, Tratamento de pessoas com doenças terminais, tratamentos longos que necessitam internação e atendimento assistido, home- care, reabilitação, concultas, fisioterapia, tratamentos de dialose, tratamentos contra cancer, doenças degenerativas, ELA, Alzhaimer. Tratamentos continuados de doencas cronicas, HIV. | AK95: 0 | AM95: 0 | AN95: 0 | AP95: 0 | AR95: 0 | AT95: Revisado | AU95: Alta | AV95: 46214
A96: 2023_BRUNO_MIRANDA_657_01 | B96: 2023 | C96: 445 | D96: emendas-2023-27-11-2025.xlsx | E96: 2023_BRUNO_MIRANDA | F96: 657 | G96: EM EXECUÇÃO | H96: Bruno Miranda | J96: para a compra de equipamento e material para o Centro de Saúde Cidade Ozanan. | K96: 2302.1030101572.690.449052.S.500 | L96: 2302 | M96: FUNDO MUNICIPAL DE SAÚDE | N96: 10 | O96: SAÚDE | P96: 301 | Q96: ATENÇÃO BÁSICA | R96: 0157 | S96: ATENÇÃO PRIMÁRIA À SAÚDE | T96: 2690 | U96: ATENÇÃO PRIMÁRIA À SAÚDE | V96: 449052 | W96: Despesa de capital | X96: Investimentos | Y96: 500 | Z96: FMS | AA96: 50000 | AB96: 29630.1 | AC96: 25280.1 | AD96: 25280.1 | AE96: B. D. R. COMERCIO DE EQUIPAMENTOS LTDA | AF96: 1 | AG96: 1 | AH96: 0322 | AI96: =IF(AH96="","",IFERROR(RIGHT("0000"&AH96,4)&" - "&UPPER(_xlfn.XLOOKUP(RIGHT("0000"&AH96,4),CODEBOOK_CAP!$C$2:$C$212,CODEBOOK_CAP!$D$2:$D$212)),"Código CAP não encontrado")) -> 0322 - ESTRUTURAS, HOSPITAIS, CLÍNICAS | AJ96: =IF(AH96="","",IFERROR(_xlfn.XLOOKUP(RIGHT("0000"&AH96,4),CODEBOOK_CAP!$C$2:$C$212,CODEBOOK_CAP!$E$2:$E$212),"Código CAP não encontrado")) -> Observações relacionadas as estruturas do sistema de saúde, como a construção de hospitais, postos de saúde, construção de maternidades, laboratórios, centros de saúde avançado, SAMU, Ambulâncias, UTI Móveis, leitos, compra de equipamentos médicos, Raio X, Ultrasom, equipamentos de diálise, capacidade de atendimento, estrutura e funcionamento de equipamentos públicos de saúde. | AK96: 0 | AM96: 1 | AN96: 1 | AO96: Centro de Saúde Cidade Ozanan | AP96: 0 | AR96: 1 | AS96: B. D. R. COMERCIO DE EQUIPAMENTOS LTDA | AT96: Revisado | AU96: Alta | AV96: 46214
A97: 2023_BRUNO_MIRANDA_659_01 | B97: 2023 | C97: 447 | D97: emendas-2023-27-11-2025.xlsx | E97: 2023_BRUNO_MIRANDA | F97: 659 | G97: CONCLUÍDO | H97: Bruno Miranda | J97: ao reforço de dotação orçamentária destinado à realização de obras e reformas no Centro de Saúde Dom Joaquim. | K97: 2302.1012201171.216.449051.S.500 | L97: 2302 | M97: FUNDO MUNICIPAL DE SAÚDE | N97: 10 | O97: SAÚDE | P97: 122 | Q97: ADMINISTRAÇÃO GERAL | R97: 0117 | S97: GESTÃO DO SUS | T97: 1216 | U97: CONSTRUÇÃO, AMPLIAÇÃO E REFORMA DE UNIDADES DE SAÚDE | V97: 449051 | W97: Despesa de capital | X97: Investimentos | Y97: 500 | Z97: FMS/SMOBI | AA97: 400000 | AB97: 305566.63 | AC97: 305566.63 | AD97: 305566.63 | AE97: ALLIANCE EMPREENDIMENTOS E PROJETOS ARQUITETONICOS LTDA | AF97: 1 | AG97: 1 | AH97: 0322 | AI97: =IF(AH97="","",IFERROR(RIGHT("0000"&AH97,4)&" - "&UPPER(_xlfn.XLOOKUP(RIGHT("0000"&AH97,4),CODEBOOK_CAP!$C$2:$C$212,CODEBOOK_CAP!$D$2:$D$212)),"Código CAP não encontrado")) -> 0322 - ESTRUTURAS, HOSPITAIS, CLÍNICAS | AJ97: =IF(AH97="","",IFERROR(_xlfn.XLOOKUP(RIGHT("0000"&AH97,4),CODEBOOK_CAP!$C$2:$C$212,CODEBOOK_CAP!$E$2:$E$212),"Código CAP não encontrado")) -> Observações relacionadas as estruturas do sistema de saúde, como a construção de hospitais, postos de saúde, construção de maternidades, laboratórios, centros de saúde avançado, SAMU, Ambulâncias, UTI Móveis, leitos, compra de equipamentos médicos, Raio X, Ultrasom, equipamentos de diálise, capacidade de atendimento, estrutura e funcionamento de equipamentos públicos de saúde. | AK97: 0 | AM97: 1 | AN97: 1 | AO97: Centro de Saúde Dom Joaquim | AP97: 0 | AR97: 1 | AS97: ALLIANCE EMPREENDIMENTOS E PROJETOS ARQUITETONICOS LTDA | AT97: Revisado | AU97: Alta | AV97: 46214
A98: 2023_BRUNO_MIRANDA_712_01 | B98: 2023 | C98: 499 | D98: emendas-2023-27-11-2025.xlsx | E98: 2023_BRUNO_MIRANDA | F98: 712 | G98: EM EXECUÇÃO | H98: Bruno Miranda | J98: ao reforço de dotação orçamentária para reforma e aquisição de equipamentos capacitação de pessoas com deficiência em vulnerabilidade social para o Centro de Estudos e Atendimento ao Menor - CEAME, localizado na Rua Maura, 749 no Bairro Ipiranga - CNPJ: 23.840.457/0001-00 | K98: 1011.0824401132.327.339039.S.500 | L98: 1011 | M98: FUNDO MUNICIPAL DE ASSISTÊNCIA SOCIAL | N98: 08 | O98: ASSISTÊNCIA SOCIAL | P98: 244 | Q98: ASSISTÊNCIA COMUNITÁRIA | R98: 0113 | S98: APRIMORAMENTO DA GESTÃO DO SUAS | T98: 2327 | U98: AÇÕES DE APOIO E SUPORTE À POLÍTICA DE ASSISTÊNCIA SOCIAL | V98: 339039 | W98: Despesa corrente | X98: Outras despesas correntes | Y98: 500 | Z98: SMASDH | AA98: 60000 | AB98: 60000 | AC98: 60000 | AD98: 60000 | AF98: 0 | AG98: 0 | AH98: 1304 | AI98: =IF(AH98="","",IFERROR(RIGHT("0000"&AH98,4)&" - "&UPPER(_xlfn.XLOOKUP(RIGHT("0000"&AH98,4),CODEBOOK_CAP!$C$2:$C$212,CODEBOOK_CAP!$D$2:$D$212)),"Código CAP não encontrado")) -> 1304 - POLÍTICAS SOCIAIS DE ASSISTÊNCIA PARA PESSOAS COM DEFICIÊNCIAS | AJ98: =IF(AH98="","",IFERROR(_xlfn.XLOOKUP(RIGHT("0000"&AH98,4),CODEBOOK_CAP!$C$2:$C$212,CODEBOOK_CAP!$E$2:$E$212),"Código CAP não encontrado")) -> Questões relacionadas com políticas sociais e de assistência social para pessoas com deficiências físicias, intelectuais NÃO relacionadas com aposentadoria. Políticas específicas sobre tarifas, precos e acessos a sistemas específicos de assistência de pessoas com deficiência. Acessibilidade, demarcação de vagas para deficientes, filas prioritárias para deficientes, transporte específico. Não confundir com serviços de saúde. | AK98: 1 | AL98: Rua Maura, 749 no Bairro Ipiranga | AM98: 1 | AN98: 1 | AO98: Centro de Estudos e Atendimento ao Menor - CEAME, localizado na Rua Maura, 749 no Bairro Ipiranga | AP98: 1 | AQ98: PCDs | AR98: 0 | AT98: Revisado | AU98: Alta | AV98: 46214
A99: 2023_BRUNO_MIRANDA_761_01 | B99: 2023 | C99: 545 | D99: emendas-2023-27-11-2025.xlsx | E99: 2023_BRUNO_MIRANDA | F99: 761 | G99: CONCLUÍDO | H99: Bruno Miranda | J99: ao reforço de dotação para realização de obras e reformas no centro de Saúde Cidade Ozanan. | K99: 2302.1012201171.216.449051.S.500 | L99: 2302 | M99: FUNDO MUNICIPAL DE SAÚDE | N99: 10 | O99: SAÚDE | P99: 122 | Q99: ADMINISTRAÇÃO GERAL | R99: 0117 | S99: GESTÃO DO SUS | T99: 1216 | U99: CONSTRUÇÃO, AMPLIAÇÃO E REFORMA DE UNIDADES DE SAÚDE | V99: 449051 | W99: Despesa de capital | X99: Investimentos | Y99: 500 | Z99: FMS/SMOBI | AA99: 250000 | AB99: 185857.95 | AC99: 185857.95 | AD99: 185857.95 | AF99: 1 | AG99: 1 | AH99: 0322 | AI99: =IF(AH99="","",IFERROR(RIGHT("0000"&AH99,4)&" - "&UPPER(_xlfn.XLOOKUP(RIGHT("0000"&AH99,4),CODEBOOK_CAP!$C$2:$C$212,CODEBOOK_CAP!$D$2:$D$212)),"Código CAP não encontrado")) -> 0322 - ESTRUTURAS, HOSPITAIS, CLÍNICAS | AJ99: =IF(AH99="","",IFERROR(_xlfn.XLOOKUP(RIGHT("0000"&AH99,4),CODEBOOK_CAP!$C$2:$C$212,CODEBOOK_CAP!$E$2:$E$212),"Código CAP não encontrado")) -> Observações relacionadas as estruturas do sistema de saúde, como a construção de hospitais, postos de saúde, construção de maternidades, laboratórios, centros de saúde avançado, SAMU, Ambulâncias, UTI Móveis, leitos, compra de equipamentos médicos, Raio X, Ultrasom, equipamentos de diálise, capacidade de atendimento, estrutura e funcionamento de equipamentos públicos de saúde. | AK99: 0 | AM99: 1 | AN99: 1 | AO99: centro de Saúde Cidade Ozanan | AP99: 0 | AR99: 0 | AT99: Revisado | AU99: Alta | AV99: 46214
A100: 2023_CIRO_PEREIRA_1022_01 | B100: 2023 | C100: 800 | D100: emendas-2023-27-11-2025.xlsx | E100: 2023_CIRO_PEREIRA | F100: 1022 | G100: CONCLUÍDO | H100: Ciro Pereira | J100: ao reforço de dotação orçamentária para atendimento ao Hospital Mario Penna CNPJ 17.513.235/0001-80, cnes 2200457, com a finalidade de custeio das atividades ambulatoriais e hospitalares, podendo a verba ser direcionada para a aquisição de medicamentos e insumos. | K100: 2302.1030201142.894.339039.S.500 | L100: 2302 | M100: FUNDO MUNICIPAL DE SAÚDE | N100: 10 | O100: SAÚDE | P100: 302 | Q100: ASSISTÊNCIA HOSPITALAR E AMBULATORIAL | R100: 0114 | S100: ATENÇÃO SECUNDÁRIA E TERCIÁRIA À SAÚDE | T100: 2894 | U100: REDE HOSPITALAR | V100: 339039 | W100: Despesa corrente | X100: Outras despesas correntes | Y100: 500 | Z100: FMS | AA100: 600000 | AB100: 600000 | AC100: 600000 | AD100: 600000 | AF100: 1 | AG100: 1 | AH100: 0322 | AI100: =IF(AH100="","",IFERROR(RIGHT("0000"&AH100,4)&" - "&UPPER(_xlfn.XLOOKUP(RIGHT("0000"&AH100,4),CODEBOOK_CAP!$C$2:$C$212,CODEBOOK_CAP!$D$2:$D$212)),"Código CAP não encontrado")) -> 0322 - ESTRUTURAS, HOSPITAIS, CLÍNICAS | AJ100: =IF(AH100="","",IFERROR(_xlfn.XLOOKUP(RIGHT("0000"&AH100,4),CODEBOOK_CAP!$C$2:$C$212,CODEBOOK_CAP!$E$2:$E$212),"Código CAP não encontrado")) -> Observações relacionadas as estruturas do sistema de saúde, como a construção de hospitais, postos de saúde, construção de maternidades, laboratórios, centros de saúde avançado, SAMU, Ambulâncias, UTI Móveis, leitos, compra de equipamentos médicos, Raio X, Ultrasom, equipamentos de diálise, capacidade de atendimento, estrutura e funcionamento de equipamentos públicos de saúde. | AK100: 0 | AM100: 1 | AN100: 1 | AO100: Hospital Mario Penna | AP100: 0 | AR100: 0 | AT100: Revisado | AU100: Alta | AV100: 46214
...

Sheet CODEBOOK_CAP
A1: macro_codigo | B1: macro_tema | C1: subcodigo | D1: subtema | E1: definicao | F1: inclui | G1: nao_inclui | H1: exemplos | I1: observacao_local | J1: ativo
A2: 01 | B2: MACROECONOMIA | C2: 0100 | D2: GERAL | E2: Quando há combinação de diversos assuntos econômicos (subcódigos) em um mesmo dado. Menção de "economia" como assunto isolado, sem especificações. Código é usado em situações generalistas em que a questão macroeconômica aparece como política principal. Termos comuns são: Crescimento econômico, desenvolvimento econômico, política econômica, indicadores econômicos, recessão econômica, estagnação econômica, melhora da economia, plano econômico, condições econômicas, estado da economia, recuperação econômica, efeitos da economia, efeitos da recessão. | J2: 1
A3: 01 | B3: MACROECONOMIA | C3: 0101 | D3: INFLAÇÃO, TAXAS DE JUROS, CONTROLE DE PREÇOS | E3: Controle da inflação, políticas de combate a inflação, indicadores de inflação no Brasil, inflação comparada a outros países, estatísticas de sumento de preços, preço de alimentos e serviços, custo de vida, indicadores de preço e de reajustes, índices de reajuste de preço - Taxa SELIC, Índice de Preço ao Consumidor Amplo (IPCA), Índice de Preços ao Produtor Amplo (IPA), Índice de Preços ao Consumidor da Fipe (IPC-Fipe), Índice Nacional de Preços ao Consumidor (INPC), Índice Nacional de Custo da Construção (INCC), Índice Geral de Preços do Mercado (IGP-M), Índice Geral de Preços de Mercado (IGP-DI). Atuação do Comitê de Política Monetária do Banco Central (COPOM) para taxas de Juros. Políticas específicas para estabilização de preços devem ser codificadas no 110. (Quando há menção de preços, sem mencionar inflação) | J3: 1
A4: 01 | B4: MACROECONOMIA | C4: 0103 | D4: DESEMPREGO | E4: Indicador específico para tratar de Desemprego. Indicadores de taxa de emprego e taxa de desemprego, relatórios sobre taxas de desemprego, análises temporais e comparadas sobre taxa de desemprego. Não confundir com política de trabalho e emprego, Código 5. Impactos econômicos do desemprego usar o (100), Políticas gerais de trabalho e emprego usar o (500), formas de qualificação para emprego usar o (502), trabalho informal (505) | J4: 1
A5: 01 | B5: MACROECONOMIA | C5: 0104 | D5: POLÍTICA MONETÁRIA, BANCO CENTRAL E TESOURO NACIONAL | E5: Observações relacionadas a política monetária, atuação do Banco Central, reserva de ouro, certificados e títulos do tesouro, disponibilidade de crédito, oferta de moeda, taxas de câmbio, compra e venda de títulos públicos, política monetária expansiva, política monetária contracionista, redesconto, depósito compulsório. (Codificar guerra cambial, câmbio em 1808) | J5: 1
A6: 01 | B6: MACROECONOMIA | C6: 0105 | D6: ORÇAMENTO PÚBLICO E DÍVIDA PÚBLICA | E6: Questões relacionadas com a composição do orçamento público, execução orçamentária, déficit público, dívida pública, indicadores e avaliações do déficit ou superávit orçamentário, processo orçamentário, propostas orçamentárias anuais, ato e execução orçamentária, déficit e dívida federal, redução do déficit e propostas de gestão, projeções orçamentárias, aumento do limite da dívida pública, impacto das reduções orçamentárias nas indústrias, estados e comunidades, emissões de dívida pública, mudanças no status do exercício fiscal, resoluções orçamentárias, alterações da peça orçamentária anual. Consulta pública. Dívidas dos Estados e Municípios com a União. (Relações Federarativas do âmbito administrativo usar (2001). Questões de dívida entre entes federados usar (105) | J6: 1
A7: 01 | B7: MACROECONOMIA | C7: 0107 | D7: IMPOSTOS, POLÍTICA FISCAL E TRIBUTÁRIA | E7: Observações relacionadas à política tributária e política fiscal. Alterações tributárias específicas devem ser codificadas com base no assunto em questão. Somente deve ser utilizado em assuntos gerais de taxas, impostos e reformas tributária e fiscal que incluem mudanças em várias áreas substantivas. Quando a Taxa, Imposto ou tributo for sobre uma política ou área específica, usar o código da área (IPTU, por exemplo, usar código Habitação (1400), ou então IPI, que deve ser identificado pelo código Política Industrial (108) . Utilizar 107 em: Imposto de Renda, IRPF, tributação sobre a renda, esclarecimento do código tributário, reforma do código tributário, impostos sobre itens de luxo e de consumo, impostos sobre o alcool, impostos sobre tabaco, impostos sobre heranças e doações, imposto de renda corporativo, propostas de impostos administrativos, reforma do imposto de renda, código tributário federal reforma e simplificação, alterações fiscais gerais, incentivos fiscais, guerra fiscal. | J7: 1
A8: 01 | B8: MACROECONOMIA | C8: 0108 | D8: POLÍTICA INDUSTRIAL | E8: Informações exclusivas de promoção da política industrial. Reestruturação industrial, Desenvolvimento industrial, Subsídios industriais, Produtividade industrial, desempenho industrial, aumento da capacidade produtiva industrial, políticas de tecnologia industrial, centros industriais, parques industriais. alteracoes no valor do IPI. Quando a política for sobre um setor ou área específica, codificar na área. Indústria farmacêutica (321) Nao confundir com crescimento tecnológico geral, parques tecnológicos e ciência. (código 17) | J8: 1
A9: 01 | B9: MACROECONOMIA | C9: 0110 | D9: CONTROLE E ESTABILIZAÇÃO DE PREÇOS | E9: Políticas econômicas para controle e estabilização de preços gerais na economia. Programas de estabilização econômica de preços, Congelamento de preços, programas emergenciais de estabilização de preços. Codificar itens específicos em suas respectivas áreas. Por exemplo: controle de preços de alimentos (tomate, por exemplo) devem ser codificados no item Agricultura (4), preço de energia elétrica ou combustível nos subcódigos de Energia (8), controle do salário mínimo no código de Trabalho (5). | J9: 1
A10: 01 | B10: MACROECONOMIA | C10: 0199 | D10: OUTROS | E10: Observações que versam sobre a economia, mas que não se enquadram em nenhum dos itens acima. | J10: 1
A11: 02 | B11: DIREITOS CIVIS, POLÍTICOS, LIBERDADES E MINORIAS | C11: 0200 | D11: GERAL | E11: Quando há combinação de diversos assuntos relacionado aos direitos civis, liberdade e atores indetificados como minorias. Questões gerais e amplas tais como Comissões, violações de direitos sem especificação, criação ou modificação ou atuação de Ministérios, departamentos ou instituições gerais, direito a propriedade privada, violação e atentados contra direitos civis em geral, cotas gerais (quando existem várias linhas, nao apenas racial), coberturas jornalisticas, estatisticas sobre minorias e sobre direitos básicos, discriminações e preconceito gerais sobre múltiplos aspectos. Quando o tema abordado for sobre uma única parte (sexo ou raça ou idade ou deficiência, codificar nos subcódigos específicos. Geral somente quando há combinação de fatores. Quando aparecer DIREITOS HUMANOS e assuntos de direito civil internacional, codificar em 1925. | J11: 1
A12: 02 | B12: DIREITOS CIVIS, POLÍTICOS, LIBERDADES E MINORIAS | C12: 0201 | D12: DISCRIMINAÇÃO POR QUESTÕES ÉTNICO-RACIAIS | E12: Informações relacionadas exclusivamente a discriminação e questões sobre prevenção e proteção de etnia tais como populações indígenas, questões de raça e cor, discriminações relacionadas a raça e cor, racismo, grupos supremacistas raciais, tratamentos diferenciados, privilégios raciais e étnicos. Questões quaisquer de políticas de saude, de educacao, de terras, de assistencia social sobre populações tradicionais brasileiras usar o 2102. Politicas de cotas, usar o local onde elas sao usadas. Se Politicas de cotas nas universidades usar 601. Se política de cotas para acesso a concursos publicos usar 2004. | J12: 1
A13: 02 | B13: DIREITOS CIVIS, POLÍTICOS, LIBERDADES E MINORIAS | C13: 0202 | D13: DISCRIMINAÇÃO POR GÊNERO OU ORIENTAÇÃO SEXUAL (MISOGINIA E HOMOFOBIA) | E13: Políticas de promoção de igualdade de gênero e de igualdade de relações sociais relacionadas a gênero e orientação sexual. Misoginia, Homofobia, ataques homofóbicos, casamento homoafetivo, igualdade salarial para mulheres, igualdade de trabalho para mulheres, feminismo, Parada LGBT, LGBTQI, transexuais, homossexuais, bissexuais, travestis, relações de gênero com emprego ( tipos de posições, renda, promoção , salário) . VIOLÊNCIA DOMESTICA contra mulheres deve ser codificado em 1208 | J13: 1
... A212: 23 | B212: CULTURA, ESPORTE E LAZER | C212: 2300 | D212: GERAL | E212: Observações relativas as políticas de cultura, Lei rouanet, patrimônio cultural, imaterial, políticas de artes, incentivos fiscais para artes, promoção de eventos culturais, amostras, teatro, dança, artes plásticas, artes visuais, museus, galerias públicas, idioma, lingua portuguesa. Grandes eventos esportivos, Copa do Mundo, Olimpiadas, Esporte e Lazer. | J212: 1

Sheet VEREADOR_ANO
A1: ano | B1: id_vereador_ano | C1: parlamentar_original | D1: Sigla | E1: partido_base | F1: Estimativa ZUCCO POWER 2021 | G1: Estimativa ZUCCO POWER 2017 | H1: ideologia
A2: 2022 | B2: 2022_ALVARO_DAMIAO | C2: Álvaro Damião | D2: DEM | E2: Democratas | F2: 0.431 | H2: direita
A3: 2022 | B3: 2022_BELLA_GONCALVES | C3: Bella Gonçalves | D3: PSOL | E3: partido socialismo e liberdade | F3: -0.874 | H3: esquerda
A4: 2022 | B4: 2022_BIM_DA_AMBULANCIA | C4: Bim da Ambulância | D4: PSD | E4: partido social democratico | F4: 0.296 | H4: direita
A5: 2022 | B5: 2022_BRAULIO_LARA | C5: Braulio Lara | D5: NOVO | E5: partido novo | F5: 0.711 | H5: direita
A6: 2022 | B6: 2022_BRUNO_MIRANDA | C6: Bruno Miranda | D6: PDT | E6: partido democratico trabalhista | F6: -0.356 | H6: esquerda
A7: 2022 | B7: 2022_CIRO_PEREIRA | C7: Ciro Pereira | D7: PTB | E7: partido trabalhista brasileiro | F7: 0.455 | H7: direita
A8: 2022 | B8: 2022_CLAUDIO_DO_MUNDO_NOVO | C8: Cláudio do Mundo Novo | D8: PSD | E8: partido social democratico | F8: 0.296 | H8: direita
A9: 2022 | B9: 2022_DR_CELIO_FROIS | C9: Dr. Célio Frois | D9: CIDADANIA | E9: cidadania | F9: -0.014 | H9: centro
A10: 2022 | B10: 2022_DUDA_SALABERT | C10: Duda Salabert | D10: PDT | E10: partido democratico trabalhista | F10: -0.356 | H10: esquerda
A11: 2022 | B11: 2022_FERNANDA_PEREIRA_ALTOE | C11: Fernanda Pereira Altoé | D11: NOVO | E11: partido novo | F11: 0.711 | H11: direita
A12: 2022 | B12: 2022_FERNANDO_LUIZ | C12: Fernando Luiz | D12: PSD | E12: partido social democratico | F12: 0.296 | H12: direita
A13: 2022 | B13: 2022_FLAVIA_BORJA | C13: Flávia Borja | D13: AVANTE | E13: avante
A14: 2022 | B14: 2022_GILSON_GUIMARAES | C14: Gilson Guimarães | D14: REDE | E14: rede sustentabilidade | G14: -0.555 | H14: esquerda
A15: 2022 | B15: 2022_HELINHO_DA_FARMACIA | C15: Helinho da Farmácia | D15: PSD | E15: partido social democratico | F15: 0.296 | H15: direita
A16: 2022 | B16: 2022_HENRIQUE_BRAGA | C16: Henrique Braga | D16: PSDB | E16: partido da social democracia brasileira | F16: 0.157 | H16: centro
A17: 2022 | B17: 2022_IRLAN_MELO | C17: Irlan Melo | D17: PSD | E17: partido social democratico | F17: 0.296 | H17: direita
A18: 2022 | B18: 2022_IZA_LOURENCA | C18: Iza Lourença | D18: PSOL | E18: partido socialismo e liberdade | F18: -0.874 | H18: esquerda
A19: 2022 | B19: 2022_JORGE_SANTOS | C19: Jorge Santos | D19: REPUBLICANOS | E19: republicanos | F19: 0.550 | H19: direita
A20: 2022 | B20: 2022_JOSE_FERREIRA | C20: José Ferreira | D20: PP | E20: progressistas | F20: 0.510 | H20: direita
A21: 2022 | B21: 2022_JUNINHO_LOS_HERMANOS | C21: Juninho Los Hermanos | D21: AVANTE | E21: avante
A22: 2022 | B22: 2022_LEO | C22: Léo | D22: PSL | E22: Partido Social Liberal | F22: 0.803 | H22: direita
A23: 2022 | B23: 2022_MACAE_EVARISTO | C23: Macaé Evaristo | D23: PT | E23: partido dos trabalhadores | F23: -0.691 | H23: esquerda
A24: 2022 | B24: 2022_MARCELA_TROPIA | C24: Marcela Trópia | D24: NOVO | E24: partido novo | F24: 0.711 | H24: direita
A25: 2022 | B25: 2022_MARCOS_CRISPIM | C25: Marcos Crispim | D25: PSC | E25: partido social cristao | F25: 0.596 | H25: direita
A26: 2022 | B26: 2022_MARILDA_PORTELA | C26: Marilda Portela | D26: CIDADANIA | E26: cidadania | F26: -0.014 | H26: centro
A27: 2022 | B27: 2022_MILTINHO_CGE | C27: Miltinho CGE | D27: PDT | E27: partido democratico trabalhista | F27: -0.356 | H27: esquerda
A28: 2022 | B28: 2022_NELY_AQUINO | C28: Nely Aquino | D28: PODE | E28: podemos | F28: 0.386 | H28: direita
A29: 2022 | B29: 2022_NIKOLAS_FERREIRA | C29: Nikolas Ferreira | D29: PRTB | E29: Partido Renovador Trabalhista Brasileiro
A30: 2022 | B30: 2022_PEDRO_PATRUS | C30: Pedro Patrus | D30: PT | E30: partido dos trabalhadores | F30: -0.691 | H30: esquerda
A31: 2022 | B31: 2022_PROFESSORA_MARLI | C31: Professora Marli | D31: PP | E31: progressistas | F31: 0.510 | H31: direita
A32: 2022 | B32: 2022_PROFESSOR_CLAUDINEY_DULIM | C32: Professor Claudiney Dulim | D32: AVANTE | E32: avante
A33: 2022 | B33: 2022_PROFESSOR_JULIANO_LOPES | C33: Professor Juliano Lopes | D33: PTC | E33: Partido Trabalhista Comunitário
A34: 2022 | B34: 2022_RAMON_BIBIANO_DA_CASA_DE_APOIO | C34: Ramon Bibiano da Casa de Apoio | D34: PSD | E34: partido social democratico | F34: 0.296 | H34: direita
A35: 2022 | B35: 2022_REINALDO_GOMES_PRETO_SACOLAO | C35: Reinaldo Gomes Preto Sacolão | D35: MDB | E35: movimento democratico brasileiro | F35: 0.137 | H35: centro
A36: 2022 | B36: 2022_ROGERIO_ALKIMIM | C36: Rogerio Alkimim | D36: PMN | E36: partido da mobilizacao nacional
A37: 2022 | B37: 2022_RUBAO | C37: Rubão | D37: PP | E37: progressistas | F37: 0.510 | H37: direita
A38: 2022 | B38: 2022_WALTER_TOSTA | C38: Walter Tosta | D38: PL | E38: partido liberal | F38: 0.493 | H38: direita
A39: 2022 | B39: 2022_WANDERLEY_PORTO | C39: Wanderley Porto | D39: PATRIOTA | E39: patriota
A40: 2022 | B40: 2022_WESLEY | C40: Wesley | D40: PROS | E40: Partido Republicano da Ordem Social | F40: 0.032 | H40: centro
A41: 2022 | B41: 2022_WILSINHO_DA_TABU | C41: Wilsinho da Tabu | D41: PP | E41: progressistas | F41: 0.510 | H41: direita
A42: 2023 | B42: 2023_BELLA_GONCALVES | C42: Bella Gonçalves | D42: PSOL | E42: partido socialismo e liberdade | F42: -0.874 | H42: esquerda
A43: 2023 | B43: 2023_BIM_DA_AMBULANCIA | C43: Bim da Ambulância | D43: AVANTE | E43: avante
A44: 2023 | B44: 2023_BRAULIO_LARA | C44: Braulio Lara | D44: NOVO | E44: partido novo | F44: 0.711 | H44: direita
A45: 2023 | B45: 2023_BRUNO_MIRANDA | C45: Bruno Miranda | D45: PDT | E45: partido democratico trabalhista | F45: -0.356 | H45: esquerda
A46: 2023 | B46: 2023_CIRO_PEREIRA | C46: Ciro Pereira | D46: PTB | E46: partido trabalhista brasileiro | F46: 0.455 | H46: direita
A47: 2023 | B47: 2023_CLEITON_XAVIER | C47: Cleiton Xavier | D47: PMN | E47: partido da mobilizacao nacional
A48: 2023 | B48: 2023_CLAUDIO_DO_MUNDO_NOVO | C48: Cláudio do Mundo Novo | D48: PSD | E48: partido social democratico | F48: 0.296 | H48: direita
A49: 2023 | B49: 2023_CESAR_GORDIN | C49: César Gordin | D49: SD | E49: solidariedade | F49: 0.190 | H49: centro
A50: 2023 | B50: 2023_DR_CELIO_FROIS | C50: Dr. Célio Frois | D50: PSC | E50: partido social cristao | F50: 0.596 | H50: direita
A51: 2023 | B51: 2023_DUDA_SALABERT | C51: Duda Salabert | D51: PDT | E51: partido democratico trabalhista | F51: -0.356 | H51: esquerda
A52: 2023 | B52: 2023_FERNANDA_PEREIRA_ALTOE | C52: Fernanda Pereira Altoé | D52: NOVO | E52: partido novo | F52: 0.711 | H52: direita
A53: 2023 | B53: 2023_FERNANDO_LUIZ | C53: Fernando Luiz | D53: PSD | E53: partido social democratico | F53: 0.296 | H53: direita
A54: 2023 | B54: 2023_FLAVIA_BORJA | C54: Flávia Borja | D54: PP | E54: progressistas | F54: 0.510 | H54: direita
A55: 2023 | B55: 2023_GABRIEL | C55: Gabriel | D55: sem partido | E55: sem partido
A56: 2023 | B56: 2023_GILSON_GUIMARAES | C56: Gilson Guimarães | D56: REDE | E56: rede sustentabilidade | G56: -0.555 | H56: esquerda
A57: 2023 | B57: 2023_HELINHO_DA_FARMACIA | C57: Helinho da Farmácia | D57: PSD | E57: partido social democratico | F57: 0.296 | H57: direita
A58: 2023 | B58: 2023_HENRIQUE_BRAGA | C58: Henrique Braga | D58: PSDB | E58: partido da social democracia brasileira | F58: 0.157 | H58: centro
A59: 2023 | B59: 2023_IRLAN_MELO | C59: Irlan Melo | D59: PATRIOTA | E59: patriota
A60: 2023 | B60: 2023_IZA_LOURENCA | C60: Iza Lourença | D60: PSOL | E60: partido socialismo e liberdade | F60: -0.874 | H60: esquerda
A61: 2023 | B61: 2023_JANAINA_CARDOSO | C61: Janaina Cardoso | D61: UNIAO | E61: uniao brasil | F61: 0.660 | H61: direita
A62: 2023 | B62: 2023_JORGE_SANTOS | C62: Jorge Santos | D62: REPUBLICANOS | E62: republicanos | F62: 0.550 | H62: direita
A63: 2023 | B63: 2023_JOSE_FERREIRA | C63: José Ferreira | D63: PP | E63: progressistas | F63: 0.510 | H63: direita
A64: 2023 | B64: 2023_JUNINHO_LOS_HERMANOS | C64: Juninho Los Hermanos | D64: AVANTE | E64: avante
A65: 2023 | B65: 2023_LEO | C65: Léo | D65: UNIAO | E65: uniao brasil | F65: 0.660 | H65: direita
A66: 2023 | B66: 2023_MACAE_EVARISTO | C66: Macaé Evaristo | D66: PT | E66: partido dos trabalhadores | F66: -0.691 | H66: esquerda
A67: 2023 | B67: 2023_MARCELA_TROPIA | C67: Marcela Trópia | D67: NOVO | E67: partido novo | F67: 0.711 | H67: direita
A68: 2023 | B68: 2023_MARCOS_CRISPIM | C68: Marcos Crispim | D68: PP | E68: progressistas | F68: 0.510 | H68: direita
A69: 2023 | B69: 2023_MARILDA_PORTELA | C69: Marilda Portela | D69: CIDADANIA | E69: cidadania | F69: -0.014 | H69: centro
A70: 2023 | B70: 2023_MILTINHO_CGE | C70: Miltinho CGE | D70: PDT | E70: partido democratico trabalhista | F70: -0.356 | H70: esquerda
A71: 2023 | B71: 2023_NELY_AQUINO | C71: Nely Aquino | D71: PODE | E71: podemos | F71: 0.386 | H71: direita
A72: 2023 | B72: 2023_NIKOLAS_FERREIRA | C72: Nikolas Ferreira | D72: PL | E72: partido liberal | F72: 0.493 | H72: direita
A73: 2023 | B73: 2023_PEDRO_PATRUS | C73: Pedro Patrus | D73: PT | E73: partido dos trabalhadores | F73: -0.691 | H73: esquerda
A74: 2023 | B74: 2023_PROFESSOR_CLAUDINEY_DULIM | C74: Professor Claudiney Dulim | D74: AVANTE | E74: avante
A75: 2023 | B75: 2023_PROFESSOR_JULIANO_LOPES | C75: Professor Juliano Lopes | D75: AGIR | E75: agir
A76: 2023 | B76: 2023_PROFESSORA_MARLI | C76: Professora Marli | D76: PP | E76: progressistas | F76: 0.510 | H76: direita
A77: 2023 | B77: 2023_RAMON_BIBIANO_DA_CASA_DE_APOIO | C77: Ramon Bibiano da Casa de Apoio | D77: PSD | E77: partido social democratico | F77: 0.296 | H77: direita
A78: 2023 | B78: 2023_REINALDO_GOMES_PRETO_SACOLAO | C78: Reinaldo Gomes Preto Sacolão | D78: MDB | E78: movimento democratico brasileiro | F78: 0.137 | H78: centro
A79: 2023 | B79: 2023_RUBAO | C79: Rubão | D79: PP | E79: progressistas | F79: 0.510 | H79: direita
A80: 2023 | B80: 2023_SERGIO_FERNANDO_PINHO_TAVARES | C80: Sérgio Fernando Pinho Tavares | D80: PL | E80: partido liberal | F80: 0.493 | H80: direita
A81: 2023 | B81: 2023_WALTER_TOSTA | C81: Walter Tosta | D81: PL | E81: partido liberal | F81: 0.493 | H81: direita
A82: 2023 | B82: 2023_WANDERLEY_PORTO | C82: Wanderley Porto | D82: PATRIOTA | E82: patriota
A83: 2023 | B83: 2023_WESLEY | C83: Wesley | D83: PP | E83: progressistas | F83: 0.510 | H83: direita
A84: 2023 | B84: 2023_WILSINHO_DA_TABU | C84: Wilsinho da Tabu | D84: PP | E84: progressistas | F84: 0.510 | H84: direita
A85: 2023 | B85: 2023_ALVARO_DAMIAO | C85: Álvaro Damião | D85: UNIAO | E85: uniao brasil | F85: 0.660 | H85: direita
A86: 2024 | B86: 2024_BRAULIO_LARA | C86: Braulio Lara | D86: NOVO | E86: partido novo | F86: 0.711 | H86: direita
A87: 2024 | B87: 2024_BRUNO_MIRANDA | C87: Bruno Miranda | D87: PDT | E87: partido democratico trabalhista | F87: -0.356 | H87: esquerda
A88: 2024 | B88: 2024_BRUNO_PEDRALVA | C88: Bruno Pedralva | D88: PT | E88: partido dos trabalhadores | F88: -0.691 | H88: esquerda
A89: 2024 | B89: 2024_CIDA_FALABELLA | C89: Cida Falabella | D89: PSOL | E89: partido socialismo e liberdade | F89: -0.874 | H89: esquerda
A90: 2024 | B90: 2024_CIRO_PEREIRA | C90: Ciro Pereira | D90: PTB | E90: partido trabalhista brasileiro | F90: 0.455 | H90: direita
A91: 2024 | B91: 2024_CLEITON_XAVIER | C91: Cleiton Xavier | D91: PMN | E91: partido da mobilizacao nacional
A92: 2024 | B92: 2024_CLAUDIO_DO_MUNDO_NOVO | C92: Cláudio do Mundo Novo | D92: PSD | E92: partido social democratico | F92: 0.296 | H92: direita
A93: 2024 | B93: 2024_CESAR_GORDIN | C93: César Gordin | D93: SD | E93: solidariedade | F93: 0.190 | H93: centro
A94: 2024 | B94: 2024_DR_CELIO_FROIS | C94: Dr. Célio Frois | D94: PV | E94: partido verde | G94: -0.069 | H94: centro
A95: 2024 | B95: 2024_FERNANDA_PEREIRA_ALTOE | C95: Fernanda Pereira Altoé | D95: NOVO | E95: partido novo | F95: 0.711 | H95: direita
A96: 2024 | B96: 2024_FERNANDO_LUIZ | C96: Fernando Luiz | D96: PSD | E96: partido social democratico | F96: 0.296 | H96: direita
A97: 2024 | B97: 2024_FLAVIA_BORJA | C97: Flávia Borja | D97: PP | E97: progressistas | F97: 0.510 | H97: direita
A98: 2024 | B98: 2024_GABRIEL | C98: Gabriel | D98: sem partido | E98: sem partido
A99: 2024 | B99: 2024_GILSON_GUIMARAES | C99: Gilson Guimarães | D99: REDE | E99: rede sustentabilidade | G99: -0.555 | H99: esquerda
A100: 2024 | B100: 2024_HELINHO_DA_FARMACIA | C100: Helinho da Farmácia | D100: PSD | E100: partido social democratico | F100: 0.296 | H100: direita
...

Sheet LOCALIDADES_APRESENTACAO
A1: LOCALIDADE | B1: id_emenda | C1: endereco_padronizado | D1: bairro | E1: regional | F1: territorio | G1: logradouro | H1: numero | I1: cep | J1: latitude | K1: longitude | L1: coordenada_x | M1: coordenada_y
A2: Abrigo Frei Otto | B2: 2023_REINALDO_GOMES_PRETO_SACOLAO_964_01 | C2: R. Rui Barbosa, 299 - Santa Monica, Belo Horizonte - MG, 31525-130 | D2: Santa Monica | E2: VENDA NOVA | F2: VN3 | G2: Rua Rui Barbosa | H2: 299 | I2: 31525-130
A3: Abrigo Pró-Criança | B3: 2023_FLAVIA_BORJA_202_01 | C3: Rua Gonçalo Alves, 116 no bairro São Cristovão | D3: Sao Cristovao | E3: NOROESTE | F3: NO1 | G3: Rua Gonçalo Alves | H3: 116 | I3: 31110-480
A4: Ação Social Filadélfia | B4: 2023_NIKOLAS_FERREIRA_921_01 | C4: Rua Epaminondas Otoni 315/265 Bairro Vista Alegre | D4: Vista Alegre | E4: OESTE | F4: O2 | G4: Rua Epaminondas Otoni | H4: 315 | I4: 30512-700
A5: Anfiteatro na Vila Senhor dos Passos | B5: 2023_PROFESSORA_MARLI_850_01 | C5: Rua 15 de Abril, Vila Senhor dos Passos, Bairro Lagoinha. | D5: Lagoinha | E5: NOROESTE | F5: NO1 | G5: Rua 15 de Abril
